Workbook

Sheet README
B2: Venture Capital Model, with Quarterly Forecast
B4: Copyright & Contact | C4: This was created by Taylor Davidson (@tdavidson) of Foresight. © 2025, Unstructured Ventures, LLC. Questions, contact taylor@foresight.is or @tdavidson
B5: License | C5: tl:dr; You can modify, edit, use, and share within your company (and with third-parties as needed to operate your business). You may not redistribute, resell, give away to others. Full license.
B6: Goal | C6: Simplified model for forecasting a venture fund, to help understand overall fund assumptions and how portfolio construction impacts returns. I've worked with countless founders building complicated models for fund construction - see Venture Investor Model for one - but want to create a simpler, more accessible model that removes some of the lesser-used edge cases and covers the basics for most emerging managers.
B7: Copy to Google Sheets or Download to Excel | C7: File > Make a Copy to copy it to your own Google Drive, or File > Download to download this to use in Excel or other spreadsheet programs. See License for warranties and liabilities.
B8: Support | C8: Questions, happy to assist, contact anytime. More details on how I provide support: https://foresight.is/help
B9: Missing a feature you need? | C9: Check out the Resources for other resources for modeling venture funds, and check out Foresight's Venture Investor Model for a more detailed fund model with financial statements, management company budgeting, and more.
B10: Quickstart | C10: Input fund structural assumptions on Get Started sheet, then review the Key Reports and Forecast sheet to see the key outputs. More details at https://foresight.is/docs/
B12: Outline
B14: README | C14: Contact into, overview on model. Safe to delete or hide.
B15: Formatting and Colors Overview | C15: Details on what the colors and formatting in the model mean. https://foresight.is/learn/colors-and-formatting
B16: License | C16: Terms of use of the model. Safe to delete or hide. https://foresight.is/license
B17: Get Started | C17: Core assumptions for the fund. Do not delete, safe to hide.
B18: Capital and Fund Assumptions | C18: Assumptions for fund economics
B19: Recycling | C19: Optional section for assuming fund recycling policy
B20: Portfolio Construction Assumptions | C20: Core portfolio construction assumptions
B21: Return Assumptions | C21: Investment performance assumptions
B22: Fund Performance | C22: Summary of fund performance. Details and more metrics on Forecast sheet
B23: Key Reports | C23: Key charts to summarize the model. Safe to delete or hide.
B24: Scenarios | C24: Output of the Scenarios, allowing you to set two alternate fund outcomes by changing assumptions for the number of value of high exits. The sheets powering the scenarios are hidden, and can be unhidden and changed if desired.
B25: Forecast | C25: The core calculations to forecast the operations of the fund. The core of the model.
... B29: Changelog | C29: List of what has been changed in model versions. Safe to delete or hide, although I'd advise to hide (instead of delete) so can always check to see what model version you are using to compare to future changes.

Sheet License
B1: License Agreement
B2: Available on website
B4: This License Agreement (“the Agreement”) between you, the licensee, and Unstructured Ventures, LLC (the “Company”) a limited liability corporation headquartered and registered in the Commonwealth of Pennsylvania and organized under the laws of the state of Delaware. The Company owns the financial model (the “Product”) and any edits, additions, or customizations (the "Service") delivered under this Agreement. This Agreement grants you a non-exclusive, non-transferable right to use and incorporate the Product and Service in personal and corporate projects for the organization that purchased the Product and/or Service.
B6: You agree as follows:
B8: 1. Scope of use
B9: * Use and incorporate the Product and/or Service in personal and commercial projects for your company including financial models, business plans, pitch decks, etc.
B10: * You may modify the Product and/or Service to better serve your project.
B11: * You are granted unlimited usage of the Product and/or Service purchased in your organization.
B12: * If an organization is the licensee, all employees of the organization may use the same license.
B14: 2. Limitations and non-use
B15: * You may not redistribute, sublicense or resell the Product and/or Service.
B16: * You may not distribute, license or sell derivative, recompiled, reverse engineered, or modified versions of the Product and/or Service.
... B29: This Agreement is governed by the laws of the Commonwealth of Pennsylvania and the applicable laws of the United States of America. Legal proceedings related to this Agreement may only be brought in the courts of Pennsylvania. You agree to service of process at the e-mail address on your original order. Notices may be sent to Unstructured Ventures, LLC by email to hello@unstructuredventures.com or by post to Unstructured Ventures, LLC, 6360 Broad St, #5226, Pittsburgh, PA, 15206, USA.

Sheet Get Started
B2: Get Started
B3: Key model assumptions and performance metrics
B5: Capital and Fund Assumptions
B6: Capital, Management Fees, base Fund-level assumptions
B8: Detail | C8: Unit | E8: Assumption | F8: Forecast | K8: Notes
B9: Total Commited Capital (Fund Size) | C9: $ | E9: 25000000 | F9: =E9 -> 25000000 | K9: Fund size. By default, assumes all committed capital is closed at the start. Can adjust that by modifying the committed capital on Forecast sheet.
B10: GP Commit, as % of committed capital | C10: % | E10: 0.02 | F10: =E10*F$9 -> 500000 | K10: GP commit is treated as an LP interest for purposes of calculating mangement fees and carried interest. see glossary for additional details
B11: Organizational Expenses (one time) | C11: =C$9 -> $ | E11: 100000 | F11: =Forecast!E39 -> 100000 | K11: paid by fund, in addition to management fees. one time costs associated with forming the fund, primarily legal fees
B12: Operational Expenses (annual) | C12: =C$9 -> $ | E12: 75000 | F12: =Forecast!E40 -> 750000 | K12: paid by fund, in addition to management fees. see https://foresight.is/docs/management-company/ for more context. calculated based on the fund operations period for operating expenses
B13: Management Fees, per year, as % of committed capital | C13: % | E13: 0.02 | F13: =Forecast!E41 -> 4900000 | K13: model works for management fees based on called and committed capital (can be edited for fee structures based on assets under management). if you have a management fee structure that steps down over time, you can edit the management fees directly on the Forecast sheet.
B14: Carry | C14: % | E14: 0.2 | F14: =E124 -> 21803315 | K14: carry is the % of gains that are paid to the managers of the fund. part of the commonly cited "2 and 20" fees structure for funds
B15: Active Investment time period (quarters) | C15: # | E15: 16 | K15: time period for new investments (follow ons by default assumed to come over time)
B16: Fund Duration (Management Fees time period) (quarters) | C16: # | E16: 40 | K16: time period used for assuming management fees, tied to the fund duration and not including the fund extension period, if applicable
B17: Fund Operations time period (quarters) | C17: # | E17: =E15+MAX(H109:H112) -> 40 | K17: time period used for assuming operational expenses, which is calculated from the new invesetment and exit timeframes, to cover the periods the fund incurrs operational expenses. you can override the calculated period if desired.
B18: Fund Duration Extension Period (quarters) | C18: # | E18: =MAX(0,E17-E16) -> 0 | K18: extra time period calculated from your deployment and holding period assumptions. purely for informational purposes, the model uses the fund duration for calculating management fees, this just shows how long of an extension you will need based on your assumptions
B21: Recycling
B22: Details on recycling provisions for closed end and evergreen funds | K22: more at https://foresight.is/docs/management-fee-recycling/
B24: Detail | C24: Unit | E24: Assumption | F24: Forecast | K24: Notes
B25: ="Target recycling %, and max achievable" -> Target recycling %, and max achievable | C25: % | E25: 0.25 | F25: =IFERROR(F29/F26,0) -> 0.0385 | K25: input is for the target % to recycle, and the forecast shows the % that is achievable given the parameters in the assumptions below. It is very common for the max acheivable to be less than the target. Note that LPAs may set the number differently; for example, some LPAs may note that recycling is 125% of committed capital (meaning that the total can be 25% higher than the amount of committed capital), or it may say that recycling is 25% of committed capital. They mean the same thing, but the number may be expressed differently. The model uses an assumption of 25% of recycling + 100% of committed capital = 125% of total committed capital plus recycling
B26: ="... based on "&E26 -> ... based on committed capital | C26: - | E26: committed capital | F26: =IF(E26="management fees",F13,F9) -> 25000000 | K26: can be set to management fees or committed capital, and the forecast outputs the amount of it forecasted in the model
B27: ="... from exits "&E27&" quarters or less post-investment" -> ... from exits 24 quarters or less post-investment | C27: # | E27: =6*4 -> 24 | F27: =Forecast!E204 -> 134979075 | K27: can set the time limit from original investment to time to proceeds (exit), and only allow exits within that timeframe to recycle their proceeds. if there is no limit, simply input a number greater thant the fund operations period or the max holding period in the return assumptions
B28: ="... up to the amount of "&E28&" per investment exited" -> ... up to the amount of invested capital per investment exited | C28: - | E28: invested capital | F28: =IF(E28="invested capital",Forecast!E206,IF(E28="invested capital plus cost basis",Forecast!E205,Forecast!E204)) -> 8085000 | K28: can set to recycle the amount originally invested in the company (meaning any profits would be distributed), the amount invested in the company plus the cost basis (allocating expenses to the invested capital, so that it reflects paid in capital related to the investent), or all proceeds, meaning all proceeds from the exit
B29: ="... able to invest in "&E29 -> ... able to invest in new investments | C29: - | E29: new investments | F29: =Forecast!E42 -> 962500 | K29: can set to new investments only, or new and follow on investments. this will set the proceeds recycling timeframe on the forecast sheet, meaning the period when recycling can be done
B32: Investment Strategy and Expectations
B33: Use to detail an investment strategy, new and follow to forecast returns
B35: Exit Outcome | E35: Fail | F35: Low | G35: Medium | H35: High | K35: change the terms to fit what you want to call the different exit outcomes, used to generate the returns expectations on get started.
B37: Investment Performance and Capital Allocation
B38: % of Investments per Exit Outcome | C38: % | E38: 0.6 | F38: 0.2 | G38: 0.1 | H38: =1-SUM(E38:G38) -> 0.1 | K38: % of the number of companies invested in; sum should equal 0%
B39: # of Companies that achieve each Exit Outcome | C39: # | E39: =E42*$E122/E78 -> 24.255 | F39: =F42*$E122/F78 -> 8.085 | G39: =G42*$E122/G78 -> 4.0425 | H39: =H42*$E122/H78 -> 4.0425 | K39: # of companies invested in, per exit outcome
B40: Index of average investment per overall average | C40: % | E40: =$E101/E78 -> 1 | F40: =$E101/F78 -> 1 | G40: =$E101/G78 -> 1 | H40: =$E101/H78 -> 1 | K40: intermediate calculation to calculation % of invested capital
B41: Adjustment to % of Investments to % of Invested Capital | C41: % | E41: =E38/E40 -> 0.6 | F41: =F38/F40 -> 0.2 | G41: =G38/G40 -> 0.1 | H41: =H38/H40 -> 0.1 | K41: intermediate calculation to calculation % of invested capital
B42: % of Invested Capital per Exit Outcome | C42: % | E42: =E41/SUM($E41:$H41) -> 0.6 | F42: =F41/SUM($E41:$H41) -> 0.2 | G42: =G41/SUM($E41:$H41) -> 0.1 | H42: =H41/SUM($E41:$H41) -> 0.1 | K42: % of overall invested capital; sum should equal 0%. this will not be equal to the % of investments (companies) if you have different investment strategies between the companies
B43: % of Initial Capital per Exit Outcome | C43: % | E43: =1/(1+E53*E54/E48+E63*E64/E48)*E42 -> 0.6 | F43: =1/(1+F53*F54/F48+F63*F64/F48)*F42 -> 0.2 | G43: =1/(1+G53*G54/G48+G63*G64/G48)*G42 -> 0.1 | H43: =1/(1+H53*H54/H48+H63*H64/H48)*H42 -> 0.1
B44: % of First Follow per Exit Outcome | C44: % | E44: =IFERROR(E53*E54/E48*E43,0) -> 0 | F44: =IFERROR(F53*F54/F48*F43,0) -> 0 | G44: =IFERROR(G53*G54/G48*G43,0) -> 0 | H44: =IFERROR(H53*H54/H48*H43,0) -> 0
B45: % of Second Follow per Exit Outcome | C45: % | E45: =IFERROR(E63*E64/E48*E43,0) -> 0 | F45: =IFERROR(F63*F64/F48*F43,0) -> 0 | G45: =IFERROR(G63*G64/G48*G43,0) -> 0 | H45: =IFERROR(H63*H64/H48*H43,0) -> 0
B47: Initial Investment
B48: Average Initial Investment | C48: =C$9 -> $ | E48: =E49*E50 -> 500000 | F48: =F49*F50 -> 500000 | G48: =G49*G50 -> 500000 | H48: =H49*H50 -> 500000 | K48: your check into the company, not including other investors in the round. calculated from your ownership % and average postmoney valuation at initial investment
B49: Postmoney Valuation | C49: =C$9 -> $ | E49: 5000000 | F49: 5000000 | G49: 5000000 | H49: 5000000 | K49: assumption, average per type of exit. note, this is an assumption becuase the model is best used to evaluate the impact of ownership % on overall returns, and to do that, it is best to hold the valuation constant and see the impact on ownership % on the size of the portfolio
B50: Ownership %, at initial investment | C50: =C$9 -> $ | E50: 0.1 | F50: 0.1 | G50: 0.1 | H50: 0.1 | K50: your assumed ownership %, not including other investors in the round. for convertibles, assume the post-conversion to equity ownership %
B52: Follow on Investments (First Follow on round)
B53: % of Initial Investments to Participate in Prorata | C53: % | E53: 0 | F53: 0 | G53: 0 | H53: 0 | K53: this should reflect the combination of (a) companies that graduate to raise a round, and (b) whether you participate in their round
B54: Follow on Investment Amount | C54: =C$9 -> $ | E54: =E56*E57*E50 -> 400000 | F54: =F56*F57*F50 -> 400000 | G54: =G56*G57*G50 -> 400000 | H54: =H56*H57*H50 -> 400000 | K54: this is calculated based on the amount raised in the round and the ownership coming into the round, but you can override this if desired
B55: Time from Initial Investment to Follow on Investment (quarters) | C55: # | E55: 0 | F55: 0 | G55: 0 | H55: 0 | K55: time from the initial investment
B56: Postmoney Valuation | C56: =C$9 -> $ | E56: =E49*4 -> 20000000 | F56: =F49*4 -> 20000000 | G56: =G49*4 -> 20000000 | H56: =H49*4 -> 20000000 | K56: many people will assume the same for all types of companies (types of exit outcomes), but you could alter this if desired
B57: Dilution from Round (from all investors) | C57: % | E57: 0.2 | F57: 0.2 | G57: 0.2 | H57: 0.2 | K57: this is used to calculate the amount raised in the round, based on the postmoney valuation in the round
B58: Dilution from New Option Pool | C58: % | E58: 0.1 | F58: 0.1 | G58: 0.1 | H58: 0.1 | K58: optional, but helps to consider the dilution from option pool expansions. remember that prorata rights do not cover dilution from prorata
B59: Ownership % per company followed on, post follow on | C59: % | E59: =E50*(1-E57-E58)+E54/E56 -> 0.09 | F59: =F50*(1-F57-F58)+F54/F56 -> 0.09 | G59: =G50*(1-G57-G58)+G54/G56 -> 0.09 | H59: =H50*(1-H57-H58)+H54/H56 -> 0.09
B60: Ownership % per average initial investment, post follow on round | C60: % | E60: =E50*(1-E57-E58)+E54/E56*E53 -> 0.07 | F60: =F50*(1-F57-F58)+F54/F56*F53 -> 0.07 | G60: =G50*(1-G57-G58)+G54/G56*G53 -> 0.07 | H60: =H50*(1-H57-H58)+H54/H56*H53 -> 0.07 | K60: average company, including ones do follow on in, and ones do not follow on in
B62: Follow on Investments (Second Follow on round)
B63: % of Initial Investments to Participate in Prorata | C63: % | E63: 0 | F63: 0 | G63: 0 | H63: 0 | K63: this should reflect the combination of (a) companies that graduate to raise a round, and (b) whether you participate in their round
B64: Follow on Investment Amount | C64: =C$9 -> $ | E64: =E67*E66*E59 -> 1080000 | F64: =F67*F66*F59 -> 1080000 | G64: =G67*G66*G59 -> 1080000 | H64: =H67*H66*H59 -> 1080000 | K64: this is calculated based on the amount raised in the round and the ownership coming into the round, but you can override this if desired
B65: Time from Initial Investment to Follow on Investment (quarters) | C65: # | E65: 0 | F65: 0 | G65: 0 | H65: 0 | K65: time from the initial investment, not the last follow round
B66: Postmoney Valuation | C66: =C$9 -> $ | E66: =E56*3 -> 60000000 | F66: =F56*3 -> 60000000 | G66: =G56*3 -> 60000000 | H66: =H56*3 -> 60000000 | K66: many people will assume the same for all types of companies (types of exit outcomes), but you could alter this if desired
B67: Dilution from Round (from all investors) | C67: % | E67: 0.2 | F67: 0.2 | G67: 0.2 | H67: 0.2 | K67: this is used to calculate the amount raised in the round, based on the postmoney valuation in the round
B68: Dilution from New Option Pool | C68: % | E68: 0.1 | F68: 0.1 | G68: 0.1 | H68: 0.1 | K68: optional, but helps to consider the dilution from option pool expansions. remember that prorata rights do not cover dilution from prorata
B69: Ownership % per company followed on, post follow on | C69: % | E69: =E59*(1-E67-E68)+E64/E66 -> 0.081 | F69: =F59*(1-F67-F68)+F64/F66 -> 0.081 | G69: =G59*(1-G67-G68)+G64/G66 -> 0.081 | H69: =H59*(1-H67-H68)+H64/H66 -> 0.081
B70: Ownership % per average initial investment, post follow on round | C70: % | E70: =E59*(1-E67-E68)+E64/E66*E63 -> 0.063 | F70: =F59*(1-F67-F68)+F64/F66*F63 -> 0.063 | G70: =G59*(1-G67-G68)+G64/G66*G63 -> 0.063 | H70: =H59*(1-H67-H68)+H64/H66*H63 -> 0.063 | K70: average company, including ones do follow on in, and ones do not follow on in
B72: Follow on Investments (Additional Follow on rounds)
B73: Additional Dilution from Second Follow on round to Exit | C73: % | E73: 0 | F73: 0.2 | G73: 0.4 | H73: =G73*2 -> 0.8 | K73: assumption to reflect all subsequent follow on rounds after the ones modeled above; you may want to assume more dilution for more successful companies to reflect more capital raised
B75: Exit
B76: Average Exit Value | C76: =C$9 -> $ | E76: 0 | F76: 50000000 | G76: 250000000 | H76: 1500000000 | K76: assumption, to reflect the average distribution to equity shareholders for this type of exit
B77: Average Hold Period (quarters) | C77: # | E77: =2*4 -> 8 | F77: =3*4 -> 12 | G77: =4*4 -> 16 | H77: =6*4 -> 24 | K77: Average Hold Period is the average time from initial investment to exit, per # of investments. assumption, please change for your strategy and assessment of your investments
B78: Average Investment per Company | C78: =C$9 -> $ | E78: =E48+E54*E53+E63*E64 -> 500000 | F78: =F48+F54*F53+F63*F64 -> 500000 | G78: =G48+G54*G53+G63*G64 -> 500000 | H78: =H48+H54*H53+H63*H64 -> 500000 | K78: average invested per company, per exit outcome
B79: Ownership % at Exit | C79: % | E79: =E70*(1-E73) -> 0.063 | F79: =F70*(1-F73) -> 0.0504 | G79: =G70*(1-G73) -> 0.0378 | H79: =H70*(1-H73) -> 0.0126 | K79: ownership %, per exit outcome
B80: Average Proceeds per Company | C80: =C$9 -> $ | E80: =E79*E76 -> 0 | F80: =F79*F76 -> 2520000 | G80: =G79*G76 -> 9450000 | H80: =H79*H76 -> 18900000 | K80: average proceeds per company, per exit outcome, reflecting ownership value at exit and total invested into each company (initial investment and follow on)
B81: Total Initial Investments | C81: =C$9 -> $ | E81: =E39*E48 -> 12127500 | F81: =F39*F48 -> 4042500 | G81: =G39*G48 -> 2021250 | H81: =H39*H48 -> 2021250 | K81: capital allocation to initial investments (first checks into companies)
B82: ="% of "&B$89 -> % of Total Invested Capital | C82: % | E82: =E43 -> 0.6 | F82: =F43 -> 0.2 | G82: =G43 -> 0.1 | H82: =H43 -> 0.1 | K82: per exit outcome / total
B83: Total First Follow Investments | C83: =C$9 -> $ | E83: =E39*E53*E54 -> 0 | F83: =F39*F53*F54 -> 0 | G83: =G39*G53*G54 -> 0 | H83: =H39*H53*H54 -> 0 | K83: capital allocation to first follow
B84: ="% of "&B$89 -> % of Total Invested Capital | C84: % | E84: =E44 -> 0 | F84: =F44 -> 0 | G84: =G44 -> 0 | H84: =H44 -> 0 | K84: per exit outcome / total
B85: Total Second Follow Investments | C85: =C$9 -> $ | E85: =E39*E63*E64 -> 0 | F85: =F39*F63*F64 -> 0 | G85: =G39*G63*G64 -> 0 | H85: =H39*H63*H64 -> 0 | K85: capital allocation to second follow
B86: ="% of "&B$89 -> % of Total Invested Capital | C86: % | E86: =E45 -> 0 | F86: =F45 -> 0 | G86: =G45 -> 0 | H86: =H45 -> 0 | K86: per exit outcome / total
B87: Total Follow Investments | C87: =C$9 -> $ | E87: =E83+E85 -> 0 | F87: =F83+F85 -> 0 | G87: =G83+G85 -> 0 | H87: =H83+H85 -> 0 | K87: capital allocation to all follow on rounds
B88: ="% of "&B$89 -> % of Total Invested Capital | C88: % | E88: =IFERROR(E87/SUM($E$89:$H$89),0) -> 0 | F88: =IFERROR(F87/SUM($E$89:$H$89),0) -> 0 | G88: =IFERROR(G87/SUM($E$89:$H$89),0) -> 0 | H88: =IFERROR(H87/SUM($E$89:$H$89),0) -> 0 | K88: per exit outcome / total
B89: Total Invested Capital | C89: =C$9 -> $ | E89: =E81+E87 -> 12127500 | F89: =F81+F87 -> 4042500 | G89: =G81+G87 -> 2021250 | H89: =H81+H87 -> 2021250 | K89: capital allocation
B90: ="% of "&B$89 -> % of Total Invested Capital | C90: % | E90: =IFERROR(E89/SUM($E$89:$H$89),0) -> 0.6 | F90: =IFERROR(F89/SUM($E$89:$H$89),0) -> 0.2 | G90: =IFERROR(G89/SUM($E$89:$H$89),0) -> 0.1 | H90: =IFERROR(H89/SUM($E$89:$H$89),0) -> 0.1 | K90: should equal the calculated % of total invested capital from above
B91: Total Proceeds | C91: =C$9 -> $ | E91: =E79*E76*E39 -> 0 | F91: =F79*F76*F39 -> 20374200 | G91: =G79*G76*G39 -> 38201625 | H91: =H79*H76*H39 -> 76403250 | K91: total proceeds per type of exit, reflecting performance, investment strategy, and exit expectations. you may want to adjust those assumptions to get this to match your expectations for where portfolio returns come from
B92: ="% of "&B91 -> % of Total Proceeds | C92: % | E92: =IFERROR(E91/SUM($E91:$H91),0) -> 0 | F92: =IFERROR(F91/SUM($E91:$H91),0) -> 0.1509434 | G92: =IFERROR(G91/SUM($E91:$H91),0) -> 0.28301887 | H92: =IFERROR(H91/SUM($E91:$H91),0) -> 0.56603774 | K92: per exit outcome / total
B93: Gross Exit Multiple, per Exit Outcome | C93: # | E93: =IFERROR(E80/E78,0) -> 0 | F93: =IFERROR(F80/F78,0) -> 5.04 | G93: =IFERROR(G80/G78,0) -> 18.9 | H93: =IFERROR(H80/H78,0) -> 37.8 | K93: proceeds / invested capital, per exit outcome
B96: Portfolio Construction
B97: Capital Allocation and Investment Timeframe Assumptions
B99: Detail | C99: Unit | E99: New | F99: Follow
B100: % Allocation of Invested Capital | C100: % | E100: =IFERROR(SUMPRODUCT(E38:H38,E48:H48)/SUMPRODUCT(E38:H38,E78:H78),0) -> 1 | F100: =1-E100 -> 0 | K100: Allocation of overall invested capital to new and follow
B101: Average Check Size | C101: =C$9 -> $ | E101: =SUMPRODUCT(E38:H38,E48:H48) -> 500000 | F101: =IFERROR(F100*$E122/F102,0) -> 0 | K101: Follow ons are assumed to be on average 1-2 years after the new investment. If more detailed required, consider the Venture Investor Model (see Model Comparison sheet)
B102: # of Checks | C102: # | E102: =F113 -> 40.425 | F102: =SUMPRODUCT(E39:H39,E63:H63)+SUMPRODUCT(E39:H39,E53:H53) -> 0 | K102: # of new checks = # of unique companies invested into. # of follow checks = # of rounds participated in, can consist of multiple follow checks into a single company
B105: Return Assumptions
B106: Used to create estimates of average investment outcome by gross exit multiple and hold period
B108: Type of Exit | C108: Unit | E108: % of Investments | F108: # of Investments | G108: Average Gross Exit Multiple | H108: Average Hold Period (quarters) | K108: Type of Exit can be defined in a few ways: by returns (writeoffs, small, medium, large), by strategy (Seed, A, B, etc.), by investment strategy (early, late, growth), or industry strategy (tech, energy, etc.)
B109: =E35 -> Fail | C109: #, % | E109: =E38 -> 0.6 | F109: =E39 -> 24.255 | G109: =E93 -> 0 | H109: =E77 -> 8 | K109: Average Hold Period is the average time from initial investment to exit, per # of investments, used to calculate the timing of proceeds and writeoffs
B110: =F35 -> Low | C110: #, % | E110: =F38 -> 0.2 | F110: =F39 -> 8.085 | G110: =F93 -> 5.04 | H110: =F77 -> 12
B111: =G35 -> Medium | C111: #, % | E111: =G38 -> 0.1 | F111: =G39 -> 4.0425 | G111: =G93 -> 18.9 | H111: =G77 -> 16
B112: =H35 -> High | C112: #, % | E112: =H38 -> 0.1 | F112: =H39 -> 4.0425 | G112: =H93 -> 37.8 | H112: =H77 -> 24 | K112: Can adjust this structure to add additional lines for types of exits, just note will need to make a few edits on Forecast sheet to pull those into the calculations of proceeds and changes in invested capital.
E113: =SUM(E109:E112) -> 1 | F113: =SUM(F109:F112) -> 40.425 | G113: =SUMPRODUCT(E93:H93,E42:H42) -> 6.678 | H113: =SUMPRODUCT(E42:H42,E77:H77) -> 11.2 | K113: note, the average gross multiple and average hold period is based off % of invested capital, *not* % of investments, since the investments may not have the same average investment $ per exit outcome, based on your assumptions above. so the average gross exit multiple *per investment* will vary from the average gross exit multiple per invested capital per outcome.
B115: Fund Performance
B116: Fund performance summary
B118: Called Capital (also called Paid in Capital) | C118: =C$9 -> $ | E118: =Forecast!E31 -> 25000000 | K118: should equal committed capital
B119: Management Fees and Fund Expenses | C119: =C$9 -> $ | E119: =Forecast!E41+Forecast!E40+Forecast!E39 -> 5750000 | K119: management fees + operating expenses + organizational expenses
B120: ="Budgeted "&B122 -> Budgeted Invested Capital | C120: =C$9 -> $ | E120: =IF(SUMPRODUCT(--(Forecast!G15:CH15<>"committed"))=0,F9-F11-F12-F13,F9-F11-F12-F9*(IF(Forecast!C17=TRUE,(1-E10),1)*SUMPRODUCT(Forecast!G14:CH14,--(Forecast!G15:CH15="committed"))))+IF(E29="new and follow investments",F9*Forecast!E219,0) -> 19250000 | K120: initially budgeted invested capital, without recycling
B121: Recycled Capital | C121: =C$9 -> $ | E121: =Forecast!E42 -> 962500 | K121: recycled capital, calculated using recycling assumptions above
B122: Invested Capital | C122: =C$9 -> $ | E122: =E120+E121 -> 20212500 | K122: committed capital - expenses - management fees + recycled capital, using subcalculations for management fees to handle assets under management
B123: Proceeds | C123: =C$9 -> $ | E123: =Forecast!E43 -> 134979075 | K123: calculated on forecast sheet
...

Sheet Get Started  2
B2: Get Started
B3: Key model assumptions and performance metrics
B5: Capital and Fund Assumptions
B6: Capital, Management Fees, base Fund-level assumptions
B8: Detail | C8: Unit | E8: Assumption | F8: Forecast | K8: Notes
B9: Total Commited Capital (Fund Size) | C9: ='Get Started'!C9 -> $ | E9: ='Get Started'!E9 -> 25000000 | F9: =E9 -> 25000000 | K9: Fund size. By default, assumes all committed capital is closed at the start. Can adjust that by modifying the committed capital on Forecast sheet.
B10: GP Commit, as % of committed capital | C10: % | E10: ='Get Started'!E10 -> 0.02 | F10: =E10*F$9 -> 500000 | K10: GP commit is treated as an LP interest for purposes of calculating mangement fees and carried interest. see glossary for additional details
B11: Organizational Expenses (one time) | C11: =C$9 -> $ | E11: ='Get Started'!E11 -> 100000 | F11: ='Forecast 2'!E39 -> 100000 | K11: paid by fund, in addition to management fees. one time costs associated with forming the fund, primarily legal fees
B12: Operational Expenses (annual) | C12: =C$9 -> $ | E12: ='Get Started'!E12 -> 75000 | F12: ='Forecast 2'!E40 -> 750000 | K12: paid by fund, in addition to management fees. see https://foresight.is/docs/management-company/ for more context. calculated based on the fund operations period for operating expenses
B13: Management Fees, per year, as % of committed capital | C13: % | E13: ='Get Started'!E13 -> 0.02 | F13: ='Forecast 2'!E41 -> 4900000 | K13: model works for management fees based on called and committed capital (can be edited for fee structures based on assets under management). if you have a management fee structure that steps down over time, you can edit the management fees directly on the Forecast sheet.
B14: Carry | C14: % | E14: ='Get Started'!E14 -> 0.2 | F14: =E124 -> 13925453 | K14: carry is the % of gains that are paid to the managers of the fund. part of the commonly cited "2 and 20" fees structure for funds
B15: Active Investment time period (quarters) | C15: # | E15: ='Get Started'!E15 -> 16 | K15: time period for new investments (follow ons by default assumed to come over time)
B16: Fund Duration (Management Fees time period) (quarters) | C16: # | E16: ='Get Started'!E16 -> 40 | K16: time period used for assuming management fees, tied to the fund duration and not including the fund extension period, if applicable
B17: Fund Operations time period (quarters) | C17: # | E17: ='Get Started'!E17 -> 40 | K17: time period used for assuming operational expenses, which is calculated from the new invesetment and exit timeframes, to cover the periods the fund incurrs operational expenses. you can override the calculated period if desired.
B18: Fund Duration Extension Period (quarters) | C18: # | E18: =MAX(0,E17-E16) -> 0 | K18: extra time period calculated from your deployment and holding period assumptions. purely for informational purposes, the model uses the fund duration for calculating management fees, this just shows how long of an extension you will need based on your assumptions
B21: Recycling
B22: Details on recycling provisions for closed end and evergreen funds | K22: more at https://foresight.is/docs/management-fee-recycling/
B24: Detail | C24: Unit | E24: Assumption | F24: Forecast | K24: Notes
B25: ="Target recycling %, and max achievable" -> Target recycling %, and max achievable | C25: % | E25: ='Get Started'!E25 -> 0.25 | F25: =IFERROR(F29/F26,0) -> 0.041708333 | K25: input is for the target % to recycle, and the forecast shows the % that is achievable given the parameters in the assumptions below. It is very common for the max acheivable to be less than the target. Note that LPAs may set the number differently; for example, some LPAs may note that recycling is 125% of committed capital (meaning that the total can be 25% higher than the amount of committed capital), or it may say that recycling is 25% of committed capital. They mean the same thing, but the number may be expressed differently. The model uses an assumption of 25% of recycling + 100% of committed capital = 125% of total committed capital plus recycling
B26: ="... based on "&E26 -> ... based on committed capital | C26: - | E26: ='Get Started'!E26 -> committed capital | F26: =IF(E26="management fees",F13,F9) -> 25000000 | K26: can be set to management fees or committed capital, and the forecast outputs the amount of it forecasted in the model
B27: ="... from exits "&E27&" quarters or less post-investment" -> ... from exits 24 quarters or less post-investment | C27: # | E27: ='Get Started'!E27 -> 24 | F27: ='Forecast 2'!E204 -> 95669973 | K27: can set the time limit from original investment to time to proceeds (exit), and only allow exits within that timeframe to recycle their proceeds. if there is no limit, simply input a number greater thant the fund operations period or the max holding period in the return assumptions
B28: ="... up to the amount of "&E28&" per investment exited" -> ... up to the amount of invested capital per investment exited | C28: - | E28: ='Get Started'!E28 -> invested capital | F28: =IF(E28="invested capital",'Forecast 2'!E206,IF(E28="invested capital plus cost basis",'Forecast 2'!E205,'Forecast 2'!E204)) -> 7778871.5 | K28: can set to recycle the amount originally invested in the company (meaning any profits would be distributed), the amount invested in the company plus the cost basis (allocating expenses to the invested capital, so that it reflects paid in capital related to the investent), or all proceeds, meaning all proceeds from the exit
B29: ="... able to invest in "&E29 -> ... able to invest in new investments | C29: - | E29: ='Get Started'!E29 -> new investments | F29: ='Forecast 2'!E42 -> 1042708.3 | K29: can set to new investments only, or new and follow on investments. this will set the proceeds recycling timeframe on the forecast sheet, meaning the period when recycling can be done
B32: Investment Strategy and Expectations
B33: Use to detail an investment strategy, new and follow to forecast returns
B35: Exit Outcome | E35: ='Get Started'!E35 -> Fail | F35: ='Get Started'!F35 -> Low | G35: ='Get Started'!G35 -> Medium | H35: ='Get Started'!H35 -> High | J35: change the terms to fit what you want to call the different exit outcomes, used to generate the returns expectations on get started.
B37: Investment Performance and Capital Allocation
B38: % of Investments per Exit Outcome | C38: % | E38: =1-SUM(F38:H38) -> 0.61666667 | F38: =MAX(0,'Get Started'!F38-($H38-'Get Started'!$H38)/3) -> 0.21666667 | G38: =MAX(0,'Get Started'!G38-($H38-'Get Started'!$H38)/3) -> 0.11666667 | H38: ='Get Started'!H38*(1+Scenarios!D28) -> 0.05 | J38: % of the number of companies invested in; sum should equal 0%
B39: # of Companies that achieve each Exit Outcome | C39: # | E39: =E42*$E122/E78 -> 25.027674 | F39: =F42*$E122/F78 -> 8.7935069 | G39: =G42*$E122/G78 -> 4.7349653 | H39: =H42*$E122/H78 -> 2.0292708 | J39: # of companies invested in, per exit outcome
B40: Index of average investment per overall average | C40: % | E40: =$E101/E78 -> 1 | F40: =$E101/F78 -> 1 | G40: =$E101/G78 -> 1 | H40: =$E101/H78 -> 1 | J40: intermediate calculation to calculation % of invested capital
B41: Adjustment to % of Investments to % of Invested Capital | C41: % | E41: =E38/E40 -> 0.61666667 | F41: =F38/F40 -> 0.21666667 | G41: =G38/G40 -> 0.11666667 | H41: =H38/H40 -> 0.05 | J41: intermediate calculation to calculation % of invested capital
B42: % of Invested Capital per Exit Outcome | C42: % | E42: =E41/SUM($E41:$H41) -> 0.61666667 | F42: =F41/SUM($E41:$H41) -> 0.21666667 | G42: =G41/SUM($E41:$H41) -> 0.11666667 | H42: =H41/SUM($E41:$H41) -> 0.05 | J42: % of overall invested capital; sum should equal 0%. this will not be equal to the % of investments (companies) if you have different investment strategies between the companies
B43: % of Initial Capital per Exit Outcome | C43: % | E43: =1/(1+E53*E54/E48+E63*E64/E48)*E42 -> 0.61666667 | F43: =1/(1+F53*F54/F48+F63*F64/F48)*F42 -> 0.21666667 | G43: =1/(1+G53*G54/G48+G63*G64/G48)*G42 -> 0.11666667 | H43: =1/(1+H53*H54/H48+H63*H64/H48)*H42 -> 0.05
B44: % of First Follow per Exit Outcome | C44: % | E44: =IFERROR(E53*E54/E48*E43,0) -> 0 | F44: =IFERROR(F53*F54/F48*F43,0) -> 0 | G44: =IFERROR(G53*G54/G48*G43,0) -> 0 | H44: =IFERROR(H53*H54/H48*H43,0) -> 0
B45: % of Second Follow per Exit Outcome | C45: % | E45: =IFERROR(E63*E64/E48*E43,0) -> 0 | F45: =IFERROR(F63*F64/F48*F43,0) -> 0 | G45: =IFERROR(G63*G64/G48*G43,0) -> 0 | H45: =IFERROR(H63*H64/H48*H43,0) -> 0
B47: Initial Investment
B48: Average Initial Investment | C48: =C$9 -> $ | E48: =E49*E50 -> 500000 | F48: =F49*F50 -> 500000 | G48: =G49*G50 -> 500000 | H48: =H49*H50 -> 500000 | J48: your check into the company, not including other investors in the round. calculated from your ownership % and average postmoney valuation at initial investment
B49: Postmoney Valuation | C49: =C$9 -> $ | E49: ='Get Started'!E49 -> 5000000 | F49: ='Get Started'!F49 -> 5000000 | G49: ='Get Started'!G49 -> 5000000 | H49: ='Get Started'!H49 -> 5000000 | J49: assumption, average per type of exit. note, this is an assumption becuase the model is best used to evaluate the impact of ownership % on overall returns, and to do that, it is best to hold the valuation constant and see the impact on ownership % on the size of the portfolio
B50: Ownership %, at initial investment | C50: =C$9 -> $ | E50: ='Get Started'!E50 -> 0.1 | F50: ='Get Started'!F50 -> 0.1 | G50: ='Get Started'!G50 -> 0.1 | H50: ='Get Started'!H50 -> 0.1 | J50: your assumed ownership %, not including other investors in the round. for convertibles, assume the post-conversion to equity ownership %
B52: Follow on Investments (First Follow on round)
B53: % of Initial Investments to Participate in Prorata | C53: % | E53: ='Get Started'!E53 -> 0 | F53: ='Get Started'!F53 -> 0 | G53: ='Get Started'!G53 -> 0 | H53: ='Get Started'!H53 -> 0 | J53: this should reflect the combination of (a) companies that graduate to raise a round, and (b) whether you participate in their round
B54: Follow on Investment Amount | C54: =C$9 -> $ | E54: ='Get Started'!E54 -> 400000 | F54: ='Get Started'!F54 -> 400000 | G54: ='Get Started'!G54 -> 400000 | H54: ='Get Started'!H54 -> 400000 | J54: this is calculated based on the amount raised in the round and the ownership coming into the round, but you can override this if desired
B55: Time from Initial Investment to Follow on Investment (quarters) | C55: # | E55: ='Get Started'!E55 -> 0 | F55: ='Get Started'!F55 -> 0 | G55: ='Get Started'!G55 -> 0 | H55: ='Get Started'!H55 -> 0 | J55: time from the initial investment
B56: Postmoney Valuation | C56: =C$9 -> $ | E56: ='Get Started'!E56 -> 20000000 | F56: ='Get Started'!F56 -> 20000000 | G56: ='Get Started'!G56 -> 20000000 | H56: ='Get Started'!H56 -> 20000000 | J56: many people will assume the same for all types of companies (types of exit outcomes), but you could alter this if desired
B57: Dilution from Round (from all investors) | C57: % | E57: ='Get Started'!E57 -> 0.2 | F57: ='Get Started'!F57 -> 0.2 | G57: ='Get Started'!G57 -> 0.2 | H57: ='Get Started'!H57 -> 0.2 | J57: this is used to calculate the amount raised in the round, based on the postmoney valuation in the round
B58: Dilution from New Option Pool | C58: % | E58: ='Get Started'!E58 -> 0.1 | F58: ='Get Started'!F58 -> 0.1 | G58: ='Get Started'!G58 -> 0.1 | H58: ='Get Started'!H58 -> 0.1 | J58: optional, but helps to consider the dilution from option pool expansions. remember that prorata rights do not cover dilution from prorata
B59: Ownership % per company followed on, post follow on | C59: % | E59: =E50*(1-E57-E58)+E54/E56 -> 0.09 | F59: =F50*(1-F57-F58)+F54/F56 -> 0.09 | G59: =G50*(1-G57-G58)+G54/G56 -> 0.09 | H59: =H50*(1-H57-H58)+H54/H56 -> 0.09
B60: Ownership % per average initial investment, post follow on round | C60: % | E60: =E50*(1-E57-E58)+E54/E56*E53 -> 0.07 | F60: =F50*(1-F57-F58)+F54/F56*F53 -> 0.07 | G60: =G50*(1-G57-G58)+G54/G56*G53 -> 0.07 | H60: =H50*(1-H57-H58)+H54/H56*H53 -> 0.07 | J60: average company, including ones do follow on in, and ones do not follow on in
B62: Follow on Investments (Second Follow on round)
B63: % of Initial Investments to Participate in Prorata | C63: % | E63: ='Get Started'!E63 -> 0 | F63: ='Get Started'!F63 -> 0 | G63: ='Get Started'!G63 -> 0 | H63: ='Get Started'!H63 -> 0 | J63: this should reflect the combination of (a) companies that graduate to raise a round, and (b) whether you participate in their round
B64: Follow on Investment Amount | C64: =C$9 -> $ | E64: ='Get Started'!E64 -> 1080000 | F64: ='Get Started'!F64 -> 1080000 | G64: ='Get Started'!G64 -> 1080000 | H64: ='Get Started'!H64 -> 1080000 | J64: this is calculated based on the amount raised in the round and the ownership coming into the round, but you can override this if desired
B65: Time from Initial Investment to Follow on Investment (quarters) | C65: # | E65: ='Get Started'!E65 -> 0 | F65: ='Get Started'!F65 -> 0 | G65: ='Get Started'!G65 -> 0 | H65: ='Get Started'!H65 -> 0 | J65: time from the initial investment, not the last follow round
B66: Postmoney Valuation | C66: =C$9 -> $ | E66: ='Get Started'!E66 -> 60000000 | F66: ='Get Started'!F66 -> 60000000 | G66: ='Get Started'!G66 -> 60000000 | H66: ='Get Started'!H66 -> 60000000 | J66: many people will assume the same for all types of companies (types of exit outcomes), but you could alter this if desired
B67: Dilution from Round (from all investors) | C67: % | E67: ='Get Started'!E67 -> 0.2 | F67: ='Get Started'!F67 -> 0.2 | G67: ='Get Started'!G67 -> 0.2 | H67: ='Get Started'!H67 -> 0.2 | J67: this is used to calculate the amount raised in the round, based on the postmoney valuation in the round
B68: Dilution from New Option Pool | C68: % | E68: ='Get Started'!E68 -> 0.1 | F68: ='Get Started'!F68 -> 0.1 | G68: ='Get Started'!G68 -> 0.1 | H68: ='Get Started'!H68 -> 0.1 | J68: optional, but helps to consider the dilution from option pool expansions. remember that prorata rights do not cover dilution from prorata
B69: Ownership % per company followed on, post follow on | C69: % | E69: =E59*(1-E67-E68)+E64/E66 -> 0.081 | F69: =F59*(1-F67-F68)+F64/F66 -> 0.081 | G69: =G59*(1-G67-G68)+G64/G66 -> 0.081 | H69: =H59*(1-H67-H68)+H64/H66 -> 0.081
B70: Ownership % per average initial investment, post follow on round | C70: % | E70: =E59*(1-E67-E68)+E64/E66*E63 -> 0.063 | F70: =F59*(1-F67-F68)+F64/F66*F63 -> 0.063 | G70: =G59*(1-G67-G68)+G64/G66*G63 -> 0.063 | H70: =H59*(1-H67-H68)+H64/H66*H63 -> 0.063 | J70: average company, including ones do follow on in, and ones do not follow on in
B72: Follow on Investments (Additional Follow on rounds)
B73: Additional Dilution from Second Follow on round to Exit | C73: % | E73: 0 | F73: 0.2 | G73: 0.4 | H73: =G73*2 -> 0.8 | J73: assumption to reflect all subsequent follow on rounds after the ones modeled above; you may want to assume more dilution for more successful companies to reflect more capital raised
B75: Exit
B76: Average Exit Value | C76: =C$9 -> $ | E76: ='Get Started'!E76 -> 0 | F76: ='Get Started'!F76 -> 50000000 | G76: ='Get Started'!G76 -> 250000000 | H76: ='Get Started'!H76*(1+Scenarios!D29) -> 1125000000 | J76: assumption, to reflect the average distribution to equity shareholders for this type of exit
B77: Average Hold Period (quarters) | C77: # | E77: ='Get Started'!E77 -> 8 | F77: ='Get Started'!F77 -> 12 | G77: ='Get Started'!G77 -> 16 | H77: ='Get Started'!H77 -> 24 | J77: Average Hold Period is the average time from initial investment to exit, per # of investments. assumption, please change for your strategy and assessment of your investments
B78: Average Investment per Company | C78: =C$9 -> $ | E78: =E48+E54*E53+E63*E64 -> 500000 | F78: =F48+F54*F53+F63*F64 -> 500000 | G78: =G48+G54*G53+G63*G64 -> 500000 | H78: =H48+H54*H53+H63*H64 -> 500000 | J78: average invested per company, per exit outcome
B79: Ownership % at Exit | C79: % | E79: =E70*(1-E73) -> 0.063 | F79: =F70*(1-F73) -> 0.0504 | G79: =G70*(1-G73) -> 0.0378 | H79: =H70*(1-H73) -> 0.0126 | J79: ownership %, per exit outcome
B80: Average Proceeds per Company | C80: =C$9 -> $ | E80: =E79*E76 -> 0 | F80: =F79*F76 -> 2520000 | G80: =G79*G76 -> 9450000 | H80: =H79*H76 -> 14175000 | J80: average proceeds per company, per exit outcome, reflecting ownership value at exit and total invested into each company (initial investment and follow on)
B81: Total Initial Investments | C81: =C$9 -> $ | E81: =E39*E48 -> 12513837 | F81: =F39*F48 -> 4396753.5 | G81: =G39*G48 -> 2367482.6 | H81: =H39*H48 -> 1014635.4 | J81: capital allocation to initial investments (first checks into companies)
B82: ="% of "&B$89 -> % of Total Invested Capital | C82: % | E82: =E43 -> 0.61666667 | F82: =F43 -> 0.21666667 | G82: =G43 -> 0.11666667 | H82: =H43 -> 0.05 | J82: per exit outcome / total
B83: Total First Follow Investments | C83: =C$9 -> $ | E83: =E39*E53*E54 -> 0 | F83: =F39*F53*F54 -> 0 | G83: =G39*G53*G54 -> 0 | H83: =H39*H53*H54 -> 0 | J83: capital allocation to first follow
B84: ="% of "&B$89 -> % of Total Invested Capital | C84: % | E84: =E44 -> 0 | F84: =F44 -> 0 | G84: =G44 -> 0 | H84: =H44 -> 0 | J84: per exit outcome / total
B85: Total Second Follow Investments | C85: =C$9 -> $ | E85: =E39*E63*E64 -> 0 | F85: =F39*F63*F64 -> 0 | G85: =G39*G63*G64 -> 0 | H85: =H39*H63*H64 -> 0 | J85: capital allocation to second follow
B86: ="% of "&B$89 -> % of Total Invested Capital | C86: % | E86: =E45 -> 0 | F86: =F45 -> 0 | G86: =G45 -> 0 | H86: =H45 -> 0 | J86: per exit outcome / total
B87: Total Follow Investments | C87: =C$9 -> $ | E87: =E83+E85 -> 0 | F87: =F83+F85 -> 0 | G87: =G83+G85 -> 0 | H87: =H83+H85 -> 0 | J87: capital allocation to all follow on rounds
B88: ="% of "&B$89 -> % of Total Invested Capital | C88: % | E88: =IFERROR(E87/SUM($E$89:$H$89),0) -> 0 | F88: =IFERROR(F87/SUM($E$89:$H$89),0) -> 0 | G88: =IFERROR(G87/SUM($E$89:$H$89),0) -> 0 | H88: =IFERROR(H87/SUM($E$89:$H$89),0) -> 0 | J88: per exit outcome / total
B89: Total Invested Capital | C89: =C$9 -> $ | E89: =E81+E87 -> 12513837 | F89: =F81+F87 -> 4396753.5 | G89: =G81+G87 -> 2367482.6 | H89: =H81+H87 -> 1014635.4 | J89: capital allocation
B90: ="% of "&B$89 -> % of Total Invested Capital | C90: % | E90: =IFERROR(E89/SUM($E$89:$H$89),0) -> 0.61666667 | F90: =IFERROR(F89/SUM($E$89:$H$89),0) -> 0.21666667 | G90: =IFERROR(G89/SUM($E$89:$H$89),0) -> 0.11666667 | H90: =IFERROR(H89/SUM($E$89:$H$89),0) -> 0.05 | J90: should equal the calculated % of total invested capital from above
B91: Total Proceeds | C91: =C$9 -> $ | E91: =E79*E76*E39 -> 0 | F91: =F79*F76*F39 -> 22159638 | G91: =G79*G76*G39 -> 44745422 | H91: =H79*H76*H39 -> 28764914 | J91: total proceeds per type of exit, reflecting performance, investment strategy, and exit expectations. you may want to adjust those assumptions to get this to match your expectations for where portfolio returns come from
B92: ="% of "&B91 -> % of Total Proceeds | C92: % | E92: =IFERROR(E91/SUM($E91:$H91),0) -> 0 | F92: =IFERROR(F91/SUM($E91:$H91),0) -> 0.23162584 | G92: =IFERROR(G91/SUM($E91:$H91),0) -> 0.46770601 | H92: =IFERROR(H91/SUM($E91:$H91),0) -> 0.30066815 | J92: per exit outcome / total
B93: Gross Exit Multiple, per Exit Outcome | C93: # | E93: =IFERROR(E80/E78,0) -> 0 | F93: =IFERROR(F80/F78,0) -> 5.04 | G93: =IFERROR(G80/G78,0) -> 18.9 | H93: =IFERROR(H80/H78,0) -> 28.35 | J93: proceeds / invested capital, per exit outcome
B96: Portfolio Construction
B97: Capital Allocation and Investment Timeframe Assumptions
B99: Detail | C99: Unit | E99: New | F99: Follow
B100: % Allocation of Invested Capital | C100: % | E100: =IFERROR(SUMPRODUCT(E38:H38,E48:H48)/SUMPRODUCT(E38:H38,E78:H78),0) -> 1 | F100: =1-E100 -> 0 | K100: Allocation of overall invested capital to new and follow
B101: Average Check Size | C101: =C$9 -> $ | E101: =SUMPRODUCT(E38:H38,E48:H48) -> 500000 | F101: =IFERROR(F100*$E122/F102,0) -> 0 | K101: Follow ons are assumed to be on average 1-2 years after the new investment. If more detailed required, consider the Venture Investor Model (see Model Comparison sheet)
B102: # of Checks | C102: # | E102: =F113 -> 40.585417 | F102: =SUMPRODUCT(E39:H39,E63:H63)+SUMPRODUCT(E39:H39,E53:H53) -> 0 | K102: # of new checks = # of unique companies invested into. # of follow checks = # of rounds participated in, can consist of multiple follow checks into a single company
B105: Return Assumptions
B106: Used to create estimates of average investment outcome by gross exit multiple and hold period
B108: Type of Exit | C108: Unit | E108: % of Investments | F108: # of Investments | G108: Average Gross Exit Multiple | H108: Average Hold Period (quarters) | K108: Type of Exit can be defined in a few ways: by returns (writeoffs, small, medium, large), by strategy (Seed, A, B, etc.), by investment strategy (early, late, growth), or industry strategy (tech, energy, etc.)
B109: =E35 -> Fail | C109: #, % | E109: =E38 -> 0.61666667 | F109: =E39 -> 25.027674 | G109: =E93 -> 0 | H109: =E77 -> 8 | K109: Average Hold Period is the average time from initial investment to exit, per # of investments, used to calculate the timing of proceeds and writeoffs
B110: =F35 -> Low | C110: #, % | E110: =F38 -> 0.21666667 | F110: =F39 -> 8.7935069 | G110: =F93 -> 5.04 | H110: =F77 -> 12 | K110: The % of total proceeds is calculated from the gross exit multiple and the % of investments for each exit type, to estimate where the fund returns come from. More complicated methods for estimated proceeds are in the paid venture models at https://foresight.is/vc
B111: =G35 -> Medium | C111: #, % | E111: =G38 -> 0.11666667 | F111: =G39 -> 4.7349653 | G111: =G93 -> 18.9 | H111: =G77 -> 16
B112: =H35 -> High | C112: #, % | E112: =H38 -> 0.05 | F112: =H39 -> 2.0292708 | G112: =H93 -> 28.35 | H112: =H77 -> 24 | K112: note, the average gross multiple and average hold period is based off % of invested capital, *not* % of investments, since the investments may not have the same average investment $ per exit outcome, based on your assumptions above
E113: =SUM(E109:E112) -> 1 | F113: =SUM(F109:F112) -> 40.585417 | G113: =SUMPRODUCT(E93:H93,E42:H42) -> 4.7145 | H113: =SUMPRODUCT(E42:H42,E77:H77) -> 10.6 | K113: Can adjust this structure to add additional lines for types of exits, just note will need to make a few edits on Forecast sheet to pull those into the calculations of proceeds and changes in invested capital.
B115: Fund Performance
B116: Fund performance summary
B118: Called Capital (also called Paid in Capital) | C118: =C$9 -> $ | E118: ='Forecast 2'!E31 -> 25000000 | K118: should equal committed capital
B119: Management Fees and Fund Expenses | C119: =C$9 -> $ | E119: ='Forecast 2'!E41+'Forecast 2'!E40+'Forecast 2'!E39 -> 5750000 | K119: management fees + operating expenses + organizational expenses
B120: ="Budgeted "&B122 -> Budgeted Invested Capital | C120: =C$9 -> $ | E120: =IF(SUMPRODUCT(--('Forecast 2'!G15:CH15<>"committed"))=0,F9-F11-F12-F13,F9-F11-F12-F9*(IF('Forecast 2'!C17=TRUE,(1-E10),1)*SUMPRODUCT('Forecast 2'!G14:CH14,--('Forecast 2'!G15:CH15="committed"))))+IF(E29="new and follow investments",F9*'Forecast 2'!E219,0) -> 19250000 | K120: initially budgeted invested capital, without recycling
B121: Recycled Capital | C121: =C$9 -> $ | E121: ='Forecast 2'!E42 -> 1042708.3 | K121: recycled capital, calculated using recycling assumptions above
B122: Invested Capital | C122: =C$9 -> $ | E122: =E120+E121 -> 20292708 | K122: committed capital - expenses - management fees + recycled capital, using subcalculations for management fees to handle assets under management
B123: Proceeds | C123: =C$9 -> $ | E123: ='Forecast 2'!E43 -> 95669973 | K123: calculated on forecast sheet
...

Sheet Forecast  2
B2: Quarterly Forecast
B4: Relative Quarter | G4: =1 -> 1 | H4: =G4+1 -> 2 | I4: =H4+1 -> 3 | J4: =I4+1 -> 4 | K4: =J4+1 -> 5 | L4: =K4+1 -> 6 | M4: =L4+1 -> 7 | N4: =M4+1 -> 8 | O4: =N4+1 -> 9 | ... CH4: =CG4+1 -> 80
B5: Date at end of period | G5: =Forecast!G5 -> 46022 | H5: =EOMONTH(EDATE(G5,3),0) -> 46112 | I5: =EOMONTH(EDATE(H5,3),0) -> 46203 | J5: =EOMONTH(EDATE(I5,3),0) -> 46295 | K5: =EOMONTH(EDATE(J5,3),0) -> 46387 | L5: =EOMONTH(EDATE(K5,3),0) -> 46477 | M5: =EOMONTH(EDATE(L5,3),0) -> 46568 | N5: =EOMONTH(EDATE(M5,3),0) -> 46660 | O5: =EOMONTH(EDATE(N5,3),0) -> 46752 | ... CH5: =EOMONTH(EDATE(CG5,3),0) -> 53235
B7: Triggers
B8: ='Get Started 2'!B15 -> Active Investment time period (quarters) | C8: period for making new investments only | D8: sum | E8: =IF(D8="sum",SUM(G8:CH8),IF(D8="final",CH8,IF(D8="initial",G8,IF(D8="average",AVERAGE(G8:CH8),0)))) -> 16 | G8: =IF(G$4<='Get Started 2'!$E15,1,0) -> 1 | H8: =IF(H$4<='Get Started 2'!$E15,1,0) -> 1 | I8: =IF(I$4<='Get Started 2'!$E15,1,0) -> 1 | J8: =IF(J$4<='Get Started 2'!$E15,1,0) -> 1 | K8: =IF(K$4<='Get Started 2'!$E15,1,0) -> 1 | L8: =IF(L$4<='Get Started 2'!$E15,1,0) -> 1 | M8: =IF(M$4<='Get Started 2'!$E15,1,0) -> 1 | N8: =IF(N$4<='Get Started 2'!$E15,1,0) -> 1 | ... CH8: =IF(CH$4<='Get Started 2'!$E15,1,0) -> 0
B9: ='Get Started 2'!B16 -> Fund Duration (Management Fees time period) (quarters) | C9: see FAST Standard for how to use triggers: https://foresight.is/learn/fast-standard | D9: sum | E9: =IF(D9="sum",SUM(G9:CH9),IF(D9="final",CH9,IF(D9="initial",G9,IF(D9="average",AVERAGE(G9:CH9),0)))) -> 40 | G9: =IF(G$4<='Get Started 2'!$E16,1,0)*G10 -> 1 | H9: =IF(H$4<='Get Started 2'!$E16,1,0)*H10 -> 1 | I9: =IF(I$4<='Get Started 2'!$E16,1,0)*I10 -> 1 | J9: =IF(J$4<='Get Started 2'!$E16,1,0)*J10 -> 1 | K9: =IF(K$4<='Get Started 2'!$E16,1,0)*K10 -> 1 | L9: =IF(L$4<='Get Started 2'!$E16,1,0)*L10 -> 1 | M9: =IF(M$4<='Get Started 2'!$E16,1,0)*M10 -> 1 | N9: =IF(N$4<='Get Started 2'!$E16,1,0)*N10 -> 1 | ... CH9: =IF(CH$4<='Get Started 2'!$E16,1,0)*CH10 -> 0
B10: ='Get Started 2'!B17 -> Fund Operations time period (quarters) | D10: sum | E10: =IF(D10="sum",SUM(G10:CH10),IF(D10="final",CH10,IF(D10="initial",G10,IF(D10="average",AVERAGE(G10:CH10),0)))) -> 40 | G10: =IF(G$4<='Get Started 2'!$E17,1,0) -> 1 | H10: =IF(H$4<='Get Started 2'!$E17,1,0) -> 1 | I10: =IF(I$4<='Get Started 2'!$E17,1,0) -> 1 | J10: =IF(J$4<='Get Started 2'!$E17,1,0) -> 1 | K10: =IF(K$4<='Get Started 2'!$E17,1,0) -> 1 | L10: =IF(L$4<='Get Started 2'!$E17,1,0) -> 1 | M10: =IF(M$4<='Get Started 2'!$E17,1,0) -> 1 | N10: =IF(N$4<='Get Started 2'!$E17,1,0) -> 1 | ... CH10: =IF(CH$4<='Get Started 2'!$E17,1,0) -> 0
B11: Proceeds Recycling period (quarters) | D11: sum | E11: =IF(D11="sum",SUM(G11:EP11),IF(D11="final",EP11,IF(D11="initial",G11,IF(D11="average",AVERAGE(G11:EP11),0)))) -> 16 | G11: =IF('Get Started 2'!$E29="new investments",G8,IF(G$4<='Get Started 2'!$E15+MAX('Get Started 2'!$E55:$H55,'Get Started 2'!$E65:$H65),1,0)) -> 1 | H11: =IF('Get Started 2'!$E29="new investments",H8,IF(H$4<='Get Started 2'!$E15+MAX('Get Started 2'!$E55:$H55,'Get Started 2'!$E65:$H65),1,0)) -> 1 | I11: =IF('Get Started 2'!$E29="new investments",I8,IF(I$4<='Get Started 2'!$E15+MAX('Get Started 2'!$E55:$H55,'Get Started 2'!$E65:$H65),1,0)) -> 1 | J11: =IF('Get Started 2'!$E29="new investments",J8,IF(J$4<='Get Started 2'!$E15+MAX('Get Started 2'!$E55:$H55,'Get Started 2'!$E65:$H65),1,0)) -> 1 | K11: =IF('Get Started 2'!$E29="new investments",K8,IF(K$4<='Get Started 2'!$E15+MAX('Get Started 2'!$E55:$H55,'Get Started 2'!$E65:$H65),1,0)) -> 1 | L11: =IF('Get Started 2'!$E29="new investments",L8,IF(L$4<='Get Started 2'!$E15+MAX('Get Started 2'!$E55:$H55,'Get Started 2'!$E65:$H65),1,0)) -> 1 | M11: =IF('Get Started 2'!$E29="new investments",M8,IF(M$4<='Get Started 2'!$E15+MAX('Get Started 2'!$E55:$H55,'Get Started 2'!$E65:$H65),1,0)) -> 1 | N11: =IF('Get Started 2'!$E29="new investments",N8,IF(N$4<='Get Started 2'!$E15+MAX('Get Started 2'!$E55:$H55,'Get Started 2'!$E65:$H65),1,0)) -> 1 | ... CH11: =IF('Get Started 2'!$E29="new investments",CH8,IF(CH$4<='Get Started 2'!$E15+MAX('Get Started 2'!$E55:$H55,'Get Started 2'!$E65:$H65),1,0)) -> 0
B13: Inputs
B14: Management Fees | D14: sum | E14: =IF(D14="sum",SUM(G14:CH14),IF(D14="final",CH14,IF(D14="initial",G14,IF(D14="average",AVERAGE(G14:CH14),0)))) -> 0.2 | G14: =Forecast!G14 -> 0.005 | H14: =IF(H9=1,'Get Started 2'!$E13/4,0) -> 0.005 | I14: =IF(I9=1,'Get Started 2'!$E13/4,0) -> 0.005 | J14: =IF(J9=1,'Get Started 2'!$E13/4,0) -> 0.005 | K14: =IF(K9=1,'Get Started 2'!$E13/4,0) -> 0.005 | L14: =IF(L9=1,'Get Started 2'!$E13/4,0) -> 0.005 | M14: =IF(M9=1,'Get Started 2'!$E13/4,0) -> 0.005 | N14: =IF(N9=1,'Get Started 2'!$E13/4,0) -> 0.005 | O14: =IF(O9=1,'Get Started 2'!$E13/4,0) -> 0.005 | ... CH14: =IF(CH9=1,'Get Started 2'!$E13/4,0) -> 0
B15: ="Management Fees based on "&G15&" capital. Can change per period if method for calc changes." -> Management Fees based on committed capital. Can change per period if method for calc changes. | D15: sum | E15: =IF(D15="sum",SUM(G15:CH15),IF(D15="final",CH15,IF(D15="initial",G15,IF(D15="average",AVERAGE(G15:CH15),0)))) -> 0 | G15: =Forecast!G15 -> committed | H15: =Forecast!H15 -> committed | I15: =Forecast!I15 -> committed | J15: =Forecast!J15 -> committed | K15: =Forecast!K15 -> committed | L15: =Forecast!L15 -> committed | M15: =Forecast!M15 -> committed | N15: =Forecast!N15 -> committed | ... CH15: =Forecast!CH15 -> committed
B16: GP Commit, excluded from LP capital. By default, GP commit is treated as an LP interest. Check the box to have the GP commit not treated as an LP investment. This will affect management fees (management fees will not be charged on the GP commit if it's not an LP interest, and it will change the waterfall so that GPs only get carried interest, and not carried interest + their share of distributions as an LP) | C16: =Forecast!C16 -> FALSE | D16: sum | E16: =IF(D16="sum",SUM(G16:CH16),IF(D16="final",CH16,IF(D16="initial",G16,IF(D16="average",AVERAGE(G16:CH16),0)))) -> 0 | G16: =IF($C16=TRUE,G31*'Get Started 2'!$E10,0) -> 0 | H16: =IF($C16=TRUE,H31*'Get Started 2'!$E10,0) -> 0 | I16: =IF($C16=TRUE,I31*'Get Started 2'!$E10,0) -> 0 | J16: =IF($C16=TRUE,J31*'Get Started 2'!$E10,0) -> 0 | K16: =IF($C16=TRUE,K31*'Get Started 2'!$E10,0) -> 0 | L16: =IF($C16=TRUE,L31*'Get Started 2'!$E10,0) -> 0 | M16: =IF($C16=TRUE,M31*'Get Started 2'!$E10,0) -> 0 | N16: =IF($C16=TRUE,N31*'Get Started 2'!$E10,0) -> 0 | ... CH16: =IF($C16=TRUE,CH31*'Get Started 2'!$E10,0) -> 0
B17: GP Commit, excluded from management fees. Check the box to have the GP commit - capital contributed by the GP as LP capital and an ownership in the fund - excluded from calculation of management fees | C17: =Forecast!C17 -> TRUE | D17: sum | E17: =IF(D17="sum",SUM(G17:CH17),IF(D17="final",CH17,IF(D17="initial",G17,IF(D17="average",AVERAGE(G17:CH17),0)))) -> 500000 | G17: =IF($C17=TRUE,G31*'Get Started 2'!$E10,0) -> 28887.5 | H17: =IF($C17=TRUE,H31*'Get Started 2'!$E10,0) -> 26887.5 | I17: =IF($C17=TRUE,I31*'Get Started 2'!$E10,0) -> 26887.5 | J17: =IF($C17=TRUE,J31*'Get Started 2'!$E10,0) -> 26887.5 | K17: =IF($C17=TRUE,K31*'Get Started 2'!$E10,0) -> 26887.5 | L17: =IF($C17=TRUE,L31*'Get Started 2'!$E10,0) -> 26887.5 | M17: =IF($C17=TRUE,M31*'Get Started 2'!$E10,0) -> 26887.5 | N17: =IF($C17=TRUE,N31*'Get Started 2'!$E10,0) -> 26887.5 | ... CH17: =IF($C17=TRUE,CH31*'Get Started 2'!$E10,0) -> 0
B18: GP Commit, covered via cashless contributions from management fees | C18: if management fees are used to cover for a GP Commit. Please discuss the implications of this with your tax advisor and fund admin if you choose this option | D18: final | E18: =IF(D18="sum",SUM(G18:EP18),IF(D18="final",EP18,IF(D18="initial",G18,IF(D18="average",AVERAGE(G18:EP18),0)))) -> 0 | G18: =Forecast!G18 -> 0 | H18: =Forecast!H18 -> 0 | I18: =Forecast!I18 -> 0 | J18: =Forecast!J18 -> 0 | K18: =Forecast!K18 -> 0 | L18: =Forecast!L18 -> 0 | M18: =Forecast!M18 -> 0 | N18: =Forecast!N18 -> 0 | ... CH18: =Forecast!CH18 -> 0
B19: Commited Capital, % of total fund committed per year | D19: sum | E19: =IF(D19="sum",SUM(G19:EP19),IF(D19="final",EP19,IF(D19="initial",G19,IF(D19="average",AVERAGE(G19:EP19),0)))) -> 1 | G19: =Forecast!G19 -> 1 | H19: =Forecast!H19 -> 0 | I19: =Forecast!I19 -> 0 | J19: =Forecast!J19 -> 0 | K19: =Forecast!K19 -> 0 | L19: =Forecast!L19 -> 0 | M19: =Forecast!M19 -> 0 | N19: =Forecast!N19 -> 0 | ... CH19: =Forecast!CH19 -> 0
B20: Called Capital, % of total fund committed | C20: optional manual override to the automatically calculated called capital schedule, if you do not want to use the calculated schedule. this will not change your investment deployment, only your called capital and cash balances | D20: sum | E20: =IF(D20="sum",SUM(G20:EP20),IF(D20="final",EP20,IF(D20="initial",G20,IF(D20="average",AVERAGE(G20:EP20),0)))) -> 0 | G20: =Forecast!G20 -> 0 | H20: =Forecast!H20 -> 0 | I20: =Forecast!I20 -> 0 | J20: =Forecast!J20 -> 0 | K20: =Forecast!K20 -> 0 | L20: =Forecast!L20 -> 0 | M20: =Forecast!M20 -> 0 | N20: =Forecast!N20 -> 0 | ... CH20: =Forecast!CH20 -> 0
B22: Capital, beginning of period | D22: initial | E22: =IF(D22="sum",SUM(G22:CH22),IF(D22="final",CH22,IF(D22="initial",G22,IF(D22="average",AVERAGE(G22:CH22),0)))) -> 0 | G22: =F28 -> 0 | H22: =G28 -> 0 | I22: =H28 -> 0 | J22: =I28 -> 0 | K22: =J28 -> 0 | L22: =K28 -> 0 | M22: =L28 -> 0 | N22: =M28 -> 0 | ... CH22: =CG28 -> 0
B23: Called Capital | D23: sum | E23: =IF(D23="sum",SUM(G23:CH23),IF(D23="final",CH23,IF(D23="initial",G23,IF(D23="average",AVERAGE(G23:CH23),0)))) -> 25000000 | G23: =G31 -> 1444375 | H23: =H31 -> 1344375 | I23: =I31 -> 1344375 | J23: =J31 -> 1344375 | K23: =K31 -> 1344375 | L23: =L31 -> 1344375 | M23: =M31 -> 1344375 | N23: =N31 -> 1344375 | ... CH23: =CH31 -> 0
B24: Proceeds | D24: sum | E24: =IF(D24="sum",SUM(G24:CH24),IF(D24="final",CH24,IF(D24="initial",G24,IF(D24="average",AVERAGE(G24:CH24),0)))) -> 95669973 | G24: =G43 -> 0 | H24: =H43 -> 0 | I24: =I43 -> 0 | J24: =J43 -> 0 | K24: =K43 -> 0 | L24: =L43 -> 0 | M24: =M43 -> 0 | N24: =N43 -> 0 | ... CH24: =CH43 -> 0
B25: Distributions + Carried Interest | D25: sum | E25: =IF(D25="sum",SUM(G25:CH25),IF(D25="final",CH25,IF(D25="initial",G25,IF(D25="average",AVERAGE(G25:CH25),0)))) -> -94627265 | G25: =SUM(G47,G46,G45)*-1 -> 0 | H25: =SUM(H47,H46,H45)*-1 -> 0 | I25: =SUM(I47,I46,I45)*-1 -> 0 | J25: =SUM(J47,J46,J45)*-1 -> 0 | K25: =SUM(K47,K46,K45)*-1 -> 0 | L25: =SUM(L47,L46,L45)*-1 -> 0 | M25: =SUM(M47,M46,M45)*-1 -> 0 | N25: =SUM(N47,N46,N45)*-1 -> 0 | ... CH25: =SUM(CH47,CH46,CH45)*-1 -> 0
B26: Fees | D26: sum | E26: =IF(D26="sum",SUM(G26:CH26),IF(D26="final",CH26,IF(D26="initial",G26,IF(D26="average",AVERAGE(G26:CH26),0)))) -> -5750000 | G26: =SUM(G39,G40,G41)*-1 -> -241250 | H26: =SUM(H39,H40,H41)*-1 -> -141250 | I26: =SUM(I39,I40,I41)*-1 -> -141250 | J26: =SUM(J39,J40,J41)*-1 -> -141250 | K26: =SUM(K39,K40,K41)*-1 -> -141250 | L26: =SUM(L39,L40,L41)*-1 -> -141250 | M26: =SUM(M39,M40,M41)*-1 -> -141250 | N26: =SUM(N39,N40,N41)*-1 -> -141250 | ... CH26: =SUM(CH39,CH40,CH41)*-1 -> 0
B27: Investments | D27: sum | E27: =IF(D27="sum",SUM(G27:CH27),IF(D27="final",CH27,IF(D27="initial",G27,IF(D27="average",AVERAGE(G27:CH27),0)))) -> -20292708 | G27: =G38*-1 -> -1203125 | H27: =H38*-1 -> -1203125 | I27: =I38*-1 -> -1203125 | J27: =J38*-1 -> -1203125 | K27: =K38*-1 -> -1203125 | L27: =L38*-1 -> -1203125 | M27: =M38*-1 -> -1203125 | N27: =N38*-1 -> -1203125 | ... CH27: =CH38*-1 -> 0
B28: Capital, end of period | D28: final | E28: =IF(D28="sum",SUM(G28:CH28),IF(D28="final",CH28,IF(D28="initial",G28,IF(D28="average",AVERAGE(G28:CH28),0)))) -> 0 | G28: =SUM(G22:G27) -> 0 | H28: =SUM(H22:H27) -> 0 | I28: =SUM(I22:I27) -> 0 | J28: =SUM(J22:J27) -> 0 | K28: =SUM(K22:K27) -> 0 | L28: =SUM(L22:L27) -> 0 | M28: =SUM(M22:M27) -> 0 | N28: =SUM(N22:N27) -> 0 | ... CH28: =SUM(CH22:CH27) -> 0
B30: Committed Capital | D30: sum | E30: =IF(D30="sum",SUM(G30:CH30),IF(D30="final",CH30,IF(D30="initial",G30,IF(D30="average",AVERAGE(G30:CH30),0)))) -> 25000000 | G30: ='Get Started 2'!$E9*G19 -> 25000000 | H30: ='Get Started 2'!$E9*H19 -> 0 | I30: ='Get Started 2'!$E9*I19 -> 0 | J30: ='Get Started 2'!$E9*J19 -> 0 | K30: ='Get Started 2'!$E9*K19 -> 0 | L30: ='Get Started 2'!$E9*L19 -> 0 | M30: ='Get Started 2'!$E9*M19 -> 0 | N30: ='Get Started 2'!$E9*N19 -> 0 | ... CH30: ='Get Started 2'!$E9*CH19 -> 0
B31: Called Capital | D31: sum | E31: =IF(D31="sum",SUM(G31:CH31),IF(D31="final",CH31,IF(D31="initial",G31,IF(D31="average",AVERAGE(G31:CH31),0)))) -> 25000000 | G31: =IF($E20<>0,G20*$E30, MIN($E30-F60, MAX(0,G38+G39+G40+G41-G42))) -> 1444375 | H31: =IF($E20<>0,H20*$E30, MIN($E30-G60, MAX(0,H38+H39+H40+H41-H42))) -> 1344375 | I31: =IF($E20<>0,I20*$E30, MIN($E30-H60, MAX(0,I38+I39+I40+I41-I42))) -> 1344375 | J31: =IF($E20<>0,J20*$E30, MIN($E30-I60, MAX(0,J38+J39+J40+J41-J42))) -> 1344375 | K31: =IF($E20<>0,K20*$E30, MIN($E30-J60, MAX(0,K38+K39+K40+K41-K42))) -> 1344375 | L31: =IF($E20<>0,L20*$E30, MIN($E30-K60, MAX(0,L38+L39+L40+L41-L42))) -> 1344375 | M31: =IF($E20<>0,M20*$E30, MIN($E30-L60, MAX(0,M38+M39+M40+M41-M42))) -> 1344375 | N31: =IF($E20<>0,N20*$E30, MIN($E30-M60, MAX(0,N38+N39+N40+N41-N42))) -> 1344375 | ... CH31: =IF($E20<>0,CH20*$E30, MIN($E30-CG60, MAX(0,CH38+CH39+CH40+CH41-CH42))) -> 0
B32: Manual Investments | D32: sum | E32: =IF(D32="sum",SUM(G32:CH32),IF(D32="final",CH32,IF(D32="initial",G32,IF(D32="average",AVERAGE(G32:CH32),0)))) -> 0 | G32: 0 | H32: 0 | I32: 0 | J32: 0 | K32: 0 | L32: 0 | M32: 0 | N32: 0 | O32: 0 | P32: 0 | Q32: 0 | R32: 0 | S32: 0 | T32: 0 | U32: 0 | V32: 0 | W32: 0 | X32: 0 | Y32: 0 | Z32: 0 | AA32: 0 | AB32: 0 | AC32: 0 | AD32: 0 | AE32: 0 | AF32: 0 | AG32: 0 | AH32: 0 | AI32: 0 | AJ32: 0 | AK32: 0 | AL32: 0 | AM32: 0 | AN32: 0 | AO32: 0 | AP32: 0 | AQ32: 0 | AR32: 0 | AS32: 0 | AT32: 0 | AU32: 0 | AV32: 0 | AW32: 0 | AX32: 0 | AY32: 0 | AZ32: 0 | BA32: 0 | BB32: 0 | BC32: 0 | BD32: 0 | BE32: 0 | BF32: 0 | BG32: 0 | BH32: 0 | BI32: 0 | BJ32: 0 | BK32: 0 | BL32: 0 | BM32: 0 | BN32: 0 | BO32: 0 | BP32: 0 | BQ32: 0 | BR32: 0 | BS32: 0 | BT32: 0 | BU32: 0 | BV32: 0 | BW32: 0 | BX32: 0 | BY32: 0 | BZ32: 0 | CA32: 0 | CB32: 0 | CC32: 0 | CD32: 0 | CE32: 0 | CF32: 0 | CG32: 0 | CH32: 0
B33: New Investments | D33: sum | E33: =IF(D33="sum",SUM(G33:CH33),IF(D33="final",CH33,IF(D33="initial",G33,IF(D33="average",AVERAGE(G33:CH33),0)))) -> 20292708 | G33: =IF(G8=1,'Get Started 2'!$E120/'Get Started 2'!$E15*'Get Started 2'!$E100+G208*'Get Started 2'!$E100,0) -> 1203125 | H33: =IF(H8=1,'Get Started 2'!$E120/'Get Started 2'!$E15*'Get Started 2'!$E100+H208*'Get Started 2'!$E100,0) -> 1203125 | I33: =IF(I8=1,'Get Started 2'!$E120/'Get Started 2'!$E15*'Get Started 2'!$E100+I208*'Get Started 2'!$E100,0) -> 1203125 | J33: =IF(J8=1,'Get Started 2'!$E120/'Get Started 2'!$E15*'Get Started 2'!$E100+J208*'Get Started 2'!$E100,0) -> 1203125 | K33: =IF(K8=1,'Get Started 2'!$E120/'Get Started 2'!$E15*'Get Started 2'!$E100+K208*'Get Started 2'!$E100,0) -> 1203125 | L33: =IF(L8=1,'Get Started 2'!$E120/'Get Started 2'!$E15*'Get Started 2'!$E100+L208*'Get Started 2'!$E100,0) -> 1203125 | M33: =IF(M8=1,'Get Started 2'!$E120/'Get Started 2'!$E15*'Get Started 2'!$E100+M208*'Get Started 2'!$E100,0) -> 1203125 | N33: =IF(N8=1,'Get Started 2'!$E120/'Get Started 2'!$E15*'Get Started 2'!$E100+N208*'Get Started 2'!$E100,0) -> 1203125 | ... CH33: =IF(CH8=1,'Get Started 2'!$E120/'Get Started 2'!$E15*'Get Started 2'!$E100+CH208*'Get Started 2'!$E100,0) -> 0
B34: Prorata Opportunities | D34: sum | E34: =IF(D34="sum",SUM(G34:CH34),IF(D34="final",CH34,IF(D34="initial",G34,IF(D34="average",AVERAGE(G34:CH34),0)))) -> 0 | G34: 0 | H34: 0 | I34: 0 | J34: 0 | K34: 0 | L34: 0 | M34: 0 | N34: 0 | O34: 0 | P34: 0 | Q34: 0 | R34: 0 | S34: 0 | T34: 0 | U34: 0 | V34: 0 | W34: 0 | X34: 0 | Y34: 0 | Z34: 0 | AA34: 0 | AB34: 0 | AC34: 0 | AD34: 0 | AE34: 0 | AF34: 0 | AG34: 0 | AH34: 0 | AI34: 0 | AJ34: 0 | AK34: 0 | AL34: 0 | AM34: 0 | AN34: 0 | AO34: 0 | AP34: 0 | AQ34: 0 | AR34: 0 | AS34: 0 | AT34: 0 | AU34: 0 | AV34: 0 | AW34: 0 | AX34: 0 | AY34: 0 | AZ34: 0 | BA34: 0 | BB34: 0 | BC34: 0 | BD34: 0 | BE34: 0 | BF34: 0 | BG34: 0 | BH34: 0 | BI34: 0 | BJ34: 0 | BK34: 0 | BL34: 0 | BM34: 0 | BN34: 0 | BO34: 0 | BP34: 0 | BQ34: 0 | BR34: 0 | BS34: 0 | BT34: 0 | BU34: 0 | BV34: 0 | BW34: 0 | BX34: 0 | BY34: 0 | BZ34: 0 | CA34: 0 | CB34: 0 | CC34: 0 | CD34: 0 | CE34: 0 | CF34: 0 | CG34: 0 | CH34: 0
B35: Reserves for Follow on | C35: change in reserves per period, increase in reserves when new investments are made, decrease when follow on are made or investments are written off | D35: sum | E35: =IF(D35="sum",SUM(G35:CH35),IF(D35="final",CH35,IF(D35="initial",G35,IF(D35="average",AVERAGE(G35:CH35),0)))) -> 0 | G35: 0 | H35: 0 | I35: 0 | J35: 0 | K35: 0 | L35: 0 | M35: 0 | N35: 0 | O35: 0 | P35: 0 | Q35: 0 | R35: 0 | S35: 0 | T35: 0 | U35: 0 | V35: 0 | W35: 0 | X35: 0 | Y35: 0 | Z35: 0 | AA35: 0 | AB35: 0 | AC35: 0 | AD35: 0 | AE35: 0 | AF35: 0 | AG35: 0 | AH35: 0 | AI35: 0 | AJ35: 0 | AK35: 0 | AL35: 0 | AM35: 0 | AN35: 0 | AO35: 0 | AP35: 0 | AQ35: 0 | AR35: 0 | AS35: 0 | AT35: 0 | AU35: 0 | AV35: 0 | AW35: 0 | AX35: 0 | AY35: 0 | AZ35: 0 | BA35: 0 | BB35: 0 | BC35: 0 | BD35: 0 | BE35: 0 | BF35: 0 | BG35: 0 | BH35: 0 | BI35: 0 | BJ35: 0 | BK35: 0 | BL35: 0 | BM35: 0 | BN35: 0 | BO35: 0 | BP35: 0 | BQ35: 0 | BR35: 0 | BS35: 0 | BT35: 0 | BU35: 0 | BV35: 0 | BW35: 0 | BX35: 0 | BY35: 0 | BZ35: 0 | CA35: 0 | CB35: 0 | CC35: 0 | CD35: 0 | CE35: 0 | CF35: 0 | CG35: 0 | CH35: 0
B36: Follow on Investments | D36: sum | E36: =IF(D36="sum",SUM(G36:CH36),IF(D36="final",CH36,IF(D36="initial",G36,IF(D36="average",AVERAGE(G36:CH36),0)))) -> 0 | G36: ='Get Started 2'!$E122*G255 -> 0 | H36: ='Get Started 2'!$E122*H255 -> 0 | I36: ='Get Started 2'!$E122*I255 -> 0 | J36: ='Get Started 2'!$E122*J255 -> 0 | K36: ='Get Started 2'!$E122*K255 -> 0 | L36: ='Get Started 2'!$E122*L255 -> 0 | M36: ='Get Started 2'!$E122*M255 -> 0 | N36: ='Get Started 2'!$E122*N255 -> 0 | ... CH36: ='Get Started 2'!$E122*CH255 -> 0
B37: Total Investments, by cohort of New Investments | D37: sum | E37: =IF(D37="sum",SUM(G37:CH37),IF(D37="final",CH37,IF(D37="initial",G37,IF(D37="average",AVERAGE(G37:CH37),0)))) -> 20292708 | G37: =G33*'Get Started 2'!$F100/'Get Started 2'!$E100+G33+G32 -> 1203125 | H37: =H33*'Get Started 2'!$F100/'Get Started 2'!$E100+H33+H32 -> 1203125 | I37: =I33*'Get Started 2'!$F100/'Get Started 2'!$E100+I33+I32 -> 1203125 | J37: =J33*'Get Started 2'!$F100/'Get Started 2'!$E100+J33+J32 -> 1203125 | K37: =K33*'Get Started 2'!$F100/'Get Started 2'!$E100+K33+K32 -> 1203125 | L37: =L33*'Get Started 2'!$F100/'Get Started 2'!$E100+L33+L32 -> 1203125 | M37: =M33*'Get Started 2'!$F100/'Get Started 2'!$E100+M33+M32 -> 1203125 | N37: =N33*'Get Started 2'!$F100/'Get Started 2'!$E100+N33+N32 -> 1203125 | ... CH37: =CH33*'Get Started 2'!$F100/'Get Started 2'!$E100+CH33+CH32 -> 0
B38: Total Investments | D38: sum | E38: =IF(D38="sum",SUM(G38:CH38),IF(D38="final",CH38,IF(D38="initial",G38,IF(D38="average",AVERAGE(G38:CH38),0)))) -> 20292708 | G38: =SUM(G33,G36,G32) -> 1203125 | H38: =SUM(H33,H36,H32) -> 1203125 | I38: =SUM(I33,I36,I32) -> 1203125 | J38: =SUM(J33,J36,J32) -> 1203125 | K38: =SUM(K33,K36,K32) -> 1203125 | L38: =SUM(L33,L36,L32) -> 1203125 | M38: =SUM(M33,M36,M32) -> 1203125 | N38: =SUM(N33,N36,N32) -> 1203125 | ... CH38: =SUM(CH33,CH36,CH32) -> 0
B39: Organizational Expenses | D39: sum | E39: =IF(D39="sum",SUM(G39:CH39),IF(D39="final",CH39,IF(D39="initial",G39,IF(D39="average",AVERAGE(G39:CH39),0)))) -> 100000 | G39: =IF(G4=1,'Get Started 2'!$E11,0) -> 100000 | H39: =IF(H4=1,'Get Started 2'!$E11,0) -> 0 | I39: =IF(I4=1,'Get Started 2'!$E11,0) -> 0 | J39: =IF(J4=1,'Get Started 2'!$E11,0) -> 0 | K39: =IF(K4=1,'Get Started 2'!$E11,0) -> 0 | L39: =IF(L4=1,'Get Started 2'!$E11,0) -> 0 | M39: =IF(M4=1,'Get Started 2'!$E11,0) -> 0 | N39: =IF(N4=1,'Get Started 2'!$E11,0) -> 0 | ... CH39: =IF(CH4=1,'Get Started 2'!$E11,0) -> 0
B40: Operational Expenses | D40: sum | E40: =IF(D40="sum",SUM(G40:CH40),IF(D40="final",CH40,IF(D40="initial",G40,IF(D40="average",AVERAGE(G40:CH40),0)))) -> 750000 | G40: ='Get Started 2'!$E12*G10/4 -> 18750 | H40: ='Get Started 2'!$E12*H10/4 -> 18750 | I40: ='Get Started 2'!$E12*I10/4 -> 18750 | J40: ='Get Started 2'!$E12*J10/4 -> 18750 | K40: ='Get Started 2'!$E12*K10/4 -> 18750 | L40: ='Get Started 2'!$E12*L10/4 -> 18750 | M40: ='Get Started 2'!$E12*M10/4 -> 18750 | N40: ='Get Started 2'!$E12*N10/4 -> 18750 | ... CH40: ='Get Started 2'!$E12*CH10/4 -> 0
B41: Management Fees | D41: sum | E41: =IF(D41="sum",SUM(G41:CH41),IF(D41="final",CH41,IF(D41="initial",G41,IF(D41="average",AVERAGE(G41:CH41),0)))) -> 4900000 | G41: =IFERROR(IF(G15="committed",G83*IF($C17=TRUE,1-'Get Started 2'!$E10,1)*G14+IF(AND(G4<>1,G54*IF($C17=TRUE,1-'Get Started 2'!$E10,1)<>0,SUM($G54:G54)*IF($C17=TRUE,1-'Get Started 2'!$E10,1)<>E54*IF($C17=TRUE,1-'Get Started 2'!$E10,1)),G54*IF($C17=TRUE,1-'Get Started 2'!$E10,1)*(G4-1)*G14,0),IF(G15="called",G14*(G60+F60)/2*IF($C17=TRUE,1-'Get Started 2'!$E10,1),G14*(G85+F85)/2*IF($C17=TRUE,1-'Get Started 2'!$E10,1))),0) -> 122500 | H41: =IFERROR(IF(H15="committed",H83*IF($C17=TRUE,1-'Get Started 2'!$E10,1)*H14+IF(AND(H4<>1,H54*IF($C17=TRUE,1-'Get Started 2'!$E10,1)<>0,SUM($G54:H54)*IF($C17=TRUE,1-'Get Started 2'!$E10,1)<>F54*IF($C17=TRUE,1-'Get Started 2'!$E10,1)),H54*IF($C17=TRUE,1-'Get Started 2'!$E10,1)*(H4-1)*H14,0),IF(H15="called",H14*(H60+G60)/2*IF($C17=TRUE,1-'Get Started 2'!$E10,1),H14*(H85+G85)/2*IF($C17=TRUE,1-'Get Started 2'!$E10,1))),0) -> 122500 | I41: =IFERROR(IF(I15="committed",I83*IF($C17=TRUE,1-'Get Started 2'!$E10,1)*I14+IF(AND(I4<>1,I54*IF($C17=TRUE,1-'Get Started 2'!$E10,1)<>0,SUM($G54:I54)*IF($C17=TRUE,1-'Get Started 2'!$E10,1)<>G54*IF($C17=TRUE,1-'Get Started 2'!$E10,1)),I54*IF($C17=TRUE,1-'Get Started 2'!$E10,1)*(I4-1)*I14,0),IF(I15="called",I14*(I60+H60)/2*IF($C17=TRUE,1-'Get Started 2'!$E10,1),I14*(I85+H85)/2*IF($C17=TRUE,1-'Get Started 2'!$E10,1))),0) -> 122500 | J41: =IFERROR(IF(J15="committed",J83*IF($C17=TRUE,1-'Get Started 2'!$E10,1)*J14+IF(AND(J4<>1,J54*IF($C17=TRUE,1-'Get Started 2'!$E10,1)<>0,SUM($G54:J54)*IF($C17=TRUE,1-'Get Started 2'!$E10,1)<>H54*IF($C17=TRUE,1-'Get Started 2'!$E10,1)),J54*IF($C17=TRUE,1-'Get Started 2'!$E10,1)*(J4-1)*J14,0),IF(J15="called",J14*(J60+I60)/2*IF($C17=TRUE,1-'Get Started 2'!$E10,1),J14*(J85+I85)/2*IF($C17=TRUE,1-'Get Started 2'!$E10,1))),0) -> 122500 | K41: =IFERROR(IF(K15="committed",K83*IF($C17=TRUE,1-'Get Started 2'!$E10,1)*K14+IF(AND(K4<>1,K54*IF($C17=TRUE,1-'Get Started 2'!$E10,1)<>0,SUM($G54:K54)*IF($C17=TRUE,1-'Get Started 2'!$E10,1)<>I54*IF($C17=TRUE,1-'Get Started 2'!$E10,1)),K54*IF($C17=TRUE,1-'Get Started 2'!$E10,1)*(K4-1)*K14,0),IF(K15="called",K14*(K60+J60)/2*IF($C17=TRUE,1-'Get Started 2'!$E10,1),K14*(K85+J85)/2*IF($C17=TRUE,1-'Get Started 2'!$E10,1))),0) -> 122500 | L41: =IFERROR(IF(L15="committed",L83*IF($C17=TRUE,1-'Get Started 2'!$E10,1)*L14+IF(AND(L4<>1,L54*IF($C17=TRUE,1-'Get Started 2'!$E10,1)<>0,SUM($G54:L54)*IF($C17=TRUE,1-'Get Started 2'!$E10,1)<>J54*IF($C17=TRUE,1-'Get Started 2'!$E10,1)),L54*IF($C17=TRUE,1-'Get Started 2'!$E10,1)*(L4-1)*L14,0),IF(L15="called",L14*(L60+K60)/2*IF($C17=TRUE,1-'Get Started 2'!$E10,1),L14*(L85+K85)/2*IF($C17=TRUE,1-'Get Started 2'!$E10,1))),0) -> 122500 | M41: =IFERROR(IF(M15="committed",M83*IF($C17=TRUE,1-'Get Started 2'!$E10,1)*M14+IF(AND(M4<>1,M54*IF($C17=TRUE,1-'Get Started 2'!$E10,1)<>0,SUM($G54:M54)*IF($C17=TRUE,1-'Get Started 2'!$E10,1)<>K54*IF($C17=TRUE,1-'Get Started 2'!$E10,1)),M54*IF($C17=TRUE,1-'Get Started 2'!$E10,1)*(M4-1)*M14,0),IF(M15="called",M14*(M60+L60)/2*IF($C17=TRUE,1-'Get Started 2'!$E10,1),M14*(M85+L85)/2*IF($C17=TRUE,1-'Get Started 2'!$E10,1))),0) -> 122500 | N41: =IFERROR(IF(N15="committed",N83*IF($C17=TRUE,1-'Get Started 2'!$E10,1)*N14+IF(AND(N4<>1,N54*IF($C17=TRUE,1-'Get Started 2'!$E10,1)<>0,SUM($G54:N54)*IF($C17=TRUE,1-'Get Started 2'!$E10,1)<>L54*IF($C17=TRUE,1-'Get Started 2'!$E10,1)),N54*IF($C17=TRUE,1-'Get Started 2'!$E10,1)*(N4-1)*N14,0),IF(N15="called",N14*(N60+M60)/2*IF($C17=TRUE,1-'Get Started 2'!$E10,1),N14*(N85+M85)/2*IF($C17=TRUE,1-'Get Started 2'!$E10,1))),0) -> 122500 | ... CH41: =IFERROR(IF(CH15="committed",CH83*IF($C17=TRUE,1-'Get Started 2'!$E10,1)*CH14+IF(AND(CH4<>1,CH54*IF($C17=TRUE,1-'Get Started 2'!$E10,1)<>0,SUM($G54:CH54)*IF($C17=TRUE,1-'Get Started 2'!$E10,1)<>CF54*IF($C17=TRUE,1-'Get Started 2'!$E10,1)),CH54*IF($C17=TRUE,1-'Get Started 2'!$E10,1)*(CH4-1)*CH14,0),IF(CH15="called",CH14*(CH60+CG60)/2*IF($C17=TRUE,1-'Get Started 2'!$E10,1),CH14*(CH85+CG85)/2*IF($C17=TRUE,1-'Get Started 2'!$E10,1))),0) -> 0
B42: Recycled Capital | D42: sum | E42: =IF(D42="sum",SUM(G42:CH42),IF(D42="final",CH42,IF(D42="initial",G42,IF(D42="average",AVERAGE(G42:CH42),0)))) -> 1042708.3 | G42: =G208 -> 0 | H42: =H208 -> 0 | I42: =I208 -> 0 | J42: =J208 -> 0 | K42: =K208 -> 0 | L42: =L208 -> 0 | M42: =M208 -> 0 | N42: =N208 -> 0 | ... CH42: =CH208 -> 0
B43: Proceeds | D43: sum | E43: =IF(D43="sum",SUM(G43:CH43),IF(D43="final",CH43,IF(D43="initial",G43,IF(D43="average",AVERAGE(G43:CH43),0)))) -> 95669973 | G43: =IF(G4<'Get Started 2'!$H112,0,OFFSET(G37,0,-1*'Get Started 2'!$H112)*'Get Started 2'!$H42*'Get Started 2'!$G112)+IF(G4<'Get Started 2'!$H111,0,OFFSET(G37,0,-1*'Get Started 2'!$H111)*'Get Started 2'!$G42*'Get Started 2'!$G111)+IF(G4<'Get Started 2'!$H110,0,OFFSET(G37,0,-1*'Get Started 2'!$H110)*'Get Started 2'!$F42*'Get Started 2'!$G110)+IF(G4<'Get Started 2'!$H109,0,OFFSET(G37,0,-1*'Get Started 2'!$H109)*'Get Started 2'!$E42*'Get Started 2'!$G109) -> 0 | H43: =IF(H4<'Get Started 2'!$H112,0,OFFSET(H37,0,-1*'Get Started 2'!$H112)*'Get Started 2'!$H42*'Get Started 2'!$G112)+IF(H4<'Get Started 2'!$H111,0,OFFSET(H37,0,-1*'Get Started 2'!$H111)*'Get Started 2'!$G42*'Get Started 2'!$G111)+IF(H4<'Get Started 2'!$H110,0,OFFSET(H37,0,-1*'Get Started 2'!$H110)*'Get Started 2'!$F42*'Get Started 2'!$G110)+IF(H4<'Get Started 2'!$H109,0,OFFSET(H37,0,-1*'Get Started 2'!$H109)*'Get Started 2'!$E42*'Get Started 2'!$G109) -> 0 | I43: =IF(I4<'Get Started 2'!$H112,0,OFFSET(I37,0,-1*'Get Started 2'!$H112)*'Get Started 2'!$H42*'Get Started 2'!$G112)+IF(I4<'Get Started 2'!$H111,0,OFFSET(I37,0,-1*'Get Started 2'!$H111)*'Get Started 2'!$G42*'Get Started 2'!$G111)+IF(I4<'Get Started 2'!$H110,0,OFFSET(I37,0,-1*'Get Started 2'!$H110)*'Get Started 2'!$F42*'Get Started 2'!$G110)+IF(I4<'Get Started 2'!$H109,0,OFFSET(I37,0,-1*'Get Started 2'!$H109)*'Get Started 2'!$E42*'Get Started 2'!$G109) -> 0 | J43: =IF(J4<'Get Started 2'!$H112,0,OFFSET(J37,0,-1*'Get Started 2'!$H112)*'Get Started 2'!$H42*'Get Started 2'!$G112)+IF(J4<'Get Started 2'!$H111,0,OFFSET(J37,0,-1*'Get Started 2'!$H111)*'Get Started 2'!$G42*'Get Started 2'!$G111)+IF(J4<'Get Started 2'!$H110,0,OFFSET(J37,0,-1*'Get Started 2'!$H110)*'Get Started 2'!$F42*'Get Started 2'!$G110)+IF(J4<'Get Started 2'!$H109,0,OFFSET(J37,0,-1*'Get Started 2'!$H109)*'Get Started 2'!$E42*'Get Started 2'!$G109) -> 0 | K43: =IF(K4<'Get Started 2'!$H112,0,OFFSET(K37,0,-1*'Get Started 2'!$H112)*'Get Started 2'!$H42*'Get Started 2'!$G112)+IF(K4<'Get Started 2'!$H111,0,OFFSET(K37,0,-1*'Get Started 2'!$H111)*'Get Started 2'!$G42*'Get Started 2'!$G111)+IF(K4<'Get Started 2'!$H110,0,OFFSET(K37,0,-1*'Get Started 2'!$H110)*'Get Started 2'!$F42*'Get Started 2'!$G110)+IF(K4<'Get Started 2'!$H109,0,OFFSET(K37,0,-1*'Get Started 2'!$H109)*'Get Started 2'!$E42*'Get Started 2'!$G109) -> 0 | L43: =IF(L4<'Get Started 2'!$H112,0,OFFSET(L37,0,-1*'Get Started 2'!$H112)*'Get Started 2'!$H42*'Get Started 2'!$G112)+IF(L4<'Get Started 2'!$H111,0,OFFSET(L37,0,-1*'Get Started 2'!$H111)*'Get Started 2'!$G42*'Get Started 2'!$G111)+IF(L4<'Get Started 2'!$H110,0,OFFSET(L37,0,-1*'Get Started 2'!$H110)*'Get Started 2'!$F42*'Get Started 2'!$G110)+IF(L4<'Get Started 2'!$H109,0,OFFSET(L37,0,-1*'Get Started 2'!$H109)*'Get Started 2'!$E42*'Get Started 2'!$G109) -> 0 | M43: =IF(M4<'Get Started 2'!$H112,0,OFFSET(M37,0,-1*'Get Started 2'!$H112)*'Get Started 2'!$H42*'Get Started 2'!$G112)+IF(M4<'Get Started 2'!$H111,0,OFFSET(M37,0,-1*'Get Started 2'!$H111)*'Get Started 2'!$G42*'Get Started 2'!$G111)+IF(M4<'Get Started 2'!$H110,0,OFFSET(M37,0,-1*'Get Started 2'!$H110)*'Get Started 2'!$F42*'Get Started 2'!$G110)+IF(M4<'Get Started 2'!$H109,0,OFFSET(M37,0,-1*'Get Started 2'!$H109)*'Get Started 2'!$E42*'Get Started 2'!$G109) -> 0 | N43: =IF(N4<'Get Started 2'!$H112,0,OFFSET(N37,0,-1*'Get Started 2'!$H112)*'Get Started 2'!$H42*'Get Started 2'!$G112)+IF(N4<'Get Started 2'!$H111,0,OFFSET(N37,0,-1*'Get Started 2'!$H111)*'Get Started 2'!$G42*'Get Started 2'!$G111)+IF(N4<'Get Started 2'!$H110,0,OFFSET(N37,0,-1*'Get Started 2'!$H110)*'Get Started 2'!$F42*'Get Started 2'!$G110)+IF(N4<'Get Started 2'!$H109,0,OFFSET(N37,0,-1*'Get Started 2'!$H109)*'Get Started 2'!$E42*'Get Started 2'!$G109) -> 0 | ... CH43: =IF(CH4<'Get Started 2'!$H112,0,OFFSET(CH37,0,-1*'Get Started 2'!$H112)*'Get Started 2'!$H42*'Get Started 2'!$G112)+IF(CH4<'Get Started 2'!$H111,0,OFFSET(CH37,0,-1*'Get Started 2'!$H111)*'Get Started 2'!$G42*'Get Started 2'!$G111)+IF(CH4<'Get Started 2'!$H110,0,OFFSET(CH37,0,-1*'Get Started 2'!$H110)*'Get Started 2'!$F42*'Get Started 2'!$G110)+IF(CH4<'Get Started 2'!$H109,0,OFFSET(CH37,0,-1*'Get Started 2'!$H109)*'Get Started 2'!$E42*'Get Started 2'!$G109) -> 0
B44: Preferred Return | D44: sum | E44: =IF(D44="sum",SUM(G44:CH44),IF(D44="final",CH44,IF(D44="initial",G44,IF(D44="average",AVERAGE(G44:CH44),0)))) -> 0 | G44: 0 | H44: 0 | I44: 0 | J44: 0 | K44: 0 | L44: 0 | M44: 0 | N44: 0 | O44: 0 | P44: 0 | Q44: 0 | R44: 0 | S44: 0 | T44: 0 | U44: 0 | V44: 0 | W44: 0 | X44: 0 | Y44: 0 | Z44: 0 | AA44: 0 | AB44: 0 | AC44: 0 | AD44: 0 | AE44: 0 | AF44: 0 | AG44: 0 | AH44: 0 | AI44: 0 | AJ44: 0 | AK44: 0 | AL44: 0 | AM44: 0 | AN44: 0 | AO44: 0 | AP44: 0 | AQ44: 0 | AR44: 0 | AS44: 0 | AT44: 0 | AU44: 0 | AV44: 0 | AW44: 0 | AX44: 0 | AY44: 0 | AZ44: 0 | BA44: 0 | BB44: 0 | BC44: 0 | BD44: 0 | BE44: 0 | BF44: 0 | BG44: 0 | BH44: 0 | BI44: 0 | BJ44: 0 | BK44: 0 | BL44: 0 | BM44: 0 | BN44: 0 | BO44: 0 | BP44: 0 | BQ44: 0 | BR44: 0 | BS44: 0 | BT44: 0 | BU44: 0 | BV44: 0 | BW44: 0 | BX44: 0 | BY44: 0 | BZ44: 0 | CA44: 0 | CB44: 0 | CC44: 0 | CD44: 0 | CE44: 0 | CF44: 0 | CG44: 0 | CH44: 0
B45: GP Catchup | D45: sum | E45: =IF(D45="sum",SUM(G45:CH45),IF(D45="final",CH45,IF(D45="initial",G45,IF(D45="average",AVERAGE(G45:CH45),0)))) -> 0 | G45: 0 | H45: 0 | I45: 0 | J45: 0 | K45: 0 | L45: 0 | M45: 0 | N45: 0 | O45: 0 | P45: 0 | Q45: 0 | R45: 0 | S45: 0 | T45: 0 | U45: 0 | V45: 0 | W45: 0 | X45: 0 | Y45: 0 | Z45: 0 | AA45: 0 | AB45: 0 | AC45: 0 | AD45: 0 | AE45: 0 | AF45: 0 | AG45: 0 | AH45: 0 | AI45: 0 | AJ45: 0 | AK45: 0 | AL45: 0 | AM45: 0 | AN45: 0 | AO45: 0 | AP45: 0 | AQ45: 0 | AR45: 0 | AS45: 0 | AT45: 0 | AU45: 0 | AV45: 0 | AW45: 0 | AX45: 0 | AY45: 0 | AZ45: 0 | BA45: 0 | BB45: 0 | BC45: 0 | BD45: 0 | BE45: 0 | BF45: 0 | BG45: 0 | BH45: 0 | BI45: 0 | BJ45: 0 | BK45: 0 | BL45: 0 | BM45: 0 | BN45: 0 | BO45: 0 | BP45: 0 | BQ45: 0 | BR45: 0 | BS45: 0 | BT45: 0 | BU45: 0 | BV45: 0 | BW45: 0 | BX45: 0 | BY45: 0 | BZ45: 0 | CA45: 0 | CB45: 0 | CC45: 0 | CD45: 0 | CE45: 0 | CF45: 0 | CG45: 0 | CH45: 0
B46: Carried Interest | D46: sum | E46: =IF(D46="sum",SUM(G46:CH46),IF(D46="final",CH46,IF(D46="initial",G46,IF(D46="average",AVERAGE(G46:CH46),0)))) -> 13925453 | G46: =G194 -> 0 | H46: =H194 -> 0 | I46: =I194 -> 0 | J46: =J194 -> 0 | K46: =K194 -> 0 | L46: =L194 -> 0 | M46: =M194 -> 0 | N46: =N194 -> 0 | ... CH46: =CH194 -> 0
B47: Distributions | D47: sum | E47: =IF(D47="sum",SUM(G47:CH47),IF(D47="final",CH47,IF(D47="initial",G47,IF(D47="average",AVERAGE(G47:CH47),0)))) -> 80701812 | G47: =G190+G193-G194 -> 0 | H47: =H190+H193-H194 -> 0 | I47: =I190+I193-I194 -> 0 | J47: =J190+J193-J194 -> 0 | K47: =K190+K193-K194 -> 0 | L47: =L190+L193-L194 -> 0 | M47: =M190+M193-M194 -> 0 | N47: =N190+N193-N194 -> 0 | ... CH47: =CH190+CH193-CH194 -> 0
B48: Writeoffs | D48: sum | E48: =IF(D48="sum",SUM(G48:CH48),IF(D48="final",CH48,IF(D48="initial",G48,IF(D48="average",AVERAGE(G48:CH48),0)))) -> 12513837 | G48: =IF('Get Started 2'!$G112<>0,0,IF(G4<'Get Started 2'!$H112,0,OFFSET(G37,0,-1*'Get Started 2'!$H112)*'Get Started 2'!$H42))+IF('Get Started 2'!$G111<>0,0,IF(G4<'Get Started 2'!$H111,0,OFFSET(G37,0,-1*'Get Started 2'!$H111)*'Get Started 2'!$G42))+IF('Get Started 2'!$G110<>0,0,IF(G4<'Get Started 2'!$H110,0,OFFSET(G37,0,-1*'Get Started 2'!$H110)*'Get Started 2'!$F42))+IF('Get Started 2'!$G109<>0,0,IF(G4<'Get Started 2'!$H109,0,OFFSET(G37,0,-1*'Get Started 2'!$H109)*'Get Started 2'!$E42)) -> 0 | H48: =IF('Get Started 2'!$G112<>0,0,IF(H4<'Get Started 2'!$H112,0,OFFSET(H37,0,-1*'Get Started 2'!$H112)*'Get Started 2'!$H42))+IF('Get Started 2'!$G111<>0,0,IF(H4<'Get Started 2'!$H111,0,OFFSET(H37,0,-1*'Get Started 2'!$H111)*'Get Started 2'!$G42))+IF('Get Started 2'!$G110<>0,0,IF(H4<'Get Started 2'!$H110,0,OFFSET(H37,0,-1*'Get Started 2'!$H110)*'Get Started 2'!$F42))+IF('Get Started 2'!$G109<>0,0,IF(H4<'Get Started 2'!$H109,0,OFFSET(H37,0,-1*'Get Started 2'!$H109)*'Get Started 2'!$E42)) -> 0 | I48: =IF('Get Started 2'!$G112<>0,0,IF(I4<'Get Started 2'!$H112,0,OFFSET(I37,0,-1*'Get Started 2'!$H112)*'Get Started 2'!$H42))+IF('Get Started 2'!$G111<>0,0,IF(I4<'Get Started 2'!$H111,0,OFFSET(I37,0,-1*'Get Started 2'!$H111)*'Get Started 2'!$G42))+IF('Get Started 2'!$G110<>0,0,IF(I4<'Get Started 2'!$H110,0,OFFSET(I37,0,-1*'Get Started 2'!$H110)*'Get Started 2'!$F42))+IF('Get Started 2'!$G109<>0,0,IF(I4<'Get Started 2'!$H109,0,OFFSET(I37,0,-1*'Get Started 2'!$H109)*'Get Started 2'!$E42)) -> 0 | J48: =IF('Get Started 2'!$G112<>0,0,IF(J4<'Get Started 2'!$H112,0,OFFSET(J37,0,-1*'Get Started 2'!$H112)*'Get Started 2'!$H42))+IF('Get Started 2'!$G111<>0,0,IF(J4<'Get Started 2'!$H111,0,OFFSET(J37,0,-1*'Get Started 2'!$H111)*'Get Started 2'!$G42))+IF('Get Started 2'!$G110<>0,0,IF(J4<'Get Started 2'!$H110,0,OFFSET(J37,0,-1*'Get Started 2'!$H110)*'Get Started 2'!$F42))+IF('Get Started 2'!$G109<>0,0,IF(J4<'Get Started 2'!$H109,0,OFFSET(J37,0,-1*'Get Started 2'!$H109)*'Get Started 2'!$E42)) -> 0 | K48: =IF('Get Started 2'!$G112<>0,0,IF(K4<'Get Started 2'!$H112,0,OFFSET(K37,0,-1*'Get Started 2'!$H112)*'Get Started 2'!$H42))+IF('Get Started 2'!$G111<>0,0,IF(K4<'Get Started 2'!$H111,0,OFFSET(K37,0,-1*'Get Started 2'!$H111)*'Get Started 2'!$G42))+IF('Get Started 2'!$G110<>0,0,IF(K4<'Get Started 2'!$H110,0,OFFSET(K37,0,-1*'Get Started 2'!$H110)*'Get Started 2'!$F42))+IF('Get Started 2'!$G109<>0,0,IF(K4<'Get Started 2'!$H109,0,OFFSET(K37,0,-1*'Get Started 2'!$H109)*'Get Started 2'!$E42)) -> 0 | L48: =IF('Get Started 2'!$G112<>0,0,IF(L4<'Get Started 2'!$H112,0,OFFSET(L37,0,-1*'Get Started 2'!$H112)*'Get Started 2'!$H42))+IF('Get Started 2'!$G111<>0,0,IF(L4<'Get Started 2'!$H111,0,OFFSET(L37,0,-1*'Get Started 2'!$H111)*'Get Started 2'!$G42))+IF('Get Started 2'!$G110<>0,0,IF(L4<'Get Started 2'!$H110,0,OFFSET(L37,0,-1*'Get Started 2'!$H110)*'Get Started 2'!$F42))+IF('Get Started 2'!$G109<>0,0,IF(L4<'Get Started 2'!$H109,0,OFFSET(L37,0,-1*'Get Started 2'!$H109)*'Get Started 2'!$E42)) -> 0 | M48: =IF('Get Started 2'!$G112<>0,0,IF(M4<'Get Started 2'!$H112,0,OFFSET(M37,0,-1*'Get Started 2'!$H112)*'Get Started 2'!$H42))+IF('Get Started 2'!$G111<>0,0,IF(M4<'Get Started 2'!$H111,0,OFFSET(M37,0,-1*'Get Started 2'!$H111)*'Get Started 2'!$G42))+IF('Get Started 2'!$G110<>0,0,IF(M4<'Get Started 2'!$H110,0,OFFSET(M37,0,-1*'Get Started 2'!$H110)*'Get Started 2'!$F42))+IF('Get Started 2'!$G109<>0,0,IF(M4<'Get Started 2'!$H109,0,OFFSET(M37,0,-1*'Get Started 2'!$H109)*'Get Started 2'!$E42)) -> 0 | N48: =IF('Get Started 2'!$G112<>0,0,IF(N4<'Get Started 2'!$H112,0,OFFSET(N37,0,-1*'Get Started 2'!$H112)*'Get Started 2'!$H42))+IF('Get Started 2'!$G111<>0,0,IF(N4<'Get Started 2'!$H111,0,OFFSET(N37,0,-1*'Get Started 2'!$H111)*'Get Started 2'!$G42))+IF('Get Started 2'!$G110<>0,0,IF(N4<'Get Started 2'!$H110,0,OFFSET(N37,0,-1*'Get Started 2'!$H110)*'Get Started 2'!$F42))+IF('Get Started 2'!$G109<>0,0,IF(N4<'Get Started 2'!$H109,0,OFFSET(N37,0,-1*'Get Started 2'!$H109)*'Get Started 2'!$E42)) -> 0 | ... CH48: =IF('Get Started 2'!$G112<>0,0,IF(CH4<'Get Started 2'!$H112,0,OFFSET(CH37,0,-1*'Get Started 2'!$H112)*'Get Started 2'!$H42))+IF('Get Started 2'!$G111<>0,0,IF(CH4<'Get Started 2'!$H111,0,OFFSET(CH37,0,-1*'Get Started 2'!$H111)*'Get Started 2'!$G42))+IF('Get Started 2'!$G110<>0,0,IF(CH4<'Get Started 2'!$H110,0,OFFSET(CH37,0,-1*'Get Started 2'!$H110)*'Get Started 2'!$F42))+IF('Get Started 2'!$G109<>0,0,IF(CH4<'Get Started 2'!$H109,0,OFFSET(CH37,0,-1*'Get Started 2'!$H109)*'Get Started 2'!$E42)) -> 0
B49: Invested Capital Exited | C49: value of the original capital invested, that exits (proceeds > 0) | D49: sum | E49: =IF(D49="sum",SUM(G49:CH49),IF(D49="final",CH49,IF(D49="initial",G49,IF(D49="average",AVERAGE(G49:CH49),0)))) -> 7778871.5 | G49: =IF('Get Started 2'!$G112=0,0,IF(G4<'Get Started 2'!$H112,0,OFFSET(G37,0,-1*'Get Started 2'!$H112)*'Get Started 2'!$H42))+IF('Get Started 2'!$G111=0,0,IF(G4<'Get Started 2'!$H111,0,OFFSET(G37,0,-1*'Get Started 2'!$H111)*'Get Started 2'!$G42))+IF('Get Started 2'!$G110=0,0,IF(G4<'Get Started 2'!$H110,0,OFFSET(G37,0,-1*'Get Started 2'!$H110)*'Get Started 2'!$F42))+IF('Get Started 2'!$G109=0,0,IF(G4<'Get Started 2'!$H109,0,OFFSET(G37,0,-1*'Get Started 2'!$H109)*'Get Started 2'!$E42)) -> 0 | H49: =IF('Get Started 2'!$G112=0,0,IF(H4<'Get Started 2'!$H112,0,OFFSET(H37,0,-1*'Get Started 2'!$H112)*'Get Started 2'!$H42))+IF('Get Started 2'!$G111=0,0,IF(H4<'Get Started 2'!$H111,0,OFFSET(H37,0,-1*'Get Started 2'!$H111)*'Get Started 2'!$G42))+IF('Get Started 2'!$G110=0,0,IF(H4<'Get Started 2'!$H110,0,OFFSET(H37,0,-1*'Get Started 2'!$H110)*'Get Started 2'!$F42))+IF('Get Started 2'!$G109=0,0,IF(H4<'Get Started 2'!$H109,0,OFFSET(H37,0,-1*'Get Started 2'!$H109)*'Get Started 2'!$E42)) -> 0 | I49: =IF('Get Started 2'!$G112=0,0,IF(I4<'Get Started 2'!$H112,0,OFFSET(I37,0,-1*'Get Started 2'!$H112)*'Get Started 2'!$H42))+IF('Get Started 2'!$G111=0,0,IF(I4<'Get Started 2'!$H111,0,OFFSET(I37,0,-1*'Get Started 2'!$H111)*'Get Started 2'!$G42))+IF('Get Started 2'!$G110=0,0,IF(I4<'Get Started 2'!$H110,0,OFFSET(I37,0,-1*'Get Started 2'!$H110)*'Get Started 2'!$F42))+IF('Get Started 2'!$G109=0,0,IF(I4<'Get Started 2'!$H109,0,OFFSET(I37,0,-1*'Get Started 2'!$H109)*'Get Started 2'!$E42)) -> 0 | J49: =IF('Get Started 2'!$G112=0,0,IF(J4<'Get Started 2'!$H112,0,OFFSET(J37,0,-1*'Get Started 2'!$H112)*'Get Started 2'!$H42))+IF('Get Started 2'!$G111=0,0,IF(J4<'Get Started 2'!$H111,0,OFFSET(J37,0,-1*'Get Started 2'!$H111)*'Get Started 2'!$G42))+IF('Get Started 2'!$G110=0,0,IF(J4<'Get Started 2'!$H110,0,OFFSET(J37,0,-1*'Get Started 2'!$H110)*'Get Started 2'!$F42))+IF('Get Started 2'!$G109=0,0,IF(J4<'Get Started 2'!$H109,0,OFFSET(J37,0,-1*'Get Started 2'!$H109)*'Get Started 2'!$E42)) -> 0 | K49: =IF('Get Started 2'!$G112=0,0,IF(K4<'Get Started 2'!$H112,0,OFFSET(K37,0,-1*'Get Started 2'!$H112)*'Get Started 2'!$H42))+IF('Get Started 2'!$G111=0,0,IF(K4<'Get Started 2'!$H111,0,OFFSET(K37,0,-1*'Get Started 2'!$H111)*'Get Started 2'!$G42))+IF('Get Started 2'!$G110=0,0,IF(K4<'Get Started 2'!$H110,0,OFFSET(K37,0,-1*'Get Started 2'!$H110)*'Get Started 2'!$F42))+IF('Get Started 2'!$G109=0,0,IF(K4<'Get Started 2'!$H109,0,OFFSET(K37,0,-1*'Get Started 2'!$H109)*'Get Started 2'!$E42)) -> 0 | L49: =IF('Get Started 2'!$G112=0,0,IF(L4<'Get Started 2'!$H112,0,OFFSET(L37,0,-1*'Get Started 2'!$H112)*'Get Started 2'!$H42))+IF('Get Started 2'!$G111=0,0,IF(L4<'Get Started 2'!$H111,0,OFFSET(L37,0,-1*'Get Started 2'!$H111)*'Get Started 2'!$G42))+IF('Get Started 2'!$G110=0,0,IF(L4<'Get Started 2'!$H110,0,OFFSET(L37,0,-1*'Get Started 2'!$H110)*'Get Started 2'!$F42))+IF('Get Started 2'!$G109=0,0,IF(L4<'Get Started 2'!$H109,0,OFFSET(L37,0,-1*'Get Started 2'!$H109)*'Get Started 2'!$E42)) -> 0 | M49: =IF('Get Started 2'!$G112=0,0,IF(M4<'Get Started 2'!$H112,0,OFFSET(M37,0,-1*'Get Started 2'!$H112)*'Get Started 2'!$H42))+IF('Get Started 2'!$G111=0,0,IF(M4<'Get Started 2'!$H111,0,OFFSET(M37,0,-1*'Get Started 2'!$H111)*'Get Started 2'!$G42))+IF('Get Started 2'!$G110=0,0,IF(M4<'Get Started 2'!$H110,0,OFFSET(M37,0,-1*'Get Started 2'!$H110)*'Get Started 2'!$F42))+IF('Get Started 2'!$G109=0,0,IF(M4<'Get Started 2'!$H109,0,OFFSET(M37,0,-1*'Get Started 2'!$H109)*'Get Started 2'!$E42)) -> 0 | N49: =IF('Get Started 2'!$G112=0,0,IF(N4<'Get Started 2'!$H112,0,OFFSET(N37,0,-1*'Get Started 2'!$H112)*'Get Started 2'!$H42))+IF('Get Started 2'!$G111=0,0,IF(N4<'Get Started 2'!$H111,0,OFFSET(N37,0,-1*'Get Started 2'!$H111)*'Get Started 2'!$G42))+IF('Get Started 2'!$G110=0,0,IF(N4<'Get Started 2'!$H110,0,OFFSET(N37,0,-1*'Get Started 2'!$H110)*'Get Started 2'!$F42))+IF('Get Started 2'!$G109=0,0,IF(N4<'Get Started 2'!$H109,0,OFFSET(N37,0,-1*'Get Started 2'!$H109)*'Get Started 2'!$E42)) -> 0 | ... CH49: =IF('Get Started 2'!$G112=0,0,IF(CH4<'Get Started 2'!$H112,0,OFFSET(CH37,0,-1*'Get Started 2'!$H112)*'Get Started 2'!$H42))+IF('Get Started 2'!$G111=0,0,IF(CH4<'Get Started 2'!$H111,0,OFFSET(CH37,0,-1*'Get Started 2'!$H111)*'Get Started 2'!$G42))+IF('Get Started 2'!$G110=0,0,IF(CH4<'Get Started 2'!$H110,0,OFFSET(CH37,0,-1*'Get Started 2'!$H110)*'Get Started 2'!$F42))+IF('Get Started 2'!$G109=0,0,IF(CH4<'Get Started 2'!$H109,0,OFFSET(CH37,0,-1*'Get Started 2'!$H109)*'Get Started 2'!$E42)) -> 0
B50: Change in Invested Capital | C50: value of the original capital invested. goes up when investments are made, down when investments are written off, and down when investments exit | D50: sum | E50: =IF(D50="sum",SUM(G50:CH50),IF(D50="final",CH50,IF(D50="initial",G50,IF(D50="average",AVERAGE(G50:CH50),0)))) -> -5.2677933e-09 | G50: =G38+ABS(G48)*-1+ABS(G49)*-1 -> 1203125 | H50: =H38+ABS(H48)*-1+ABS(H49)*-1 -> 1203125 | I50: =I38+ABS(I48)*-1+ABS(I49)*-1 -> 1203125 | J50: =J38+ABS(J48)*-1+ABS(J49)*-1 -> 1203125 | K50: =K38+ABS(K48)*-1+ABS(K49)*-1 -> 1203125 | L50: =L38+ABS(L48)*-1+ABS(L49)*-1 -> 1203125 | M50: =M38+ABS(M48)*-1+ABS(M49)*-1 -> 1203125 | N50: =N38+ABS(N48)*-1+ABS(N49)*-1 -> 1203125 | ... CH50: =CH38+ABS(CH48)*-1+ABS(CH49)*-1 -> 0
B51: Change in Unrealized Gain (Loss) | C51: estimated from the gross IRR and accounting for value of invested capital and exits; please note this an estimate created as the model does not have sufficient tracking of intermediate changes in value of the portfolio to actually do this accurately, and you may alter the logic behind this if you want to change the estimate | D51: sum | E51: =IF(D51="sum",SUM(G51:CH51),IF(D51="final",CH51,IF(D51="initial",G51,IF(D51="average",AVERAGE(G51:CH51),0)))) -> 0 | G51: =IF(G76=$E76,SUM(F51:$G51)*-1,IF(G77=0,0,IF(G4<>1,(F79+G50/2)*((1+'Get Started 2'!$E129)^(1/4)-1)-G49*(1+((1+'Get Started 2'!$E129)^(1/4)-1))^('Get Started 2'!$H113-1),0))) -> 0 | H51: =IF(H76=$E76,SUM(G51:$G51)*-1,IF(H77=0,0,IF(H4<>1,(G79+H50/2)*((1+'Get Started 2'!$E129)^(1/4)-1)-H49*(1+((1+'Get Started 2'!$E129)^(1/4)-1))^('Get Started 2'!$H113-1),0))) -> 0 | I51: =IF(I76=$E76,SUM($G51:H51)*-1,IF(I77=0,0,IF(I4<>1,(H79+I50/2)*((1+'Get Started 2'!$E129)^(1/4)-1)-I49*(1+((1+'Get Started 2'!$E129)^(1/4)-1))^('Get Started 2'!$H113-1),0))) -> 0 | J51: =IF(J76=$E76,SUM($G51:I51)*-1,IF(J77=0,0,IF(J4<>1,(I79+J50/2)*((1+'Get Started 2'!$E129)^(1/4)-1)-J49*(1+((1+'Get Started 2'!$E129)^(1/4)-1))^('Get Started 2'!$H113-1),0))) -> 0 | K51: =IF(K76=$E76,SUM($G51:J51)*-1,IF(K77=0,0,IF(K4<>1,(J79+K50/2)*((1+'Get Started 2'!$E129)^(1/4)-1)-K49*(1+((1+'Get Started 2'!$E129)^(1/4)-1))^('Get Started 2'!$H113-1),0))) -> 0 | L51: =IF(L76=$E76,SUM($G51:K51)*-1,IF(L77=0,0,IF(L4<>1,(K79+L50/2)*((1+'Get Started 2'!$E129)^(1/4)-1)-L49*(1+((1+'Get Started 2'!$E129)^(1/4)-1))^('Get Started 2'!$H113-1),0))) -> 0 | M51: =IF(M76=$E76,SUM($G51:L51)*-1,IF(M77=0,0,IF(M4<>1,(L79+M50/2)*((1+'Get Started 2'!$E129)^(1/4)-1)-M49*(1+((1+'Get Started 2'!$E129)^(1/4)-1))^('Get Started 2'!$H113-1),0))) -> 0 | N51: =IF(N76=$E76,SUM($G51:M51)*-1,IF(N77=0,0,IF(N4<>1,(M79+N50/2)*((1+'Get Started 2'!$E129)^(1/4)-1)-N49*(1+((1+'Get Started 2'!$E129)^(1/4)-1))^('Get Started 2'!$H113-1),0))) -> 0 | O51: =IF(O76=$E76,SUM($G51:N51)*-1,IF(O77=0,0,IF(O4<>1,(N79+O50/2)*((1+'Get Started 2'!$E129)^(1/4)-1)-O49*(1+((1+'Get Started 2'!$E129)^(1/4)-1))^('Get Started 2'!$H113-1),0))) -> 965137.17 | P51: =IF(P76=$E76,SUM($G51:O51)*-1,IF(P77=0,0,IF(P4<>1,(O79+P50/2)*((1+'Get Started 2'!$E129)^(1/4)-1)-P49*(1+((1+'Get Started 2'!$E129)^(1/4)-1))^('Get Started 2'!$H113-1),0))) -> 1010301.3 | ... CH51: =IF(CH76=$E76,SUM($G51:CG51)*-1,IF(CH77=0,0,IF(CH4<>1,(CG79+CH50/2)*((1+'Get Started 2'!$E129)^(1/4)-1)-CH49*(1+((1+'Get Started 2'!$E129)^(1/4)-1))^('Get Started 2'!$H113-1),0))) -> 0
B52: Change in Residual Value | C52: change in invested capital + change in residual value | D52: sum | E52: =IF(D52="sum",SUM(G52:CH52),IF(D52="final",CH52,IF(D52="initial",G52,IF(D52="average",AVERAGE(G52:CH52),0)))) -> -4.6566129e-10 | G52: =G51+G50 -> 1203125 | H52: =H51+H50 -> 1203125 | I52: =I51+I50 -> 1203125 | J52: =J51+J50 -> 1203125 | K52: =K51+K50 -> 1203125 | L52: =L51+L50 -> 1203125 | M52: =M51+M50 -> 1203125 | N52: =N51+N50 -> 1203125 | ... CH52: =CH51+CH50 -> 0
B53: Change in Undrawn Capital Commitments | D53: sum | E53: =IF(D53="sum",SUM(G53:CH53),IF(D53="final",CH53,IF(D53="initial",G53,IF(D53="average",AVERAGE(G53:CH53),0)))) -> 0 | G53: =G30-G31 -> 23555625 | H53: =H30-H31 -> -1344375 | I53: =I30-I31 -> -1344375 | J53: =J30-J31 -> -1344375 | K53: =K30-K31 -> -1344375 | L53: =L30-L31 -> -1344375 | M53: =M30-M31 -> -1344375 | N53: =N30-N31 -> -1344375 | ... CH53: =CH30-CH31 -> 0
B54: Committed Capital from LPs | D54: sum | E54: =IF(D54="sum",SUM(G54:CH54),IF(D54="final",CH54,IF(D54="initial",G54,IF(D54="average",AVERAGE(G54:CH54),0)))) -> 25000000 | G54: =IF($C16=TRUE,G30*(1-'Get Started 2'!$E10),G30) -> 25000000 | H54: =IF($C16=TRUE,H30*(1-'Get Started 2'!$E10),H30) -> 0 | I54: =IF($C16=TRUE,I30*(1-'Get Started 2'!$E10),I30) -> 0 | J54: =IF($C16=TRUE,J30*(1-'Get Started 2'!$E10),J30) -> 0 | K54: =IF($C16=TRUE,K30*(1-'Get Started 2'!$E10),K30) -> 0 | L54: =IF($C16=TRUE,L30*(1-'Get Started 2'!$E10),L30) -> 0 | M54: =IF($C16=TRUE,M30*(1-'Get Started 2'!$E10),M30) -> 0 | N54: =IF($C16=TRUE,N30*(1-'Get Started 2'!$E10),N30) -> 0 | ... CH54: =IF($C16=TRUE,CH30*(1-'Get Started 2'!$E10),CH30) -> 0
B55: Called Capital from LPs | D55: sum | E55: =IF(D55="sum",SUM(G55:CH55),IF(D55="final",CH55,IF(D55="initial",G55,IF(D55="average",AVERAGE(G55:CH55),0)))) -> 25000000 | G55: =IF($C16=TRUE,G31*(1-'Get Started 2'!$E10),G31) -> 1444375 | H55: =IF($C16=TRUE,H31*(1-'Get Started 2'!$E10),H31) -> 1344375 | I55: =IF($C16=TRUE,I31*(1-'Get Started 2'!$E10),I31) -> 1344375 | J55: =IF($C16=TRUE,J31*(1-'Get Started 2'!$E10),J31) -> 1344375 | K55: =IF($C16=TRUE,K31*(1-'Get Started 2'!$E10),K31) -> 1344375 | L55: =IF($C16=TRUE,L31*(1-'Get Started 2'!$E10),L31) -> 1344375 | M55: =IF($C16=TRUE,M31*(1-'Get Started 2'!$E10),M31) -> 1344375 | N55: =IF($C16=TRUE,N31*(1-'Get Started 2'!$E10),N31) -> 1344375 | ... CH55: =IF($C16=TRUE,CH31*(1-'Get Started 2'!$E10),CH31) -> 0
B56: =B50&", from LPs" -> Change in Invested Capital, from LPs | D56: sum | E56: =IF(D56="sum",SUM(G56:CH56),IF(D56="final",CH56,IF(D56="initial",G56,IF(D56="average",AVERAGE(G56:CH56),0)))) -> -5.2677933e-09 | G56: =IF($C16=TRUE,G50*(1-'Get Started 2'!$E10),G50) -> 1203125 | H56: =IF($C16=TRUE,H50*(1-'Get Started 2'!$E10),H50) -> 1203125 | I56: =IF($C16=TRUE,I50*(1-'Get Started 2'!$E10),I50) -> 1203125 | J56: =IF($C16=TRUE,J50*(1-'Get Started 2'!$E10),J50) -> 1203125 | K56: =IF($C16=TRUE,K50*(1-'Get Started 2'!$E10),K50) -> 1203125 | L56: =IF($C16=TRUE,L50*(1-'Get Started 2'!$E10),L50) -> 1203125 | M56: =IF($C16=TRUE,M50*(1-'Get Started 2'!$E10),M50) -> 1203125 | N56: =IF($C16=TRUE,N50*(1-'Get Started 2'!$E10),N50) -> 1203125 | ... CH56: =IF($C16=TRUE,CH50*(1-'Get Started 2'!$E10),CH50) -> 0
B57: Distributions to LPs | D57: sum | E57: =IF(D57="sum",SUM(G57:CH57),IF(D57="final",CH57,IF(D57="initial",G57,IF(D57="average",AVERAGE(G57:CH57),0)))) -> 79087776 | G57: =G47-G58+G46+G45 -> 0 | H57: =H47-H58+H46+H45 -> 0 | I57: =I47-I58+I46+I45 -> 0 | J57: =J47-J58+J46+J45 -> 0 | K57: =K47-K58+K46+K45 -> 0 | L57: =L47-L58+L46+L45 -> 0 | M57: =M47-M58+M46+M45 -> 0 | N57: =N47-N58+N46+N45 -> 0 | ... CH57: =CH47-CH58+CH46+CH45 -> 0
B58: Distributions to GPs | D58: sum | E58: =IF(D58="sum",SUM(G58:CH58),IF(D58="final",CH58,IF(D58="initial",G58,IF(D58="average",AVERAGE(G58:CH58),0)))) -> 15539489 | G58: =IF($C16=TRUE,G46+G45,G46+G45+G47*'Get Started 2'!$E10) -> 0 | H58: =IF($C16=TRUE,H46+H45,H46+H45+H47*'Get Started 2'!$E10) -> 0 | I58: =IF($C16=TRUE,I46+I45,I46+I45+I47*'Get Started 2'!$E10) -> 0 | J58: =IF($C16=TRUE,J46+J45,J46+J45+J47*'Get Started 2'!$E10) -> 0 | K58: =IF($C16=TRUE,K46+K45,K46+K45+K47*'Get Started 2'!$E10) -> 0 | L58: =IF($C16=TRUE,L46+L45,L46+L45+L47*'Get Started 2'!$E10) -> 0 | M58: =IF($C16=TRUE,M46+M45,M46+M45+M47*'Get Started 2'!$E10) -> 0 | N58: =IF($C16=TRUE,N46+N45,N46+N45+N47*'Get Started 2'!$E10) -> 0 | ... CH58: =IF($C16=TRUE,CH46+CH45,CH46+CH45+CH47*'Get Started 2'!$E10) -> 0
B59: ="Cumulative "&B30 -> Cumulative Committed Capital | D59: final | E59: =IF(D59="sum",SUM(G59:CH59),IF(D59="final",CH59,IF(D59="initial",G59,IF(D59="average",AVERAGE(G59:CH59),0)))) -> 25000000 | G59: =F59+G30 -> 25000000 | H59: =G59+H30 -> 25000000 | I59: =H59+I30 -> 25000000 | J59: =I59+J30 -> 25000000 | K59: =J59+K30 -> 25000000 | L59: =K59+L30 -> 25000000 | M59: =L59+M30 -> 25000000 | N59: =M59+N30 -> 25000000 | ... CH59: =CG59+CH30 -> 25000000
B60: ="Cumulative "&B31 -> Cumulative Called Capital | D60: final | E60: =IF(D60="sum",SUM(G60:CH60),IF(D60="final",CH60,IF(D60="initial",G60,IF(D60="average",AVERAGE(G60:CH60),0)))) -> 25000000 | G60: =F60+G31 -> 1444375 | H60: =G60+H31 -> 2788750 | I60: =H60+I31 -> 4133125 | J60: =I60+J31 -> 5477500 | K60: =J60+K31 -> 6821875 | L60: =K60+L31 -> 8166250 | M60: =L60+M31 -> 9510625 | N60: =M60+N31 -> 10855000 | ... CH60: =CG60+CH31 -> 25000000
B61: ="Cumulative "&B32 -> Cumulative Manual Investments | D61: final | E61: =IF(D61="sum",SUM(G61:CH61),IF(D61="final",CH61,IF(D61="initial",G61,IF(D61="average",AVERAGE(G61:CH61),0)))) -> 0 | G61: =F61+G32 -> 0 | H61: =G61+H32 -> 0 | I61: =H61+I32 -> 0 | J61: =I61+J32 -> 0 | K61: =J61+K32 -> 0 | L61: =K61+L32 -> 0 | M61: =L61+M32 -> 0 | N61: =M61+N32 -> 0 | ... CH61: =CG61+CH32 -> 0
B62: ="Cumulative "&B33 -> Cumulative New Investments | D62: final | E62: =IF(D62="sum",SUM(G62:CH62),IF(D62="final",CH62,IF(D62="initial",G62,IF(D62="average",AVERAGE(G62:CH62),0)))) -> 20292708 | G62: =F62+G33 -> 1203125 | H62: =G62+H33 -> 2406250 | I62: =H62+I33 -> 3609375 | J62: =I62+J33 -> 4812500 | K62: =J62+K33 -> 6015625 | L62: =K62+L33 -> 7218750 | M62: =L62+M33 -> 8421875 | N62: =M62+N33 -> 9625000 | ... CH62: =CG62+CH33 -> 20292708
B63: ="Cumulative "&B34 -> Cumulative Prorata Opportunities | D63: final | E63: =IF(D63="sum",SUM(G63:CH63),IF(D63="final",CH63,IF(D63="initial",G63,IF(D63="average",AVERAGE(G63:CH63),0)))) -> 0 | G63: =F63+G34 -> 0 | H63: =G63+H34 -> 0 | I63: =H63+I34 -> 0 | J63: =I63+J34 -> 0 | K63: =J63+K34 -> 0 | L63: =K63+L34 -> 0 | M63: =L63+M34 -> 0 | N63: =M63+N34 -> 0 | ... CH63: =CG63+CH34 -> 0
B64: ="Cumulative "&B35 -> Cumulative Reserves for Follow on | D64: final | E64: =IF(D64="sum",SUM(G64:CH64),IF(D64="final",CH64,IF(D64="initial",G64,IF(D64="average",AVERAGE(G64:CH64),0)))) -> 0 | G64: =F64+G35 -> 0 | H64: =G64+H35 -> 0 | I64: =H64+I35 -> 0 | J64: =I64+J35 -> 0 | K64: =J64+K35 -> 0 | L64: =K64+L35 -> 0 | M64: =L64+M35 -> 0 | N64: =M64+N35 -> 0 | ... CH64: =CG64+CH35 -> 0
B65: ="Cumulative "&B36 -> Cumulative Follow on Investments | D65: final | E65: =IF(D65="sum",SUM(G65:CH65),IF(D65="final",CH65,IF(D65="initial",G65,IF(D65="average",AVERAGE(G65:CH65),0)))) -> 0 | G65: =F65+G36 -> 0 | H65: =G65+H36 -> 0 | I65: =H65+I36 -> 0 | J65: =I65+J36 -> 0 | K65: =J65+K36 -> 0 | L65: =K65+L36 -> 0 | M65: =L65+M36 -> 0 | N65: =M65+N36 -> 0 | ... CH65: =CG65+CH36 -> 0
B66: ="Cumulative "&B37 -> Cumulative Total Investments, by cohort of New Investments | D66: final | E66: =IF(D66="sum",SUM(G66:CH66),IF(D66="final",CH66,IF(D66="initial",G66,IF(D66="average",AVERAGE(G66:CH66),0)))) -> 20292708 | G66: =F66+G37 -> 1203125 | H66: =G66+H37 -> 2406250 | I66: =H66+I37 -> 3609375 | J66: =I66+J37 -> 4812500 | K66: =J66+K37 -> 6015625 | L66: =K66+L37 -> 7218750 | M66: =L66+M37 -> 8421875 | N66: =M66+N37 -> 9625000 | ... CH66: =CG66+CH37 -> 20292708
B67: ="Cumulative "&B38 -> Cumulative Total Investments | D67: final | E67: =IF(D67="sum",SUM(G67:CH67),IF(D67="final",CH67,IF(D67="initial",G67,IF(D67="average",AVERAGE(G67:CH67),0)))) -> 20292708 | G67: =F67+G38 -> 1203125 | H67: =G67+H38 -> 2406250 | I67: =H67+I38 -> 3609375 | J67: =I67+J38 -> 4812500 | K67: =J67+K38 -> 6015625 | L67: =K67+L38 -> 7218750 | M67: =L67+M38 -> 8421875 | N67: =M67+N38 -> 9625000 | ... CH67: =CG67+CH38 -> 20292708
B68: ="Cumulative "&B39 -> Cumulative Organizational Expenses | D68: final | E68: =IF(D68="sum",SUM(G68:CH68),IF(D68="final",CH68,IF(D68="initial",G68,IF(D68="average",AVERAGE(G68:CH68),0)))) -> 100000 | G68: =F68+G39 -> 100000 | H68: =G68+H39 -> 100000 | I68: =H68+I39 -> 100000 | J68: =I68+J39 -> 100000 | K68: =J68+K39 -> 100000 | L68: =K68+L39 -> 100000 | M68: =L68+M39 -> 100000 | N68: =M68+N39 -> 100000 | ... CH68: =CG68+CH39 -> 100000
B69: ="Cumulative "&B40 -> Cumulative Operational Expenses | D69: final | E69: =IF(D69="sum",SUM(G69:CH69),IF(D69="final",CH69,IF(D69="initial",G69,IF(D69="average",AVERAGE(G69:CH69),0)))) -> 750000 | G69: =F69+G40 -> 18750 | H69: =G69+H40 -> 37500 | I69: =H69+I40 -> 56250 | J69: =I69+J40 -> 75000 | K69: =J69+K40 -> 93750 | L69: =K69+L40 -> 112500 | M69: =L69+M40 -> 131250 | N69: =M69+N40 -> 150000 | ... CH69: =CG69+CH40 -> 750000
B70: ="Cumulative "&B41 -> Cumulative Management Fees | D70: final | E70: =IF(D70="sum",SUM(G70:CH70),IF(D70="final",CH70,IF(D70="initial",G70,IF(D70="average",AVERAGE(G70:CH70),0)))) -> 4900000 | G70: =F70+G41 -> 122500 | H70: =G70+H41 -> 245000 | I70: =H70+I41 -> 367500 | J70: =I70+J41 -> 490000 | K70: =J70+K41 -> 612500 | L70: =K70+L41 -> 735000 | M70: =L70+M41 -> 857500 | N70: =M70+N41 -> 980000 | ... CH70: =CG70+CH41 -> 4900000
... B80: ="Cumulative "&B51 -> Cumulative Change in Unrealized Gain (Loss) | D80: final | E80: =IF(D80="sum",SUM(G80:CH80),IF(D80="final",CH80,IF(D80="initial",G80,IF(D80="average",AVERAGE(G80:CH80),0)))) -> 0 | G80: =F80+G51 -> 0 | H80: =G80+H51 -> 0 | I80: =H80+I51 -> 0 | J80: =I80+J51 -> 0 | K80: =J80+K51 -> 0 | L80: =K80+L51 -> 0 | M80: =L80+M51 -> 0 | N80: =M80+N51 -> 0 | ... CH80: =CG80+CH51 -> 0
B81: ="Cumulative "&B52 -> Cumulative Change in Residual Value | C81: equal to residual value at end of period. also known as net asset value | D81: final | E81: =IF(D81="sum",SUM(G81:CH81),IF(D81="final",CH81,IF(D81="initial",G81,IF(D81="average",AVERAGE(G81:CH81),0)))) -> 0 | G81: =F81+G52 -> 1203125 | H81: =G81+H52 -> 2406250 | I81: =H81+I52 -> 3609375 | J81: =I81+J52 -> 4812500 | K81: =J81+K52 -> 6015625 | L81: =K81+L52 -> 7218750 | M81: =L81+M52 -> 8421875 | N81: =M81+N52 -> 9625000 | ... CH81: =CG81+CH52 -> 0
B82: ="Cumulative "&B53 -> Cumulative Change in Undrawn Capital Commitments | D82: final | E82: =IF(D82="sum",SUM(G82:CH82),IF(D82="final",CH82,IF(D82="initial",G82,IF(D82="average",AVERAGE(G82:CH82),0)))) -> 0 | G82: =F82+G53 -> 23555625 | H82: =G82+H53 -> 22211250 | I82: =H82+I53 -> 20866875 | J82: =I82+J53 -> 19522500 | K82: =J82+K53 -> 18178125 | L82: =K82+L53 -> 16833750 | M82: =L82+M53 -> 15489375 | N82: =M82+N53 -> 14145000 | ... CH82: =CG82+CH53 -> 0
B83: ="Cumulative "&B54 -> Cumulative Committed Capital from LPs | D83: final | E83: =IF(D83="sum",SUM(G83:CH83),IF(D83="final",CH83,IF(D83="initial",G83,IF(D83="average",AVERAGE(G83:CH83),0)))) -> 25000000 | G83: =F83+G54 -> 25000000 | H83: =G83+H54 -> 25000000 | I83: =H83+I54 -> 25000000 | J83: =I83+J54 -> 25000000 | K83: =J83+K54 -> 25000000 | L83: =K83+L54 -> 25000000 | M83: =L83+M54 -> 25000000 | N83: =M83+N54 -> 25000000 | ... CH83: =CG83+CH54 -> 25000000
B84: ="Cumulative "&B55 -> Cumulative Called Capital from LPs | D84: final | E84: =IF(D84="sum",SUM(G84:CH84),IF(D84="final",CH84,IF(D84="initial",G84,IF(D84="average",AVERAGE(G84:CH84),0)))) -> 25000000 | G84: =F84+G55 -> 1444375 | H84: =G84+H55 -> 2788750 | I84: =H84+I55 -> 4133125 | J84: =I84+J55 -> 5477500 | K84: =J84+K55 -> 6821875 | L84: =K84+L55 -> 8166250 | M84: =L84+M55 -> 9510625 | N84: =M84+N55 -> 10855000 | ... CH84: =CG84+CH55 -> 25000000
B85: ="Cumulative "&B56 -> Cumulative Change in Invested Capital, from LPs | D85: final | E85: =IF(D85="sum",SUM(G85:CH85),IF(D85="final",CH85,IF(D85="initial",G85,IF(D85="average",AVERAGE(G85:CH85),0)))) -> -5.2677933e-09 | G85: =F85+G56 -> 1203125 | H85: =G85+H56 -> 2406250 | I85: =H85+I56 -> 3609375 | J85: =I85+J56 -> 4812500 | K85: =J85+K56 -> 6015625 | L85: =K85+L56 -> 7218750 | M85: =L85+M56 -> 8421875 | N85: =M85+N56 -> 9625000 | ... CH85: =CG85+CH56 -> -5.2677933e-09
B86: ="Cumulative "&B57 -> Cumulative Distributions to LPs | D86: final | E86: =IF(D86="sum",SUM(G86:CH86),IF(D86="final",CH86,IF(D86="initial",G86,IF(D86="average",AVERAGE(G86:CH86),0)))) -> 79087776 | G86: =F86+G57 -> 0 | H86: =G86+H57 -> 0 | I86: =H86+I57 -> 0 | J86: =I86+J57 -> 0 | K86: =J86+K57 -> 0 | L86: =K86+L57 -> 0 | M86: =L86+M57 -> 0 | N86: =M86+N57 -> 0 | ... CH86: =CG86+CH57 -> 79087776
B87: ="Cumulative "&B58 -> Cumulative Distributions to GPs | D87: final | E87: =IF(D87="sum",SUM(G87:CH87),IF(D87="final",CH87,IF(D87="initial",G87,IF(D87="average",AVERAGE(G87:CH87),0)))) -> 15539489 | G87: =F87+G58 -> 0 | H87: =G87+H58 -> 0 | I87: =H87+I58 -> 0 | J87: =I87+J58 -> 0 | K87: =J87+K58 -> 0 | L87: =K87+L58 -> 0 | M87: =L87+M58 -> 0 | N87: =M87+N58 -> 0 | ... CH87: =CG87+CH58 -> 15539489
B89: Paid in Capital (PIC) | D89: final | E89: =IF(D89="sum",SUM(G89:CH89),IF(D89="final",CH89,IF(D89="initial",G89,IF(D89="average",AVERAGE(G89:CH89),0)))) -> 1 | F89: =B89 -> Paid in Capital (PIC) | G89: =IFERROR(G60/$E60,0) -> 0.057775 | H89: =IFERROR(H60/$E60,0) -> 0.11155 | I89: =IFERROR(I60/$E60,0) -> 0.165325 | J89: =IFERROR(J60/$E60,0) -> 0.2191 | K89: =IFERROR(K60/$E60,0) -> 0.272875 | L89: =IFERROR(L60/$E60,0) -> 0.32665 | M89: =IFERROR(M60/$E60,0) -> 0.380425 | N89: =IFERROR(N60/$E60,0) -> 0.4342 | ... CH89: =IFERROR(CH60/$E60,0) -> 1
B90: Residual Value to Paid in Capital (RVPI) | D90: final | E90: =IF(D90="sum",SUM(G90:CH90),IF(D90="final",CH90,IF(D90="initial",G90,IF(D90="average",AVERAGE(G90:CH90),0)))) -> -2.9802322e-16 | F90: =B90 -> Residual Value to Paid in Capital (RVPI) | G90: =IFERROR((G81-(MAX(0,(F81+G51+G50+G72-G71-G60))*'Get Started 2'!$E14-G75))/G60,0) -> 0.83297274 | H90: =IFERROR((H81-(MAX(0,(G81+H51+H50+H72-H71-H60))*'Get Started 2'!$E14-H75))/H60,0) -> 0.86284177 | I90: =IFERROR((I81-(MAX(0,(H81+I51+I50+I72-I71-I60))*'Get Started 2'!$E14-I75))/I60,0) -> 0.8732799 | J90: =IFERROR((J81-(MAX(0,(I81+J51+J50+J72-J71-J60))*'Get Started 2'!$E14-J75))/J60,0) -> 0.87859425 | K90: =IFERROR((K81-(MAX(0,(J81+K51+K50+K72-K71-K60))*'Get Started 2'!$E14-K75))/K60,0) -> 0.88181402 | L90: =IFERROR((L81-(MAX(0,(K81+L51+L50+L72-L71-L60))*'Get Started 2'!$E14-L75))/L60,0) -> 0.88397367 | M90: =IFERROR((M81-(MAX(0,(L81+M51+M50+M72-M71-M60))*'Get Started 2'!$E14-M75))/M60,0) -> 0.88552277 | N90: =IFERROR((N81-(MAX(0,(M81+N51+N50+N72-N71-N60))*'Get Started 2'!$E14-N75))/N60,0) -> 0.88668816 | ... CH90: =IFERROR((CH81-(MAX(0,(CG81+CH51+CH50+CH72-CH71-CH60))*'Get Started 2'!$E14-CH75))/CH60,0) -> -2.9802322e-16
B91: Distributed Value to Paid in Capital (DVPI) | D91: final | E91: =IF(D91="sum",SUM(G91:CH91),IF(D91="final",CH91,IF(D91="initial",G91,IF(D91="average",AVERAGE(G91:CH91),0)))) -> 3.2280725 | F91: =B91 -> Distributed Value to Paid in Capital (DVPI) | G91: =IFERROR(G76/G60,0) -> 0 | H91: =IFERROR(H76/H60,0) -> 0 | I91: =IFERROR(I76/I60,0) -> 0 | J91: =IFERROR(J76/J60,0) -> 0 | K91: =IFERROR(K76/K60,0) -> 0 | L91: =IFERROR(L76/L60,0) -> 0 | M91: =IFERROR(M76/M60,0) -> 0 | N91: =IFERROR(N76/N60,0) -> 0 | ... CH91: =IFERROR(CH76/CH60,0) -> 3.2280725
B92: Total Value to Paid in Capital (TVPI) | D92: final | E92: =IF(D92="sum",SUM(G92:CH92),IF(D92="final",CH92,IF(D92="initial",G92,IF(D92="average",AVERAGE(G92:CH92),0)))) -> 3.2280725 | F92: =B92 -> Total Value to Paid in Capital (TVPI) | G92: =G91+G90 -> 0.83297274 | H92: =H91+H90 -> 0.86284177 | I92: =I91+I90 -> 0.8732799 | J92: =J91+J90 -> 0.87859425 | K92: =K91+K90 -> 0.88181402 | L92: =L91+L90 -> 0.88397367 | M92: =M91+M90 -> 0.88552277 | N92: =N91+N90 -> 0.88668816 | ... CH92: =CH91+CH90 -> 3.2280725
B93: Exposure, as % of Total Committed Capital | C93: idea from https://blog.newfundcap.com/vc-calculator/ | D93: max | E93: =IF(D93="max",MAX(G93:CH93),IF(D93="sum",SUM(G93:CH93),IF(D93="final",CH93,IF(D93="initial",G93,IF(D93="average",AVERAGE(G93:CH93),0))))) -> 0.69589833 | G93: =IF(G100<=0,ABS(G100)/G59,0) -> 0.057775 | H93: =IF(H100<=0,ABS(H100)/H59,0) -> 0.11155 | I93: =IF(I100<=0,ABS(I100)/I59,0) -> 0.165325 | J93: =IF(J100<=0,ABS(J100)/J59,0) -> 0.2191 | K93: =IF(K100<=0,ABS(K100)/K59,0) -> 0.272875 | L93: =IF(L100<=0,ABS(L100)/L59,0) -> 0.32665 | M93: =IF(M100<=0,ABS(M100)/M59,0) -> 0.380425 | N93: =IF(N100<=0,ABS(N100)/N59,0) -> 0.4342 | ... CH93: =IF(CH100<=0,ABS(CH100)/CH59,0) -> 0
B95: Net (Investments) Proceeds | C95: realized only | D95: sum | E95: =IF(D95="sum",SUM(G95:CH95),IF(D95="final",CH95,IF(D95="initial",G95,IF(D95="average",AVERAGE(G95:CH95),0)))) -> 75377265 | G95: =-1*G38+G43 -> -1203125 | H95: =-1*H38+H43 -> -1203125 | I95: =-1*I38+I43 -> -1203125 | J95: =-1*J38+J43 -> -1203125 | K95: =-1*K38+K43 -> -1203125 | L95: =-1*L38+L43 -> -1203125 | M95: =-1*M38+M43 -> -1203125 | N95: =-1*N38+N43 -> -1203125 | ... CH95: =-1*CH38+CH43 -> 0
B96: ="Cumulative "&B95 -> Cumulative Net (Investments) Proceeds | C96: realized only | D96: final | E96: =IF(D96="sum",SUM(G96:CH96),IF(D96="final",CH96,IF(D96="initial",G96,IF(D96="average",AVERAGE(G96:CH96),0)))) -> 75377265 | G96: =F96+G95 -> -1203125 | H96: =G96+H95 -> -2406250 | I96: =H96+I95 -> -3609375 | J96: =I96+J95 -> -4812500 | K96: =J96+K95 -> -6015625 | L96: =K96+L95 -> -7218750 | M96: =L96+M95 -> -8421875 | N96: =M96+N95 -> -9625000 | ... CH96: =CG96+CH95 -> 75377265
B97: Gross Multiple | C97: realized only | D97: final | E97: =IF(D97="sum",SUM(G97:CH97),IF(D97="final",CH97,IF(D97="initial",G97,IF(D97="average",AVERAGE(G97:CH97),0)))) -> 4.7145 | G97: =IFERROR(G72/G67,0) -> 0 | H97: =IFERROR(H72/H67,0) -> 0 | I97: =IFERROR(I72/I67,0) -> 0 | J97: =IFERROR(J72/J67,0) -> 0 | K97: =IFERROR(K72/K67,0) -> 0 | L97: =IFERROR(L72/L67,0) -> 0 | M97: =IFERROR(M72/M67,0) -> 0 | N97: =IFERROR(N72/N67,0) -> 0 | ... CH97: =IFERROR(CH72/CH67,0) -> 4.7145
B98: Gross IRR | C98: realized only | D98: final | E98: =IF(D98="sum",SUM(G98:CH98),IF(D98="final",CH98,IF(D98="initial",G98,IF(D98="average",AVERAGE(G98:CH98),0)))) -> 0.45309877 | G98: =IFERROR(XIRR(INDIRECT(""&ADDRESS(ROW($D95),COLUMN($G95)+MATCH(INDEX($G95:$CH95,MATCH(TRUE,INDEX($G95:$CH95<>0,),0)),$G95:$CH95,0)-1,4)&":"&ADDRESS(ROW($G95),COLUMN($G95)+MATCH(F$5,$G$5:$CH$5,1),4)),INDIRECT(""&ADDRESS(ROW(F$5),COLUMN($G95)+MATCH(INDEX($G95:$CH95,MATCH(TRUE,INDEX($G95:$CH95<>0,),0)),$G95:$CH95,0)-1,4) & ":" & ADDRESS(ROW($G$5),COLUMN($G95)+MATCH(F$5,$G$5:$CH$5,1),4))),"na") -> na | H98: =IFERROR(XIRR(INDIRECT(""&ADDRESS(ROW($D95),COLUMN($G95)+MATCH(INDEX($G95:$CH95,MATCH(TRUE,INDEX($G95:$CH95<>0,),0)),$G95:$CH95,0)-1,4)&":"&ADDRESS(ROW($G95),COLUMN($G95)+MATCH(G$5,$G$5:$CH$5,1),4)),INDIRECT(""&ADDRESS(ROW(G$5),COLUMN($G95)+MATCH(INDEX($G95:$CH95,MATCH(TRUE,INDEX($G95:$CH95<>0,),0)),$G95:$CH95,0)-1,4) & ":" & ADDRESS(ROW($G$5),COLUMN($G95)+MATCH(G$5,$G$5:$CH$5,1),4))),"na") -> na | I98: =IFERROR(XIRR(INDIRECT(""&ADDRESS(ROW($D95),COLUMN($G95)+MATCH(INDEX($G95:$CH95,MATCH(TRUE,INDEX($G95:$CH95<>0,),0)),$G95:$CH95,0)-1,4)&":"&ADDRESS(ROW($G95),COLUMN($G95)+MATCH(H$5,$G$5:$CH$5,1),4)),INDIRECT(""&ADDRESS(ROW(H$5),COLUMN($G95)+MATCH(INDEX($G95:$CH95,MATCH(TRUE,INDEX($G95:$CH95<>0,),0)),$G95:$CH95,0)-1,4) & ":" & ADDRESS(ROW($G$5),COLUMN($G95)+MATCH(H$5,$G$5:$CH$5,1),4))),"na") -> na | J98: =IFERROR(XIRR(INDIRECT(""&ADDRESS(ROW($D95),COLUMN($G95)+MATCH(INDEX($G95:$CH95,MATCH(TRUE,INDEX($G95:$CH95<>0,),0)),$G95:$CH95,0)-1,4)&":"&ADDRESS(ROW($G95),COLUMN($G95)+MATCH(I$5,$G$5:$CH$5,1),4)),INDIRECT(""&ADDRESS(ROW(I$5),COLUMN($G95)+MATCH(INDEX($G95:$CH95,MATCH(TRUE,INDEX($G95:$CH95<>0,),0)),$G95:$CH95,0)-1,4) & ":" & ADDRESS(ROW($G$5),COLUMN($G95)+MATCH(I$5,$G$5:$CH$5,1),4))),"na") -> na | K98: =IFERROR(XIRR(INDIRECT(""&ADDRESS(ROW($D95),COLUMN($G95)+MATCH(INDEX($G95:$CH95,MATCH(TRUE,INDEX($G95:$CH95<>0,),0)),$G95:$CH95,0)-1,4)&":"&ADDRESS(ROW($G95),COLUMN($G95)+MATCH(J$5,$G$5:$CH$5,1),4)),INDIRECT(""&ADDRESS(ROW(J$5),COLUMN($G95)+MATCH(INDEX($G95:$CH95,MATCH(TRUE,INDEX($G95:$CH95<>0,),0)),$G95:$CH95,0)-1,4) & ":" & ADDRESS(ROW($G$5),COLUMN($G95)+MATCH(J$5,$G$5:$CH$5,1),4))),"na") -> na | L98: =IFERROR(XIRR(INDIRECT(""&ADDRESS(ROW($D95),COLUMN($G95)+MATCH(INDEX($G95:$CH95,MATCH(TRUE,INDEX($G95:$CH95<>0,),0)),$G95:$CH95,0)-1,4)&":"&ADDRESS(ROW($G95),COLUMN($G95)+MATCH(K$5,$G$5:$CH$5,1),4)),INDIRECT(""&ADDRESS(ROW(K$5),COLUMN($G95)+MATCH(INDEX($G95:$CH95,MATCH(TRUE,INDEX($G95:$CH95<>0,),0)),$G95:$CH95,0)-1,4) & ":" & ADDRESS(ROW($G$5),COLUMN($G95)+MATCH(K$5,$G$5:$CH$5,1),4))),"na") -> na | M98: =IFERROR(XIRR(INDIRECT(""&ADDRESS(ROW($D95),COLUMN($G95)+MATCH(INDEX($G95:$CH95,MATCH(TRUE,INDEX($G95:$CH95<>0,),0)),$G95:$CH95,0)-1,4)&":"&ADDRESS(ROW($G95),COLUMN($G95)+MATCH(L$5,$G$5:$CH$5,1),4)),INDIRECT(""&ADDRESS(ROW(L$5),COLUMN($G95)+MATCH(INDEX($G95:$CH95,MATCH(TRUE,INDEX($G95:$CH95<>0,),0)),$G95:$CH95,0)-1,4) & ":" & ADDRESS(ROW($G$5),COLUMN($G95)+MATCH(L$5,$G$5:$CH$5,1),4))),"na") -> na | N98: =IFERROR(XIRR(INDIRECT(""&ADDRESS(ROW($D95),COLUMN($G95)+MATCH(INDEX($G95:$CH95,MATCH(TRUE,INDEX($G95:$CH95<>0,),0)),$G95:$CH95,0)-1,4)&":"&ADDRESS(ROW($G95),COLUMN($G95)+MATCH(M$5,$G$5:$CH$5,1),4)),INDIRECT(""&ADDRESS(ROW(M$5),COLUMN($G95)+MATCH(INDEX($G95:$CH95,MATCH(TRUE,INDEX($G95:$CH95<>0,),0)),$G95:$CH95,0)-1,4) & ":" & ADDRESS(ROW($G$5),COLUMN($G95)+MATCH(M$5,$G$5:$CH$5,1),4))),"na") -> na | ... CH98: =IFERROR(XIRR(INDIRECT(""&ADDRESS(ROW($D95),COLUMN($G95)+MATCH(INDEX($G95:$CH95,MATCH(TRUE,INDEX($G95:$CH95<>0,),0)),$G95:$CH95,0)-1,4)&":"&ADDRESS(ROW($G95),COLUMN($G95)+MATCH(CG$5,$G$5:$CH$5,1),4)),INDIRECT(""&ADDRESS(ROW(CG$5),COLUMN($G95)+MATCH(INDEX($G95:$CH95,MATCH(TRUE,INDEX($G95:$CH95<>0,),0)),$G95:$CH95,0)-1,4) & ":" & ADDRESS(ROW($G$5),COLUMN($G95)+MATCH(CG$5,$G$5:$CH$5,1),4))),"na") -> 0.45309877
B99: Net (Called Capital) Distributions | C99: realized only | D99: sum | E99: =IF(D99="sum",SUM(G99:CH99),IF(D99="final",CH99,IF(D99="initial",G99,IF(D99="average",AVERAGE(G99:CH99),0)))) -> 55701812 | G99: =-1*G31+G47 -> -1444375 | H99: =-1*H31+H47 -> -1344375 | I99: =-1*I31+I47 -> -1344375 | J99: =-1*J31+J47 -> -1344375 | K99: =-1*K31+K47 -> -1344375 | L99: =-1*L31+L47 -> -1344375 | M99: =-1*M31+M47 -> -1344375 | N99: =-1*N31+N47 -> -1344375 | ... CH99: =-1*CH31+CH47 -> 0
B100: ="Cumulative "&B99 -> Cumulative Net (Called Capital) Distributions | C100: realized only | D100: final | E100: =IF(D100="sum",SUM(G100:CH100),IF(D100="final",CH100,IF(D100="initial",G100,IF(D100="average",AVERAGE(G100:CH100),0)))) -> 55701812 | G100: =F100+G99 -> -1444375 | H100: =G100+H99 -> -2788750 | I100: =H100+I99 -> -4133125 | J100: =I100+J99 -> -5477500 | K100: =J100+K99 -> -6821875 | L100: =K100+L99 -> -8166250 | M100: =L100+M99 -> -9510625 | N100: =M100+N99 -> -10855000 | ... CH100: =CG100+CH99 -> 55701812
B101: Net Multiple | C101: realized only | D101: final | E101: =IF(D101="sum",SUM(G101:CH101),IF(D101="final",CH101,IF(D101="initial",G101,IF(D101="average",AVERAGE(G101:CH101),0)))) -> 3.2280725 | G101: =IFERROR(G76/G60,0) -> 0 | H101: =IFERROR(H76/H60,0) -> 0 | I101: =IFERROR(I76/I60,0) -> 0 | J101: =IFERROR(J76/J60,0) -> 0 | K101: =IFERROR(K76/K60,0) -> 0 | L101: =IFERROR(L76/L60,0) -> 0 | M101: =IFERROR(M76/M60,0) -> 0 | N101: =IFERROR(N76/N60,0) -> 0 | ... CH101: =IFERROR(CH76/CH60,0) -> 3.2280725
B102: Net IRR | C102: realized only | D102: final | E102: =IF(D102="sum",SUM(G102:CH102),IF(D102="final",CH102,IF(D102="initial",G102,IF(D102="average",AVERAGE(G102:CH102),0)))) -> 0.35571062 | G102: =IFERROR(XIRR(INDIRECT(""&ADDRESS(ROW($D99),COLUMN($G99)+MATCH(INDEX($G99:$CH99,MATCH(TRUE,INDEX($G99:$CH99<>0,),0)),$G99:$CH99,0)-1,4)&":"&ADDRESS(ROW($G99),COLUMN($G99)+MATCH(F$5,$G$5:$CH$5,1),4)),INDIRECT(""&ADDRESS(ROW(F$5),COLUMN($G99)+MATCH(INDEX($G99:$CH99,MATCH(TRUE,INDEX($G99:$CH99<>0,),0)),$G99:$CH99,0)-1,4) & ":" & ADDRESS(ROW($G$5),COLUMN($G99)+MATCH(F$5,$G$5:$CH$5,1),4))),"na") -> na | H102: =IFERROR(XIRR(INDIRECT(""&ADDRESS(ROW($D99),COLUMN($G99)+MATCH(INDEX($G99:$CH99,MATCH(TRUE,INDEX($G99:$CH99<>0,),0)),$G99:$CH99,0)-1,4)&":"&ADDRESS(ROW($G99),COLUMN($G99)+MATCH(G$5,$G$5:$CH$5,1),4)),INDIRECT(""&ADDRESS(ROW(G$5),COLUMN($G99)+MATCH(INDEX($G99:$CH99,MATCH(TRUE,INDEX($G99:$CH99<>0,),0)),$G99:$CH99,0)-1,4) & ":" & ADDRESS(ROW($G$5),COLUMN($G99)+MATCH(G$5,$G$5:$CH$5,1),4))),"na") -> na | I102: =IFERROR(XIRR(INDIRECT(""&ADDRESS(ROW($D99),COLUMN($G99)+MATCH(INDEX($G99:$CH99,MATCH(TRUE,INDEX($G99:$CH99<>0,),0)),$G99:$CH99,0)-1,4)&":"&ADDRESS(ROW($G99),COLUMN($G99)+MATCH(H$5,$G$5:$CH$5,1),4)),INDIRECT(""&ADDRESS(ROW(H$5),COLUMN($G99)+MATCH(INDEX($G99:$CH99,MATCH(TRUE,INDEX($G99:$CH99<>0,),0)),$G99:$CH99,0)-1,4) & ":" & ADDRESS(ROW($G$5),COLUMN($G99)+MATCH(H$5,$G$5:$CH$5,1),4))),"na") -> na | J102: =IFERROR(XIRR(INDIRECT(""&ADDRESS(ROW($D99),COLUMN($G99)+MATCH(INDEX($G99:$CH99,MATCH(TRUE,INDEX($G99:$CH99<>0,),0)),$G99:$CH99,0)-1,4)&":"&ADDRESS(ROW($G99),COLUMN($G99)+MATCH(I$5,$G$5:$CH$5,1),4)),INDIRECT(""&ADDRESS(ROW(I$5),COLUMN($G99)+MATCH(INDEX($G99:$CH99,MATCH(TRUE,INDEX($G99:$CH99<>0,),0)),$G99:$CH99,0)-1,4) & ":" & ADDRESS(ROW($G$5),COLUMN($G99)+MATCH(I$5,$G$5:$CH$5,1),4))),"na") -> na | K102: =IFERROR(XIRR(INDIRECT(""&ADDRESS(ROW($D99),COLUMN($G99)+MATCH(INDEX($G99:$CH99,MATCH(TRUE,INDEX($G99:$CH99<>0,),0)),$G99:$CH99,0)-1,4)&":"&ADDRESS(ROW($G99),COLUMN($G99)+MATCH(J$5,$G$5:$CH$5,1),4)),INDIRECT(""&ADDRESS(ROW(J$5),COLUMN($G99)+MATCH(INDEX($G99:$CH99,MATCH(TRUE,INDEX($G99:$CH99<>0,),0)),$G99:$CH99,0)-1,4) & ":" & ADDRESS(ROW($G$5),COLUMN($G99)+MATCH(J$5,$G$5:$CH$5,1),4))),"na") -> na | L102: =IFERROR(XIRR(INDIRECT(""&ADDRESS(ROW($D99),COLUMN($G99)+MATCH(INDEX($G99:$CH99,MATCH(TRUE,INDEX($G99:$CH99<>0,),0)),$G99:$CH99,0)-1,4)&":"&ADDRESS(ROW($G99),COLUMN($G99)+MATCH(K$5,$G$5:$CH$5,1),4)),INDIRECT(""&ADDRESS(ROW(K$5),COLUMN($G99)+MATCH(INDEX($G99:$CH99,MATCH(TRUE,INDEX($G99:$CH99<>0,),0)),$G99:$CH99,0)-1,4) & ":" & ADDRESS(ROW($G$5),COLUMN($G99)+MATCH(K$5,$G$5:$CH$5,1),4))),"na") -> na | M102: =IFERROR(XIRR(INDIRECT(""&ADDRESS(ROW($D99),COLUMN($G99)+MATCH(INDEX($G99:$CH99,MATCH(TRUE,INDEX($G99:$CH99<>0,),0)),$G99:$CH99,0)-1,4)&":"&ADDRESS(ROW($G99),COLUMN($G99)+MATCH(L$5,$G$5:$CH$5,1),4)),INDIRECT(""&ADDRESS(ROW(L$5),COLUMN($G99)+MATCH(INDEX($G99:$CH99,MATCH(TRUE,INDEX($G99:$CH99<>0,),0)),$G99:$CH99,0)-1,4) & ":" & ADDRESS(ROW($G$5),COLUMN($G99)+MATCH(L$5,$G$5:$CH$5,1),4))),"na") -> na | N102: =IFERROR(XIRR(INDIRECT(""&ADDRESS(ROW($D99),COLUMN($G99)+MATCH(INDEX($G99:$CH99,MATCH(TRUE,INDEX($G99:$CH99<>0,),0)),$G99:$CH99,0)-1,4)&":"&ADDRESS(ROW($G99),COLUMN($G99)+MATCH(M$5,$G$5:$CH$5,1),4)),INDIRECT(""&ADDRESS(ROW(M$5),COLUMN($G99)+MATCH(INDEX($G99:$CH99,MATCH(TRUE,INDEX($G99:$CH99<>0,),0)),$G99:$CH99,0)-1,4) & ":" & ADDRESS(ROW($G$5),COLUMN($G99)+MATCH(M$5,$G$5:$CH$5,1),4))),"na") -> na | ... CH102: =IFERROR(XIRR(INDIRECT(""&ADDRESS(ROW($D99),COLUMN($G99)+MATCH(INDEX($G99:$CH99,MATCH(TRUE,INDEX($G99:$CH99<>0,),0)),$G99:$CH99,0)-1,4)&":"&ADDRESS(ROW($G99),COLUMN($G99)+MATCH(CG$5,$G$5:$CH$5,1),4)),INDIRECT(""&ADDRESS(ROW(CG$5),COLUMN($G99)+MATCH(INDEX($G99:$CH99,MATCH(TRUE,INDEX($G99:$CH99<>0,),0)),$G99:$CH99,0)-1,4) & ":" & ADDRESS(ROW($G$5),COLUMN($G99)+MATCH(CG$5,$G$5:$CH$5,1),4))),"na") -> 0.35571062
B103: Interim Net IRR | C103: will differ from net IRR simply because of difference in using XIRR and IRR and how they handle dates differently | D103: final | E103: =IF(D103="sum",SUM(G103:CH103),IF(D103="final",CH103,IF(D103="initial",G103,IF(D103="average",AVERAGE(G103:CH103),0)))) -> 0.35600376 | G103: =INDEX($C104:$C183,G4) -> 0 | H103: =INDEX($C104:$C183,H4) -> -0.70787163 | I103: =INDEX($C104:$C183,I4) -> -0.42563576 | J103: =INDEX($C104:$C183,J4) -> -0.29657944 | K103: =INDEX($C104:$C183,K4) -> -0.2259411 | L103: =INDEX($C104:$C183,L4) -> -0.18194488 | M103: =INDEX($C104:$C183,M4) -> -0.15207268 | N103: =INDEX($C104:$C183,N4) -> -0.13052387 | ... CH103: =INDEX($C104:$C183,CH4) -> 0.35600376
B104: 1 | C104: =IFERROR((1+IRR(F104:CH104))^4-1,0) -> 0 | D104: sum | E104: =IF(D104="sum",SUM(G104:CH104),IF(D104="final",CH104,IF(D104="initial",G104,IF(D104="average",AVERAGE(G104:CH104),0)))) -> 1203125 | G104: =IF($B104=G$4,G$81,0) -> 1203125 | H104: =IF(H$4<=$B104,ABS(H$31)*-1+H$47,0)+IF($B104=H$4,H$81,0) -> 0 | I104: =IF(I$4<=$B104,ABS(I$31)*-1+I$47,0)+IF($B104=I$4,I$81,0) -> 0 | J104: =IF(J$4<=$B104,ABS(J$31)*-1+J$47,0)+IF($B104=J$4,J$81,0) -> 0 | K104: =IF(K$4<=$B104,ABS(K$31)*-1+K$47,0)+IF($B104=K$4,K$81,0) -> 0 | L104: =IF(L$4<=$B104,ABS(L$31)*-1+L$47,0)+IF($B104=L$4,L$81,0) -> 0 | M104: =IF(M$4<=$B104,ABS(M$31)*-1+M$47,0)+IF($B104=M$4,M$81,0) -> 0 | N104: =IF(N$4<=$B104,ABS(N$31)*-1+N$47,0)+IF($B104=N$4,N$81,0) -> 0 | O104: =IF(O$4<=$B104,ABS(O$31)*-1+O$47,0)+IF($B104=O$4,O$81,0) -> 0 | ... CH104: =IF(CH$4<=$B104,ABS(CH$31)*-1+CH$47,0)+IF($B104=CH$4,CH$81,0) -> 0
B105: =B104+1 -> 2 | C105: =IFERROR((1+IRR(F105:CH105))^4-1,0) -> -0.70787163 | D105: sum | E105: =IF(D105="sum",SUM(G105:CH105),IF(D105="final",CH105,IF(D105="initial",G105,IF(D105="average",AVERAGE(G105:CH105),0)))) -> -382500 | G105: =IF(G$4<=$B105,ABS(G$31)*-1+G$47,0)+IF($B105=G$4,G$81,0) -> -1444375 | H105: =IF(H$4<=$B105,ABS(H$31)*-1+H$47,0)+IF($B105=H$4,H$81,0) -> 1061875 | I105: =IF(I$4<=$B105,ABS(I$31)*-1+I$47,0)+IF($B105=I$4,I$81,0) -> 0 | J105: =IF(J$4<=$B105,ABS(J$31)*-1+J$47,0)+IF($B105=J$4,J$81,0) -> 0 | K105: =IF(K$4<=$B105,ABS(K$31)*-1+K$47,0)+IF($B105=K$4,K$81,0) -> 0 | L105: =IF(L$4<=$B105,ABS(L$31)*-1+L$47,0)+IF($B105=L$4,L$81,0) -> 0 | M105: =IF(M$4<=$B105,ABS(M$31)*-1+M$47,0)+IF($B105=M$4,M$81,0) -> 0 | N105: =IF(N$4<=$B105,ABS(N$31)*-1+N$47,0)+IF($B105=N$4,N$81,0) -> 0 | ... CH105: =IF(CH$4<=$B105,ABS(CH$31)*-1+CH$47,0)+IF($B105=CH$4,CH$81,0) -> 0
B106: =B105+1 -> 3 | C106: =IFERROR((1+IRR(F106:CH106))^4-1,0) -> -0.42563576 | D106: sum | E106: =IF(D106="sum",SUM(G106:CH106),IF(D106="final",CH106,IF(D106="initial",G106,IF(D106="average",AVERAGE(G106:CH106),0)))) -> -523750 | G106: =IF(G$4<=$B106,ABS(G$31)*-1+G$47,0)+IF($B106=G$4,G$81,0) -> -1444375 | H106: =IF(H$4<=$B106,ABS(H$31)*-1+H$47,0)+IF($B106=H$4,H$81,0) -> -1344375 | I106: =IF(I$4<=$B106,ABS(I$31)*-1+I$47,0)+IF($B106=I$4,I$81,0) -> 2265000 | J106: =IF(J$4<=$B106,ABS(J$31)*-1+J$47,0)+IF($B106=J$4,J$81,0) -> 0 | K106: =IF(K$4<=$B106,ABS(K$31)*-1+K$47,0)+IF($B106=K$4,K$81,0) -> 0 | L106: =IF(L$4<=$B106,ABS(L$31)*-1+L$47,0)+IF($B106=L$4,L$81,0) -> 0 | M106: =IF(M$4<=$B106,ABS(M$31)*-1+M$47,0)+IF($B106=M$4,M$81,0) -> 0 | N106: =IF(N$4<=$B106,ABS(N$31)*-1+N$47,0)+IF($B106=N$4,N$81,0) -> 0 | ... CH106: =IF(CH$4<=$B106,ABS(CH$31)*-1+CH$47,0)+IF($B106=CH$4,CH$81,0) -> 0
B107: =B106+1 -> 4 | C107: =IFERROR((1+IRR(F107:CH107))^4-1,0) -> -0.29657944 | D107: sum | E107: =IF(D107="sum",SUM(G107:CH107),IF(D107="final",CH107,IF(D107="initial",G107,IF(D107="average",AVERAGE(G107:CH107),0)))) -> -665000 | G107: =IF(G$4<=$B107,ABS(G$31)*-1+G$47,0)+IF($B107=G$4,G$81,0) -> -1444375 | H107: =IF(H$4<=$B107,ABS(H$31)*-1+H$47,0)+IF($B107=H$4,H$81,0) -> -1344375 | I107: =IF(I$4<=$B107,ABS(I$31)*-1+I$47,0)+IF($B107=I$4,I$81,0) -> -1344375 | J107: =IF(J$4<=$B107,ABS(J$31)*-1+J$47,0)+IF($B107=J$4,J$81,0) -> 3468125 | K107: =IF(K$4<=$B107,ABS(K$31)*-1+K$47,0)+IF($B107=K$4,K$81,0) -> 0 | L107: =IF(L$4<=$B107,ABS(L$31)*-1+L$47,0)+IF($B107=L$4,L$81,0) -> 0 | M107: =IF(M$4<=$B107,ABS(M$31)*-1+M$47,0)+IF($B107=M$4,M$81,0) -> 0 | N107: =IF(N$4<=$B107,ABS(N$31)*-1+N$47,0)+IF($B107=N$4,N$81,0) -> 0 | ... CH107: =IF(CH$4<=$B107,ABS(CH$31)*-1+CH$47,0)+IF($B107=CH$4,CH$81,0) -> 0
B108: =B107+1 -> 5 | C108: =IFERROR((1+IRR(F108:CH108))^4-1,0) -> -0.2259411 | D108: sum | E108: =IF(D108="sum",SUM(G108:CH108),IF(D108="final",CH108,IF(D108="initial",G108,IF(D108="average",AVERAGE(G108:CH108),0)))) -> -806250 | G108: =IF(G$4<=$B108,ABS(G$31)*-1+G$47,0)+IF($B108=G$4,G$81,0) -> -1444375 | H108: =IF(H$4<=$B108,ABS(H$31)*-1+H$47,0)+IF($B108=H$4,H$81,0) -> -1344375 | I108: =IF(I$4<=$B108,ABS(I$31)*-1+I$47,0)+IF($B108=I$4,I$81,0) -> -1344375 | J108: =IF(J$4<=$B108,ABS(J$31)*-1+J$47,0)+IF($B108=J$4,J$81,0) -> -1344375 | K108: =IF(K$4<=$B108,ABS(K$31)*-1+K$47,0)+IF($B108=K$4,K$81,0) -> 4671250 | L108: =IF(L$4<=$B108,ABS(L$31)*-1+L$47,0)+IF($B108=L$4,L$81,0) -> 0 | M108: =IF(M$4<=$B108,ABS(M$31)*-1+M$47,0)+IF($B108=M$4,M$81,0) -> 0 | N108: =IF(N$4<=$B108,ABS(N$31)*-1+N$47,0)+IF($B108=N$4,N$81,0) -> 0 | ... CH108: =IF(CH$4<=$B108,ABS(CH$31)*-1+CH$47,0)+IF($B108=CH$4,CH$81,0) -> 0
B109: =B108+1 -> 6 | C109: =IFERROR((1+IRR(F109:CH109))^4-1,0) -> -0.18194488 | D109: sum | E109: =IF(D109="sum",SUM(G109:CH109),IF(D109="final",CH109,IF(D109="initial",G109,IF(D109="average",AVERAGE(G109:CH109),0)))) -> -947500 | G109: =IF(G$4<=$B109,ABS(G$31)*-1+G$47,0)+IF($B109=G$4,G$81,0) -> -1444375 | H109: =IF(H$4<=$B109,ABS(H$31)*-1+H$47,0)+IF($B109=H$4,H$81,0) -> -1344375 | I109: =IF(I$4<=$B109,ABS(I$31)*-1+I$47,0)+IF($B109=I$4,I$81,0) -> -1344375 | J109: =IF(J$4<=$B109,ABS(J$31)*-1+J$47,0)+IF($B109=J$4,J$81,0) -> -1344375 | K109: =IF(K$4<=$B109,ABS(K$31)*-1+K$47,0)+IF($B109=K$4,K$81,0) -> -1344375 | L109: =IF(L$4<=$B109,ABS(L$31)*-1+L$47,0)+IF($B109=L$4,L$81,0) -> 5874375 | M109: =IF(M$4<=$B109,ABS(M$31)*-1+M$47,0)+IF($B109=M$4,M$81,0) -> 0 | N109: =IF(N$4<=$B109,ABS(N$31)*-1+N$47,0)+IF($B109=N$4,N$81,0) -> 0 | ... CH109: =IF(CH$4<=$B109,ABS(CH$31)*-1+CH$47,0)+IF($B109=CH$4,CH$81,0) -> 0
B110: =B109+1 -> 7 | C110: =IFERROR((1+IRR(F110:CH110))^4-1,0) -> -0.15207268 | D110: sum | E110: =IF(D110="sum",SUM(G110:CH110),IF(D110="final",CH110,IF(D110="initial",G110,IF(D110="average",AVERAGE(G110:CH110),0)))) -> -1088750 | G110: =IF(G$4<=$B110,ABS(G$31)*-1+G$47,0)+IF($B110=G$4,G$81,0) -> -1444375 | H110: =IF(H$4<=$B110,ABS(H$31)*-1+H$47,0)+IF($B110=H$4,H$81,0) -> -1344375 | I110: =IF(I$4<=$B110,ABS(I$31)*-1+I$47,0)+IF($B110=I$4,I$81,0) -> -1344375 | J110: =IF(J$4<=$B110,ABS(J$31)*-1+J$47,0)+IF($B110=J$4,J$81,0) -> -1344375 | K110: =IF(K$4<=$B110,ABS(K$31)*-1+K$47,0)+IF($B110=K$4,K$81,0) -> -1344375 | L110: =IF(L$4<=$B110,ABS(L$31)*-1+L$47,0)+IF($B110=L$4,L$81,0) -> -1344375 | M110: =IF(M$4<=$B110,ABS(M$31)*-1+M$47,0)+IF($B110=M$4,M$81,0) -> 7077500 | N110: =IF(N$4<=$B110,ABS(N$31)*-1+N$47,0)+IF($B110=N$4,N$81,0) -> 0 | ... CH110: =IF(CH$4<=$B110,ABS(CH$31)*-1+CH$47,0)+IF($B110=CH$4,CH$81,0) -> 0
B111: =B110+1 -> 8 | C111: =IFERROR((1+IRR(F111:CH111))^4-1,0) -> -0.13052387 | D111: sum | E111: =IF(D111="sum",SUM(G111:CH111),IF(D111="final",CH111,IF(D111="initial",G111,IF(D111="average",AVERAGE(G111:CH111),0)))) -> -1230000 | G111: =IF(G$4<=$B111,ABS(G$31)*-1+G$47,0)+IF($B111=G$4,G$81,0) -> -1444375 | H111: =IF(H$4<=$B111,ABS(H$31)*-1+H$47,0)+IF($B111=H$4,H$81,0) -> -1344375 | I111: =IF(I$4<=$B111,ABS(I$31)*-1+I$47,0)+IF($B111=I$4,I$81,0) -> -1344375 | J111: =IF(J$4<=$B111,ABS(J$31)*-1+J$47,0)+IF($B111=J$4,J$81,0) -> -1344375 | K111: =IF(K$4<=$B111,ABS(K$31)*-1+K$47,0)+IF($B111=K$4,K$81,0) -> -1344375 | L111: =IF(L$4<=$B111,ABS(L$31)*-1+L$47,0)+IF($B111=L$4,L$81,0) -> -1344375 | M111: =IF(M$4<=$B111,ABS(M$31)*-1+M$47,0)+IF($B111=M$4,M$81,0) -> -1344375 | N111: =IF(N$4<=$B111,ABS(N$31)*-1+N$47,0)+IF($B111=N$4,N$81,0) -> 8280625 | ... CH111: =IF(CH$4<=$B111,ABS(CH$31)*-1+CH$47,0)+IF($B111=CH$4,CH$81,0) -> 0
B112: =B111+1 -> 9 | C112: =IFERROR((1+IRR(F112:CH112))^4-1,0) -> -0.095275078 | D112: sum | E112: =IF(D112="sum",SUM(G112:CH112),IF(D112="final",CH112,IF(D112="initial",G112,IF(D112="average",AVERAGE(G112:CH112),0)))) -> -1148039.9 | G112: =IF(G$4<=$B112,ABS(G$31)*-1+G$47,0)+IF($B112=G$4,G$81,0) -> -1444375 | H112: =IF(H$4<=$B112,ABS(H$31)*-1+H$47,0)+IF($B112=H$4,H$81,0) -> -1344375 | I112: =IF(I$4<=$B112,ABS(I$31)*-1+I$47,0)+IF($B112=I$4,I$81,0) -> -1344375 | J112: =IF(J$4<=$B112,ABS(J$31)*-1+J$47,0)+IF($B112=J$4,J$81,0) -> -1344375 | K112: =IF(K$4<=$B112,ABS(K$31)*-1+K$47,0)+IF($B112=K$4,K$81,0) -> -1344375 | L112: =IF(L$4<=$B112,ABS(L$31)*-1+L$47,0)+IF($B112=L$4,L$81,0) -> -1344375 | M112: =IF(M$4<=$B112,ABS(M$31)*-1+M$47,0)+IF($B112=M$4,M$81,0) -> -1344375 | N112: =IF(N$4<=$B112,ABS(N$31)*-1+N$47,0)+IF($B112=N$4,N$81,0) -> -1344375 | ... CH112: =IF(CH$4<=$B112,ABS(CH$31)*-1+CH$47,0)+IF($B112=CH$4,CH$81,0) -> 0
B113: =B112+1 -> 10 | C113: =IFERROR((1+IRR(F113:CH113))^4-1,0) -> -0.06787521 | D113: sum | E113: =IF(D113="sum",SUM(G113:CH113),IF(D113="final",CH113,IF(D113="initial",G113,IF(D113="average",AVERAGE(G113:CH113),0)))) -> -1020915.7 | G113: =IF(G$4<=$B113,ABS(G$31)*-1+G$47,0)+IF($B113=G$4,G$81,0) -> -1444375 | H113: =IF(H$4<=$B113,ABS(H$31)*-1+H$47,0)+IF($B113=H$4,H$81,0) -> -1344375 | I113: =IF(I$4<=$B113,ABS(I$31)*-1+I$47,0)+IF($B113=I$4,I$81,0) -> -1344375 | J113: =IF(J$4<=$B113,ABS(J$31)*-1+J$47,0)+IF($B113=J$4,J$81,0) -> -1344375 | K113: =IF(K$4<=$B113,ABS(K$31)*-1+K$47,0)+IF($B113=K$4,K$81,0) -> -1344375 | L113: =IF(L$4<=$B113,ABS(L$31)*-1+L$47,0)+IF($B113=L$4,L$81,0) -> -1344375 | M113: =IF(M$4<=$B113,ABS(M$31)*-1+M$47,0)+IF($B113=M$4,M$81,0) -> -1344375 | N113: =IF(N$4<=$B113,ABS(N$31)*-1+N$47,0)+IF($B113=N$4,N$81,0) -> -1344375 | ... CH113: =IF(CH$4<=$B113,ABS(CH$31)*-1+CH$47,0)+IF($B113=CH$4,CH$81,0) -> 0
B114: =B113+1 -> 11 | C114: =IFERROR((1+IRR(F114:CH114))^4-1,0) -> -0.046100371 | D114: sum | E114: =IF(D114="sum",SUM(G114:CH114),IF(D114="final",CH114,IF(D114="initial",G114,IF(D114="average",AVERAGE(G114:CH114),0)))) -> -848627.44 | G114: =IF(G$4<=$B114,ABS(G$31)*-1+G$47,0)+IF($B114=G$4,G$81,0) -> -1444375 | H114: =IF(H$4<=$B114,ABS(H$31)*-1+H$47,0)+IF($B114=H$4,H$81,0) -> -1344375 | I114: =IF(I$4<=$B114,ABS(I$31)*-1+I$47,0)+IF($B114=I$4,I$81,0) -> -1344375 | J114: =IF(J$4<=$B114,ABS(J$31)*-1+J$47,0)+IF($B114=J$4,J$81,0) -> -1344375 | K114: =IF(K$4<=$B114,ABS(K$31)*-1+K$47,0)+IF($B114=K$4,K$81,0) -> -1344375 | L114: =IF(L$4<=$B114,ABS(L$31)*-1+L$47,0)+IF($B114=L$4,L$81,0) -> -1344375 | M114: =IF(M$4<=$B114,ABS(M$31)*-1+M$47,0)+IF($B114=M$4,M$81,0) -> -1344375 | N114: =IF(N$4<=$B114,ABS(N$31)*-1+N$47,0)+IF($B114=N$4,N$81,0) -> -1344375 | ... CH114: =IF(CH$4<=$B114,ABS(CH$31)*-1+CH$47,0)+IF($B114=CH$4,CH$81,0) -> 0
B115: =B114+1 -> 12 | C115: =IFERROR((1+IRR(F115:CH115))^4-1,0) -> -0.02848011 | D115: sum | E115: =IF(D115="sum",SUM(G115:CH115),IF(D115="final",CH115,IF(D115="initial",G115,IF(D115="average",AVERAGE(G115:CH115),0)))) -> -631175.05 | G115: =IF(G$4<=$B115,ABS(G$31)*-1+G$47,0)+IF($B115=G$4,G$81,0) -> -1444375 | H115: =IF(H$4<=$B115,ABS(H$31)*-1+H$47,0)+IF($B115=H$4,H$81,0) -> -1344375 | I115: =IF(I$4<=$B115,ABS(I$31)*-1+I$47,0)+IF($B115=I$4,I$81,0) -> -1344375 | J115: =IF(J$4<=$B115,ABS(J$31)*-1+J$47,0)+IF($B115=J$4,J$81,0) -> -1344375 | K115: =IF(K$4<=$B115,ABS(K$31)*-1+K$47,0)+IF($B115=K$4,K$81,0) -> -1344375 | L115: =IF(L$4<=$B115,ABS(L$31)*-1+L$47,0)+IF($B115=L$4,L$81,0) -> -1344375 | M115: =IF(M$4<=$B115,ABS(M$31)*-1+M$47,0)+IF($B115=M$4,M$81,0) -> -1344375 | N115: =IF(N$4<=$B115,ABS(N$31)*-1+N$47,0)+IF($B115=N$4,N$81,0) -> -1344375 | ... CH115: =IF(CH$4<=$B115,ABS(CH$31)*-1+CH$47,0)+IF($B115=CH$4,CH$81,0) -> 0
B116: =B115+1 -> 13 | C116: =IFERROR((1+IRR(F116:CH116))^4-1,0) -> 0.0017111638 | D116: sum | E116: =IF(D116="sum",SUM(G116:CH116),IF(D116="final",CH116,IF(D116="initial",G116,IF(D116="average",AVERAGE(G116:CH116),0)))) -> 45414.513 | G116: =IF(G$4<=$B116,ABS(G$31)*-1+G$47,0)+IF($B116=G$4,G$81,0) -> -1444375 | H116: =IF(H$4<=$B116,ABS(H$31)*-1+H$47,0)+IF($B116=H$4,H$81,0) -> -1344375 | I116: =IF(I$4<=$B116,ABS(I$31)*-1+I$47,0)+IF($B116=I$4,I$81,0) -> -1344375 | J116: =IF(J$4<=$B116,ABS(J$31)*-1+J$47,0)+IF($B116=J$4,J$81,0) -> -1344375 | K116: =IF(K$4<=$B116,ABS(K$31)*-1+K$47,0)+IF($B116=K$4,K$81,0) -> -1344375 | L116: =IF(L$4<=$B116,ABS(L$31)*-1+L$47,0)+IF($B116=L$4,L$81,0) -> -1344375 | M116: =IF(M$4<=$B116,ABS(M$31)*-1+M$47,0)+IF($B116=M$4,M$81,0) -> -1344375 | N116: =IF(N$4<=$B116,ABS(N$31)*-1+N$47,0)+IF($B116=N$4,N$81,0) -> -1344375 | ... CH116: =IF(CH$4<=$B116,ABS(CH$31)*-1+CH$47,0)+IF($B116=CH$4,CH$81,0) -> 0
... B183: =B182+1 -> 80 | C183: =IFERROR((1+IRR(F183:CH183))^4-1,0) -> 0.35600376 | D183: sum | E183: =IF(D183="sum",SUM(G183:CH183),IF(D183="final",CH183,IF(D183="initial",G183,IF(D183="average",AVERAGE(G183:CH183),0)))) -> 55701812 | G183: =IF(G$4<=$B183,ABS(G$31)*-1+G$47,0)+IF($B183=G$4,G$81,0) -> -1444375 | H183: =IF(H$4<=$B183,ABS(H$31)*-1+H$47,0)+IF($B183=H$4,H$81,0) -> -1344375 | I183: =IF(I$4<=$B183,ABS(I$31)*-1+I$47,0)+IF($B183=I$4,I$81,0) -> -1344375 | J183: =IF(J$4<=$B183,ABS(J$31)*-1+J$47,0)+IF($B183=J$4,J$81,0) -> -1344375 | K183: =IF(K$4<=$B183,ABS(K$31)*-1+K$47,0)+IF($B183=K$4,K$81,0) -> -1344375 | L183: =IF(L$4<=$B183,ABS(L$31)*-1+L$47,0)+IF($B183=L$4,L$81,0) -> -1344375 | M183: =IF(M$4<=$B183,ABS(M$31)*-1+M$47,0)+IF($B183=M$4,M$81,0) -> -1344375 | N183: =IF(N$4<=$B183,ABS(N$31)*-1+N$47,0)+IF($B183=N$4,N$81,0) -> -1344375 | ... CH183: =IF(CH$4<=$B183,ABS(CH$31)*-1+CH$47,0)+IF($B183=CH$4,CH$81,0) -> 0
...

Sheet Get Started  3
B2: Get Started
B3: Key model assumptions and performance metrics
B5: Capital and Fund Assumptions
B6: Capital, Management Fees, base Fund-level assumptions
B8: Detail | C8: Unit | E8: Assumption | F8: Forecast | K8: Notes
B9: Total Commited Capital (Fund Size) | C9: ='Get Started'!C9 -> $ | E9: ='Get Started'!E9 -> 25000000 | F9: =E9 -> 25000000 | K9: Fund size. By default, assumes all committed capital is closed at the start. Can adjust that by modifying the committed capital on Forecast sheet.
B10: GP Commit, as % of committed capital | C10: % | E10: ='Get Started'!E10 -> 0.02 | F10: =E10*F$9 -> 500000 | K10: GP commit is treated as an LP interest for purposes of calculating mangement fees and carried interest. see glossary for additional details
B11: Organizational Expenses (one time) | C11: =C$9 -> $ | E11: ='Get Started'!E11 -> 100000 | F11: ='Forecast 3'!E39 -> 100000 | K11: paid by fund, in addition to management fees. one time costs associated with forming the fund, primarily legal fees
B12: Operational Expenses (annual) | C12: =C$9 -> $ | E12: ='Get Started'!E12 -> 75000 | F12: ='Forecast 3'!E40 -> 750000 | K12: paid by fund, in addition to management fees. see https://foresight.is/docs/management-company/ for more context. calculated based on the fund operations period for operating expenses
B13: Management Fees, per year, as % of committed capital | C13: % | E13: ='Get Started'!E13 -> 0.02 | F13: ='Forecast 3'!E41 -> 4900000 | K13: model works for management fees based on called and committed capital (can be edited for fee structures based on assets under management). if you have a management fee structure that steps down over time, you can edit the management fees directly on the Forecast sheet.
B14: Carry | C14: % | E14: ='Get Started'!E14 -> 0.2 | F14: =E124 -> 41159896 | K14: carry is the % of gains that are paid to the managers of the fund. part of the commonly cited "2 and 20" fees structure for funds
B15: Active Investment time period (quarters) | C15: # | E15: ='Get Started'!E15 -> 16 | K15: time period for new investments (follow ons by default assumed to come over time)
B16: Fund Duration (Management Fees time period) (quarters) | C16: # | E16: ='Get Started'!E16 -> 40 | K16: time period used for assuming management fees, tied to the fund duration and not including the fund extension period, if applicable
B17: Fund Operations time period (quarters) | C17: # | E17: ='Get Started'!E17 -> 40 | K17: time period used for assuming operational expenses, which is calculated from the new invesetment and exit timeframes, to cover the periods the fund incurrs operational expenses. you can override the calculated period if desired.
B18: Fund Duration Extension Period (quarters) | C18: # | E18: =MAX(0,E17-E16) -> 0 | K18: extra time period calculated from your deployment and holding period assumptions. purely for informational purposes, the model uses the fund duration for calculating management fees, this just shows how long of an extension you will need based on your assumptions
B21: Recycling
B22: Details on recycling provisions for closed end and evergreen funds | K22: more at https://foresight.is/docs/management-fee-recycling/
B24: Detail | C24: Unit | E24: Assumption | F24: Forecast | K24: Notes
B25: ="Target recycling %, and max achievable" -> Target recycling %, and max achievable | C25: % | E25: ='Get Started'!E25 -> 0.25 | F25: =IFERROR(F29/F26,0) -> 0.032083333 | K25: input is for the target % to recycle, and the forecast shows the % that is achievable given the parameters in the assumptions below. It is very common for the max acheivable to be less than the target. Note that LPAs may set the number differently; for example, some LPAs may note that recycling is 125% of committed capital (meaning that the total can be 25% higher than the amount of committed capital), or it may say that recycling is 25% of committed capital. They mean the same thing, but the number may be expressed differently. The model uses an assumption of 25% of recycling + 100% of committed capital = 125% of total committed capital plus recycling
B26: ="... based on "&E26 -> ... based on committed capital | C26: - | E26: ='Get Started'!E26 -> committed capital | F26: =IF(E26="management fees",F13,F9) -> 25000000 | K26: can be set to management fees or committed capital, and the forecast outputs the amount of it forecasted in the model
B27: ="... from exits "&E27&" quarters or less post-investment" -> ... from exits 24 quarters or less post-investment | C27: # | E27: ='Get Started'!E27 -> 24 | F27: ='Forecast 3'!E204 -> 2.3160156e+08 | K27: can set the time limit from original investment to time to proceeds (exit), and only allow exits within that timeframe to recycle their proceeds. if there is no limit, simply input a number greater thant the fund operations period or the max holding period in the return assumptions
B28: ="... up to the amount of "&E28&" per investment exited" -> ... up to the amount of invested capital per investment exited | C28: - | E28: ='Get Started'!E28 -> invested capital | F28: =IF(E28="invested capital",'Forecast 3'!E206,IF(E28="invested capital plus cost basis",'Forecast 3'!E205,'Forecast 3'!E204)) -> 8689236.1 | K28: can set to recycle the amount originally invested in the company (meaning any profits would be distributed), the amount invested in the company plus the cost basis (allocating expenses to the invested capital, so that it reflects paid in capital related to the investent), or all proceeds, meaning all proceeds from the exit
B29: ="... able to invest in "&E29 -> ... able to invest in new investments | C29: - | E29: ='Get Started'!E29 -> new investments | F29: ='Forecast 3'!E42 -> 802083.33 | K29: can set to new investments only, or new and follow on investments. this will set the proceeds recycling timeframe on the forecast sheet, meaning the period when recycling can be done
B32: Investment Strategy and Expectations
B33: Use to detail an investment strategy, new and follow to forecast returns
B35: Exit Outcome | E35: ='Get Started'!E35 -> Fail | F35: ='Get Started'!F35 -> Low | G35: ='Get Started'!G35 -> Medium | H35: ='Get Started'!H35 -> High | J35: change the terms to fit what you want to call the different exit outcomes, used to generate the returns expectations on get started.
B37: Investment Performance and Capital Allocation
B38: % of Investments per Exit Outcome | C38: % | E38: =1-SUM(F38:H38) -> 0.56666667 | F38: =MAX(0,'Get Started'!F38-($H38-'Get Started'!$H38)/3) -> 0.16666667 | G38: =MAX(0,'Get Started'!G38-($H38-'Get Started'!$H38)/3) -> 0.066666667 | H38: ='Get Started'!H38*(1+Scenarios!N28) -> 0.2 | J38: % of the number of companies invested in; sum should equal 0%
B39: # of Companies that achieve each Exit Outcome | C39: # | E39: =E42*$E122/E78 -> 22.725694 | F39: =F42*$E122/F78 -> 6.6840278 | G39: =G42*$E122/G78 -> 2.6736111 | H39: =H42*$E122/H78 -> 8.0208333 | J39: # of companies invested in, per exit outcome
B40: Index of average investment per overall average | C40: % | E40: =$E101/E78 -> 1 | F40: =$E101/F78 -> 1 | G40: =$E101/G78 -> 1 | H40: =$E101/H78 -> 1 | J40: intermediate calculation to calculation % of invested capital
B41: Adjustment to % of Investments to % of Invested Capital | C41: % | E41: =E38/E40 -> 0.56666667 | F41: =F38/F40 -> 0.16666667 | G41: =G38/G40 -> 0.066666667 | H41: =H38/H40 -> 0.2 | J41: intermediate calculation to calculation % of invested capital
B42: % of Invested Capital per Exit Outcome | C42: % | E42: =E41/SUM($E41:$H41) -> 0.56666667 | F42: =F41/SUM($E41:$H41) -> 0.16666667 | G42: =G41/SUM($E41:$H41) -> 0.066666667 | H42: =H41/SUM($E41:$H41) -> 0.2 | J42: % of overall invested capital; sum should equal 0%. this will not be equal to the % of investments (companies) if you have different investment strategies between the companies
B43: % of Initial Capital per Exit Outcome | C43: % | E43: =1/(1+E53*E54/E48+E63*E64/E48)*E42 -> 0.56666667 | F43: =1/(1+F53*F54/F48+F63*F64/F48)*F42 -> 0.16666667 | G43: =1/(1+G53*G54/G48+G63*G64/G48)*G42 -> 0.066666667 | H43: =1/(1+H53*H54/H48+H63*H64/H48)*H42 -> 0.2
B44: % of First Follow per Exit Outcome | C44: % | E44: =IFERROR(E53*E54/E48*E43,0) -> 0 | F44: =IFERROR(F53*F54/F48*F43,0) -> 0 | G44: =IFERROR(G53*G54/G48*G43,0) -> 0 | H44: =IFERROR(H53*H54/H48*H43,0) -> 0
B45: % of Second Follow per Exit Outcome | C45: % | E45: =IFERROR(E63*E64/E48*E43,0) -> 0 | F45: =IFERROR(F63*F64/F48*F43,0) -> 0 | G45: =IFERROR(G63*G64/G48*G43,0) -> 0 | H45: =IFERROR(H63*H64/H48*H43,0) -> 0
B47: Initial Investment
B48: Average Initial Investment | C48: =C$9 -> $ | E48: =E49*E50 -> 500000 | F48: =F49*F50 -> 500000 | G48: =G49*G50 -> 500000 | H48: =H49*H50 -> 500000 | J48: your check into the company, not including other investors in the round. calculated from your ownership % and average postmoney valuation at initial investment
B49: Postmoney Valuation | C49: =C$9 -> $ | E49: ='Get Started'!E49 -> 5000000 | F49: ='Get Started'!F49 -> 5000000 | G49: ='Get Started'!G49 -> 5000000 | H49: ='Get Started'!H49 -> 5000000 | J49: assumption, average per type of exit. note, this is an assumption becuase the model is best used to evaluate the impact of ownership % on overall returns, and to do that, it is best to hold the valuation constant and see the impact on ownership % on the size of the portfolio
B50: Ownership %, at initial investment | C50: =C$9 -> $ | E50: ='Get Started'!E50 -> 0.1 | F50: ='Get Started'!F50 -> 0.1 | G50: ='Get Started'!G50 -> 0.1 | H50: ='Get Started'!H50 -> 0.1 | J50: your assumed ownership %, not including other investors in the round. for convertibles, assume the post-conversion to equity ownership %
B52: Follow on Investments (First Follow on round)
B53: % of Initial Investments to Participate in Prorata | C53: % | E53: ='Get Started'!E53 -> 0 | F53: ='Get Started'!F53 -> 0 | G53: ='Get Started'!G53 -> 0 | H53: ='Get Started'!H53 -> 0 | J53: this should reflect the combination of (a) companies that graduate to raise a round, and (b) whether you participate in their round
B54: Follow on Investment Amount | C54: =C$9 -> $ | E54: ='Get Started'!E54 -> 400000 | F54: ='Get Started'!F54 -> 400000 | G54: ='Get Started'!G54 -> 400000 | H54: ='Get Started'!H54 -> 400000 | J54: this is calculated based on the amount raised in the round and the ownership coming into the round, but you can override this if desired
B55: Time from Initial Investment to Follow on Investment (quarters) | C55: # | E55: ='Get Started'!E55 -> 0 | F55: ='Get Started'!F55 -> 0 | G55: ='Get Started'!G55 -> 0 | H55: ='Get Started'!H55 -> 0 | J55: time from the initial investment
B56: Postmoney Valuation | C56: =C$9 -> $ | E56: ='Get Started'!E56 -> 20000000 | F56: ='Get Started'!F56 -> 20000000 | G56: ='Get Started'!G56 -> 20000000 | H56: ='Get Started'!H56 -> 20000000 | J56: many people will assume the same for all types of companies (types of exit outcomes), but you could alter this if desired
B57: Dilution from Round (from all investors) | C57: % | E57: ='Get Started'!E57 -> 0.2 | F57: ='Get Started'!F57 -> 0.2 | G57: ='Get Started'!G57 -> 0.2 | H57: ='Get Started'!H57 -> 0.2 | J57: this is used to calculate the amount raised in the round, based on the postmoney valuation in the round
B58: Dilution from New Option Pool | C58: % | E58: ='Get Started'!E58 -> 0.1 | F58: ='Get Started'!F58 -> 0.1 | G58: ='Get Started'!G58 -> 0.1 | H58: ='Get Started'!H58 -> 0.1 | J58: optional, but helps to consider the dilution from option pool expansions. remember that prorata rights do not cover dilution from prorata
B59: Ownership % per company followed on, post follow on | C59: % | E59: =E50*(1-E57-E58)+E54/E56 -> 0.09 | F59: =F50*(1-F57-F58)+F54/F56 -> 0.09 | G59: =G50*(1-G57-G58)+G54/G56 -> 0.09 | H59: =H50*(1-H57-H58)+H54/H56 -> 0.09
B60: Ownership % per average initial investment, post follow on round | C60: % | E60: =E50*(1-E57-E58)+E54/E56*E53 -> 0.07 | F60: =F50*(1-F57-F58)+F54/F56*F53 -> 0.07 | G60: =G50*(1-G57-G58)+G54/G56*G53 -> 0.07 | H60: =H50*(1-H57-H58)+H54/H56*H53 -> 0.07 | J60: average company, including ones do follow on in, and ones do not follow on in
B62: Follow on Investments (Second Follow on round)
B63: % of Initial Investments to Participate in Prorata | C63: % | E63: ='Get Started'!E63 -> 0 | F63: ='Get Started'!F63 -> 0 | G63: ='Get Started'!G63 -> 0 | H63: ='Get Started'!H63 -> 0 | J63: this should reflect the combination of (a) companies that graduate to raise a round, and (b) whether you participate in their round
B64: Follow on Investment Amount | C64: =C$9 -> $ | E64: ='Get Started'!E64 -> 1080000 | F64: ='Get Started'!F64 -> 1080000 | G64: ='Get Started'!G64 -> 1080000 | H64: ='Get Started'!H64 -> 1080000 | J64: this is calculated based on the amount raised in the round and the ownership coming into the round, but you can override this if desired
B65: Time from Initial Investment to Follow on Investment (quarters) | C65: # | E65: ='Get Started'!E65 -> 0 | F65: ='Get Started'!F65 -> 0 | G65: ='Get Started'!G65 -> 0 | H65: ='Get Started'!H65 -> 0 | J65: time from the initial investment, not the last follow round
B66: Postmoney Valuation | C66: =C$9 -> $ | E66: ='Get Started'!E66 -> 60000000 | F66: ='Get Started'!F66 -> 60000000 | G66: ='Get Started'!G66 -> 60000000 | H66: ='Get Started'!H66 -> 60000000 | J66: many people will assume the same for all types of companies (types of exit outcomes), but you could alter this if desired
B67: Dilution from Round (from all investors) | C67: % | E67: ='Get Started'!E67 -> 0.2 | F67: ='Get Started'!F67 -> 0.2 | G67: ='Get Started'!G67 -> 0.2 | H67: ='Get Started'!H67 -> 0.2 | J67: this is used to calculate the amount raised in the round, based on the postmoney valuation in the round
B68: Dilution from New Option Pool | C68: % | E68: ='Get Started'!E68 -> 0.1 | F68: ='Get Started'!F68 -> 0.1 | G68: ='Get Started'!G68 -> 0.1 | H68: ='Get Started'!H68 -> 0.1 | J68: optional, but helps to consider the dilution from option pool expansions. remember that prorata rights do not cover dilution from prorata
B69: Ownership % per company followed on, post follow on | C69: % | E69: =E59*(1-E67-E68)+E64/E66 -> 0.081 | F69: =F59*(1-F67-F68)+F64/F66 -> 0.081 | G69: =G59*(1-G67-G68)+G64/G66 -> 0.081 | H69: =H59*(1-H67-H68)+H64/H66 -> 0.081
B70: Ownership % per average initial investment, post follow on round | C70: % | E70: =E59*(1-E67-E68)+E64/E66*E63 -> 0.063 | F70: =F59*(1-F67-F68)+F64/F66*F63 -> 0.063 | G70: =G59*(1-G67-G68)+G64/G66*G63 -> 0.063 | H70: =H59*(1-H67-H68)+H64/H66*H63 -> 0.063 | J70: average company, including ones do follow on in, and ones do not follow on in
B72: Follow on Investments (Additional Follow on rounds)
B73: Additional Dilution from Second Follow on round to Exit | C73: % | E73: 0 | F73: 0.2 | G73: 0.4 | H73: =G73*2 -> 0.8 | J73: assumption to reflect all subsequent follow on rounds after the ones modeled above; you may want to assume more dilution for more successful companies to reflect more capital raised
B75: Exit
B76: Average Exit Value | C76: =C$9 -> $ | E76: ='Get Started'!E76 -> 0 | F76: ='Get Started'!F76 -> 50000000 | G76: ='Get Started'!G76 -> 250000000 | H76: ='Get Started'!H76*(1+Scenarios!N29) -> 1875000000 | J76: assumption, to reflect the average distribution to equity shareholders for this type of exit
B77: Average Hold Period (quarters) | C77: # | E77: ='Get Started'!E77 -> 8 | F77: ='Get Started'!F77 -> 12 | G77: ='Get Started'!G77 -> 16 | H77: ='Get Started'!H77 -> 24 | J77: Average Hold Period is the average time from initial investment to exit, per # of investments. assumption, please change for your strategy and assessment of your investments
B78: Average Investment per Company | C78: =C$9 -> $ | E78: =E48+E54*E53+E63*E64 -> 500000 | F78: =F48+F54*F53+F63*F64 -> 500000 | G78: =G48+G54*G53+G63*G64 -> 500000 | H78: =H48+H54*H53+H63*H64 -> 500000 | J78: average invested per company, per exit outcome
B79: Ownership % at Exit | C79: % | E79: =E70*(1-E73) -> 0.063 | F79: =F70*(1-F73) -> 0.0504 | G79: =G70*(1-G73) -> 0.0378 | H79: =H70*(1-H73) -> 0.0126 | J79: ownership %, per exit outcome
B80: Average Proceeds per Company | C80: =C$9 -> $ | E80: =E79*E76 -> 0 | F80: =F79*F76 -> 2520000 | G80: =G79*G76 -> 9450000 | H80: =H79*H76 -> 23625000 | J80: average proceeds per company, per exit outcome, reflecting ownership value at exit and total invested into each company (initial investment and follow on)
B81: Total Initial Investments | C81: =C$9 -> $ | E81: =E39*E48 -> 11362847 | F81: =F39*F48 -> 3342013.9 | G81: =G39*G48 -> 1336805.6 | H81: =H39*H48 -> 4010416.7 | J81: capital allocation to initial investments (first checks into companies)
B82: ="% of "&B$89 -> % of Total Invested Capital | C82: % | E82: =E43 -> 0.56666667 | F82: =F43 -> 0.16666667 | G82: =G43 -> 0.066666667 | H82: =H43 -> 0.2 | J82: per exit outcome / total
B83: Total First Follow Investments | C83: =C$9 -> $ | E83: =E39*E53*E54 -> 0 | F83: =F39*F53*F54 -> 0 | G83: =G39*G53*G54 -> 0 | H83: =H39*H53*H54 -> 0 | J83: capital allocation to first follow
B84: ="% of "&B$89 -> % of Total Invested Capital | C84: % | E84: =E44 -> 0 | F84: =F44 -> 0 | G84: =G44 -> 0 | H84: =H44 -> 0 | J84: per exit outcome / total
B85: Total Second Follow Investments | C85: =C$9 -> $ | E85: =E39*E63*E64 -> 0 | F85: =F39*F63*F64 -> 0 | G85: =G39*G63*G64 -> 0 | H85: =H39*H63*H64 -> 0 | J85: capital allocation to second follow
B86: ="% of "&B$89 -> % of Total Invested Capital | C86: % | E86: =E45 -> 0 | F86: =F45 -> 0 | G86: =G45 -> 0 | H86: =H45 -> 0 | J86: per exit outcome / total
B87: Total Follow Investments | C87: =C$9 -> $ | E87: =E83+E85 -> 0 | F87: =F83+F85 -> 0 | G87: =G83+G85 -> 0 | H87: =H83+H85 -> 0 | J87: capital allocation to all follow on rounds
B88: ="% of "&B$89 -> % of Total Invested Capital | C88: % | E88: =IFERROR(E87/SUM($E$89:$H$89),0) -> 0 | F88: =IFERROR(F87/SUM($E$89:$H$89),0) -> 0 | G88: =IFERROR(G87/SUM($E$89:$H$89),0) -> 0 | H88: =IFERROR(H87/SUM($E$89:$H$89),0) -> 0 | J88: per exit outcome / total
B89: Total Invested Capital | C89: =C$9 -> $ | E89: =E81+E87 -> 11362847 | F89: =F81+F87 -> 3342013.9 | G89: =G81+G87 -> 1336805.6 | H89: =H81+H87 -> 4010416.7 | J89: capital allocation
B90: ="% of "&B$89 -> % of Total Invested Capital | C90: % | E90: =IFERROR(E89/SUM($E$89:$H$89),0) -> 0.56666667 | F90: =IFERROR(F89/SUM($E$89:$H$89),0) -> 0.16666667 | G90: =IFERROR(G89/SUM($E$89:$H$89),0) -> 0.066666667 | H90: =IFERROR(H89/SUM($E$89:$H$89),0) -> 0.2 | J90: should equal the calculated % of total invested capital from above
B91: Total Proceeds | C91: =C$9 -> $ | E91: =E79*E76*E39 -> 0 | F91: =F79*F76*F39 -> 16843750 | G91: =G79*G76*G39 -> 25265625 | H91: =H79*H76*H39 -> 1.8949219e+08 | J91: total proceeds per type of exit, reflecting performance, investment strategy, and exit expectations. you may want to adjust those assumptions to get this to match your expectations for where portfolio returns come from
B92: ="% of "&B91 -> % of Total Proceeds | C92: % | E92: =IFERROR(E91/SUM($E91:$H91),0) -> 0 | F92: =IFERROR(F91/SUM($E91:$H91),0) -> 0.072727273 | G92: =IFERROR(G91/SUM($E91:$H91),0) -> 0.10909091 | H92: =IFERROR(H91/SUM($E91:$H91),0) -> 0.81818182 | J92: per exit outcome / total
B93: Gross Exit Multiple, per Exit Outcome | C93: # | E93: =IFERROR(E80/E78,0) -> 0 | F93: =IFERROR(F80/F78,0) -> 5.04 | G93: =IFERROR(G80/G78,0) -> 18.9 | H93: =IFERROR(H80/H78,0) -> 47.25 | J93: proceeds / invested capital, per exit outcome
B96: Portfolio Construction
B97: Capital Allocation and Investment Timeframe Assumptions
B99: Detail | C99: Unit | E99: New | F99: Follow
B100: % Allocation of Invested Capital | C100: % | E100: =IFERROR(SUMPRODUCT(E38:H38,E48:H48)/SUMPRODUCT(E38:H38,E78:H78),0) -> 1 | F100: =1-E100 -> 0 | K100: Allocation of overall invested capital to new and follow
B101: Average Check Size | C101: =C$9 -> $ | E101: =SUMPRODUCT(E38:H38,E48:H48) -> 500000 | F101: =IFERROR(F100*$E122/F102,0) -> 0 | K101: Follow ons are assumed to be on average 1-2 years after the new investment. If more detailed required, consider the Venture Investor Model (see Model Comparison sheet)
B102: # of Checks | C102: # | E102: =F113 -> 40.104167 | F102: =SUMPRODUCT(E39:H39,E63:H63)+SUMPRODUCT(E39:H39,E53:H53) -> 0 | K102: # of new checks = # of unique companies invested into. # of follow checks = # of rounds participated in, can consist of multiple follow checks into a single company
B105: Return Assumptions
B106: Used to create estimates of average investment outcome by gross exit multiple and hold period
B108: Type of Exit | C108: Unit | E108: % of Investments | F108: # of Investments | G108: Average Gross Exit Multiple | H108: Average Hold Period (quarters) | K108: Type of Exit can be defined in a few ways: by returns (writeoffs, small, medium, large), by strategy (Seed, A, B, etc.), by investment strategy (early, late, growth), or industry strategy (tech, energy, etc.)
B109: =E35 -> Fail | C109: #, % | E109: =E38 -> 0.56666667 | F109: =E39 -> 22.725694 | G109: =E93 -> 0 | H109: =E77 -> 8 | K109: Average Hold Period is the average time from initial investment to exit, per # of investments, used to calculate the timing of proceeds and writeoffs
B110: =F35 -> Low | C110: #, % | E110: =F38 -> 0.16666667 | F110: =F39 -> 6.6840278 | G110: =F93 -> 5.04 | H110: =F77 -> 12 | K110: The % of total proceeds is calculated from the gross exit multiple and the % of investments for each exit type, to estimate where the fund returns come from. More complicated methods for estimated proceeds are in the paid venture models at https://foresight.is/vc
B111: =G35 -> Medium | C111: #, % | E111: =G38 -> 0.066666667 | F111: =G39 -> 2.6736111 | G111: =G93 -> 18.9 | H111: =G77 -> 16
B112: =H35 -> High | C112: #, % | E112: =H38 -> 0.2 | F112: =H39 -> 8.0208333 | G112: =H93 -> 47.25 | H112: =H77 -> 24 | K112: note, the average gross multiple and average hold period is based off % of invested capital, *not* % of investments, since the investments may not have the same average investment $ per exit outcome, based on your assumptions above
E113: =SUM(E109:E112) -> 1 | F113: =SUM(F109:F112) -> 40.104167 | G113: =SUMPRODUCT(E93:H93,E42:H42) -> 11.55 | H113: =SUMPRODUCT(E42:H42,E77:H77) -> 12.4 | K113: Can adjust this structure to add additional lines for types of exits, just note will need to make a few edits on Forecast sheet to pull those into the calculations of proceeds and changes in invested capital.
B115: Fund Performance
B116: Fund performance summary
B118: Called Capital (also called Paid in Capital) | C118: =C$9 -> $ | E118: ='Forecast 3'!E31 -> 25000000 | K118: should equal committed capital
B119: Management Fees and Fund Expenses | C119: =C$9 -> $ | E119: ='Forecast 3'!E41+'Forecast 3'!E40+'Forecast 3'!E39 -> 5750000 | K119: management fees + operating expenses + organizational expenses
B120: ="Budgeted "&B122 -> Budgeted Invested Capital | C120: =C$9 -> $ | E120: =IF(SUMPRODUCT(--('Forecast 3'!G15:CH15<>"committed"))=0,F9-F11-F12-F13,F9-F11-F12-F9*(IF('Forecast 3'!C17=TRUE,(1-E10),1)*SUMPRODUCT('Forecast 3'!G14:CH14,--('Forecast 3'!G15:CH15="committed"))))+IF(E29="new and follow investments",F9*'Forecast 3'!E219,0) -> 19250000 | K120: initially budgeted invested capital, without recycling
B121: Recycled Capital | C121: =C$9 -> $ | E121: ='Forecast 3'!E42 -> 802083.33 | K121: recycled capital, calculated using recycling assumptions above
B122: Invested Capital | C122: =C$9 -> $ | E122: =E120+E121 -> 20052083 | K122: committed capital - expenses - management fees + recycled capital, using subcalculations for management fees to handle assets under management
B123: Proceeds | C123: =C$9 -> $ | E123: ='Forecast 3'!E43 -> 2.3160156e+08 | K123: calculated on forecast sheet
...

Sheet Forecast  3
B2: Quarterly Forecast
B4: Relative Quarter | G4: =1 -> 1 | H4: =G4+1 -> 2 | I4: =H4+1 -> 3 | J4: =I4+1 -> 4 | K4: =J4+1 -> 5 | L4: =K4+1 -> 6 | M4: =L4+1 -> 7 | N4: =M4+1 -> 8 | O4: =N4+1 -> 9 | ... CH4: =CG4+1 -> 80
B5: Date at end of period | G5: =Forecast!G5 -> 46022 | H5: =EOMONTH(EDATE(G5,3),0) -> 46112 | I5: =EOMONTH(EDATE(H5,3),0) -> 46203 | J5: =EOMONTH(EDATE(I5,3),0) -> 46295 | K5: =EOMONTH(EDATE(J5,3),0) -> 46387 | L5: =EOMONTH(EDATE(K5,3),0) -> 46477 | M5: =EOMONTH(EDATE(L5,3),0) -> 46568 | N5: =EOMONTH(EDATE(M5,3),0) -> 46660 | O5: =EOMONTH(EDATE(N5,3),0) -> 46752 | ... CH5: =EOMONTH(EDATE(CG5,3),0) -> 53235
B7: Triggers
B8: ='Get Started 3'!B15 -> Active Investment time period (quarters) | C8: period for making new investments only | D8: sum | E8: =IF(D8="sum",SUM(G8:CH8),IF(D8="final",CH8,IF(D8="initial",G8,IF(D8="average",AVERAGE(G8:CH8),0)))) -> 16 | G8: =IF(G$4<='Get Started 3'!$E15,1,0) -> 1 | H8: =IF(H$4<='Get Started 3'!$E15,1,0) -> 1 | I8: =IF(I$4<='Get Started 3'!$E15,1,0) -> 1 | J8: =IF(J$4<='Get Started 3'!$E15,1,0) -> 1 | K8: =IF(K$4<='Get Started 3'!$E15,1,0) -> 1 | L8: =IF(L$4<='Get Started 3'!$E15,1,0) -> 1 | M8: =IF(M$4<='Get Started 3'!$E15,1,0) -> 1 | N8: =IF(N$4<='Get Started 3'!$E15,1,0) -> 1 | ... CH8: =IF(CH$4<='Get Started 3'!$E15,1,0) -> 0
B9: ='Get Started 3'!B16 -> Fund Duration (Management Fees time period) (quarters) | C9: see FAST Standard for how to use triggers: https://foresight.is/learn/fast-standard | D9: sum | E9: =IF(D9="sum",SUM(G9:CH9),IF(D9="final",CH9,IF(D9="initial",G9,IF(D9="average",AVERAGE(G9:CH9),0)))) -> 40 | G9: =IF(G$4<='Get Started 3'!$E16,1,0)*G10 -> 1 | H9: =IF(H$4<='Get Started 3'!$E16,1,0)*H10 -> 1 | I9: =IF(I$4<='Get Started 3'!$E16,1,0)*I10 -> 1 | J9: =IF(J$4<='Get Started 3'!$E16,1,0)*J10 -> 1 | K9: =IF(K$4<='Get Started 3'!$E16,1,0)*K10 -> 1 | L9: =IF(L$4<='Get Started 3'!$E16,1,0)*L10 -> 1 | M9: =IF(M$4<='Get Started 3'!$E16,1,0)*M10 -> 1 | N9: =IF(N$4<='Get Started 3'!$E16,1,0)*N10 -> 1 | ... CH9: =IF(CH$4<='Get Started 3'!$E16,1,0)*CH10 -> 0
B10: ='Get Started 3'!B17 -> Fund Operations time period (quarters) | D10: sum | E10: =IF(D10="sum",SUM(G10:CH10),IF(D10="final",CH10,IF(D10="initial",G10,IF(D10="average",AVERAGE(G10:CH10),0)))) -> 40 | G10: =IF(G$4<='Get Started 3'!$E17,1,0) -> 1 | H10: =IF(H$4<='Get Started 3'!$E17,1,0) -> 1 | I10: =IF(I$4<='Get Started 3'!$E17,1,0) -> 1 | J10: =IF(J$4<='Get Started 3'!$E17,1,0) -> 1 | K10: =IF(K$4<='Get Started 3'!$E17,1,0) -> 1 | L10: =IF(L$4<='Get Started 3'!$E17,1,0) -> 1 | M10: =IF(M$4<='Get Started 3'!$E17,1,0) -> 1 | N10: =IF(N$4<='Get Started 3'!$E17,1,0) -> 1 | ... CH10: =IF(CH$4<='Get Started 3'!$E17,1,0) -> 0
B11: Proceeds Recycling period (quarters) | D11: sum | E11: =IF(D11="sum",SUM(G11:EP11),IF(D11="final",EP11,IF(D11="initial",G11,IF(D11="average",AVERAGE(G11:EP11),0)))) -> 16 | G11: =IF('Get Started 3'!$E29="new investments",G8,IF(G$4<='Get Started 3'!$E15+MAX('Get Started 3'!$E55:$H55,'Get Started 3'!$E65:$H65),1,0)) -> 1 | H11: =IF('Get Started 3'!$E29="new investments",H8,IF(H$4<='Get Started 3'!$E15+MAX('Get Started 3'!$E55:$H55,'Get Started 3'!$E65:$H65),1,0)) -> 1 | I11: =IF('Get Started 3'!$E29="new investments",I8,IF(I$4<='Get Started 3'!$E15+MAX('Get Started 3'!$E55:$H55,'Get Started 3'!$E65:$H65),1,0)) -> 1 | J11: =IF('Get Started 3'!$E29="new investments",J8,IF(J$4<='Get Started 3'!$E15+MAX('Get Started 3'!$E55:$H55,'Get Started 3'!$E65:$H65),1,0)) -> 1 | K11: =IF('Get Started 3'!$E29="new investments",K8,IF(K$4<='Get Started 3'!$E15+MAX('Get Started 3'!$E55:$H55,'Get Started 3'!$E65:$H65),1,0)) -> 1 | L11: =IF('Get Started 3'!$E29="new investments",L8,IF(L$4<='Get Started 3'!$E15+MAX('Get Started 3'!$E55:$H55,'Get Started 3'!$E65:$H65),1,0)) -> 1 | M11: =IF('Get Started 3'!$E29="new investments",M8,IF(M$4<='Get Started 3'!$E15+MAX('Get Started 3'!$E55:$H55,'Get Started 3'!$E65:$H65),1,0)) -> 1 | N11: =IF('Get Started 3'!$E29="new investments",N8,IF(N$4<='Get Started 3'!$E15+MAX('Get Started 3'!$E55:$H55,'Get Started 3'!$E65:$H65),1,0)) -> 1 | ... CH11: =IF('Get Started 3'!$E29="new investments",CH8,IF(CH$4<='Get Started 3'!$E15+MAX('Get Started 3'!$E55:$H55,'Get Started 3'!$E65:$H65),1,0)) -> 0
B13: Inputs
B14: Management Fees | D14: sum | E14: =IF(D14="sum",SUM(G14:CH14),IF(D14="final",CH14,IF(D14="initial",G14,IF(D14="average",AVERAGE(G14:CH14),0)))) -> 0.2 | G14: =Forecast!G14 -> 0.005 | H14: =IF(H9=1,'Get Started 3'!$E13/4,0) -> 0.005 | I14: =IF(I9=1,'Get Started 3'!$E13/4,0) -> 0.005 | J14: =IF(J9=1,'Get Started 3'!$E13/4,0) -> 0.005 | K14: =IF(K9=1,'Get Started 3'!$E13/4,0) -> 0.005 | L14: =IF(L9=1,'Get Started 3'!$E13/4,0) -> 0.005 | M14: =IF(M9=1,'Get Started 3'!$E13/4,0) -> 0.005 | N14: =IF(N9=1,'Get Started 3'!$E13/4,0) -> 0.005 | O14: =IF(O9=1,'Get Started 3'!$E13/4,0) -> 0.005 | ... CH14: =IF(CH9=1,'Get Started 3'!$E13/4,0) -> 0
B15: ="Management Fees based on "&G15&" capital. Can change per period if method for calc changes." -> Management Fees based on committed capital. Can change per period if method for calc changes. | D15: sum | E15: =IF(D15="sum",SUM(G15:CH15),IF(D15="final",CH15,IF(D15="initial",G15,IF(D15="average",AVERAGE(G15:CH15),0)))) -> 0 | G15: =Forecast!G15 -> committed | H15: =Forecast!H15 -> committed | I15: =Forecast!I15 -> committed | J15: =Forecast!J15 -> committed | K15: =Forecast!K15 -> committed | L15: =Forecast!L15 -> committed | M15: =Forecast!M15 -> committed | N15: =Forecast!N15 -> committed | ... CH15: =Forecast!CH15 -> committed
B16: GP Commit, excluded from LP capital. By default, GP commit is treated as an LP interest. Check the box to have the GP commit not treated as an LP investment. This will affect management fees (management fees will not be charged on the GP commit if it's not an LP interest, and it will change the waterfall so that GPs only get carried interest, and not carried interest + their share of distributions as an LP) | C16: =Forecast!C16 -> FALSE | D16: sum | E16: =IF(D16="sum",SUM(G16:CH16),IF(D16="final",CH16,IF(D16="initial",G16,IF(D16="average",AVERAGE(G16:CH16),0)))) -> 0 | G16: =IF($C16=TRUE,G31*'Get Started 3'!$E10,0) -> 0 | H16: =IF($C16=TRUE,H31*'Get Started 3'!$E10,0) -> 0 | I16: =IF($C16=TRUE,I31*'Get Started 3'!$E10,0) -> 0 | J16: =IF($C16=TRUE,J31*'Get Started 3'!$E10,0) -> 0 | K16: =IF($C16=TRUE,K31*'Get Started 3'!$E10,0) -> 0 | L16: =IF($C16=TRUE,L31*'Get Started 3'!$E10,0) -> 0 | M16: =IF($C16=TRUE,M31*'Get Started 3'!$E10,0) -> 0 | N16: =IF($C16=TRUE,N31*'Get Started 3'!$E10,0) -> 0 | ... CH16: =IF($C16=TRUE,CH31*'Get Started 3'!$E10,0) -> 0
B17: GP Commit, excluded from management fees. Check the box to have the GP commit - capital contributed by the GP as LP capital and an ownership in the fund - excluded from calculation of management fees | C17: =Forecast!C17 -> TRUE | D17: sum | E17: =IF(D17="sum",SUM(G17:CH17),IF(D17="final",CH17,IF(D17="initial",G17,IF(D17="average",AVERAGE(G17:CH17),0)))) -> 500000 | G17: =IF($C17=TRUE,G31*'Get Started 3'!$E10,0) -> 28887.5 | H17: =IF($C17=TRUE,H31*'Get Started 3'!$E10,0) -> 26887.5 | I17: =IF($C17=TRUE,I31*'Get Started 3'!$E10,0) -> 26887.5 | J17: =IF($C17=TRUE,J31*'Get Started 3'!$E10,0) -> 26887.5 | K17: =IF($C17=TRUE,K31*'Get Started 3'!$E10,0) -> 26887.5 | L17: =IF($C17=TRUE,L31*'Get Started 3'!$E10,0) -> 26887.5 | M17: =IF($C17=TRUE,M31*'Get Started 3'!$E10,0) -> 26887.5 | N17: =IF($C17=TRUE,N31*'Get Started 3'!$E10,0) -> 26887.5 | ... CH17: =IF($C17=TRUE,CH31*'Get Started 3'!$E10,0) -> 0
B18: GP Commit, covered via cashless contributions from management fees | C18: if management fees are used to cover for a GP Commit. Please discuss the implications of this with your tax advisor and fund admin if you choose this option | D18: final | E18: =IF(D18="sum",SUM(G18:EP18),IF(D18="final",EP18,IF(D18="initial",G18,IF(D18="average",AVERAGE(G18:EP18),0)))) -> 0 | G18: =Forecast!G18 -> 0 | H18: =Forecast!H18 -> 0 | I18: =Forecast!I18 -> 0 | J18: =Forecast!J18 -> 0 | K18: =Forecast!K18 -> 0 | L18: =Forecast!L18 -> 0 | M18: =Forecast!M18 -> 0 | N18: =Forecast!N18 -> 0 | ... CH18: =Forecast!CH18 -> 0
B19: Commited Capital, % of total fund committed per year | D19: sum | E19: =IF(D19="sum",SUM(G19:EP19),IF(D19="final",EP19,IF(D19="initial",G19,IF(D19="average",AVERAGE(G19:EP19),0)))) -> 1 | G19: =Forecast!G19 -> 1 | H19: =Forecast!H19 -> 0 | I19: =Forecast!I19 -> 0 | J19: =Forecast!J19 -> 0 | K19: =Forecast!K19 -> 0 | L19: =Forecast!L19 -> 0 | M19: =Forecast!M19 -> 0 | N19: =Forecast!N19 -> 0 | ... CH19: =Forecast!CH19 -> 0
B20: Called Capital, % of total fund committed | C20: optional manual override to the automatically calculated called capital schedule, if you do not want to use the calculated schedule. this will not change your investment deployment, only your called capital and cash balances | D20: sum | E20: =IF(D20="sum",SUM(G20:EP20),IF(D20="final",EP20,IF(D20="initial",G20,IF(D20="average",AVERAGE(G20:EP20),0)))) -> 0 | G20: =Forecast!G20 -> 0 | H20: =Forecast!H20 -> 0 | I20: =Forecast!I20 -> 0 | J20: =Forecast!J20 -> 0 | K20: =Forecast!K20 -> 0 | L20: =Forecast!L20 -> 0 | M20: =Forecast!M20 -> 0 | N20: =Forecast!N20 -> 0 | ... CH20: =Forecast!CH20 -> 0
B22: Capital, beginning of period | D22: initial | E22: =IF(D22="sum",SUM(G22:CH22),IF(D22="final",CH22,IF(D22="initial",G22,IF(D22="average",AVERAGE(G22:CH22),0)))) -> 0 | G22: =F28 -> 0 | H22: =G28 -> 0 | I22: =H28 -> 0 | J22: =I28 -> 0 | K22: =J28 -> 0 | L22: =K28 -> 0 | M22: =L28 -> 0 | N22: =M28 -> 0 | ... CH22: =CG28 -> 0
B23: Called Capital | D23: sum | E23: =IF(D23="sum",SUM(G23:CH23),IF(D23="final",CH23,IF(D23="initial",G23,IF(D23="average",AVERAGE(G23:CH23),0)))) -> 25000000 | G23: =G31 -> 1444375 | H23: =H31 -> 1344375 | I23: =I31 -> 1344375 | J23: =J31 -> 1344375 | K23: =K31 -> 1344375 | L23: =L31 -> 1344375 | M23: =M31 -> 1344375 | N23: =N31 -> 1344375 | ... CH23: =CH31 -> 0
B24: Proceeds | D24: sum | E24: =IF(D24="sum",SUM(G24:CH24),IF(D24="final",CH24,IF(D24="initial",G24,IF(D24="average",AVERAGE(G24:CH24),0)))) -> 2.3160156e+08 | G24: =G43 -> 0 | H24: =H43 -> 0 | I24: =I43 -> 0 | J24: =J43 -> 0 | K24: =K43 -> 0 | L24: =L43 -> 0 | M24: =M43 -> 0 | N24: =N43 -> 0 | ... CH24: =CH43 -> 0
B25: Distributions + Carried Interest | D25: sum | E25: =IF(D25="sum",SUM(G25:CH25),IF(D25="final",CH25,IF(D25="initial",G25,IF(D25="average",AVERAGE(G25:CH25),0)))) -> -2.3079948e+08 | G25: =SUM(G47,G46,G45)*-1 -> 0 | H25: =SUM(H47,H46,H45)*-1 -> 0 | I25: =SUM(I47,I46,I45)*-1 -> 0 | J25: =SUM(J47,J46,J45)*-1 -> 0 | K25: =SUM(K47,K46,K45)*-1 -> 0 | L25: =SUM(L47,L46,L45)*-1 -> 0 | M25: =SUM(M47,M46,M45)*-1 -> 0 | N25: =SUM(N47,N46,N45)*-1 -> 0 | ... CH25: =SUM(CH47,CH46,CH45)*-1 -> 0
B26: Fees | D26: sum | E26: =IF(D26="sum",SUM(G26:CH26),IF(D26="final",CH26,IF(D26="initial",G26,IF(D26="average",AVERAGE(G26:CH26),0)))) -> -5750000 | G26: =SUM(G39,G40,G41)*-1 -> -241250 | H26: =SUM(H39,H40,H41)*-1 -> -141250 | I26: =SUM(I39,I40,I41)*-1 -> -141250 | J26: =SUM(J39,J40,J41)*-1 -> -141250 | K26: =SUM(K39,K40,K41)*-1 -> -141250 | L26: =SUM(L39,L40,L41)*-1 -> -141250 | M26: =SUM(M39,M40,M41)*-1 -> -141250 | N26: =SUM(N39,N40,N41)*-1 -> -141250 | ... CH26: =SUM(CH39,CH40,CH41)*-1 -> 0
B27: Investments | D27: sum | E27: =IF(D27="sum",SUM(G27:CH27),IF(D27="final",CH27,IF(D27="initial",G27,IF(D27="average",AVERAGE(G27:CH27),0)))) -> -20052083 | G27: =G38*-1 -> -1203125 | H27: =H38*-1 -> -1203125 | I27: =I38*-1 -> -1203125 | J27: =J38*-1 -> -1203125 | K27: =K38*-1 -> -1203125 | L27: =L38*-1 -> -1203125 | M27: =M38*-1 -> -1203125 | N27: =N38*-1 -> -1203125 | ... CH27: =CH38*-1 -> 0
B28: Capital, end of period | D28: final | E28: =IF(D28="sum",SUM(G28:CH28),IF(D28="final",CH28,IF(D28="initial",G28,IF(D28="average",AVERAGE(G28:CH28),0)))) -> 0 | G28: =SUM(G22:G27) -> 0 | H28: =SUM(H22:H27) -> 0 | I28: =SUM(I22:I27) -> 0 | J28: =SUM(J22:J27) -> 0 | K28: =SUM(K22:K27) -> 0 | L28: =SUM(L22:L27) -> 0 | M28: =SUM(M22:M27) -> 0 | N28: =SUM(N22:N27) -> 0 | ... CH28: =SUM(CH22:CH27) -> 0
B30: Committed Capital | D30: sum | E30: =IF(D30="sum",SUM(G30:CH30),IF(D30="final",CH30,IF(D30="initial",G30,IF(D30="average",AVERAGE(G30:CH30),0)))) -> 25000000 | G30: ='Get Started 3'!$E9*G19 -> 25000000 | H30: ='Get Started 3'!$E9*H19 -> 0 | I30: ='Get Started 3'!$E9*I19 -> 0 | J30: ='Get Started 3'!$E9*J19 -> 0 | K30: ='Get Started 3'!$E9*K19 -> 0 | L30: ='Get Started 3'!$E9*L19 -> 0 | M30: ='Get Started 3'!$E9*M19 -> 0 | N30: ='Get Started 3'!$E9*N19 -> 0 | ... CH30: ='Get Started 3'!$E9*CH19 -> 0
B31: Called Capital | D31: sum | E31: =IF(D31="sum",SUM(G31:CH31),IF(D31="final",CH31,IF(D31="initial",G31,IF(D31="average",AVERAGE(G31:CH31),0)))) -> 25000000 | G31: =IF($E20<>0,G20*$E30, MIN($E30-F60, MAX(0,G38+G39+G40+G41-G42))) -> 1444375 | H31: =IF($E20<>0,H20*$E30, MIN($E30-G60, MAX(0,H38+H39+H40+H41-H42))) -> 1344375 | I31: =IF($E20<>0,I20*$E30, MIN($E30-H60, MAX(0,I38+I39+I40+I41-I42))) -> 1344375 | J31: =IF($E20<>0,J20*$E30, MIN($E30-I60, MAX(0,J38+J39+J40+J41-J42))) -> 1344375 | K31: =IF($E20<>0,K20*$E30, MIN($E30-J60, MAX(0,K38+K39+K40+K41-K42))) -> 1344375 | L31: =IF($E20<>0,L20*$E30, MIN($E30-K60, MAX(0,L38+L39+L40+L41-L42))) -> 1344375 | M31: =IF($E20<>0,M20*$E30, MIN($E30-L60, MAX(0,M38+M39+M40+M41-M42))) -> 1344375 | N31: =IF($E20<>0,N20*$E30, MIN($E30-M60, MAX(0,N38+N39+N40+N41-N42))) -> 1344375 | ... CH31: =IF($E20<>0,CH20*$E30, MIN($E30-CG60, MAX(0,CH38+CH39+CH40+CH41-CH42))) -> 0
B32: Manual Investments | D32: sum | E32: =IF(D32="sum",SUM(G32:CH32),IF(D32="final",CH32,IF(D32="initial",G32,IF(D32="average",AVERAGE(G32:CH32),0)))) -> 0 | G32: 0 | H32: 0 | I32: 0 | J32: 0 | K32: 0 | L32: 0 | M32: 0 | N32: 0 | O32: 0 | P32: 0 | Q32: 0 | R32: 0 | S32: 0 | T32: 0 | U32: 0 | V32: 0 | W32: 0 | X32: 0 | Y32: 0 | Z32: 0 | AA32: 0 | AB32: 0 | AC32: 0 | AD32: 0 | AE32: 0 | AF32: 0 | AG32: 0 | AH32: 0 | AI32: 0 | AJ32: 0 | AK32: 0 | AL32: 0 | AM32: 0 | AN32: 0 | AO32: 0 | AP32: 0 | AQ32: 0 | AR32: 0 | AS32: 0 | AT32: 0 | AU32: 0 | AV32: 0 | AW32: 0 | AX32: 0 | AY32: 0 | AZ32: 0 | BA32: 0 | BB32: 0 | BC32: 0 | BD32: 0 | BE32: 0 | BF32: 0 | BG32: 0 | BH32: 0 | BI32: 0 | BJ32: 0 | BK32: 0 | BL32: 0 | BM32: 0 | BN32: 0 | BO32: 0 | BP32: 0 | BQ32: 0 | BR32: 0 | BS32: 0 | BT32: 0 | BU32: 0 | BV32: 0 | BW32: 0 | BX32: 0 | BY32: 0 | BZ32: 0 | CA32: 0 | CB32: 0 | CC32: 0 | CD32: 0 | CE32: 0 | CF32: 0 | CG32: 0 | CH32: 0
B33: New Investments | D33: sum | E33: =IF(D33="sum",SUM(G33:CH33),IF(D33="final",CH33,IF(D33="initial",G33,IF(D33="average",AVERAGE(G33:CH33),0)))) -> 20052083 | G33: =IF(G8=1,'Get Started 3'!$E120/'Get Started 3'!$E15*'Get Started 3'!$E100+G208*'Get Started 3'!$E100,0) -> 1203125 | H33: =IF(H8=1,'Get Started 3'!$E120/'Get Started 3'!$E15*'Get Started 3'!$E100+H208*'Get Started 3'!$E100,0) -> 1203125 | I33: =IF(I8=1,'Get Started 3'!$E120/'Get Started 3'!$E15*'Get Started 3'!$E100+I208*'Get Started 3'!$E100,0) -> 1203125 | J33: =IF(J8=1,'Get Started 3'!$E120/'Get Started 3'!$E15*'Get Started 3'!$E100+J208*'Get Started 3'!$E100,0) -> 1203125 | K33: =IF(K8=1,'Get Started 3'!$E120/'Get Started 3'!$E15*'Get Started 3'!$E100+K208*'Get Started 3'!$E100,0) -> 1203125 | L33: =IF(L8=1,'Get Started 3'!$E120/'Get Started 3'!$E15*'Get Started 3'!$E100+L208*'Get Started 3'!$E100,0) -> 1203125 | M33: =IF(M8=1,'Get Started 3'!$E120/'Get Started 3'!$E15*'Get Started 3'!$E100+M208*'Get Started 3'!$E100,0) -> 1203125 | N33: =IF(N8=1,'Get Started 3'!$E120/'Get Started 3'!$E15*'Get Started 3'!$E100+N208*'Get Started 3'!$E100,0) -> 1203125 | ... CH33: =IF(CH8=1,'Get Started 3'!$E120/'Get Started 3'!$E15*'Get Started 3'!$E100+CH208*'Get Started 3'!$E100,0) -> 0
B34: Prorata Opportunities | D34: sum | E34: =IF(D34="sum",SUM(G34:CH34),IF(D34="final",CH34,IF(D34="initial",G34,IF(D34="average",AVERAGE(G34:CH34),0)))) -> 0 | G34: 0 | H34: 0 | I34: 0 | J34: 0 | K34: 0 | L34: 0 | M34: 0 | N34: 0 | O34: 0 | P34: 0 | Q34: 0 | R34: 0 | S34: 0 | T34: 0 | U34: 0 | V34: 0 | W34: 0 | X34: 0 | Y34: 0 | Z34: 0 | AA34: 0 | AB34: 0 | AC34: 0 | AD34: 0 | AE34: 0 | AF34: 0 | AG34: 0 | AH34: 0 | AI34: 0 | AJ34: 0 | AK34: 0 | AL34: 0 | AM34: 0 | AN34: 0 | AO34: 0 | AP34: 0 | AQ34: 0 | AR34: 0 | AS34: 0 | AT34: 0 | AU34: 0 | AV34: 0 | AW34: 0 | AX34: 0 | AY34: 0 | AZ34: 0 | BA34: 0 | BB34: 0 | BC34: 0 | BD34: 0 | BE34: 0 | BF34: 0 | BG34: 0 | BH34: 0 | BI34: 0 | BJ34: 0 | BK34: 0 | BL34: 0 | BM34: 0 | BN34: 0 | BO34: 0 | BP34: 0 | BQ34: 0 | BR34: 0 | BS34: 0 | BT34: 0 | BU34: 0 | BV34: 0 | BW34: 0 | BX34: 0 | BY34: 0 | BZ34: 0 | CA34: 0 | CB34: 0 | CC34: 0 | CD34: 0 | CE34: 0 | CF34: 0 | CG34: 0 | CH34: 0
B35: Reserves for Follow on | C35: change in reserves per period, increase in reserves when new investments are made, decrease when follow on are made or investments are written off | D35: sum | E35: =IF(D35="sum",SUM(G35:CH35),IF(D35="final",CH35,IF(D35="initial",G35,IF(D35="average",AVERAGE(G35:CH35),0)))) -> 0 | G35: 0 | H35: 0 | I35: 0 | J35: 0 | K35: 0 | L35: 0 | M35: 0 | N35: 0 | O35: 0 | P35: 0 | Q35: 0 | R35: 0 | S35: 0 | T35: 0 | U35: 0 | V35: 0 | W35: 0 | X35: 0 | Y35: 0 | Z35: 0 | AA35: 0 | AB35: 0 | AC35: 0 | AD35: 0 | AE35: 0 | AF35: 0 | AG35: 0 | AH35: 0 | AI35: 0 | AJ35: 0 | AK35: 0 | AL35: 0 | AM35: 0 | AN35: 0 | AO35: 0 | AP35: 0 | AQ35: 0 | AR35: 0 | AS35: 0 | AT35: 0 | AU35: 0 | AV35: 0 | AW35: 0 | AX35: 0 | AY35: 0 | AZ35: 0 | BA35: 0 | BB35: 0 | BC35: 0 | BD35: 0 | BE35: 0 | BF35: 0 | BG35: 0 | BH35: 0 | BI35: 0 | BJ35: 0 | BK35: 0 | BL35: 0 | BM35: 0 | BN35: 0 | BO35: 0 | BP35: 0 | BQ35: 0 | BR35: 0 | BS35: 0 | BT35: 0 | BU35: 0 | BV35: 0 | BW35: 0 | BX35: 0 | BY35: 0 | BZ35: 0 | CA35: 0 | CB35: 0 | CC35: 0 | CD35: 0 | CE35: 0 | CF35: 0 | CG35: 0 | CH35: 0
B36: Follow on Investments | D36: sum | E36: =IF(D36="sum",SUM(G36:CH36),IF(D36="final",CH36,IF(D36="initial",G36,IF(D36="average",AVERAGE(G36:CH36),0)))) -> 0 | G36: ='Get Started 3'!$E122*G255 -> 0 | H36: ='Get Started 3'!$E122*H255 -> 0 | I36: ='Get Started 3'!$E122*I255 -> 0 | J36: ='Get Started 3'!$E122*J255 -> 0 | K36: ='Get Started 3'!$E122*K255 -> 0 | L36: ='Get Started 3'!$E122*L255 -> 0 | M36: ='Get Started 3'!$E122*M255 -> 0 | N36: ='Get Started 3'!$E122*N255 -> 0 | ... CH36: ='Get Started 3'!$E122*CH255 -> 0
B37: Total Investments, by cohort of New Investments | D37: sum | E37: =IF(D37="sum",SUM(G37:CH37),IF(D37="final",CH37,IF(D37="initial",G37,IF(D37="average",AVERAGE(G37:CH37),0)))) -> 20052083 | G37: =G33*'Get Started 3'!$F100/'Get Started 3'!$E100+G33+G32 -> 1203125 | H37: =H33*'Get Started 3'!$F100/'Get Started 3'!$E100+H33+H32 -> 1203125 | I37: =I33*'Get Started 3'!$F100/'Get Started 3'!$E100+I33+I32 -> 1203125 | J37: =J33*'Get Started 3'!$F100/'Get Started 3'!$E100+J33+J32 -> 1203125 | K37: =K33*'Get Started 3'!$F100/'Get Started 3'!$E100+K33+K32 -> 1203125 | L37: =L33*'Get Started 3'!$F100/'Get Started 3'!$E100+L33+L32 -> 1203125 | M37: =M33*'Get Started 3'!$F100/'Get Started 3'!$E100+M33+M32 -> 1203125 | N37: =N33*'Get Started 3'!$F100/'Get Started 3'!$E100+N33+N32 -> 1203125 | ... CH37: =CH33*'Get Started 3'!$F100/'Get Started 3'!$E100+CH33+CH32 -> 0
B38: Total Investments | D38: sum | E38: =IF(D38="sum",SUM(G38:CH38),IF(D38="final",CH38,IF(D38="initial",G38,IF(D38="average",AVERAGE(G38:CH38),0)))) -> 20052083 | G38: =SUM(G33,G36,G32) -> 1203125 | H38: =SUM(H33,H36,H32) -> 1203125 | I38: =SUM(I33,I36,I32) -> 1203125 | J38: =SUM(J33,J36,J32) -> 1203125 | K38: =SUM(K33,K36,K32) -> 1203125 | L38: =SUM(L33,L36,L32) -> 1203125 | M38: =SUM(M33,M36,M32) -> 1203125 | N38: =SUM(N33,N36,N32) -> 1203125 | ... CH38: =SUM(CH33,CH36,CH32) -> 0
B39: Organizational Expenses | D39: sum | E39: =IF(D39="sum",SUM(G39:CH39),IF(D39="final",CH39,IF(D39="initial",G39,IF(D39="average",AVERAGE(G39:CH39),0)))) -> 100000 | G39: =IF(G4=1,'Get Started 3'!$E11,0) -> 100000 | H39: =IF(H4=1,'Get Started 3'!$E11,0) -> 0 | I39: =IF(I4=1,'Get Started 3'!$E11,0) -> 0 | J39: =IF(J4=1,'Get Started 3'!$E11,0) -> 0 | K39: =IF(K4=1,'Get Started 3'!$E11,0) -> 0 | L39: =IF(L4=1,'Get Started 3'!$E11,0) -> 0 | M39: =IF(M4=1,'Get Started 3'!$E11,0) -> 0 | N39: =IF(N4=1,'Get Started 3'!$E11,0) -> 0 | ... CH39: =IF(CH4=1,'Get Started 3'!$E11,0) -> 0
B40: Operational Expenses | D40: sum | E40: =IF(D40="sum",SUM(G40:CH40),IF(D40="final",CH40,IF(D40="initial",G40,IF(D40="average",AVERAGE(G40:CH40),0)))) -> 750000 | G40: ='Get Started 3'!$E12*G10/4 -> 18750 | H40: ='Get Started 3'!$E12*H10/4 -> 18750 | I40: ='Get Started 3'!$E12*I10/4 -> 18750 | J40: ='Get Started 3'!$E12*J10/4 -> 18750 | K40: ='Get Started 3'!$E12*K10/4 -> 18750 | L40: ='Get Started 3'!$E12*L10/4 -> 18750 | M40: ='Get Started 3'!$E12*M10/4 -> 18750 | N40: ='Get Started 3'!$E12*N10/4 -> 18750 | ... CH40: ='Get Started 3'!$E12*CH10/4 -> 0
B41: Management Fees | D41: sum | E41: =IF(D41="sum",SUM(G41:CH41),IF(D41="final",CH41,IF(D41="initial",G41,IF(D41="average",AVERAGE(G41:CH41),0)))) -> 4900000 | G41: =IFERROR(IF(G15="committed",G83*IF($C17=TRUE,1-'Get Started 3'!$E10,1)*G14+IF(AND(G4<>1,G54*IF($C17=TRUE,1-'Get Started 3'!$E10,1)<>0,SUM($G54:G54)*IF($C17=TRUE,1-'Get Started 3'!$E10,1)<>E54*IF($C17=TRUE,1-'Get Started 3'!$E10,1)),G54*IF($C17=TRUE,1-'Get Started 3'!$E10,1)*(G4-1)*G14,0),IF(G15="called",G14*(G60+F60)/2*IF($C17=TRUE,1-'Get Started 3'!$E10,1),G14*(G85+F85)/2*IF($C17=TRUE,1-'Get Started 3'!$E10,1))),0) -> 122500 | H41: =IFERROR(IF(H15="committed",H83*IF($C17=TRUE,1-'Get Started 3'!$E10,1)*H14+IF(AND(H4<>1,H54*IF($C17=TRUE,1-'Get Started 3'!$E10,1)<>0,SUM($G54:H54)*IF($C17=TRUE,1-'Get Started 3'!$E10,1)<>F54*IF($C17=TRUE,1-'Get Started 3'!$E10,1)),H54*IF($C17=TRUE,1-'Get Started 3'!$E10,1)*(H4-1)*H14,0),IF(H15="called",H14*(H60+G60)/2*IF($C17=TRUE,1-'Get Started 3'!$E10,1),H14*(H85+G85)/2*IF($C17=TRUE,1-'Get Started 3'!$E10,1))),0) -> 122500 | I41: =IFERROR(IF(I15="committed",I83*IF($C17=TRUE,1-'Get Started 3'!$E10,1)*I14+IF(AND(I4<>1,I54*IF($C17=TRUE,1-'Get Started 3'!$E10,1)<>0,SUM($G54:I54)*IF($C17=TRUE,1-'Get Started 3'!$E10,1)<>G54*IF($C17=TRUE,1-'Get Started 3'!$E10,1)),I54*IF($C17=TRUE,1-'Get Started 3'!$E10,1)*(I4-1)*I14,0),IF(I15="called",I14*(I60+H60)/2*IF($C17=TRUE,1-'Get Started 3'!$E10,1),I14*(I85+H85)/2*IF($C17=TRUE,1-'Get Started 3'!$E10,1))),0) -> 122500 | J41: =IFERROR(IF(J15="committed",J83*IF($C17=TRUE,1-'Get Started 3'!$E10,1)*J14+IF(AND(J4<>1,J54*IF($C17=TRUE,1-'Get Started 3'!$E10,1)<>0,SUM($G54:J54)*IF($C17=TRUE,1-'Get Started 3'!$E10,1)<>H54*IF($C17=TRUE,1-'Get Started 3'!$E10,1)),J54*IF($C17=TRUE,1-'Get Started 3'!$E10,1)*(J4-1)*J14,0),IF(J15="called",J14*(J60+I60)/2*IF($C17=TRUE,1-'Get Started 3'!$E10,1),J14*(J85+I85)/2*IF($C17=TRUE,1-'Get Started 3'!$E10,1))),0) -> 122500 | K41: =IFERROR(IF(K15="committed",K83*IF($C17=TRUE,1-'Get Started 3'!$E10,1)*K14+IF(AND(K4<>1,K54*IF($C17=TRUE,1-'Get Started 3'!$E10,1)<>0,SUM($G54:K54)*IF($C17=TRUE,1-'Get Started 3'!$E10,1)<>I54*IF($C17=TRUE,1-'Get Started 3'!$E10,1)),K54*IF($C17=TRUE,1-'Get Started 3'!$E10,1)*(K4-1)*K14,0),IF(K15="called",K14*(K60+J60)/2*IF($C17=TRUE,1-'Get Started 3'!$E10,1),K14*(K85+J85)/2*IF($C17=TRUE,1-'Get Started 3'!$E10,1))),0) -> 122500 | L41: =IFERROR(IF(L15="committed",L83*IF($C17=TRUE,1-'Get Started 3'!$E10,1)*L14+IF(AND(L4<>1,L54*IF($C17=TRUE,1-'Get Started 3'!$E10,1)<>0,SUM($G54:L54)*IF($C17=TRUE,1-'Get Started 3'!$E10,1)<>J54*IF($C17=TRUE,1-'Get Started 3'!$E10,1)),L54*IF($C17=TRUE,1-'Get Started 3'!$E10,1)*(L4-1)*L14,0),IF(L15="called",L14*(L60+K60)/2*IF($C17=TRUE,1-'Get Started 3'!$E10,1),L14*(L85+K85)/2*IF($C17=TRUE,1-'Get Started 3'!$E10,1))),0) -> 122500 | M41: =IFERROR(IF(M15="committed",M83*IF($C17=TRUE,1-'Get Started 3'!$E10,1)*M14+IF(AND(M4<>1,M54*IF($C17=TRUE,1-'Get Started 3'!$E10,1)<>0,SUM($G54:M54)*IF($C17=TRUE,1-'Get Started 3'!$E10,1)<>K54*IF($C17=TRUE,1-'Get Started 3'!$E10,1)),M54*IF($C17=TRUE,1-'Get Started 3'!$E10,1)*(M4-1)*M14,0),IF(M15="called",M14*(M60+L60)/2*IF($C17=TRUE,1-'Get Started 3'!$E10,1),M14*(M85+L85)/2*IF($C17=TRUE,1-'Get Started 3'!$E10,1))),0) -> 122500 | N41: =IFERROR(IF(N15="committed",N83*IF($C17=TRUE,1-'Get Started 3'!$E10,1)*N14+IF(AND(N4<>1,N54*IF($C17=TRUE,1-'Get Started 3'!$E10,1)<>0,SUM($G54:N54)*IF($C17=TRUE,1-'Get Started 3'!$E10,1)<>L54*IF($C17=TRUE,1-'Get Started 3'!$E10,1)),N54*IF($C17=TRUE,1-'Get Started 3'!$E10,1)*(N4-1)*N14,0),IF(N15="called",N14*(N60+M60)/2*IF($C17=TRUE,1-'Get Started 3'!$E10,1),N14*(N85+M85)/2*IF($C17=TRUE,1-'Get Started 3'!$E10,1))),0) -> 122500 | ... CH41: =IFERROR(IF(CH15="committed",CH83*IF($C17=TRUE,1-'Get Started 3'!$E10,1)*CH14+IF(AND(CH4<>1,CH54*IF($C17=TRUE,1-'Get Started 3'!$E10,1)<>0,SUM($G54:CH54)*IF($C17=TRUE,1-'Get Started 3'!$E10,1)<>CF54*IF($C17=TRUE,1-'Get Started 3'!$E10,1)),CH54*IF($C17=TRUE,1-'Get Started 3'!$E10,1)*(CH4-1)*CH14,0),IF(CH15="called",CH14*(CH60+CG60)/2*IF($C17=TRUE,1-'Get Started 3'!$E10,1),CH14*(CH85+CG85)/2*IF($C17=TRUE,1-'Get Started 3'!$E10,1))),0) -> 0
B42: Recycled Capital | D42: sum | E42: =IF(D42="sum",SUM(G42:CH42),IF(D42="final",CH42,IF(D42="initial",G42,IF(D42="average",AVERAGE(G42:CH42),0)))) -> 802083.33 | G42: =G208 -> 0 | H42: =H208 -> 0 | I42: =I208 -> 0 | J42: =J208 -> 0 | K42: =K208 -> 0 | L42: =L208 -> 0 | M42: =M208 -> 0 | N42: =N208 -> 0 | ... CH42: =CH208 -> 0
B43: Proceeds | D43: sum | E43: =IF(D43="sum",SUM(G43:CH43),IF(D43="final",CH43,IF(D43="initial",G43,IF(D43="average",AVERAGE(G43:CH43),0)))) -> 2.3160156e+08 | G43: =IF(G4<'Get Started 3'!$H112,0,OFFSET(G37,0,-1*'Get Started 3'!$H112)*'Get Started 3'!$H42*'Get Started 3'!$G112)+IF(G4<'Get Started 3'!$H111,0,OFFSET(G37,0,-1*'Get Started 3'!$H111)*'Get Started 3'!$G42*'Get Started 3'!$G111)+IF(G4<'Get Started 3'!$H110,0,OFFSET(G37,0,-1*'Get Started 3'!$H110)*'Get Started 3'!$F42*'Get Started 3'!$G110)+IF(G4<'Get Started 3'!$H109,0,OFFSET(G37,0,-1*'Get Started 3'!$H109)*'Get Started 3'!$E42*'Get Started 3'!$G109) -> 0 | H43: =IF(H4<'Get Started 3'!$H112,0,OFFSET(H37,0,-1*'Get Started 3'!$H112)*'Get Started 3'!$H42*'Get Started 3'!$G112)+IF(H4<'Get Started 3'!$H111,0,OFFSET(H37,0,-1*'Get Started 3'!$H111)*'Get Started 3'!$G42*'Get Started 3'!$G111)+IF(H4<'Get Started 3'!$H110,0,OFFSET(H37,0,-1*'Get Started 3'!$H110)*'Get Started 3'!$F42*'Get Started 3'!$G110)+IF(H4<'Get Started 3'!$H109,0,OFFSET(H37,0,-1*'Get Started 3'!$H109)*'Get Started 3'!$E42*'Get Started 3'!$G109) -> 0 | I43: =IF(I4<'Get Started 3'!$H112,0,OFFSET(I37,0,-1*'Get Started 3'!$H112)*'Get Started 3'!$H42*'Get Started 3'!$G112)+IF(I4<'Get Started 3'!$H111,0,OFFSET(I37,0,-1*'Get Started 3'!$H111)*'Get Started 3'!$G42*'Get Started 3'!$G111)+IF(I4<'Get Started 3'!$H110,0,OFFSET(I37,0,-1*'Get Started 3'!$H110)*'Get Started 3'!$F42*'Get Started 3'!$G110)+IF(I4<'Get Started 3'!$H109,0,OFFSET(I37,0,-1*'Get Started 3'!$H109)*'Get Started 3'!$E42*'Get Started 3'!$G109) -> 0 | J43: =IF(J4<'Get Started 3'!$H112,0,OFFSET(J37,0,-1*'Get Started 3'!$H112)*'Get Started 3'!$H42*'Get Started 3'!$G112)+IF(J4<'Get Started 3'!$H111,0,OFFSET(J37,0,-1*'Get Started 3'!$H111)*'Get Started 3'!$G42*'Get Started 3'!$G111)+IF(J4<'Get Started 3'!$H110,0,OFFSET(J37,0,-1*'Get Started 3'!$H110)*'Get Started 3'!$F42*'Get Started 3'!$G110)+IF(J4<'Get Started 3'!$H109,0,OFFSET(J37,0,-1*'Get Started 3'!$H109)*'Get Started 3'!$E42*'Get Started 3'!$G109) -> 0 | K43: =IF(K4<'Get Started 3'!$H112,0,OFFSET(K37,0,-1*'Get Started 3'!$H112)*'Get Started 3'!$H42*'Get Started 3'!$G112)+IF(K4<'Get Started 3'!$H111,0,OFFSET(K37,0,-1*'Get Started 3'!$H111)*'Get Started 3'!$G42*'Get Started 3'!$G111)+IF(K4<'Get Started 3'!$H110,0,OFFSET(K37,0,-1*'Get Started 3'!$H110)*'Get Started 3'!$F42*'Get Started 3'!$G110)+IF(K4<'Get Started 3'!$H109,0,OFFSET(K37,0,-1*'Get Started 3'!$H109)*'Get Started 3'!$E42*'Get Started 3'!$G109) -> 0 | L43: =IF(L4<'Get Started 3'!$H112,0,OFFSET(L37,0,-1*'Get Started 3'!$H112)*'Get Started 3'!$H42*'Get Started 3'!$G112)+IF(L4<'Get Started 3'!$H111,0,OFFSET(L37,0,-1*'Get Started 3'!$H111)*'Get Started 3'!$G42*'Get Started 3'!$G111)+IF(L4<'Get Started 3'!$H110,0,OFFSET(L37,0,-1*'Get Started 3'!$H110)*'Get Started 3'!$F42*'Get Started 3'!$G110)+IF(L4<'Get Started 3'!$H109,0,OFFSET(L37,0,-1*'Get Started 3'!$H109)*'Get Started 3'!$E42*'Get Started 3'!$G109) -> 0 | M43: =IF(M4<'Get Started 3'!$H112,0,OFFSET(M37,0,-1*'Get Started 3'!$H112)*'Get Started 3'!$H42*'Get Started 3'!$G112)+IF(M4<'Get Started 3'!$H111,0,OFFSET(M37,0,-1*'Get Started 3'!$H111)*'Get Started 3'!$G42*'Get Started 3'!$G111)+IF(M4<'Get Started 3'!$H110,0,OFFSET(M37,0,-1*'Get Started 3'!$H110)*'Get Started 3'!$F42*'Get Started 3'!$G110)+IF(M4<'Get Started 3'!$H109,0,OFFSET(M37,0,-1*'Get Started 3'!$H109)*'Get Started 3'!$E42*'Get Started 3'!$G109) -> 0 | N43: =IF(N4<'Get Started 3'!$H112,0,OFFSET(N37,0,-1*'Get Started 3'!$H112)*'Get Started 3'!$H42*'Get Started 3'!$G112)+IF(N4<'Get Started 3'!$H111,0,OFFSET(N37,0,-1*'Get Started 3'!$H111)*'Get Started 3'!$G42*'Get Started 3'!$G111)+IF(N4<'Get Started 3'!$H110,0,OFFSET(N37,0,-1*'Get Started 3'!$H110)*'Get Started 3'!$F42*'Get Started 3'!$G110)+IF(N4<'Get Started 3'!$H109,0,OFFSET(N37,0,-1*'Get Started 3'!$H109)*'Get Started 3'!$E42*'Get Started 3'!$G109) -> 0 | ... CH43: =IF(CH4<'Get Started 3'!$H112,0,OFFSET(CH37,0,-1*'Get Started 3'!$H112)*'Get Started 3'!$H42*'Get Started 3'!$G112)+IF(CH4<'Get Started 3'!$H111,0,OFFSET(CH37,0,-1*'Get Started 3'!$H111)*'Get Started 3'!$G42*'Get Started 3'!$G111)+IF(CH4<'Get Started 3'!$H110,0,OFFSET(CH37,0,-1*'Get Started 3'!$H110)*'Get Started 3'!$F42*'Get Started 3'!$G110)+IF(CH4<'Get Started 3'!$H109,0,OFFSET(CH37,0,-1*'Get Started 3'!$H109)*'Get Started 3'!$E42*'Get Started 3'!$G109) -> 0
B44: Preferred Return | D44: sum | E44: =IF(D44="sum",SUM(G44:CH44),IF(D44="final",CH44,IF(D44="initial",G44,IF(D44="average",AVERAGE(G44:CH44),0)))) -> 0 | G44: 0 | H44: 0 | I44: 0 | J44: 0 | K44: 0 | L44: 0 | M44: 0 | N44: 0 | O44: 0 | P44: 0 | Q44: 0 | R44: 0 | S44: 0 | T44: 0 | U44: 0 | V44: 0 | W44: 0 | X44: 0 | Y44: 0 | Z44: 0 | AA44: 0 | AB44: 0 | AC44: 0 | AD44: 0 | AE44: 0 | AF44: 0 | AG44: 0 | AH44: 0 | AI44: 0 | AJ44: 0 | AK44: 0 | AL44: 0 | AM44: 0 | AN44: 0 | AO44: 0 | AP44: 0 | AQ44: 0 | AR44: 0 | AS44: 0 | AT44: 0 | AU44: 0 | AV44: 0 | AW44: 0 | AX44: 0 | AY44: 0 | AZ44: 0 | BA44: 0 | BB44: 0 | BC44: 0 | BD44: 0 | BE44: 0 | BF44: 0 | BG44: 0 | BH44: 0 | BI44: 0 | BJ44: 0 | BK44: 0 | BL44: 0 | BM44: 0 | BN44: 0 | BO44: 0 | BP44: 0 | BQ44: 0 | BR44: 0 | BS44: 0 | BT44: 0 | BU44: 0 | BV44: 0 | BW44: 0 | BX44: 0 | BY44: 0 | BZ44: 0 | CA44: 0 | CB44: 0 | CC44: 0 | CD44: 0 | CE44: 0 | CF44: 0 | CG44: 0 | CH44: 0
B45: GP Catchup | D45: sum | E45: =IF(D45="sum",SUM(G45:CH45),IF(D45="final",CH45,IF(D45="initial",G45,IF(D45="average",AVERAGE(G45:CH45),0)))) -> 0 | G45: 0 | H45: 0 | I45: 0 | J45: 0 | K45: 0 | L45: 0 | M45: 0 | N45: 0 | O45: 0 | P45: 0 | Q45: 0 | R45: 0 | S45: 0 | T45: 0 | U45: 0 | V45: 0 | W45: 0 | X45: 0 | Y45: 0 | Z45: 0 | AA45: 0 | AB45: 0 | AC45: 0 | AD45: 0 | AE45: 0 | AF45: 0 | AG45: 0 | AH45: 0 | AI45: 0 | AJ45: 0 | AK45: 0 | AL45: 0 | AM45: 0 | AN45: 0 | AO45: 0 | AP45: 0 | AQ45: 0 | AR45: 0 | AS45: 0 | AT45: 0 | AU45: 0 | AV45: 0 | AW45: 0 | AX45: 0 | AY45: 0 | AZ45: 0 | BA45: 0 | BB45: 0 | BC45: 0 | BD45: 0 | BE45: 0 | BF45: 0 | BG45: 0 | BH45: 0 | BI45: 0 | BJ45: 0 | BK45: 0 | BL45: 0 | BM45: 0 | BN45: 0 | BO45: 0 | BP45: 0 | BQ45: 0 | BR45: 0 | BS45: 0 | BT45: 0 | BU45: 0 | BV45: 0 | BW45: 0 | BX45: 0 | BY45: 0 | BZ45: 0 | CA45: 0 | CB45: 0 | CC45: 0 | CD45: 0 | CE45: 0 | CF45: 0 | CG45: 0 | CH45: 0
B46: Carried Interest | D46: sum | E46: =IF(D46="sum",SUM(G46:CH46),IF(D46="final",CH46,IF(D46="initial",G46,IF(D46="average",AVERAGE(G46:CH46),0)))) -> 41159896 | G46: =G194 -> 0 | H46: =H194 -> 0 | I46: =I194 -> 0 | J46: =J194 -> 0 | K46: =K194 -> 0 | L46: =L194 -> 0 | M46: =M194 -> 0 | N46: =N194 -> 0 | ... CH46: =CH194 -> 0
B47: Distributions | D47: sum | E47: =IF(D47="sum",SUM(G47:CH47),IF(D47="final",CH47,IF(D47="initial",G47,IF(D47="average",AVERAGE(G47:CH47),0)))) -> 1.8963958e+08 | G47: =G190+G193-G194 -> 0 | H47: =H190+H193-H194 -> 0 | I47: =I190+I193-I194 -> 0 | J47: =J190+J193-J194 -> 0 | K47: =K190+K193-K194 -> 0 | L47: =L190+L193-L194 -> 0 | M47: =M190+M193-M194 -> 0 | N47: =N190+N193-N194 -> 0 | ... CH47: =CH190+CH193-CH194 -> 0
B48: Writeoffs | D48: sum | E48: =IF(D48="sum",SUM(G48:CH48),IF(D48="final",CH48,IF(D48="initial",G48,IF(D48="average",AVERAGE(G48:CH48),0)))) -> 11362847 | G48: =IF('Get Started 3'!$G112<>0,0,IF(G4<'Get Started 3'!$H112,0,OFFSET(G37,0,-1*'Get Started 3'!$H112)*'Get Started 3'!$H42))+IF('Get Started 3'!$G111<>0,0,IF(G4<'Get Started 3'!$H111,0,OFFSET(G37,0,-1*'Get Started 3'!$H111)*'Get Started 3'!$G42))+IF('Get Started 3'!$G110<>0,0,IF(G4<'Get Started 3'!$H110,0,OFFSET(G37,0,-1*'Get Started 3'!$H110)*'Get Started 3'!$F42))+IF('Get Started 3'!$G109<>0,0,IF(G4<'Get Started 3'!$H109,0,OFFSET(G37,0,-1*'Get Started 3'!$H109)*'Get Started 3'!$E42)) -> 0 | H48: =IF('Get Started 3'!$G112<>0,0,IF(H4<'Get Started 3'!$H112,0,OFFSET(H37,0,-1*'Get Started 3'!$H112)*'Get Started 3'!$H42))+IF('Get Started 3'!$G111<>0,0,IF(H4<'Get Started 3'!$H111,0,OFFSET(H37,0,-1*'Get Started 3'!$H111)*'Get Started 3'!$G42))+IF('Get Started 3'!$G110<>0,0,IF(H4<'Get Started 3'!$H110,0,OFFSET(H37,0,-1*'Get Started 3'!$H110)*'Get Started 3'!$F42))+IF('Get Started 3'!$G109<>0,0,IF(H4<'Get Started 3'!$H109,0,OFFSET(H37,0,-1*'Get Started 3'!$H109)*'Get Started 3'!$E42)) -> 0 | I48: =IF('Get Started 3'!$G112<>0,0,IF(I4<'Get Started 3'!$H112,0,OFFSET(I37,0,-1*'Get Started 3'!$H112)*'Get Started 3'!$H42))+IF('Get Started 3'!$G111<>0,0,IF(I4<'Get Started 3'!$H111,0,OFFSET(I37,0,-1*'Get Started 3'!$H111)*'Get Started 3'!$G42))+IF('Get Started 3'!$G110<>0,0,IF(I4<'Get Started 3'!$H110,0,OFFSET(I37,0,-1*'Get Started 3'!$H110)*'Get Started 3'!$F42))+IF('Get Started 3'!$G109<>0,0,IF(I4<'Get Started 3'!$H109,0,OFFSET(I37,0,-1*'Get Started 3'!$H109)*'Get Started 3'!$E42)) -> 0 | J48: =IF('Get Started 3'!$G112<>0,0,IF(J4<'Get Started 3'!$H112,0,OFFSET(J37,0,-1*'Get Started 3'!$H112)*'Get Started 3'!$H42))+IF('Get Started 3'!$G111<>0,0,IF(J4<'Get Started 3'!$H111,0,OFFSET(J37,0,-1*'Get Started 3'!$H111)*'Get Started 3'!$G42))+IF('Get Started 3'!$G110<>0,0,IF(J4<'Get Started 3'!$H110,0,OFFSET(J37,0,-1*'Get Started 3'!$H110)*'Get Started 3'!$F42))+IF('Get Started 3'!$G109<>0,0,IF(J4<'Get Started 3'!$H109,0,OFFSET(J37,0,-1*'Get Started 3'!$H109)*'Get Started 3'!$E42)) -> 0 | K48: =IF('Get Started 3'!$G112<>0,0,IF(K4<'Get Started 3'!$H112,0,OFFSET(K37,0,-1*'Get Started 3'!$H112)*'Get Started 3'!$H42))+IF('Get Started 3'!$G111<>0,0,IF(K4<'Get Started 3'!$H111,0,OFFSET(K37,0,-1*'Get Started 3'!$H111)*'Get Started 3'!$G42))+IF('Get Started 3'!$G110<>0,0,IF(K4<'Get Started 3'!$H110,0,OFFSET(K37,0,-1*'Get Started 3'!$H110)*'Get Started 3'!$F42))+IF('Get Started 3'!$G109<>0,0,IF(K4<'Get Started 3'!$H109,0,OFFSET(K37,0,-1*'Get Started 3'!$H109)*'Get Started 3'!$E42)) -> 0 | L48: =IF('Get Started 3'!$G112<>0,0,IF(L4<'Get Started 3'!$H112,0,OFFSET(L37,0,-1*'Get Started 3'!$H112)*'Get Started 3'!$H42))+IF('Get Started 3'!$G111<>0,0,IF(L4<'Get Started 3'!$H111,0,OFFSET(L37,0,-1*'Get Started 3'!$H111)*'Get Started 3'!$G42))+IF('Get Started 3'!$G110<>0,0,IF(L4<'Get Started 3'!$H110,0,OFFSET(L37,0,-1*'Get Started 3'!$H110)*'Get Started 3'!$F42))+IF('Get Started 3'!$G109<>0,0,IF(L4<'Get Started 3'!$H109,0,OFFSET(L37,0,-1*'Get Started 3'!$H109)*'Get Started 3'!$E42)) -> 0 | M48: =IF('Get Started 3'!$G112<>0,0,IF(M4<'Get Started 3'!$H112,0,OFFSET(M37,0,-1*'Get Started 3'!$H112)*'Get Started 3'!$H42))+IF('Get Started 3'!$G111<>0,0,IF(M4<'Get Started 3'!$H111,0,OFFSET(M37,0,-1*'Get Started 3'!$H111)*'Get Started 3'!$G42))+IF('Get Started 3'!$G110<>0,0,IF(M4<'Get Started 3'!$H110,0,OFFSET(M37,0,-1*'Get Started 3'!$H110)*'Get Started 3'!$F42))+IF('Get Started 3'!$G109<>0,0,IF(M4<'Get Started 3'!$H109,0,OFFSET(M37,0,-1*'Get Started 3'!$H109)*'Get Started 3'!$E42)) -> 0 | N48: =IF('Get Started 3'!$G112<>0,0,IF(N4<'Get Started 3'!$H112,0,OFFSET(N37,0,-1*'Get Started 3'!$H112)*'Get Started 3'!$H42))+IF('Get Started 3'!$G111<>0,0,IF(N4<'Get Started 3'!$H111,0,OFFSET(N37,0,-1*'Get Started 3'!$H111)*'Get Started 3'!$G42))+IF('Get Started 3'!$G110<>0,0,IF(N4<'Get Started 3'!$H110,0,OFFSET(N37,0,-1*'Get Started 3'!$H110)*'Get Started 3'!$F42))+IF('Get Started 3'!$G109<>0,0,IF(N4<'Get Started 3'!$H109,0,OFFSET(N37,0,-1*'Get Started 3'!$H109)*'Get Started 3'!$E42)) -> 0 | ... CH48: =IF('Get Started 3'!$G112<>0,0,IF(CH4<'Get Started 3'!$H112,0,OFFSET(CH37,0,-1*'Get Started 3'!$H112)*'Get Started 3'!$H42))+IF('Get Started 3'!$G111<>0,0,IF(CH4<'Get Started 3'!$H111,0,OFFSET(CH37,0,-1*'Get Started 3'!$H111)*'Get Started 3'!$G42))+IF('Get Started 3'!$G110<>0,0,IF(CH4<'Get Started 3'!$H110,0,OFFSET(CH37,0,-1*'Get Started 3'!$H110)*'Get Started 3'!$F42))+IF('Get Started 3'!$G109<>0,0,IF(CH4<'Get Started 3'!$H109,0,OFFSET(CH37,0,-1*'Get Started 3'!$H109)*'Get Started 3'!$E42)) -> 0
