Workbook

Sheet README
B2: Enterprise SaaS Forecasting Tool, by Foresight
B3: A basic tool to help you model the revenues and costs of an SaaS business.
B5: Copyright & Contact | C5: This was created by Taylor Davidson (@tdavidson) of Foresight. © 2023, Unstructured Ventures, LLC. Questions, contact taylor@foresight.is or @tdavidson
B6: License | C6: tl:dr; You can modify, edit, use, and share within your company (and with third-parties as needed to operate your business). You may not redistribute, resell, give away to others. Full license.
B7: Goal | C7: Goal of this model is to create an easy way for anyone to model the basic revenue operations of an SaaS business. The model uses external market data where applicable and estimates when necessary. You should adjust all metrics and inputs to fit your business.
B8: Copy to Google Sheets or Download to Excel | C8: File > Make a Copy to copy it to your own Google Drive, or File > Download to download this to use in Excel or other spreadsheet programs. See License for warranties and liabilities.
B9: Support | C9: Questions, happy to assist, contact anytime. More details on how I provide support: https://foresight.is/learn/support
B10: Missing a feature you need? | C10: Check out Alternatives to Foresight for more modeling tools, and check out Foresight's Standard Financial Model for a more comprehensive model with extensive prebuilt options for different revenue models, MRR and ARR, historical financials, budget variances, and more.
B11: Quickstart | C11: 1) Any number in blue with grey shaded background is an input (i.e. an assumption or data point that can be changed), anything in black is the result of a formula. Change blue at will, change anything in black with caution. 2) All cells and formulas are unlocked - as in all Foresight models - so that you can make edits as needed and completely understand what is going on. 3) All assumptions are illustrative ONLY, do not assume they are market data or standard. 4) As with all templates, feel free to create your own model from scratch, using this as a guide. 5) The model is constructed to fit a wide variety of businesses, and therefore, some sections may or may not be relevant to yours. I have grouped together sections on all sheets so that you can review different sections and see all the possibilities, but also easily hide the sections not relevant for you. Simply click on the "+" button on the left-hand side to unhide a section, and click on the "-" button to hide it.
B13: Outline
B15: README | C15: Contact into, overview on model. Safe to delete or hide.
B16: Formatting and Colors Overview | C16: Details on what the colors and formatting in the model mean. https://foresight.is/learn/colors-and-formatting
B17: License | C17: Terms of use of the model. Safe to delete or hide. https://foresight.is/license
B18: Get Started | C18: Assumptions used in the model
B19: Forecast | C19: Calculations for the model, with a couple detailed optional assumptions.
B20: Key Reports | C20: Key charts, using data from the Forecast sheet
B21: Model Comparison | C21: Informational sheet with links to other models available to use. Safe to delete or hide.
B22: Glossary | C22: Informational sheet on common financial terms used in the model. Safe to delete or hide.
B23: Changelog | C23: List of what has been changed in model versions. Safe to delete or hide, although I'd advise to hide (instead of delete) so can always check to see what model version you are using to compare to future changes.

Sheet License
B1: License Agreement
B2: Available on website
B4: This License Agreement (“the Agreement”) between you, the licensee, and Unstructured Ventures, LLC (the “Company”) a limited liability corporation headquartered and registered in the Commonwealth of Pennsylvania and organized under the laws of the state of Delaware. The Company owns the financial model (the “Product”) and any edits, additions, or customizations (the "Service") delivered under this Agreement. This Agreement grants you a non-exclusive, non-transferable right to use and incorporate the Product and Service in personal and corporate projects for the organization that purchased the Product and/or Service.
B6: You agree as follows:
B8: 1. Scope of use
B9: * Use and incorporate the Product and/or Service in personal and commercial projects for your company including financial models, business plans, pitch decks, etc.
B10: * You may modify the Product and/or Service to better serve your project.
B11: * You are granted unlimited usage of the Product and/or Service purchased in your organization.
B12: * If an organization is the licensee, all employees of the organization may use the same license.
B14: 2. Limitations and non-use
B15: * You may not redistribute, sublicense or resell the Product and/or Service.
B16: * You may not distribute, license or sell derivative, recompiled, reverse engineered, or modified versions of the Product and/or Service.
... B29: This Agreement is governed by the laws of the Commonwealth of Pennsylvania and the applicable laws of the United States of America. Legal proceedings related to this Agreement may only be brought in the courts of Pennsylvania. You agree to service of process at the e-mail address on your original order. Notices may be sent to Unstructured Ventures, LLC by email to hello@unstructuredventures.com or by post to Unstructured Ventures, LLC, 6360 Broad St, #5226, Pittsburgh, PA, 15206, USA.

Sheet Disclaimer
B2: Disclaimer
B4: ="This Investor Presentation is provided for informational purposes only and does not constitute an offer to buy or a solicitation of an offer to invest, or to procure an investment in "&#REF!&" (the “Company”)." -> #REF!
B5: Investments in the Company, if offered, will only be offered to a selected number of accredited investors, and only on the basis of a private offering memorandum for the Company. There are significant risks that are not presented and disclosed in this Investor Presentation. These risks could have a significant negative impact on the performance of the Company.
B6: This Investor Presentation contains forward-looking statements regarding our business plans and prospects and financial conditions, all statements, other than statements of historical fact, in this Investor Presentation, and the attached exhibits, including, among other things, statements regarding our competitive strengths, business strategy, financial projections and plans and objectives of management are forward-looking statements. Although we believe that the expectations reflected in such forward-looking statements are reasonable, there can be no assurance that such expectations will prove to be correct. Forward-looking statements are inherently subject to risks and uncertainties, many of which cannot be predicted with accuracy and some of which might not even be anticipated. Future events and actual results, financial or otherwise, could differ materially from those set forth in, or contemplated by, the forward-looking statements in this Investor Presentation, and, as such, the forward-looking statements contained herein should not be relied upon when making your investment decision. We undertake no obligation to update or revise any forward-looking statements.
B7: The financial projections in this Investor Presentation present, to the best of management’s knowledge and belief, the Company’s expected financial position, results of operations, and cash flows for the forecast period. Accordingly, the financial projections reflect its judgment, as of the date of these financial projections, of the expected conditions and its expected course of action following the sale of securities by the Company. The assumptions disclosed herein are those that management believes are significant to the financial projections. There will usually be differences between the projected and actual results, because events and circumstances frequently do not occur as expected, and those differences may be material. Since the projections are based upon assumptions about circumstances and events that have not yet taken place regarding costs, income, expenses and federal tax matters, which are subject to variations and economic events as future operations actually occur, they do not necessarily reflect the results that will be achieved and should not be relied upon. In all cases, the targeted returns are not predictions or projections that the results in the pro forma financials will be achieved nor of the performance of any investment, and are expressly subject to all assumptions embedded in the pro forma financials and the risk factors disclosed herein. This investment has a high degree of risk, and there can be no assurances that all or any of the assumptions will be true or that an investment’s actual performance will bear any relation to these hypothetical illustrations.
B8: This information contained in this Investor Presentation includes proprietary information, is strictly confidential, and is not to be used or distributed to others without the express written consent of the Company.
B9: This document has been prepared solely for information purposes and is being furnished solely for use by prospective purchasers in considering their interest in obtaining additional information and making their own evaluation of the Company and does not contain all of the information that a prospective purchaser may desire. This information reflects various assumptions by the Company concerning anticipated results, which assumptions may or may not prove to be correct, and the Company has no obligation to update such information. The only information that will have any legal effect will be that specifically contained in definitive documentation. This Investor Presentation has been submitted confidentially to a limited number of investors so that they can consider their interest in obtaining additional information and making their own evaluation of the Company. No offers to purchase the securities of the Company will be accepted prior to (1) the receipt by recipient of a complete private offering memorandum and (2) determination by the Company that the recipient is an appropriate purchaser in light of standards contained in U.S. Securities laws after a full evaluation of recipient by the Company. The Company has not authorized its use for any other purpose. This Investor Presentation may not be copied or reproduced in whole or in part. By accepting a copy of this Investor Presentation, the recipient agrees that neither it nor any of its representatives, agents or employees shall use it for any other purpose or divulge to any party any confidential information about the Company.

Sheet Get Started
B2: Get Started
B3: Setup and timescale
B5: What is the name of your company? | D5: Company | F5: This is used in the Legal Disclaimer sheet, which is purely optional, but something many people choose to include in their projections when they provide them to potential investors
B7: What is the first date you want to forecast? | D7: 44927 | E7: First month in the model; if this model is entirely a forecast of the future, input the first month you want to forecast from.
B8: What is the fiscal year end of the first year modeled? | D8: =DATE(YEAR(D7),12,31) -> 45291 | E8: Define the month that is the fiscal year end of the first year in the model. This allows you to set the fiscal years in the model, and thus the # of months in the first year forecasted in the model. The default setting uses a formula to return the year end (in December) from the first month in the forecast. Feel free to overwrite this to set a different fiscal year end, just overwrite the formula with a date.
B10: Aggregation Options | D10: only used for the aggregation options column (sum, average, initial, final)
B11: initial | D11: returns the value from the beginning of a period
B12: final | D12: returns the value from the end of a period
B13: sum | D13: returns the total during the period
B14: average | D14: returns the simple average during the period; averages are not weighted-averages, and for % growths, do not represent the average growth over the time period.

Sheet Key Reports
B2: Clients, Revenues | G2: Clients
B3: total clients and total revenues, per period | G3: new per period, and total, end of period
B27: Revenues and Deferred Revenue
B28: during and at end of each period; helps understand future revenues to be recognized from deferred revenues

Sheet Forecast
B2: Forecast
B4: Date | C4: Unit | D4: Note | V4: =EDATE(W4,-1) -> 44926 | W4: =EOMONTH('Get Started'!D7,0) -> 44957 | X4: =EOMONTH(EDATE(W4,1),0) -> 44985 | Y4: =EOMONTH(EDATE(X4,1),0) -> 45016 | Z4: =EOMONTH(EDATE(Y4,1),0) -> 45046 | AA4: =EOMONTH(EDATE(Z4,1),0) -> 45077 | AB4: =EOMONTH(EDATE(AA4,1),0) -> 45107 | AC4: =EOMONTH(EDATE(AB4,1),0) -> 45138 | AD4: =EOMONTH(EDATE(AC4,1),0) -> 45169 | AE4: =EOMONTH(EDATE(AD4,1),0) -> 45199 | ... BS4: =EOMONTH(EDATE(BR4,1),0) -> 46418
B5: Timestep | C5: # | D5: where the first month in the period = 0 | V5: 0 | W5: 0 | X5: =W5+1 -> 1 | Y5: =X5+1 -> 2 | Z5: =Y5+1 -> 3 | AA5: =Z5+1 -> 4 | AB5: =AA5+1 -> 5 | AC5: =AB5+1 -> 6 | AD5: =AC5+1 -> 7 | AE5: =AD5+1 -> 8 | ... BS5: =BR5+1 -> 48
B6: Month # in Model | C6: # | D6: ="the model structure runs for "&BS6&" months. Month 0 is a pre-structure month, meant to capture opening items that help calculate the first month" -> the model structure runs for 49 months. Month 0 is a pre-structure month, meant to capture opening items that help calculate the first month | V6: =W6-1 -> 0 | W6: 1 | X6: =W6+1 -> 2 | Y6: =X6+1 -> 3 | Z6: =Y6+1 -> 4 | AA6: =Z6+1 -> 5 | AB6: =AA6+1 -> 6 | AC6: =AB6+1 -> 7 | AD6: =AC6+1 -> 8 | AE6: =AD6+1 -> 9 | ... BS6: =BR6+1 -> 49
B7: Fiscal Year | C7: # | D7: the fiscal year can vary from the calendar year, this is calculated based on the assumption for fiscal year end | V7: =YEAR(V4) -> 2022 | W7: {=IF(EOMONTH(W4,0)<=EOMONTH('Get Started'!$D8,0),YEAR('Get Started'!$D8),IF(W6<=(MONTH('Get Started'!$D8)-MONTH('Get Started'!$D7)),YEAR('Get Started'!$D8),IF(W6<=12,YEAR('Get Started'!$D8)+1,IFERROR(INDEX(V7:$W7,0,MATCH(W5-12,V5:$W5,0)),0)+1)))} -> 2023 | X7: {=IF(EOMONTH(X4,0)<=EOMONTH('Get Started'!$D8,0),YEAR('Get Started'!$D8),IF(X6<=(MONTH('Get Started'!$D8)-MONTH('Get Started'!$D7)),YEAR('Get Started'!$D8),IF(X6<=12,YEAR('Get Started'!$D8)+1,IFERROR(INDEX(W7:$W7,0,MATCH(X5-12,W5:$W5,0)),0)+1)))} -> 2023 | Y7: {=IF(EOMONTH(Y4,0)<=EOMONTH('Get Started'!$D8,0),YEAR('Get Started'!$D8),IF(Y6<=(MONTH('Get Started'!$D8)-MONTH('Get Started'!$D7)),YEAR('Get Started'!$D8),IF(Y6<=12,YEAR('Get Started'!$D8)+1,IFERROR(INDEX($W7:X7,0,MATCH(Y5-12,$W5:X5,0)),0)+1)))} -> 2023 | Z7: {=IF(EOMONTH(Z4,0)<=EOMONTH('Get Started'!$D8,0),YEAR('Get Started'!$D8),IF(Z6<=(MONTH('Get Started'!$D8)-MONTH('Get Started'!$D7)),YEAR('Get Started'!$D8),IF(Z6<=12,YEAR('Get Started'!$D8)+1,IFERROR(INDEX($W7:Y7,0,MATCH(Z5-12,$W5:Y5,0)),0)+1)))} -> 2023 | AA7: {=IF(EOMONTH(AA4,0)<=EOMONTH('Get Started'!$D8,0),YEAR('Get Started'!$D8),IF(AA6<=(MONTH('Get Started'!$D8)-MONTH('Get Started'!$D7)),YEAR('Get Started'!$D8),IF(AA6<=12,YEAR('Get Started'!$D8)+1,IFERROR(INDEX($W7:Z7,0,MATCH(AA5-12,$W5:Z5,0)),0)+1)))} -> 2023 | AB7: {=IF(EOMONTH(AB4,0)<=EOMONTH('Get Started'!$D8,0),YEAR('Get Started'!$D8),IF(AB6<=(MONTH('Get Started'!$D8)-MONTH('Get Started'!$D7)),YEAR('Get Started'!$D8),IF(AB6<=12,YEAR('Get Started'!$D8)+1,IFERROR(INDEX($W7:AA7,0,MATCH(AB5-12,$W5:AA5,0)),0)+1)))} -> 2023 | AC7: {=IF(EOMONTH(AC4,0)<=EOMONTH('Get Started'!$D8,0),YEAR('Get Started'!$D8),IF(AC6<=(MONTH('Get Started'!$D8)-MONTH('Get Started'!$D7)),YEAR('Get Started'!$D8),IF(AC6<=12,YEAR('Get Started'!$D8)+1,IFERROR(INDEX($W7:AB7,0,MATCH(AC5-12,$W5:AB5,0)),0)+1)))} -> 2023 | AD7: {=IF(EOMONTH(AD4,0)<=EOMONTH('Get Started'!$D8,0),YEAR('Get Started'!$D8),IF(AD6<=(MONTH('Get Started'!$D8)-MONTH('Get Started'!$D7)),YEAR('Get Started'!$D8),IF(AD6<=12,YEAR('Get Started'!$D8)+1,IFERROR(INDEX($W7:AC7,0,MATCH(AD5-12,$W5:AC5,0)),0)+1)))} -> 2023 | AE7: {=IF(EOMONTH(AE4,0)<=EOMONTH('Get Started'!$D8,0),YEAR('Get Started'!$D8),IF(AE6<=(MONTH('Get Started'!$D8)-MONTH('Get Started'!$D7)),YEAR('Get Started'!$D8),IF(AE6<=12,YEAR('Get Started'!$D8)+1,IFERROR(INDEX($W7:AD7,0,MATCH(AE5-12,$W5:AD5,0)),0)+1)))} -> 2023 | AF7: {=IF(EOMONTH(AF4,0)<=EOMONTH('Get Started'!$D8,0),YEAR('Get Started'!$D8),IF(AF6<=(MONTH('Get Started'!$D8)-MONTH('Get Started'!$D7)),YEAR('Get Started'!$D8),IF(AF6<=12,YEAR('Get Started'!$D8)+1,IFERROR(INDEX($W7:AE7,0,MATCH(AF5-12,$W5:AE5,0)),0)+1)))} -> 2023 | ... BS7: {=IF(EOMONTH(BS4,0)<=EOMONTH('Get Started'!$D8,0),YEAR('Get Started'!$D8),IF(BS6<=(MONTH('Get Started'!$D8)-MONTH('Get Started'!$D7)),YEAR('Get Started'!$D8),IF(BS6<=12,YEAR('Get Started'!$D8)+1,IFERROR(INDEX($W7:BR7,0,MATCH(BS5-12,$W5:BR5,0)),0)+1)))} -> 2027
B8: Quarter in Fiscal Year | C8: text | D8: the quarters of the year vary according by the fiscal year end | V8: =IF(OR(V11=3,V11=2,V11=1),"Q1",IF(OR(V11=6,V11=5,V11=4),"Q2",IF(OR(V11=9,V11=8,V11=7),"Q3","Q4"))) -> Q4 | W8: =IF(OR(W11=3,W11=2,W11=1),"Q1",IF(OR(W11=6,W11=5,W11=4),"Q2",IF(OR(W11=9,W11=8,W11=7),"Q3","Q4"))) -> Q1 | X8: =IF(OR(X11=3,X11=2,X11=1),"Q1",IF(OR(X11=6,X11=5,X11=4),"Q2",IF(OR(X11=9,X11=8,X11=7),"Q3","Q4"))) -> Q1 | Y8: =IF(OR(Y11=3,Y11=2,Y11=1),"Q1",IF(OR(Y11=6,Y11=5,Y11=4),"Q2",IF(OR(Y11=9,Y11=8,Y11=7),"Q3","Q4"))) -> Q1 | Z8: =IF(OR(Z11=3,Z11=2,Z11=1),"Q1",IF(OR(Z11=6,Z11=5,Z11=4),"Q2",IF(OR(Z11=9,Z11=8,Z11=7),"Q3","Q4"))) -> Q2 | AA8: =IF(OR(AA11=3,AA11=2,AA11=1),"Q1",IF(OR(AA11=6,AA11=5,AA11=4),"Q2",IF(OR(AA11=9,AA11=8,AA11=7),"Q3","Q4"))) -> Q2 | AB8: =IF(OR(AB11=3,AB11=2,AB11=1),"Q1",IF(OR(AB11=6,AB11=5,AB11=4),"Q2",IF(OR(AB11=9,AB11=8,AB11=7),"Q3","Q4"))) -> Q2 | AC8: =IF(OR(AC11=3,AC11=2,AC11=1),"Q1",IF(OR(AC11=6,AC11=5,AC11=4),"Q2",IF(OR(AC11=9,AC11=8,AC11=7),"Q3","Q4"))) -> Q3 | ... BS8: =IF(OR(BS11=3,BS11=2,BS11=1),"Q1",IF(OR(BS11=6,BS11=5,BS11=4),"Q2",IF(OR(BS11=9,BS11=8,BS11=7),"Q3","Q4"))) -> Q1
B9: Quarter / Year | C9: text | D9: quarters and year, reported in text form for some charts and graphs | V9: =V8&" "&V7 -> Q4 2022 | W9: =W8&" "&W7 -> Q1 2023 | X9: =X8&" "&X7 -> Q1 2023 | Y9: =Y8&" "&Y7 -> Q1 2023 | Z9: =Z8&" "&Z7 -> Q2 2023 | AA9: =AA8&" "&AA7 -> Q2 2023 | AB9: =AB8&" "&AB7 -> Q2 2023 | AC9: =AC8&" "&AC7 -> Q3 2023 | ... BS9: =BS8&" "&BS7 -> Q1 2027
B10: Month (Text) | C10: text | D10: the month of the calendar year, used for reporting and seasonality calculations | V10: =TEXT(V4,"mmmm") -> December | W10: =TEXT(W4,"mmmm") -> January | X10: =TEXT(X4,"mmmm") -> February | Y10: =TEXT(Y4,"mmmm") -> March | Z10: =TEXT(Z4,"mmmm") -> April | AA10: =TEXT(AA4,"mmmm") -> May | AB10: =TEXT(AB4,"mmmm") -> June | AC10: =TEXT(AC4,"mmmm") -> July | ... BS10: =TEXT(BS4,"mmmm") -> January
B11: Month # in Fiscal year | C11: # | D11: the month # in the fiscal year. This rolls over to 1 at the start of each fiscal year | V11: =IF(MOD(MONTH(V4)+12-MONTH('Get Started'!$D8),12)=0,12,MOD(MONTH(V4)+12-MONTH('Get Started'!$D8),12)) -> 12 | W11: =IF(MOD(MONTH(W4)+12-MONTH('Get Started'!$D8),12)=0,12,MOD(MONTH(W4)+12-MONTH('Get Started'!$D8),12)) -> 1 | X11: =IF(MOD(MONTH(X4)+12-MONTH('Get Started'!$D8),12)=0,12,MOD(MONTH(X4)+12-MONTH('Get Started'!$D8),12)) -> 2 | Y11: =IF(MOD(MONTH(Y4)+12-MONTH('Get Started'!$D8),12)=0,12,MOD(MONTH(Y4)+12-MONTH('Get Started'!$D8),12)) -> 3 | Z11: =IF(MOD(MONTH(Z4)+12-MONTH('Get Started'!$D8),12)=0,12,MOD(MONTH(Z4)+12-MONTH('Get Started'!$D8),12)) -> 4 | AA11: =IF(MOD(MONTH(AA4)+12-MONTH('Get Started'!$D8),12)=0,12,MOD(MONTH(AA4)+12-MONTH('Get Started'!$D8),12)) -> 5 | AB11: =IF(MOD(MONTH(AB4)+12-MONTH('Get Started'!$D8),12)=0,12,MOD(MONTH(AB4)+12-MONTH('Get Started'!$D8),12)) -> 6 | AC11: =IF(MOD(MONTH(AC4)+12-MONTH('Get Started'!$D8),12)=0,12,MOD(MONTH(AC4)+12-MONTH('Get Started'!$D8),12)) -> 7 | ... BS11: =IF(MOD(MONTH(BS4)+12-MONTH('Get Started'!$D8),12)=0,12,MOD(MONTH(BS4)+12-MONTH('Get Started'!$D8),12)) -> 1
B12: Year of Operations | C12: # | D12: the year of operations. Used for some reports based on time of operations, not calendar year | W12: 1 | X12: =W12 -> 1 | Y12: =X12 -> 1 | Z12: =Y12 -> 1 | AA12: =Z12 -> 1 | AB12: =AA12 -> 1 | AC12: =AB12 -> 1 | AD12: =AC12 -> 1 | AE12: =AD12 -> 1 | ... AH12: =AG12 -> 1 | AI12: =W12+1 -> 2 | AJ12: =X12+1 -> 2 | AK12: =Y12+1 -> 2 | AL12: =Z12+1 -> 2 | AM12: =AA12+1 -> 2 | AN12: =AB12+1 -> 2 | AO12: =AC12+1 -> 2 | AP12: =AD12+1 -> 2 | ... BS12: =BG12+1 -> 5
B15: Client | D15: % Likelihood to Close | E15: =Forecast!C$36&" Total Contract" -> $ Total Contract | F15: Contract Cycle | G15: Billing Cycle | H15: Start Date | I15: # Month Start | J15: % Revenue Churn or % Expansion
F16: months | G16: months | J16: at end of contract cycle
B17: Example: Enterprise Customer | D17: 1 | E17: 200 | F17: 3 | G17: 3 | H17: =W$4 -> 44957 | I17: =MATCH(EOMONTH(H17,0),W$4:BS$4,0) -> 1 | J17: 1 | L17: sum | M17: =IF(L17='Get Started'!$B$11,W17,IF(L17='Get Started'!$B$12,BS17,IF(L17='Get Started'!$B$13,SUM(W17:BS17),IF(L17='Get Started'!$B$14,AVERAGE(W17:BS17),0)))) -> 17476067 | W17: =IF(EOMONTH($H17,0)=W$4,$E17/$F17*$D17,IF(MOD(W$6-MATCH(EOMONTH($H17,0),$W$4:$BS$4,0)+1,$F17)=1,V17*(1+$J17),V17)) -> 66.666667 | X17: =IF(EOMONTH($H17,0)=X$4,$E17/$F17*$D17,IF(MOD(X$6-MATCH(EOMONTH($H17,0),$W$4:$BS$4,0)+1,$F17)=1,W17*(1+$J17),W17)) -> 66.666667 | Y17: =IF(EOMONTH($H17,0)=Y$4,$E17/$F17*$D17,IF(MOD(Y$6-MATCH(EOMONTH($H17,0),$W$4:$BS$4,0)+1,$F17)=1,X17*(1+$J17),X17)) -> 66.666667 | Z17: =IF(EOMONTH($H17,0)=Z$4,$E17/$F17*$D17,IF(MOD(Z$6-MATCH(EOMONTH($H17,0),$W$4:$BS$4,0)+1,$F17)=1,Y17*(1+$J17),Y17)) -> 133.33333 | AA17: =IF(EOMONTH($H17,0)=AA$4,$E17/$F17*$D17,IF(MOD(AA$6-MATCH(EOMONTH($H17,0),$W$4:$BS$4,0)+1,$F17)=1,Z17*(1+$J17),Z17)) -> 133.33333 | AB17: =IF(EOMONTH($H17,0)=AB$4,$E17/$F17*$D17,IF(MOD(AB$6-MATCH(EOMONTH($H17,0),$W$4:$BS$4,0)+1,$F17)=1,AA17*(1+$J17),AA17)) -> 133.33333 | AC17: =IF(EOMONTH($H17,0)=AC$4,$E17/$F17*$D17,IF(MOD(AC$6-MATCH(EOMONTH($H17,0),$W$4:$BS$4,0)+1,$F17)=1,AB17*(1+$J17),AB17)) -> 266.66667 | AD17: =IF(EOMONTH($H17,0)=AD$4,$E17/$F17*$D17,IF(MOD(AD$6-MATCH(EOMONTH($H17,0),$W$4:$BS$4,0)+1,$F17)=1,AC17*(1+$J17),AC17)) -> 266.66667 | ... BS17: =IF(EOMONTH($H17,0)=BS$4,$E17/$F17*$D17,IF(MOD(BS$6-MATCH(EOMONTH($H17,0),$W$4:$BS$4,0)+1,$F17)=1,BR17*(1+$J17),BR17)) -> 4369066.7
B18: Example: Channel Partner | D18: 0.5 | E18: 200 | F18: 3 | G18: 3 | H18: =EDATE(H17,1) -> 44985 | I18: =MATCH(EOMONTH(H18,0),W$4:BS$4,0) -> 2 | J18: 1 | L18: sum | M18: =IF(L18='Get Started'!$B$11,W18,IF(L18='Get Started'!$B$12,BS18,IF(L18='Get Started'!$B$13,SUM(W18:BS18),IF(L18='Get Started'!$B$14,AVERAGE(W18:BS18),0)))) -> 6553500 | W18: =IF(EOMONTH($H18,0)=W$4,$E18/$F18*$D18,IF(MOD(W$6-MATCH(EOMONTH($H18,0),$W$4:$BS$4,0)+1,$F18)=1,V18*(1+$J18),V18)) -> 0 | X18: =IF(EOMONTH($H18,0)=X$4,$E18/$F18*$D18,IF(MOD(X$6-MATCH(EOMONTH($H18,0),$W$4:$BS$4,0)+1,$F18)=1,W18*(1+$J18),W18)) -> 33.333333 | Y18: =IF(EOMONTH($H18,0)=Y$4,$E18/$F18*$D18,IF(MOD(Y$6-MATCH(EOMONTH($H18,0),$W$4:$BS$4,0)+1,$F18)=1,X18*(1+$J18),X18)) -> 33.333333 | Z18: =IF(EOMONTH($H18,0)=Z$4,$E18/$F18*$D18,IF(MOD(Z$6-MATCH(EOMONTH($H18,0),$W$4:$BS$4,0)+1,$F18)=1,Y18*(1+$J18),Y18)) -> 33.333333 | AA18: =IF(EOMONTH($H18,0)=AA$4,$E18/$F18*$D18,IF(MOD(AA$6-MATCH(EOMONTH($H18,0),$W$4:$BS$4,0)+1,$F18)=1,Z18*(1+$J18),Z18)) -> 66.666667 | AB18: =IF(EOMONTH($H18,0)=AB$4,$E18/$F18*$D18,IF(MOD(AB$6-MATCH(EOMONTH($H18,0),$W$4:$BS$4,0)+1,$F18)=1,AA18*(1+$J18),AA18)) -> 66.666667 | AC18: =IF(EOMONTH($H18,0)=AC$4,$E18/$F18*$D18,IF(MOD(AC$6-MATCH(EOMONTH($H18,0),$W$4:$BS$4,0)+1,$F18)=1,AB18*(1+$J18),AB18)) -> 66.666667 | AD18: =IF(EOMONTH($H18,0)=AD$4,$E18/$F18*$D18,IF(MOD(AD$6-MATCH(EOMONTH($H18,0),$W$4:$BS$4,0)+1,$F18)=1,AC18*(1+$J18),AC18)) -> 133.33333 | ... BS18: =IF(EOMONTH($H18,0)=BS$4,$E18/$F18*$D18,IF(MOD(BS$6-MATCH(EOMONTH($H18,0),$W$4:$BS$4,0)+1,$F18)=1,BR18*(1+$J18),BR18)) -> 1092266.7
B19: Example: Total all Q2 2023 new Customers | D19: 1 | E19: 200 | F19: 36 | G19: 12 | H19: =EDATE(H18,1) -> 45013 | I19: =MATCH(EOMONTH(H19,0),W$4:BS$4,0) -> 3 | J19: -0.5 | L19: sum | M19: =IF(L19='Get Started'!$B$11,W19,IF(L19='Get Started'!$B$12,BS19,IF(L19='Get Started'!$B$13,SUM(W19:BS19),IF(L19='Get Started'!$B$14,AVERAGE(W19:BS19),0)))) -> 230.55556 | W19: =IF(EOMONTH($H19,0)=W$4,$E19/$F19*$D19,IF(MOD(W$6-MATCH(EOMONTH($H19,0),$W$4:$BS$4,0)+1,$F19)=1,V19*(1+$J19),V19)) -> 0 | X19: =IF(EOMONTH($H19,0)=X$4,$E19/$F19*$D19,IF(MOD(X$6-MATCH(EOMONTH($H19,0),$W$4:$BS$4,0)+1,$F19)=1,W19*(1+$J19),W19)) -> 0 | Y19: =IF(EOMONTH($H19,0)=Y$4,$E19/$F19*$D19,IF(MOD(Y$6-MATCH(EOMONTH($H19,0),$W$4:$BS$4,0)+1,$F19)=1,X19*(1+$J19),X19)) -> 5.5555556 | Z19: =IF(EOMONTH($H19,0)=Z$4,$E19/$F19*$D19,IF(MOD(Z$6-MATCH(EOMONTH($H19,0),$W$4:$BS$4,0)+1,$F19)=1,Y19*(1+$J19),Y19)) -> 5.5555556 | AA19: =IF(EOMONTH($H19,0)=AA$4,$E19/$F19*$D19,IF(MOD(AA$6-MATCH(EOMONTH($H19,0),$W$4:$BS$4,0)+1,$F19)=1,Z19*(1+$J19),Z19)) -> 5.5555556 | AB19: =IF(EOMONTH($H19,0)=AB$4,$E19/$F19*$D19,IF(MOD(AB$6-MATCH(EOMONTH($H19,0),$W$4:$BS$4,0)+1,$F19)=1,AA19*(1+$J19),AA19)) -> 5.5555556 | AC19: =IF(EOMONTH($H19,0)=AC$4,$E19/$F19*$D19,IF(MOD(AC$6-MATCH(EOMONTH($H19,0),$W$4:$BS$4,0)+1,$F19)=1,AB19*(1+$J19),AB19)) -> 5.5555556 | AD19: =IF(EOMONTH($H19,0)=AD$4,$E19/$F19*$D19,IF(MOD(AD$6-MATCH(EOMONTH($H19,0),$W$4:$BS$4,0)+1,$F19)=1,AC19*(1+$J19),AC19)) -> 5.5555556 | ... BS19: =IF(EOMONTH($H19,0)=BS$4,$E19/$F19*$D19,IF(MOD(BS$6-MATCH(EOMONTH($H19,0),$W$4:$BS$4,0)+1,$F19)=1,BR19*(1+$J19),BR19)) -> 2.7777778
B20: TBD | D20: 0.75 | E20: 200 | F20: 3 | G20: 3 | H20: =EDATE(H19,1) -> 45044 | I20: =MATCH(EOMONTH(H20,0),W$4:BS$4,0) -> 4 | J20: 0 | L20: sum | M20: =IF(L20='Get Started'!$B$11,W20,IF(L20='Get Started'!$B$12,BS20,IF(L20='Get Started'!$B$13,SUM(W20:BS20),IF(L20='Get Started'!$B$14,AVERAGE(W20:BS20),0)))) -> 2300 | W20: =IF(EOMONTH($H20,0)=W$4,$E20/$F20*$D20,IF(MOD(W$6-MATCH(EOMONTH($H20,0),$W$4:$BS$4,0)+1,$F20)=1,V20*(1+$J20),V20)) -> 0 | X20: =IF(EOMONTH($H20,0)=X$4,$E20/$F20*$D20,IF(MOD(X$6-MATCH(EOMONTH($H20,0),$W$4:$BS$4,0)+1,$F20)=1,W20*(1+$J20),W20)) -> 0 | Y20: =IF(EOMONTH($H20,0)=Y$4,$E20/$F20*$D20,IF(MOD(Y$6-MATCH(EOMONTH($H20,0),$W$4:$BS$4,0)+1,$F20)=1,X20*(1+$J20),X20)) -> 0 | Z20: =IF(EOMONTH($H20,0)=Z$4,$E20/$F20*$D20,IF(MOD(Z$6-MATCH(EOMONTH($H20,0),$W$4:$BS$4,0)+1,$F20)=1,Y20*(1+$J20),Y20)) -> 50 | AA20: =IF(EOMONTH($H20,0)=AA$4,$E20/$F20*$D20,IF(MOD(AA$6-MATCH(EOMONTH($H20,0),$W$4:$BS$4,0)+1,$F20)=1,Z20*(1+$J20),Z20)) -> 50 | AB20: =IF(EOMONTH($H20,0)=AB$4,$E20/$F20*$D20,IF(MOD(AB$6-MATCH(EOMONTH($H20,0),$W$4:$BS$4,0)+1,$F20)=1,AA20*(1+$J20),AA20)) -> 50 | AC20: =IF(EOMONTH($H20,0)=AC$4,$E20/$F20*$D20,IF(MOD(AC$6-MATCH(EOMONTH($H20,0),$W$4:$BS$4,0)+1,$F20)=1,AB20*(1+$J20),AB20)) -> 50 | AD20: =IF(EOMONTH($H20,0)=AD$4,$E20/$F20*$D20,IF(MOD(AD$6-MATCH(EOMONTH($H20,0),$W$4:$BS$4,0)+1,$F20)=1,AC20*(1+$J20),AC20)) -> 50 | ... BS20: =IF(EOMONTH($H20,0)=BS$4,$E20/$F20*$D20,IF(MOD(BS$6-MATCH(EOMONTH($H20,0),$W$4:$BS$4,0)+1,$F20)=1,BR20*(1+$J20),BR20)) -> 50
B21: TBD | D21: 0.25 | E21: 200 | F21: 3 | G21: 1 | H21: =EDATE(H20,1) -> 45074 | I21: =MATCH(EOMONTH(H21,0),W$4:BS$4,0) -> 5 | J21: -1 | L21: sum | M21: =IF(L21='Get Started'!$B$11,W21,IF(L21='Get Started'!$B$12,BS21,IF(L21='Get Started'!$B$13,SUM(W21:BS21),IF(L21='Get Started'!$B$14,AVERAGE(W21:BS21),0)))) -> 50 | W21: =IF(EOMONTH($H21,0)=W$4,$E21/$F21*$D21,IF(MOD(W$6-MATCH(EOMONTH($H21,0),$W$4:$BS$4,0)+1,$F21)=1,V21*(1+$J21),V21)) -> 0 | X21: =IF(EOMONTH($H21,0)=X$4,$E21/$F21*$D21,IF(MOD(X$6-MATCH(EOMONTH($H21,0),$W$4:$BS$4,0)+1,$F21)=1,W21*(1+$J21),W21)) -> 0 | Y21: =IF(EOMONTH($H21,0)=Y$4,$E21/$F21*$D21,IF(MOD(Y$6-MATCH(EOMONTH($H21,0),$W$4:$BS$4,0)+1,$F21)=1,X21*(1+$J21),X21)) -> 0 | Z21: =IF(EOMONTH($H21,0)=Z$4,$E21/$F21*$D21,IF(MOD(Z$6-MATCH(EOMONTH($H21,0),$W$4:$BS$4,0)+1,$F21)=1,Y21*(1+$J21),Y21)) -> 0 | AA21: =IF(EOMONTH($H21,0)=AA$4,$E21/$F21*$D21,IF(MOD(AA$6-MATCH(EOMONTH($H21,0),$W$4:$BS$4,0)+1,$F21)=1,Z21*(1+$J21),Z21)) -> 16.666667 | AB21: =IF(EOMONTH($H21,0)=AB$4,$E21/$F21*$D21,IF(MOD(AB$6-MATCH(EOMONTH($H21,0),$W$4:$BS$4,0)+1,$F21)=1,AA21*(1+$J21),AA21)) -> 16.666667 | AC21: =IF(EOMONTH($H21,0)=AC$4,$E21/$F21*$D21,IF(MOD(AC$6-MATCH(EOMONTH($H21,0),$W$4:$BS$4,0)+1,$F21)=1,AB21*(1+$J21),AB21)) -> 16.666667 | AD21: =IF(EOMONTH($H21,0)=AD$4,$E21/$F21*$D21,IF(MOD(AD$6-MATCH(EOMONTH($H21,0),$W$4:$BS$4,0)+1,$F21)=1,AC21*(1+$J21),AC21)) -> 0 | ... BS21: =IF(EOMONTH($H21,0)=BS$4,$E21/$F21*$D21,IF(MOD(BS$6-MATCH(EOMONTH($H21,0),$W$4:$BS$4,0)+1,$F21)=1,BR21*(1+$J21),BR21)) -> 0
B22: TBD | D22: 0 | E22: 0 | F22: 12 | G22: 12 | H22: =EDATE(H21,1) -> 45105 | I22: =MATCH(EOMONTH(H22,0),W$4:BS$4,0) -> 6 | J22: 0 | L22: sum | M22: =IF(L22='Get Started'!$B$11,W22,IF(L22='Get Started'!$B$12,BS22,IF(L22='Get Started'!$B$13,SUM(W22:BS22),IF(L22='Get Started'!$B$14,AVERAGE(W22:BS22),0)))) -> 0 | W22: =IF(EOMONTH($H22,0)=W$4,$E22/$F22*$D22,IF(MOD(W$6-MATCH(EOMONTH($H22,0),$W$4:$BS$4,0)+1,$F22)=1,V22*(1+$J22),V22)) -> 0 | X22: =IF(EOMONTH($H22,0)=X$4,$E22/$F22*$D22,IF(MOD(X$6-MATCH(EOMONTH($H22,0),$W$4:$BS$4,0)+1,$F22)=1,W22*(1+$J22),W22)) -> 0 | Y22: =IF(EOMONTH($H22,0)=Y$4,$E22/$F22*$D22,IF(MOD(Y$6-MATCH(EOMONTH($H22,0),$W$4:$BS$4,0)+1,$F22)=1,X22*(1+$J22),X22)) -> 0 | Z22: =IF(EOMONTH($H22,0)=Z$4,$E22/$F22*$D22,IF(MOD(Z$6-MATCH(EOMONTH($H22,0),$W$4:$BS$4,0)+1,$F22)=1,Y22*(1+$J22),Y22)) -> 0 | AA22: =IF(EOMONTH($H22,0)=AA$4,$E22/$F22*$D22,IF(MOD(AA$6-MATCH(EOMONTH($H22,0),$W$4:$BS$4,0)+1,$F22)=1,Z22*(1+$J22),Z22)) -> 0 | AB22: =IF(EOMONTH($H22,0)=AB$4,$E22/$F22*$D22,IF(MOD(AB$6-MATCH(EOMONTH($H22,0),$W$4:$BS$4,0)+1,$F22)=1,AA22*(1+$J22),AA22)) -> 0 | AC22: =IF(EOMONTH($H22,0)=AC$4,$E22/$F22*$D22,IF(MOD(AC$6-MATCH(EOMONTH($H22,0),$W$4:$BS$4,0)+1,$F22)=1,AB22*(1+$J22),AB22)) -> 0 | AD22: =IF(EOMONTH($H22,0)=AD$4,$E22/$F22*$D22,IF(MOD(AD$6-MATCH(EOMONTH($H22,0),$W$4:$BS$4,0)+1,$F22)=1,AC22*(1+$J22),AC22)) -> 0 | ... BS22: =IF(EOMONTH($H22,0)=BS$4,$E22/$F22*$D22,IF(MOD(BS$6-MATCH(EOMONTH($H22,0),$W$4:$BS$4,0)+1,$F22)=1,BR22*(1+$J22),BR22)) -> 0
B23: TBD | D23: 0 | E23: 0 | F23: 12 | G23: 12 | H23: =EDATE(H22,1) -> 45135 | I23: =MATCH(EOMONTH(H23,0),W$4:BS$4,0) -> 7 | J23: 0 | L23: sum | M23: =IF(L23='Get Started'!$B$11,W23,IF(L23='Get Started'!$B$12,BS23,IF(L23='Get Started'!$B$13,SUM(W23:BS23),IF(L23='Get Started'!$B$14,AVERAGE(W23:BS23),0)))) -> 0 | W23: =IF(EOMONTH($H23,0)=W$4,$E23/$F23*$D23,IF(MOD(W$6-MATCH(EOMONTH($H23,0),$W$4:$BS$4,0)+1,$F23)=1,V23*(1+$J23),V23)) -> 0 | X23: =IF(EOMONTH($H23,0)=X$4,$E23/$F23*$D23,IF(MOD(X$6-MATCH(EOMONTH($H23,0),$W$4:$BS$4,0)+1,$F23)=1,W23*(1+$J23),W23)) -> 0 | Y23: =IF(EOMONTH($H23,0)=Y$4,$E23/$F23*$D23,IF(MOD(Y$6-MATCH(EOMONTH($H23,0),$W$4:$BS$4,0)+1,$F23)=1,X23*(1+$J23),X23)) -> 0 | Z23: =IF(EOMONTH($H23,0)=Z$4,$E23/$F23*$D23,IF(MOD(Z$6-MATCH(EOMONTH($H23,0),$W$4:$BS$4,0)+1,$F23)=1,Y23*(1+$J23),Y23)) -> 0 | AA23: =IF(EOMONTH($H23,0)=AA$4,$E23/$F23*$D23,IF(MOD(AA$6-MATCH(EOMONTH($H23,0),$W$4:$BS$4,0)+1,$F23)=1,Z23*(1+$J23),Z23)) -> 0 | AB23: =IF(EOMONTH($H23,0)=AB$4,$E23/$F23*$D23,IF(MOD(AB$6-MATCH(EOMONTH($H23,0),$W$4:$BS$4,0)+1,$F23)=1,AA23*(1+$J23),AA23)) -> 0 | AC23: =IF(EOMONTH($H23,0)=AC$4,$E23/$F23*$D23,IF(MOD(AC$6-MATCH(EOMONTH($H23,0),$W$4:$BS$4,0)+1,$F23)=1,AB23*(1+$J23),AB23)) -> 0 | AD23: =IF(EOMONTH($H23,0)=AD$4,$E23/$F23*$D23,IF(MOD(AD$6-MATCH(EOMONTH($H23,0),$W$4:$BS$4,0)+1,$F23)=1,AC23*(1+$J23),AC23)) -> 0 | ... BS23: =IF(EOMONTH($H23,0)=BS$4,$E23/$F23*$D23,IF(MOD(BS$6-MATCH(EOMONTH($H23,0),$W$4:$BS$4,0)+1,$F23)=1,BR23*(1+$J23),BR23)) -> 0
B24: TBD | D24: 0 | E24: 0 | F24: 12 | G24: 12 | H24: =EDATE(H23,1) -> 45166 | I24: =MATCH(EOMONTH(H24,0),W$4:BS$4,0) -> 8 | J24: 0 | L24: sum | M24: =IF(L24='Get Started'!$B$11,W24,IF(L24='Get Started'!$B$12,BS24,IF(L24='Get Started'!$B$13,SUM(W24:BS24),IF(L24='Get Started'!$B$14,AVERAGE(W24:BS24),0)))) -> 0 | W24: =IF(EOMONTH($H24,0)=W$4,$E24/$F24*$D24,IF(MOD(W$6-MATCH(EOMONTH($H24,0),$W$4:$BS$4,0)+1,$F24)=1,V24*(1+$J24),V24)) -> 0 | X24: =IF(EOMONTH($H24,0)=X$4,$E24/$F24*$D24,IF(MOD(X$6-MATCH(EOMONTH($H24,0),$W$4:$BS$4,0)+1,$F24)=1,W24*(1+$J24),W24)) -> 0 | Y24: =IF(EOMONTH($H24,0)=Y$4,$E24/$F24*$D24,IF(MOD(Y$6-MATCH(EOMONTH($H24,0),$W$4:$BS$4,0)+1,$F24)=1,X24*(1+$J24),X24)) -> 0 | Z24: =IF(EOMONTH($H24,0)=Z$4,$E24/$F24*$D24,IF(MOD(Z$6-MATCH(EOMONTH($H24,0),$W$4:$BS$4,0)+1,$F24)=1,Y24*(1+$J24),Y24)) -> 0 | AA24: =IF(EOMONTH($H24,0)=AA$4,$E24/$F24*$D24,IF(MOD(AA$6-MATCH(EOMONTH($H24,0),$W$4:$BS$4,0)+1,$F24)=1,Z24*(1+$J24),Z24)) -> 0 | AB24: =IF(EOMONTH($H24,0)=AB$4,$E24/$F24*$D24,IF(MOD(AB$6-MATCH(EOMONTH($H24,0),$W$4:$BS$4,0)+1,$F24)=1,AA24*(1+$J24),AA24)) -> 0 | AC24: =IF(EOMONTH($H24,0)=AC$4,$E24/$F24*$D24,IF(MOD(AC$6-MATCH(EOMONTH($H24,0),$W$4:$BS$4,0)+1,$F24)=1,AB24*(1+$J24),AB24)) -> 0 | AD24: =IF(EOMONTH($H24,0)=AD$4,$E24/$F24*$D24,IF(MOD(AD$6-MATCH(EOMONTH($H24,0),$W$4:$BS$4,0)+1,$F24)=1,AC24*(1+$J24),AC24)) -> 0 | ... BS24: =IF(EOMONTH($H24,0)=BS$4,$E24/$F24*$D24,IF(MOD(BS$6-MATCH(EOMONTH($H24,0),$W$4:$BS$4,0)+1,$F24)=1,BR24*(1+$J24),BR24)) -> 0
B25: TBD | D25: 0 | E25: 0 | F25: 12 | G25: 12 | H25: =EDATE(H24,1) -> 45197 | I25: =MATCH(EOMONTH(H25,0),W$4:BS$4,0) -> 9 | J25: 0 | L25: sum | M25: =IF(L25='Get Started'!$B$11,W25,IF(L25='Get Started'!$B$12,BS25,IF(L25='Get Started'!$B$13,SUM(W25:BS25),IF(L25='Get Started'!$B$14,AVERAGE(W25:BS25),0)))) -> 0 | W25: =IF(EOMONTH($H25,0)=W$4,$E25/$F25*$D25,IF(MOD(W$6-MATCH(EOMONTH($H25,0),$W$4:$BS$4,0)+1,$F25)=1,V25*(1+$J25),V25)) -> 0 | X25: =IF(EOMONTH($H25,0)=X$4,$E25/$F25*$D25,IF(MOD(X$6-MATCH(EOMONTH($H25,0),$W$4:$BS$4,0)+1,$F25)=1,W25*(1+$J25),W25)) -> 0 | Y25: =IF(EOMONTH($H25,0)=Y$4,$E25/$F25*$D25,IF(MOD(Y$6-MATCH(EOMONTH($H25,0),$W$4:$BS$4,0)+1,$F25)=1,X25*(1+$J25),X25)) -> 0 | Z25: =IF(EOMONTH($H25,0)=Z$4,$E25/$F25*$D25,IF(MOD(Z$6-MATCH(EOMONTH($H25,0),$W$4:$BS$4,0)+1,$F25)=1,Y25*(1+$J25),Y25)) -> 0 | AA25: =IF(EOMONTH($H25,0)=AA$4,$E25/$F25*$D25,IF(MOD(AA$6-MATCH(EOMONTH($H25,0),$W$4:$BS$4,0)+1,$F25)=1,Z25*(1+$J25),Z25)) -> 0 | AB25: =IF(EOMONTH($H25,0)=AB$4,$E25/$F25*$D25,IF(MOD(AB$6-MATCH(EOMONTH($H25,0),$W$4:$BS$4,0)+1,$F25)=1,AA25*(1+$J25),AA25)) -> 0 | AC25: =IF(EOMONTH($H25,0)=AC$4,$E25/$F25*$D25,IF(MOD(AC$6-MATCH(EOMONTH($H25,0),$W$4:$BS$4,0)+1,$F25)=1,AB25*(1+$J25),AB25)) -> 0 | AD25: =IF(EOMONTH($H25,0)=AD$4,$E25/$F25*$D25,IF(MOD(AD$6-MATCH(EOMONTH($H25,0),$W$4:$BS$4,0)+1,$F25)=1,AC25*(1+$J25),AC25)) -> 0 | ... BS25: =IF(EOMONTH($H25,0)=BS$4,$E25/$F25*$D25,IF(MOD(BS$6-MATCH(EOMONTH($H25,0),$W$4:$BS$4,0)+1,$F25)=1,BR25*(1+$J25),BR25)) -> 0
B26: TBD | D26: 0 | E26: 0 | F26: 12 | G26: 12 | H26: =EDATE(H25,1) -> 45227 | I26: =MATCH(EOMONTH(H26,0),W$4:BS$4,0) -> 10 | J26: 0 | L26: sum | M26: =IF(L26='Get Started'!$B$11,W26,IF(L26='Get Started'!$B$12,BS26,IF(L26='Get Started'!$B$13,SUM(W26:BS26),IF(L26='Get Started'!$B$14,AVERAGE(W26:BS26),0)))) -> 0 | W26: =IF(EOMONTH($H26,0)=W$4,$E26/$F26*$D26,IF(MOD(W$6-MATCH(EOMONTH($H26,0),$W$4:$BS$4,0)+1,$F26)=1,V26*(1+$J26),V26)) -> 0 | X26: =IF(EOMONTH($H26,0)=X$4,$E26/$F26*$D26,IF(MOD(X$6-MATCH(EOMONTH($H26,0),$W$4:$BS$4,0)+1,$F26)=1,W26*(1+$J26),W26)) -> 0 | Y26: =IF(EOMONTH($H26,0)=Y$4,$E26/$F26*$D26,IF(MOD(Y$6-MATCH(EOMONTH($H26,0),$W$4:$BS$4,0)+1,$F26)=1,X26*(1+$J26),X26)) -> 0 | Z26: =IF(EOMONTH($H26,0)=Z$4,$E26/$F26*$D26,IF(MOD(Z$6-MATCH(EOMONTH($H26,0),$W$4:$BS$4,0)+1,$F26)=1,Y26*(1+$J26),Y26)) -> 0 | AA26: =IF(EOMONTH($H26,0)=AA$4,$E26/$F26*$D26,IF(MOD(AA$6-MATCH(EOMONTH($H26,0),$W$4:$BS$4,0)+1,$F26)=1,Z26*(1+$J26),Z26)) -> 0 | AB26: =IF(EOMONTH($H26,0)=AB$4,$E26/$F26*$D26,IF(MOD(AB$6-MATCH(EOMONTH($H26,0),$W$4:$BS$4,0)+1,$F26)=1,AA26*(1+$J26),AA26)) -> 0 | AC26: =IF(EOMONTH($H26,0)=AC$4,$E26/$F26*$D26,IF(MOD(AC$6-MATCH(EOMONTH($H26,0),$W$4:$BS$4,0)+1,$F26)=1,AB26*(1+$J26),AB26)) -> 0 | AD26: =IF(EOMONTH($H26,0)=AD$4,$E26/$F26*$D26,IF(MOD(AD$6-MATCH(EOMONTH($H26,0),$W$4:$BS$4,0)+1,$F26)=1,AC26*(1+$J26),AC26)) -> 0 | ... BS26: =IF(EOMONTH($H26,0)=BS$4,$E26/$F26*$D26,IF(MOD(BS$6-MATCH(EOMONTH($H26,0),$W$4:$BS$4,0)+1,$F26)=1,BR26*(1+$J26),BR26)) -> 0
B27: TBD | D27: 0 | E27: 0 | F27: 12 | G27: 12 | H27: =EDATE(H26,1) -> 45258 | I27: =MATCH(EOMONTH(H27,0),W$4:BS$4,0) -> 11 | J27: 0 | L27: sum | M27: =IF(L27='Get Started'!$B$11,W27,IF(L27='Get Started'!$B$12,BS27,IF(L27='Get Started'!$B$13,SUM(W27:BS27),IF(L27='Get Started'!$B$14,AVERAGE(W27:BS27),0)))) -> 0 | W27: =IF(EOMONTH($H27,0)=W$4,$E27/$F27*$D27,IF(MOD(W$6-MATCH(EOMONTH($H27,0),$W$4:$BS$4,0)+1,$F27)=1,V27*(1+$J27),V27)) -> 0 | X27: =IF(EOMONTH($H27,0)=X$4,$E27/$F27*$D27,IF(MOD(X$6-MATCH(EOMONTH($H27,0),$W$4:$BS$4,0)+1,$F27)=1,W27*(1+$J27),W27)) -> 0 | Y27: =IF(EOMONTH($H27,0)=Y$4,$E27/$F27*$D27,IF(MOD(Y$6-MATCH(EOMONTH($H27,0),$W$4:$BS$4,0)+1,$F27)=1,X27*(1+$J27),X27)) -> 0 | Z27: =IF(EOMONTH($H27,0)=Z$4,$E27/$F27*$D27,IF(MOD(Z$6-MATCH(EOMONTH($H27,0),$W$4:$BS$4,0)+1,$F27)=1,Y27*(1+$J27),Y27)) -> 0 | AA27: =IF(EOMONTH($H27,0)=AA$4,$E27/$F27*$D27,IF(MOD(AA$6-MATCH(EOMONTH($H27,0),$W$4:$BS$4,0)+1,$F27)=1,Z27*(1+$J27),Z27)) -> 0 | AB27: =IF(EOMONTH($H27,0)=AB$4,$E27/$F27*$D27,IF(MOD(AB$6-MATCH(EOMONTH($H27,0),$W$4:$BS$4,0)+1,$F27)=1,AA27*(1+$J27),AA27)) -> 0 | AC27: =IF(EOMONTH($H27,0)=AC$4,$E27/$F27*$D27,IF(MOD(AC$6-MATCH(EOMONTH($H27,0),$W$4:$BS$4,0)+1,$F27)=1,AB27*(1+$J27),AB27)) -> 0 | AD27: =IF(EOMONTH($H27,0)=AD$4,$E27/$F27*$D27,IF(MOD(AD$6-MATCH(EOMONTH($H27,0),$W$4:$BS$4,0)+1,$F27)=1,AC27*(1+$J27),AC27)) -> 0 | ... BS27: =IF(EOMONTH($H27,0)=BS$4,$E27/$F27*$D27,IF(MOD(BS$6-MATCH(EOMONTH($H27,0),$W$4:$BS$4,0)+1,$F27)=1,BR27*(1+$J27),BR27)) -> 0
B28: TBD | D28: 0 | E28: 0 | F28: 12 | G28: 12 | H28: =EDATE(H27,1) -> 45288 | I28: =MATCH(EOMONTH(H28,0),W$4:BS$4,0) -> 12 | J28: 0 | L28: sum | M28: =IF(L28='Get Started'!$B$11,W28,IF(L28='Get Started'!$B$12,BS28,IF(L28='Get Started'!$B$13,SUM(W28:BS28),IF(L28='Get Started'!$B$14,AVERAGE(W28:BS28),0)))) -> 0 | W28: =IF(EOMONTH($H28,0)=W$4,$E28/$F28*$D28,IF(MOD(W$6-MATCH(EOMONTH($H28,0),$W$4:$BS$4,0)+1,$F28)=1,V28*(1+$J28),V28)) -> 0 | X28: =IF(EOMONTH($H28,0)=X$4,$E28/$F28*$D28,IF(MOD(X$6-MATCH(EOMONTH($H28,0),$W$4:$BS$4,0)+1,$F28)=1,W28*(1+$J28),W28)) -> 0 | Y28: =IF(EOMONTH($H28,0)=Y$4,$E28/$F28*$D28,IF(MOD(Y$6-MATCH(EOMONTH($H28,0),$W$4:$BS$4,0)+1,$F28)=1,X28*(1+$J28),X28)) -> 0 | Z28: =IF(EOMONTH($H28,0)=Z$4,$E28/$F28*$D28,IF(MOD(Z$6-MATCH(EOMONTH($H28,0),$W$4:$BS$4,0)+1,$F28)=1,Y28*(1+$J28),Y28)) -> 0 | AA28: =IF(EOMONTH($H28,0)=AA$4,$E28/$F28*$D28,IF(MOD(AA$6-MATCH(EOMONTH($H28,0),$W$4:$BS$4,0)+1,$F28)=1,Z28*(1+$J28),Z28)) -> 0 | AB28: =IF(EOMONTH($H28,0)=AB$4,$E28/$F28*$D28,IF(MOD(AB$6-MATCH(EOMONTH($H28,0),$W$4:$BS$4,0)+1,$F28)=1,AA28*(1+$J28),AA28)) -> 0 | AC28: =IF(EOMONTH($H28,0)=AC$4,$E28/$F28*$D28,IF(MOD(AC$6-MATCH(EOMONTH($H28,0),$W$4:$BS$4,0)+1,$F28)=1,AB28*(1+$J28),AB28)) -> 0 | AD28: =IF(EOMONTH($H28,0)=AD$4,$E28/$F28*$D28,IF(MOD(AD$6-MATCH(EOMONTH($H28,0),$W$4:$BS$4,0)+1,$F28)=1,AC28*(1+$J28),AC28)) -> 0 | ... BS28: =IF(EOMONTH($H28,0)=BS$4,$E28/$F28*$D28,IF(MOD(BS$6-MATCH(EOMONTH($H28,0),$W$4:$BS$4,0)+1,$F28)=1,BR28*(1+$J28),BR28)) -> 0
B29: TBD | D29: 0 | E29: 0 | F29: 12 | G29: 12 | H29: =EDATE(H28,1) -> 45319 | I29: =MATCH(EOMONTH(H29,0),W$4:BS$4,0) -> 13 | J29: 0 | L29: sum | M29: =IF(L29='Get Started'!$B$11,W29,IF(L29='Get Started'!$B$12,BS29,IF(L29='Get Started'!$B$13,SUM(W29:BS29),IF(L29='Get Started'!$B$14,AVERAGE(W29:BS29),0)))) -> 0 | W29: =IF(EOMONTH($H29,0)=W$4,$E29/$F29*$D29,IF(MOD(W$6-MATCH(EOMONTH($H29,0),$W$4:$BS$4,0)+1,$F29)=1,V29*(1+$J29),V29)) -> 0 | X29: =IF(EOMONTH($H29,0)=X$4,$E29/$F29*$D29,IF(MOD(X$6-MATCH(EOMONTH($H29,0),$W$4:$BS$4,0)+1,$F29)=1,W29*(1+$J29),W29)) -> 0 | Y29: =IF(EOMONTH($H29,0)=Y$4,$E29/$F29*$D29,IF(MOD(Y$6-MATCH(EOMONTH($H29,0),$W$4:$BS$4,0)+1,$F29)=1,X29*(1+$J29),X29)) -> 0 | Z29: =IF(EOMONTH($H29,0)=Z$4,$E29/$F29*$D29,IF(MOD(Z$6-MATCH(EOMONTH($H29,0),$W$4:$BS$4,0)+1,$F29)=1,Y29*(1+$J29),Y29)) -> 0 | AA29: =IF(EOMONTH($H29,0)=AA$4,$E29/$F29*$D29,IF(MOD(AA$6-MATCH(EOMONTH($H29,0),$W$4:$BS$4,0)+1,$F29)=1,Z29*(1+$J29),Z29)) -> 0 | AB29: =IF(EOMONTH($H29,0)=AB$4,$E29/$F29*$D29,IF(MOD(AB$6-MATCH(EOMONTH($H29,0),$W$4:$BS$4,0)+1,$F29)=1,AA29*(1+$J29),AA29)) -> 0 | AC29: =IF(EOMONTH($H29,0)=AC$4,$E29/$F29*$D29,IF(MOD(AC$6-MATCH(EOMONTH($H29,0),$W$4:$BS$4,0)+1,$F29)=1,AB29*(1+$J29),AB29)) -> 0 | AD29: =IF(EOMONTH($H29,0)=AD$4,$E29/$F29*$D29,IF(MOD(AD$6-MATCH(EOMONTH($H29,0),$W$4:$BS$4,0)+1,$F29)=1,AC29*(1+$J29),AC29)) -> 0 | ... BS29: =IF(EOMONTH($H29,0)=BS$4,$E29/$F29*$D29,IF(MOD(BS$6-MATCH(EOMONTH($H29,0),$W$4:$BS$4,0)+1,$F29)=1,BR29*(1+$J29),BR29)) -> 0
B30: TBD | D30: 0 | E30: 0 | F30: 12 | G30: 12 | H30: =EDATE(H29,1) -> 45350 | I30: =MATCH(EOMONTH(H30,0),W$4:BS$4,0) -> 14 | J30: 0 | L30: sum | M30: =IF(L30='Get Started'!$B$11,W30,IF(L30='Get Started'!$B$12,BS30,IF(L30='Get Started'!$B$13,SUM(W30:BS30),IF(L30='Get Started'!$B$14,AVERAGE(W30:BS30),0)))) -> 0 | W30: =IF(EOMONTH($H30,0)=W$4,$E30/$F30*$D30,IF(MOD(W$6-MATCH(EOMONTH($H30,0),$W$4:$BS$4,0)+1,$F30)=1,V30*(1+$J30),V30)) -> 0 | X30: =IF(EOMONTH($H30,0)=X$4,$E30/$F30*$D30,IF(MOD(X$6-MATCH(EOMONTH($H30,0),$W$4:$BS$4,0)+1,$F30)=1,W30*(1+$J30),W30)) -> 0 | Y30: =IF(EOMONTH($H30,0)=Y$4,$E30/$F30*$D30,IF(MOD(Y$6-MATCH(EOMONTH($H30,0),$W$4:$BS$4,0)+1,$F30)=1,X30*(1+$J30),X30)) -> 0 | Z30: =IF(EOMONTH($H30,0)=Z$4,$E30/$F30*$D30,IF(MOD(Z$6-MATCH(EOMONTH($H30,0),$W$4:$BS$4,0)+1,$F30)=1,Y30*(1+$J30),Y30)) -> 0 | AA30: =IF(EOMONTH($H30,0)=AA$4,$E30/$F30*$D30,IF(MOD(AA$6-MATCH(EOMONTH($H30,0),$W$4:$BS$4,0)+1,$F30)=1,Z30*(1+$J30),Z30)) -> 0 | AB30: =IF(EOMONTH($H30,0)=AB$4,$E30/$F30*$D30,IF(MOD(AB$6-MATCH(EOMONTH($H30,0),$W$4:$BS$4,0)+1,$F30)=1,AA30*(1+$J30),AA30)) -> 0 | AC30: =IF(EOMONTH($H30,0)=AC$4,$E30/$F30*$D30,IF(MOD(AC$6-MATCH(EOMONTH($H30,0),$W$4:$BS$4,0)+1,$F30)=1,AB30*(1+$J30),AB30)) -> 0 | AD30: =IF(EOMONTH($H30,0)=AD$4,$E30/$F30*$D30,IF(MOD(AD$6-MATCH(EOMONTH($H30,0),$W$4:$BS$4,0)+1,$F30)=1,AC30*(1+$J30),AC30)) -> 0 | ... BS30: =IF(EOMONTH($H30,0)=BS$4,$E30/$F30*$D30,IF(MOD(BS$6-MATCH(EOMONTH($H30,0),$W$4:$BS$4,0)+1,$F30)=1,BR30*(1+$J30),BR30)) -> 0
B31: Insert additional rows to insert more clients *above* the last row
B33: ="New "&B15&"s" -> New Clients | C33: # | D33: current period number of clients less previous period. Does not use likelihood to close % to weight | W33: =W34-V34 -> 1 | X33: =X34-W34 -> 1 | Y33: =Y34-X34 -> 1 | Z33: =Z34-Y34 -> 1 | AA33: =AA34-Z34 -> 1 | AB33: =AB34-AA34 -> 0 | AC33: =AC34-AB34 -> 0 | AD33: =AD34-AC34 -> -1 | ... BS33: =BS34-BR34 -> 0
B34: =B15&"s, end of period" -> Clients, end of period | C34: # | D34: sums all active clients, using the logic of revenues > 0, then it's a client. Does not use liklihood to close % to weight. Can alter for your specific business | V34: 0 | W34: =COUNTIFS(W17:W30,">0") -> 1 | X34: =COUNTIFS(X17:X30,">0") -> 2 | Y34: =COUNTIFS(Y17:Y30,">0") -> 3 | Z34: =COUNTIFS(Z17:Z30,">0") -> 4 | AA34: =COUNTIFS(AA17:AA30,">0") -> 5 | AB34: =COUNTIFS(AB17:AB30,">0") -> 5 | AC34: =COUNTIFS(AC17:AC30,">0") -> 5 | AD34: =COUNTIFS(AD17:AD30,">0") -> 4 | ... BS34: =COUNTIFS(BS17:BS30,">0") -> 4
B36: Bookings | C36: $ | D36: for all new, assumes bookings = contract length, in months * average monthly revenue * liklihood to close. Includes renewed bookings | L36: sum | M36: =IF(L36='Get Started'!$B$11,W36,IF(L36='Get Started'!$B$12,BS36,IF(L36='Get Started'!$B$13,SUM(W36:BS36),IF(L36='Get Started'!$B$14,AVERAGE(W36:BS36),0)))) -> 32770450 | W36: =SUMPRODUCT(W17:W30,--(MOD(W$6-$I17:$I30,$F17:$F30)=0),--(W$6>=$I17:$I30),$F17:$F30) -> 200 | X36: =SUMPRODUCT(X17:X30,--(MOD(X$6-$I17:$I30,$F17:$F30)=0),--(X$6>=$I17:$I30),$F17:$F30) -> 100 | Y36: =SUMPRODUCT(Y17:Y30,--(MOD(Y$6-$I17:$I30,$F17:$F30)=0),--(Y$6>=$I17:$I30),$F17:$F30) -> 200 | Z36: =SUMPRODUCT(Z17:Z30,--(MOD(Z$6-$I17:$I30,$F17:$F30)=0),--(Z$6>=$I17:$I30),$F17:$F30) -> 550 | AA36: =SUMPRODUCT(AA17:AA30,--(MOD(AA$6-$I17:$I30,$F17:$F30)=0),--(AA$6>=$I17:$I30),$F17:$F30) -> 250 | AB36: =SUMPRODUCT(AB17:AB30,--(MOD(AB$6-$I17:$I30,$F17:$F30)=0),--(AB$6>=$I17:$I30),$F17:$F30) -> 0 | AC36: =SUMPRODUCT(AC17:AC30,--(MOD(AC$6-$I17:$I30,$F17:$F30)=0),--(AC$6>=$I17:$I30),$F17:$F30) -> 950 | AD36: =SUMPRODUCT(AD17:AD30,--(MOD(AD$6-$I17:$I30,$F17:$F30)=0),--(AD$6>=$I17:$I30),$F17:$F30) -> 400 | ... BS36: =SUMPRODUCT(BS17:BS30,--(MOD(BS$6-$I17:$I30,$F17:$F30)=0),--(BS$6>=$I17:$I30),$F17:$F30) -> 13107350
B37: Billings | C37: =Forecast!C$36 -> $ | D37: billings uses the billing cycle assumptions to calculate billings per month. | L37: sum | M37: =IF(L37='Get Started'!$B$11,W37,IF(L37='Get Started'!$B$12,BS37,IF(L37='Get Started'!$B$13,SUM(W37:BS37),IF(L37='Get Started'!$B$14,AVERAGE(W37:BS37),0)))) -> 32770383 | W37: =SUMPRODUCT(W17:W30,--(MOD(W$6-$I17:$I30,$G17:$G30)=0),--(W$6>=$I17:$I30),$G17:$G30) -> 200 | X37: =SUMPRODUCT(X17:X30,--(MOD(X$6-$I17:$I30,$G17:$G30)=0),--(X$6>=$I17:$I30),$G17:$G30) -> 100 | Y37: =SUMPRODUCT(Y17:Y30,--(MOD(Y$6-$I17:$I30,$G17:$G30)=0),--(Y$6>=$I17:$I30),$G17:$G30) -> 66.666667 | Z37: =SUMPRODUCT(Z17:Z30,--(MOD(Z$6-$I17:$I30,$G17:$G30)=0),--(Z$6>=$I17:$I30),$G17:$G30) -> 550 | AA37: =SUMPRODUCT(AA17:AA30,--(MOD(AA$6-$I17:$I30,$G17:$G30)=0),--(AA$6>=$I17:$I30),$G17:$G30) -> 216.66667 | AB37: =SUMPRODUCT(AB17:AB30,--(MOD(AB$6-$I17:$I30,$G17:$G30)=0),--(AB$6>=$I17:$I30),$G17:$G30) -> 16.666667 | AC37: =SUMPRODUCT(AC17:AC30,--(MOD(AC$6-$I17:$I30,$G17:$G30)=0),--(AC$6>=$I17:$I30),$G17:$G30) -> 966.66667 | AD37: =SUMPRODUCT(AD17:AD30,--(MOD(AD$6-$I17:$I30,$G17:$G30)=0),--(AD$6>=$I17:$I30),$G17:$G30) -> 400 | ... BS37: =SUMPRODUCT(BS17:BS30,--(MOD(BS$6-$I17:$I30,$G17:$G30)=0),--(BS$6>=$I17:$I30),$G17:$G30) -> 13107350
B38: Revenues | C38: =Forecast!C$36 -> $ | D38: sums all revenues from above, can be broken out into categories if desired, contact hello@foresight.is | L38: sum | M38: =IF(L38='Get Started'!$B$11,W38,IF(L38='Get Started'!$B$12,BS38,IF(L38='Get Started'!$B$13,SUM(W38:BS38),IF(L38='Get Started'!$B$14,AVERAGE(W38:BS38),0)))) -> 24032147 | W38: =SUMPRODUCT(W17:W30) -> 66.666667 | X38: =SUMPRODUCT(X17:X30) -> 100 | Y38: =SUMPRODUCT(Y17:Y30) -> 105.55556 | Z38: =SUMPRODUCT(Z17:Z30) -> 222.22222 | AA38: =SUMPRODUCT(AA17:AA30) -> 272.22222 | AB38: =SUMPRODUCT(AB17:AB30) -> 272.22222 | AC38: =SUMPRODUCT(AC17:AC30) -> 405.55556 | AD38: =SUMPRODUCT(AD17:AD30) -> 455.55556 | ... BS38: =SUMPRODUCT(BS17:BS30) -> 5461386.1
B40: Deferred Revenues
B41: Deferred Revenues, beginning of period | C41: =Forecast!C$36 -> $ | D41: deferred revenues at beginning of period | L41: initial | M41: =IF(L41='Get Started'!$B$11,W41,IF(L41='Get Started'!$B$12,BS41,IF(L41='Get Started'!$B$13,SUM(W41:BS41),IF(L41='Get Started'!$B$14,AVERAGE(W41:BS41),0)))) -> 0 | W41: 0 | X41: =W44 -> 133.33333 | Y41: =X44 -> 133.33333 | Z41: =Y44 -> 94.444444 | AA41: =Z44 -> 422.22222 | AB41: =AA44 -> 366.66667 | AC41: =AB44 -> 111.11111 | AD41: =AC44 -> 672.22222 | AE41: =AD44 -> 616.66667 | ... BS41: =BR44 -> 1092272.2
B42: Billings | C42: =Forecast!C$36 -> $ | D42: billings during period | L42: sum | M42: =IF(L42='Get Started'!$B$11,W42,IF(L42='Get Started'!$B$12,BS42,IF(L42='Get Started'!$B$13,SUM(W42:BS42),IF(L42='Get Started'!$B$14,AVERAGE(W42:BS42),0)))) -> 32770383 | W42: =W37 -> 200 | X42: =X37 -> 100 | Y42: =Y37 -> 66.666667 | Z42: =Z37 -> 550 | AA42: =AA37 -> 216.66667 | AB42: =AB37 -> 16.666667 | AC42: =AC37 -> 966.66667 | AD42: =AD37 -> 400 | ... BS42: =BS37 -> 13107350
B43: Revenues | C43: =Forecast!C$36 -> $ | D43: recognized revenues during period, * -1 | L43: sum | M43: =IF(L43='Get Started'!$B$11,W43,IF(L43='Get Started'!$B$12,BS43,IF(L43='Get Started'!$B$13,SUM(W43:BS43),IF(L43='Get Started'!$B$14,AVERAGE(W43:BS43),0)))) -> -24032147 | W43: =(W38)*-1 -> -66.666667 | X43: =(X38)*-1 -> -100 | Y43: =(Y38)*-1 -> -105.55556 | Z43: =(Z38)*-1 -> -222.22222 | AA43: =(AA38)*-1 -> -272.22222 | AB43: =(AB38)*-1 -> -272.22222 | AC43: =(AC38)*-1 -> -405.55556 | AD43: =(AD38)*-1 -> -455.55556 | ... BS43: =(BS38)*-1 -> -5461386.1
B44: Deferred Revenues, end of period | C44: =Forecast!C$36 -> $ | D44: deferred revenues at end of period | L44: final | M44: =IF(L44='Get Started'!$B$11,W44,IF(L44='Get Started'!$B$12,BS44,IF(L44='Get Started'!$B$13,SUM(W44:BS44),IF(L44='Get Started'!$B$14,AVERAGE(W44:BS44),0)))) -> 8738236.1 | W44: =SUM(W41:W43) -> 133.33333 | X44: =SUM(X41:X43) -> 133.33333 | Y44: =SUM(Y41:Y43) -> 94.444444 | Z44: =SUM(Z41:Z43) -> 422.22222 | AA44: =SUM(AA41:AA43) -> 366.66667 | AB44: =SUM(AB41:AB43) -> 111.11111 | AC44: =SUM(AC41:AC43) -> 672.22222 | AD44: =SUM(AD41:AD43) -> 616.66667 | ... BS44: =SUM(BS41:BS43) -> 8738236.1

Sheet Model Comparison
B2: Foresight Template Comparison
B3: I offer a range of templates for venture funds and angels. Here's a breakdown of the models and how they compare.
B5: Template | C5: Link | D5: Software | E5: Usecase | F5: Price | G5: Time Scale | H5: Prebuilt Revenue Model | I5: Operating Expenses | J5: Hiring Plan | K5: Consolidated Financials | L5: Charts and Graphs | M5: Key Performance Metrics | N5: Historical Financials and Budget Variances | O5: Prebuilt Inventory Calcs | P5: Capital Structure (Equity, Debt, Grants, etc.) | Q5: Cap Table and Valuation
B7: Runway and Cash Forecasting Tool | C7: https://foresight.is/runway-cash-forecasting | D7: Google Sheets, download to Excel | E7: Seed-stage companies building first model | F7: Free | G7: 3 years | H7: FALSE | I7: TRUE | J7: FALSE | K7: TRUE | L7: TRUE | M7: TRUE | N7: FALSE | O7: FALSE | P7: TRUE | Q7: FALSE
B8: Starter Financial Model | C8: https://foresight.is/starter-financial-model | D8: Excel, upload to Google Sheets | E8: Seed - A stage companies building their own custom revenue model | F8: $74 USD | G8: 5 years | H8: FALSE | I8: TRUE | J8: TRUE | K8: TRUE | L8: TRUE | M8: TRUE | N8: FALSE | O8: TRUE | P8: TRUE | Q8: FALSE
B9: Standard Financial Model | C9: https://foresight.is/standard-financial-model | D9: Excel, upload to Google Sheets | E9: Seed - B stage companies leveraging the prebuilt revenue model or building their own | F9: $149 USD | G9: 5 years | H9: TRUE | I9: TRUE | J9: TRUE | K9: TRUE | L9: TRUE | M9: TRUE | N9: TRUE | O9: TRUE | P9: TRUE | Q9: TRUE
B10: Standard Financial Model for SaaS | C10: https://foresight.is/saas-financial-model | D10: Excel, upload to Google Sheets | E10: Companies with SaaS business models | F10: $149 USD | G10: 5 years | H10: TRUE | I10: TRUE | J10: TRUE | K10: TRUE | L10: TRUE | M10: TRUE | N10: TRUE | O10: TRUE | P10: TRUE | Q10: TRUE
B11: Standard Financial Model for Ecommerce | C11: https://foresight.is/ecommerce-financial-model | D11: Excel, upload to Google Sheets | E11: Companies with Ecommerce business models | F11: $149 USD | G11: 5 years | H11: TRUE | I11: TRUE | J11: TRUE | K11: TRUE | L11: TRUE | M11: TRUE | N11: TRUE | O11: TRUE | P11: TRUE | Q11: TRUE
B12: SaaS Forecasting Tool | C12: https://foresight.is/saas-forecasting-tool | D12: Excel, upload to Google Sheets | E12: Seed-stage entrepreneurs wanting to understand how to forecast SaaS businesses | F12: Free | G12: 3 years | H12: TRUE | I12: FALSE | J12: FALSE | K12: FALSE | L12: TRUE | M12: TRUE | N12: FALSE | O12: FALSE | P12: FALSE | Q12: FALSE
B13: Ecommerce ForecastingTool | C13: https://foresight.is/ecommerce-forecasting-tool | D13: Excel, upload to Google Sheets | E13: Seed-stage entrepreneurs wanting to understand how to forecast Ecommerce businesses | F13: Free | G13: 3 years | H13: TRUE | I13: FALSE | J13: FALSE | K13: FALSE | L13: TRUE | M13: TRUE | N13: FALSE | O13: FALSE | P13: FALSE | Q13: FALSE
B14: Unit Economics Tool | C14: https://foresight.is/unit-economics-template | D14: Excel, upload to Google Sheets | E14: Seed - B stage companies wanting to detail their unit economics, LTV, and cash flows on a per-user (subscriber, client, customer, etc.) basis. | F14: Free | G14: ~ | H14: TRUE | I14: FALSE | J14: FALSE | K14: FALSE | L14: FALSE | M14: FALSE | N14: FALSE | O14: FALSE | P14: FALSE | Q14: FALSE
B15: Enterprise SaaS Forecasting Tool | C15: https://foresight.is/enterprise-saas-template | D15: Excel, upload to Google Sheets | E15: Enterprise SaaS businesses wanting to use an enterprise pipeline and specific customer method to forecast their revenues | F15: Free | G15: 3 years | H15: TRUE | I15: FALSE | J15: FALSE | K15: FALSE | L15: TRUE | M15: TRUE | N15: FALSE | O15: FALSE | P15: FALSE | Q15: FALSE

Sheet Changelog
B2: Changelog
B3: Here's what has changed.
B5: v1.03 - December 22, 2023
B6: Edits to Forecast sheet to remove the use of the liklihood to close on every renewal cycle, and just use once on the first customer period.
B7: Edit to Forecast to remove the liklihood to close in the bookings, billings, and revenue structure; if the liklihood to close is being used in the per-period revenues, no need to apply it a second time.
B9: v1.02 - September 23, 2022
B10: Small styling edits, to changes to core structure
B12: v1.01 - July 30, 2021
B13: Forecast: Edited to remove usage of OFFSET function. Standardizing across templates to replace use of volative OFFSET with INDEX MATCH
B15: v1.00 - August 11, 2020
B16: First version of the Enterprise SaaS Forecasting Tool, which leverages the Pipeline built into the Standard Model, detailed at https://foresight.is/learn/pipeline
B18: Questions, ask hello@foresight.is anytime.
