Workbook
Name AnnExp: 'Annual Expense'!$A$1:$L$57
Name Basis: Basis!$A$1:$W$31
Name CostAllocation: 'Cost Allocation Basis'!$A$1:$O$53
Name CreditCalculation: 'CR Calculation'!$A$1:$I$33
Name EstimateCost: 'Cost Estimate'!$A$1:$G$66
Name LoanConstruction: 'Construction Loan'!$A$1:$J$53
Name Mortgage1: #REF!
Name Mortgage2: 'Interest Calculation'!$A$1:$G$30
Name Parish: '[1]2)Summary'!$H$8
Name Proforma15: 'Proforma (Reality) '!$A$1:$S$39
Name Proforma15: 'Proforma (Application)'!$A$1:$S$39
Name Rent: Rent!$A$1:$K$47
Name ReplacementReserve: 'Repl.-Reserve'!$A$1:$J$29
Name ScatteredSite: 'Cost by Building'!$A$1:$W$101
Name source: 'Sources & Uses'!$A$1:$I$83
Name SqFtg: 'Sq Footage'!$A$1:$O$114
Name TDCPERUNIT: 'Cost by Building'!$A$1:$U$19
Name TotalOperating: Expenses!$C$51
Name Units: '[1]2)Summary'!$D$11
Name utility: 'Utility Allowance'!$A$1:$K$21

Sheet 0000

Sheet Recovered_Sheet1

Sheet Source Use  OS
A1: Hollywood Acres | E1: =+B81 -> 72 | F1: New Construction
A2: Sources And Uses Statement | F2: =+Rent!C3 -> Augusta GA | T2: Workspace and Notes
A4: Sources: | AI4: Source of Funds
T5: Other Sources of Funds | AI5: Bond Funds (Interim) | AJ5: 4000000
A6: First Mortgage - HOPE | F6: =+#REF! -> #REF! | T6: GP Capital | V6: 100 | AI6: =+A6 -> First Mortgage - HOPE | AJ6: =+F6 -> #REF!
A7: Second Mortgage - CDBG | F7: =+'Interest Calculation'!C4 -> 18500000 | T7: SLP Capital | V7: 239 | AI7: =+A7 -> Second Mortgage - CDBG | AJ7: =+F7 -> 18500000
A8: Other Sources of Funds | C8: SLP-GP | F8: =+AJ8+AJ9 -> 339 | V8: 0 | AI8: Other - SLP | AJ8: 239
A9: Total Sources From Debt | I9: =SUM(F6:F8) -> #REF! | V9: =SUM(V6:V8) -> 339 | AI9: Other - GP | AJ9: 100
A10: Deferred Development Fee | H10: Cash Shortfall | I10: =+'Sources & Uses'!#REF! -> #REF! | AI10: =+A10 -> Deferred Development Fee | AJ10: =+I10 -> #REF!
A11: Sub Total - Sources for Gap Calculation | I11: =SUM(I9:I10) -> #REF! | K11: =SUM(I11) -> #REF! | T11: Land Acquisition Price | V11: 500000
M12: Must Be Zero
A13: Tax Credit - LP Equity Contribution | I13: =+'Sources & Uses'!I10-F8 -> 24499661 | K13: =+'CR Calculation'!F30 -> 3825871.7 | M13: =SUM(I13-K13) -> 20673789 | T13: Construction Breakdown: | AI13: =+A13 -> Tax Credit - LP Equity Contribution | AJ13: =+I13 -> 24499661
A14: TOTAL SOURCES | I14: =SUM(I11:I13) -> #REF! | K14: =SUM(I14) -> #REF! | T14: Total Land Improvements | V14: 204405
T15: Construction Hard Cost | V15: 4245865 | AJ15: =SUM(AJ5:AJ13) -> #REF!
F16: Uses included in | H16: Uses excluded from | T16: Total Hard Cost | V16: =SUM(V14:V15) -> 4450270
A17: Uses: | F17: Total Dev. Fee Cal. | H17: Total Dev. Fee Cal. | T17: Per Unit Hard Costs | V17: =+V16/E1 -> 61809.306
A19: Land | B19: Acres/Price | D19: 0 | E19: =+'Sources & Uses'!E16 -> 0 | H19: =+E19 -> 0 | T19: Pojected Hard Cost Contingency | V19: 255000 | X19: 5344695 | Y19: =+E27 -> 5349669.1 | AI19: =+A19 -> Land | AJ19: =+'Sources & Uses'!V11 -> 0 | AK19: Per D Stromburg 11.25.19
A20: Building Acquistion | H20: =+E19-H19 -> 0
A21: Land Improvements
A22: Unusual Land Improvements | V22: =SUM(V19:V21) -> 255000
A23: Other Land Improvements | F23: 0
A24: Sub-Total Land Improvements | F24: =SUM(F22:F23) -> 0 | T24: Deferred Developer Fee Analysis
T25: Max Deferred Fee (50% 15 Year Cash Flow) | V25: =+'Proforma (Application)'!S33 -> 0 | AI25: Construction Hard Cost
A26: Buildings | T26: Projected Deferred Fee | V26: =+I10+M13 -> #REF!
A27: Construction Hard Costs | C27: Ttl Constr Contract | E27: =SUM(F24+F27+F28+F29+F33+F34)+F35 -> 5349669.1 | F27: =+E1*H88 -> 4450270 | T27: Cash Flow For Soft Debt | V27: =+V25-V26 -> #REF! | AI27: =+A27 -> Construction Hard Costs | AJ27: =+F27 -> 4450270
A28: (Contingency) Hard Costs | E28: =+F28/SUM(E27-V22) -> 0.050052318 | F28: =+V22 -> 255000 | T28: Deferred Fee Feasibility | V28: =IF(V25>V26,"TEST MET","TEST NOT MET") -> #REF! | AI28: =+A28 -> (Contingency) Hard Costs | AJ28: =+F28 -> 255000
A29: General Requirements | E29: 0.06 | F29: =SUM(F27*E29) -> 267016.2 | AI29: =+A29 -> General Requirements | AJ29: =+F29 -> 267016.2
A30: Sub-Total Buildings | F30: =SUM(F27:F29) -> 4972286.2 | AI30: =+A33 -> Builders Profit | AJ30: =+F33 -> 283037.17
AI31: =+A34 -> Builders O/H (2%) | AJ31: =+F34 -> 94345.724
A32: Fees | AI32: Total Const. Costs | AJ32: =SUM(AJ27:AJ31) -> 5349669.1
A33: Builders Profit | E33: 0.06 | F33: =SUM(F27+F29)*E33 -> 283037.17
A34: Builders O/H (2%) | E34: 0.02 | F34: =SUM(F27+F29)*E34 -> 94345.724 | T34: Architect Worksheet: | AI34: Const. Soft Costs
A35: Bond Premium/Impact Fees | F35: 0 | T35: Architect Contract: | U35: 0.8 | V35: =SUM(V38*U35) -> 61600 | AI35: =+A36 -> Architects Fee-Design | AJ35: =+F36 -> 61600
A36: Architects Fee-Design | D36: =+U35 -> 0.8 | E36: 0.04 | F36: =+V35 -> 61600 | U36: 0.2 | V36: =SUM(V38*U36) -> 15400 | AI36: =+A37 -> Architects Fee-Supervision | AJ36: =+F37 -> 15400
A37: Architects Fee-Supervision | D37: =+U36 -> 0.2 | F37: =+V36 -> 15400 | G37: =SUM(F37) -> 15400 | H37: =SUM(F36:F37) -> 77000 | U37: =+V37/E27 -> 0.014393414 | V37: =+V35+V36 -> 77000 | AI37: =+A38 -> Other- Engineering | AJ37: =+F38 -> 41900
A38: Other- Engineering | F38: =35000+6900 -> 41900 | T38: Total Fees | U38: Fixed Fee | V38: 77000 | AI38: =+A46 -> Taxes | AJ38: =+F46 -> 5000
A39: Sub-Total Fees | F39: =SUM(F33:F38) -> 496282.9 | T39: Legal Fees Breakdown | AI39: =+A47 -> Insurance | AJ39: =+F47 -> 25000
U40: Basis Elig. | AI40: =+A53 -> CPA Fees | AJ40: =+F53 -> 10000
A41: Charges and Financing | T41: Real Estate Legal | U41: x | V41: 35000 | W41: =IF(U41="x",V41/V$46,0) -> 0.2991453 | Y41: Regions | AE41: 41000 | AI41: =+A55 -> Cost Certification | AJ41: =+F55 -> 15000
A42: Interest | F42: =+'Construction Loan'!E34 -> #REF! | T42: Lender Legal Const | U42: x | V42: =15000+10000 -> 25000 | W42: =IF(U42="x",V42/V$46,0) -> 0.21367521 | Y42: CR | AE42: 55000 | AI42: =+A62 -> Other Third Party Costs | AJ42: =+F62 -> 146419
A43: Financing Fee - Permanent | E43: 0.01 | F43: =SUM(E43*F6) -> #REF! | T43: Lender Legal Perm | V43: 27000 | W43: =IF(U43="x",V43/V$46,0) -> 0 | Y43: Perm | AE43: 21000 | AI43: =+A67 -> Operation Reserves | AJ43: =+H67 -> 0
A44: Financing Fee - Construction | E44: 0.01 | F44: =SUM(E44*'Construction Loan'!E4) -> 40000 | T44: Legal - Syndication | U44: 10K org syn. Rest in legal | V44: 30000 | Y44: Total | AE44: =SUM(AE41:AE43) -> 117000 | AI44: =+A68 -> Initial Deposit to R4R | AJ44: =+H68 -> 45000
A45: Bond Cost of Issuance | E45: =+#REF! -> #REF! | F45: =+#REF! -> #REF! | AI45: =+'Sources & Uses'!#REF! -> #REF! | AJ45: =+'Sources & Uses'!#REF! -> #REF!
A46: Taxes | F46: 5000 | T46: Total Legal | V46: =SUM(V41:V44) -> 117000 | W46: =SUM(W41:W44) -> 0.51282051 | AA46: Title Calc
A47: Insurance | E47: 0 | F47: =+V76 -> 25000 | W47: =1-W46 -> 0.48717949 | AA47: =SUM(F6/AC47*AB47) -> #REF! | AB47: 2.25 | AC47: 1000 | AD47: 1st
A48: Title/Recording | F48: =+V53 -> 24500 | T48: Title & Recording | AA48: =SUM(F7/AC48*AB48) -> 50875 | AB48: 2.75 | AC48: 1000 | AD48: 2nd | AI48: Total Const Soft Costs | AJ48: =SUM(AJ35:AJ45) -> #REF!
F49: =SUM(F42:F48) -> #REF! | U49: Basis Elig. | AA49: 1.5
T50: Const Loan T&R | U50: x | V50: 15000 | W50: =IF(U50="x",V50/V$53,0) -> 0.6122449
A51: Legal/Organizational | T51: Perm Loan T&R | V51: 9500 | AI51: Financing Fees/ exp % COI
A52: Legal | F52: =+V46 -> 117000
A53: CPA Fees | F53: 10000 | T53: Total T&R | V53: =SUM(V50:V52) -> 24500 | W53: =SUM(W49:W52) -> 0.6122449 | AI53: =+A42 -> Interest | AJ53: =+F42 -> #REF!
A54: Organizational | F54: 0 | W54: =1-W53 -> 0.3877551 | AI54: =+A43 -> Financing Fee - Permanent | AJ54: =+F43 -> #REF!
A55: Cost Certification | F55: 15000 | AI55: =+A44 -> Financing Fee - Construction | AJ55: =+F44 -> 40000
A56: Sub-Total Legal/Org. | F56: =SUM(F52:F55) -> 142000 | T56: Other Third Party Costs | X56: Basis | Y56: Non Basis | AI56: =+A45 -> Bond Cost of Issuance | AJ56: =+F45 -> #REF!
AI57: =+A48 -> Title/Recording | AJ57: =+F48 -> 24500
A58: Other Fees and Cost | T58: Environmental | V58: 20000 | X58: =+V58 -> 20000 | AI58: =+A52 -> Legal | AJ58: =+F52-AJ45 -> #REF!
A59: Relocation Costs | F59: 0 | T59: Mkt Sty | V59: 4500 | X59: =+V59 -> 4500 | AI59: =+A60 -> LIHTC Application Fee | AJ59: =+F60 -> 4000
A60: LIHTC Application Fee | F60: 4000 | T60: Appraisal | V60: 5000 | X60: =+V60 -> 5000 | AI60: =+A61 -> Tax Credit Commitment Fees | AJ60: =+F61 -> 22507.379
A61: Tax Credit Commitment Fees | E61: 0.05 | F61: =+E61*'CR Calculation'!F26 -> 22507.379 | T61: Surety Bond | V61: 11375 | X61: =+V61 -> 11375 | AI61: Total Financing Fees/Exp & COI | AJ61: =SUM(AJ53:AJ60) -> #REF!
A62: =+T56 -> Other Third Party Costs | F62: =+V69 -> 146419 | T62: Survey | V62: 15000 | X62: =+V62 -> 15000
A63: Contingency | E63: =SUM(F63/E27) -> 0 | F63: =+V85 -> 0 | T63: Geotech | V63: 51144 | X63: =+V63 -> 51144
A64: Sub-Total Other | F64: =SUM(F59:F63) -> 172926.38 | T64: Asbestos | V64: 15700 | X64: =+V64 -> 15700 | AI64: Developer Fees | AJ64: =+H71 -> 0
T65: LOMA | U65: Add'l Engineering | V65: 3700 | X65: =+V65 -> 3700
A66: Project Reserves | T66: Marketing | V66: 5000 | Y66: =+V66 -> 5000
A67: Operation Reserves | H67: =+'Proforma (Application)'!D55 -> 0 | T67: Other 3rd party | U67: Taxpayer Closing | V67: 15000 | X67: =+V67 -> 15000 | AI67: Repayment of Bonds | AJ67: =+AJ5 -> 4000000
A68: Initial Deposit to R4R | H68: 45000
A69: Sub-Total Reserves | H69: =SUM(H67:H68) -> 45000 | V69: =SUM(V58:V68) -> 146419 | X69: =SUM(X58:X68) -> 141419 | Y69: =SUM(Y58:Y68) -> 5000 | AI69: Total Uses of Funds | AJ69: =+AJ32+AJ48+AJ61+AJ64+AJ67+AJ19 -> #REF!
A71: Developer Fee NC/Rehab.(Maximum 15%) | E71: 0.106 | H71: =+'Sources & Uses'!H67 -> 0 | T71: Insurance
A72: Developer Fee - Acquisition | E72: 0.08 | H72: =SUM(H20*E72) -> 0
T73: Insurance Budget | V73: 25000
A74: Syndication/ Other Expenses
A75: Syndication Legal | F75: 0
A76: Accountant Fees/Synd. Fee | F76: 0 | T76: Calculated Insruance | V76: =SUM(V73:V75) -> 25000
A77: Sub-Total | F77: =SUM(F75:F76) -> 0
A79: TOTAL USES | F79: =SUM(+F77+F64+F56+F49+F39+F30+F24) -> #REF! | H79: =SUM(H19+H20+H69+H72+H71) -> 45000 | I79: =SUM(F79:H79) -> #REF! | T79: Adjustments and Contingency
A81: Total Units | B81: =+Rent!C44 -> 72 | T81: Adjustment from Environmental | V81: 0
A82: Total Uses per Unit | I82: =I79/B81 -> #REF! | T82: Other Adjustments
A83: Total Development Cost Per Unit | I83: =SUM(I79/B81) -> #REF! | T83: Additional Contingency | V83: 0
A84: Differences Uses and Debt (Represents amount of gap to be used for Subsidy Layering) | I84: =I79-K11 -> #REF!
A85: Differences Uses and Sources | I85: =K14-I79 -> #REF! | T85: Total Soft Cost Contingency | V85: =SUM(V81:V84) -> 0
A86: Profit Percentage (Rehab. Portion) | H86: 0.1
A87: Developer Fee Percentage | H87: =SUM(H71/F79) -> #REF!
A88: Hard Cost Per Unit | H88: =+V17 -> 61809.306
A89: Total Project Square Footage | H89: =+'Construction Breakdown (PBC)'!C4 -> 328000 | T89: Developer Fee Deferred | V89: =+I10+M13 -> #REF!
A90: Construction Cost per Square Foot | H90: =SUM(E27/H89) -> 16.309967 | T90: % Developer Fee Deferred | V90: =+V89/H71 -> #REF!
T91: Developer Fee Paid | V91: =+H71-V89 -> #REF!
A92: Community Room | H92: 150000
A93: Intermediary Cost Percentage | H93: =+'Intermediary Cost'!F22 -> #REF!
T94: % Developer Fee Paid | V94: =+V91/H71 -> #REF!
A95: TDC Per Unit Calculation:
A97: TDC | F97: =+I79 -> #REF!
A98: Less Reserves` | F98: =-H69 -> -45000
A99: Subtotal | F99: =+F97+F98 -> #REF!
A100: Less - Community Facility | F100: -300000
A102: TDC | F102: =+F99+F100 -> #REF!
B103: 125000 | C103: 0.9 | D103: =+C103*B103 -> 112500 | F103: =+F102/B81 -> #REF!
A105: TDC | B105: =+I79 -> #REF! | F105: =+D103-F103 -> #REF!
F106: =+F105*B81 -> #REF!
A107: 0.04 | B107: =SUM(B105*A107) -> #REF!
A108: 0.07 | B108: =SUM(B105*A108) -> #REF!
...

Sheet Modeling Assp Wkst
O3: PH I | P3: PH II | Q3: PH III | R3: Total
M4: Total Units Original Submission | O4: 213 | P4: 213 | Q4: 174 | R4: =SUM(O4:Q4) -> 600
M5: Total Units - Proposed Submission | R5: =+'Sources & Uses'!E1 -> 72
N6: All Phases
B7: Phase I | D7: Phase II | F7: Phase III | I7: Total | N7: Per Unit
A8: ITEM | B8: COST | C8: % TOTAL | D8: COST | E8: % TOTAL | F8: COST | G8: % TOTAL | I8: All Phases
A9: ACQUISITION
A10: Build Acquisition | C10: =IF($B$70>0,B10/$B$70,B10/1) -> 0 | E10: =IF($D$70>0,D10/$D$70,D10/1) -> 0 | G10: =IF($F$70>0,F10/$F$70,F10/1) -> 0 | I10: =SUM(B10+D10+F10) -> 0
A11: Land Acquisition | B11: 250000 | C11: =IF($B$70>0,B11/$B$70,B11/1) -> 0.0054224872 | D11: 0 | E11: =IF($D$70>0,D11/$D$70,D11/1) -> 0 | F11: 0 | G11: =IF($F$70>0,F11/$F$70,F11/1) -> 0 | I11: =SUM(B11+D11+F11) -> 250000 | K11: =+I11 -> 250000
A12: SITE IMPROVEMENTS
A13: Demolition | B13: 0 | C13: =IF($B$70>0,B13/$B$70,B13/1) -> 0 | D13: 0 | E13: =IF($D$70>0,D13/$D$70,D13/1) -> 0 | F13: 0 | G13: =IF($F$70>0,F13/$F$70,F13/1) -> 0 | I13: =SUM(B13+D13+F13) -> 0
A14: On-Site Imp. | B14: 1217200 | C14: =IF($B$70>0,B14/$B$70,B14/1) -> 0.026401006 | D14: 1278060 | E14: =IF($D$70>0,D14/$D$70,D14/1) -> 0.02711791 | F14: =(1217200*1.1)*0.82 -> 1097914.4 | G14: =IF($F$70>0,F14/$F$70,F14/1) -> 0.027055514 | I14: =SUM(B14+D14+F14) -> 3593174.4 | M14: Construction Costs were provided by client
A15: Off-Site Imp. | C15: =IF($B$70>0,B15/$B$70,B15/1) -> 0 | E15: =IF($D$70>0,D15/$D$70,D15/1) -> 0 | G15: =IF($F$70>0,F15/$F$70,F15/1) -> 0 | I15: =SUM(B15+D15+F15) -> 0 | M15: Construction Costs were provided by client
A16: CONSTRUCTION | M16: Construction Costs were provided by client
A17: Rehabilitation | C17: =IF($B$70>0,B17/$B$70,B17/1) -> 0 | E17: =IF($D$70>0,D17/$D$70,D17/1) -> 0 | G17: =IF($F$70>0,F17/$F$70,F17/1) -> 0 | I17: =SUM(B17+D17+F17) -> 0 | M17: Construction Costs were provided by client
A18: New Construction | B18: 29010676 | C18: =IF($B$70>0,B18/$B$70,B18/1) -> 0.62924008 | D18: 30461210 | E18: =IF($D$70>0,D18/$D$70,D18/1) -> 0.64632673 | F18: =(29010676*1.1)*0.82 -> 26167630 | G18: =IF($F$70>0,F18/$F$70,F18/1) -> 0.64483959 | I18: =SUM(B18+D18+F18) -> 85639516 | M18: Construction Costs were provided by client
A19: General Requirements | B19: 2531830 | C19: =IF($B$70>0,B19/$B$70,B19/1) -> 0.054915263 | D19: 1827673 | E19: =IF($D$70>0,D19/$D$70,D19/1) -> 0.038779613 | F19: =F18*0.06 -> 1570057.8 | G19: =IF($F$70>0,F19/$F$70,F19/1) -> 0.038690375 | I19: =SUM(B19+D19+F19) -> 5929560.8 | M19: Construction Costs were provided by client
A20: Contractor Overhead | B20: 596000 | C20: =IF($B$70>0,B20/$B$70,B20/1) -> 0.012927209 | D20: 609224 | E20: =IF($D$70>0,D20/$D$70,D20/1) -> 0.01292653 | F20: =F18*0.02 -> 523352.6 | G20: =IF($F$70>0,F20/$F$70,F20/1) -> 0.012896792 | I20: =SUM(B20+D20+F20) -> 1728576.6 | M20: Construction Costs were provided by client
A21: Contractor Profit | B21: 1450534 | C21: =IF($B$70>0,B21/$B$70,B21/1) -> 0.031462008 | D21: 1523060 | E21: =IF($D$70>0,D21/$D$70,D21/1) -> 0.032316326 | F21: =F18*0.05 -> 1308381.5 | G21: =IF($F$70>0,F21/$F$70,F21/1) -> 0.03224198 | I21: =SUM(B21+D21+F21) -> 4281975.5 | M21: Construction Costs were provided by client
A22: P & P Bond or LOC | B22: 179050 | C22: =IF($B$70>0,B22/$B$70,B22/1) -> 0.0038835853 | D22: 179050 | E22: =IF($D$70>0,D22/$D$70,D22/1) -> 0.0037990875 | F22: 150000 | G22: =IF($F$70>0,F22/$F$70,F22/1) -> 0.0036963966 | I22: =SUM(B22+D22+F22) -> 508100 | M22: Construction Costs were provided by client
A23: Contingency | B23: 2610961 | C23: =IF($B$70>0,B23/$B$70,B23/1) -> 0.05663161 | D23: 2741509 | E23: =IF($D$70>0,D23/$D$70,D23/1) -> 0.058169408 | F23: =F18*0.09 -> 2355086.7 | G23: =IF($F$70>0,F23/$F$70,F23/1) -> 0.058035563 | I23: =SUM(B23+D23+F23) -> 7707556.7 | M23: Construction Costs were provided by client
A24: Permits & Impact Fees | B24: 180120 | C24: =IF($B$70>0,B24/$B$70,B24/1) -> 0.0039067936 | D24: 180120 | E24: =IF($D$70>0,D24/$D$70,D24/1) -> 0.0038217908 | F24: 150000 | G24: =IF($F$70>0,F24/$F$70,F24/1) -> 0.0036963966 | I24: =SUM(B24+D24+F24) -> 510240 | M24: Construction Costs were provided by client
A25: Furnishings | B25: 956000 | C25: =IF($B$70>0,B25/$B$70,B25/1) -> 0.020735591 | D25: 1003800 | E25: =IF($D$70>0,D25/$D$70,D25/1) -> 0.021298654 | F25: =((478000*2)*1.1)*0.82 -> 862312 | G25: =IF($F$70>0,F25/$F$70,F25/1) -> 0.021249648 | I25: =SUM(B25+D25+F25) -> 2822112 | M25: Construction Costs were provided by client
A26: Relocation | C26: =IF($B$70>0,B26/$B$70,B26/1) -> 0 | E26: =IF($D$70>0,D26/$D$70,D26/1) -> 0 | G26: =IF($F$70>0,F26/$F$70,F26/1) -> 0 | I26: =SUM(B26+D26+F26) -> 0
A27: Other | C27: =IF($B$70>0,B27/$B$70,B27/1) -> 0 | E27: =IF($D$70>0,D27/$D$70,D27/1) -> 0 | G27: =IF($F$70>0,F27/$F$70,F27/1) -> 0 | I27: =SUM(B27+D27+F27) -> 0
A28: PROFESSIONAL FEES
A29: Architect & Engineer | B29: =B18*0.06 -> 1740640.6 | C29: =IF($B$70>0,B29/$B$70,B29/1) -> 0.037754405 | D29: =D18*0.06 -> 1827672.6 | E29: =IF($D$70>0,D29/$D$70,D29/1) -> 0.038779604 | F29: =F18*0.06 -> 1570057.8 | G29: =IF($F$70>0,F29/$F$70,F29/1) -> 0.038690375 | I29: =SUM(B29+D29+F29) -> 5138370.9 | K29: =SUM('Sources & Uses'!F24*L29) -> 554921.44 | L29: =IF($I$70>0,I29/$I$70,I29/1) -> 0.038399323 | M29: Calculated by average % of all phases X construction costs provided by client
A30: Real Estate Legal | B30: 200000 | C30: =IF($B$70>0,B30/$B$70,B30/1) -> 0.0043379898 | D30: 200000 | E30: =IF($D$70>0,D30/$D$70,D30/1) -> 0.0042436051 | F30: 200000 | G30: =IF($F$70>0,F30/$F$70,F30/1) -> 0.0049285289 | I30: =SUM(B30+D30+F30) -> 600000 | K30: =SUM(R$5*N30) -> 72000 | L30: =IF($I$70>0,I30/$I$70,I30/1) -> 0.0044838323 | M30: Calculated on Per Unit Basis | N30: =SUM(I30/R$4) -> 1000
A31: Consultants | B31: 132000 | C31: =IF($B$70>0,B31/$B$70,B31/1) -> 0.0028630732 | D31: 132000 | E31: =IF($D$70>0,D31/$D$70,D31/1) -> 0.0028007794 | F31: 132000 | G31: =IF($F$70>0,F31/$F$70,F31/1) -> 0.003252829 | I31: =SUM(B31+D31+F31) -> 396000 | K31: =SUM(R$5*N31) -> 47520 | L31: =IF($I$70>0,I31/$I$70,I31/1) -> 0.0029593293 | M31: Calculated on Per Unit Basis | N31: =SUM(I31/R$4) -> 660
A32: Developer Fee | B32: =(B18*0.09) -> 2610960.8 | C32: =IF($B$70>0,B32/$B$70,B32/1) -> 0.056631607 | D32: =(D18*0.09) -> 2741508.9 | E32: =IF($D$70>0,D32/$D$70,D32/1) -> 0.058169406 | F32: =(F18*0.09) -> 2355086.7 | G32: =IF($F$70>0,F32/$F$70,F32/1) -> 0.058035563 | I32: =SUM(B32+D32+F32) -> 7707556.4 | L32: =IF($I$70>0,I32/$I$70,I32/1) -> 0.057598984 | M32: Calculated per LHC Formula
A33: Environmental | B33: 50000 | C33: =IF($B$70>0,B33/$B$70,B33/1) -> 0.0010844974 | D33: 0 | E33: =IF($D$70>0,D33/$D$70,D33/1) -> 0 | F33: 0 | G33: =IF($F$70>0,F33/$F$70,F33/1) -> 0 | I33: =SUM(B33+D33+F33) -> 50000 | K33: =SUM(R$5*N33) -> 6000 | L33: =IF($I$70>0,I33/$I$70,I33/1) -> 0.00037365269 | N33: =SUM(I33/R$4) -> 83.333333
A34: Cost Certification | B34: 5000 | C34: =IF($B$70>0,B34/$B$70,B34/1) -> 0.00010844974 | D34: 5000 | E34: =IF($D$70>0,D34/$D$70,D34/1) -> 0.00010609013 | F34: 5000 | G34: =IF($F$70>0,F34/$F$70,F34/1) -> 0.00012321322 | I34: =SUM(B34+D34+F34) -> 15000 | K34: 25000 | L34: =IF($I$70>0,I34/$I$70,I34/1) -> 0.00011209581 | M34: Re-allocated per LHC average for similar development
A35: Accounting | B35: 25000 | C35: =IF($B$70>0,B35/$B$70,B35/1) -> 0.00054224872 | D35: 25000 | E35: =IF($D$70>0,D35/$D$70,D35/1) -> 0.00053045064 | F35: 25000 | G35: =IF($F$70>0,F35/$F$70,F35/1) -> 0.00061606611 | I35: =SUM(B35+D35+F35) -> 75000 | K35: =SUM(R$5*N35) -> 9000 | L35: =IF($I$70>0,I35/$I$70,I35/1) -> 0.00056047904 | M35: Calculated on Per Unit Basis | N35: =SUM(I35/R$4) -> 125
A36: Survey | B36: 12000 | C36: =IF($B$70>0,B36/$B$70,B36/1) -> 0.00026027939 | D36: 12000 | E36: =IF($D$70>0,D36/$D$70,D36/1) -> 0.00025461631 | F36: 12000 | G36: =IF($F$70>0,F36/$F$70,F36/1) -> 0.00029571173 | I36: =SUM(B36+D36+F36) -> 36000 | K36: =SUM(R$5*N36) -> 4320 | L36: =IF($I$70>0,I36/$I$70,I36/1) -> 0.00026902994 | M36: Calculated on Per Unit Basis | N36: =SUM(I36/R$4) -> 60
A37: GeoTech | B37: 20000 | C37: =IF($B$70>0,B37/$B$70,B37/1) -> 0.00043379898 | D37: 20000 | E37: =IF($D$70>0,D37/$D$70,D37/1) -> 0.00042436051 | F37: 20000 | G37: =IF($F$70>0,F37/$F$70,F37/1) -> 0.00049285289 | I37: =SUM(B37+D37+F37) -> 60000 | K37: =SUM(R$5*N37) -> 7200 | L37: =IF($I$70>0,I37/$I$70,I37/1) -> 0.00044838323 | M37: Calculated on Per Unit Basis | N37: =SUM(I37/R$4) -> 100
A38: CONSTRUCTION FINANCE | C38: =IF($B$70>0,B38/$B$70,B38/1) -> 0
A39: Title and Recording | B39: =500*200 -> 100000 | C39: =IF($B$70>0,B39/$B$70,B39/1) -> 0.0021689949 | D39: =500*200 -> 100000 | E39: =IF($D$70>0,D39/$D$70,D39/1) -> 0.0021218026 | F39: =500*200 -> 100000 | G39: =IF($F$70>0,F39/$F$70,F39/1) -> 0.0024642644 | I39: =SUM(B39+D39+F39) -> 300000 | K39: =SUM(R$5*N39) -> 36000 | L39: =IF($I$70>0,I39/$I$70,I39/1) -> 0.0022419162 | M39: Calculated on Per Unit Basis | N39: =SUM(I39/R$4) -> 500
A40: Constr. Interest | B40: 185000 | C40: =IF($B$70>0,B40/$B$70,B40/1) -> 0.0040126405 | D40: 185000 | E40: =IF($D$70>0,D40/$D$70,D40/1) -> 0.0039253347 | F40: 185000 | G40: =IF($F$70>0,F40/$F$70,F40/1) -> 0.0045588892 | I40: =SUM(B40+D40+F40) -> 555000 | L40: =IF($I$70>0,I40/$I$70,I40/1) -> 0.0041475449 | M40: calculated in L&A model
A41: Constr. Loan Fees | B41: 40000 | C41: =IF($B$70>0,B41/$B$70,B41/1) -> 0.00086759795 | D41: 40000 | E41: =IF($D$70>0,D41/$D$70,D41/1) -> 0.00084872103 | F41: 40000 | G41: =IF($F$70>0,F41/$F$70,F41/1) -> 0.00098570577 | I41: =SUM(B41+D41+F41) -> 120000 | L41: =IF($I$70>0,I41/$I$70,I41/1) -> 0.00089676646 | M41: Calculated 1% Loan Amount L&A Model
A42: Appraisal | B42: =200*300 -> 60000 | C42: =IF($B$70>0,B42/$B$70,B42/1) -> 0.0013013969 | D42: =200*300 -> 60000 | E42: =IF($D$70>0,D42/$D$70,D42/1) -> 0.0012730815 | F42: =200*300 -> 60000 | G42: =IF($F$70>0,F42/$F$70,F42/1) -> 0.0014785587 | I42: =SUM(B42+D42+F42) -> 180000 | K42: =SUM(R$5*N42) -> 21600 | L42: =IF($I$70>0,I42/$I$70,I42/1) -> 0.0013451497 | M42: Calculated on Per Unit Basis | N42: =SUM(I42/R$4) -> 300
A43: Market Study | B43: 4500 | C43: =IF($B$70>0,B43/$B$70,B43/1) -> 9.7604769e-05 | D43: 4500 | E43: =IF($D$70>0,D43/$D$70,D43/1) -> 9.5481115e-05 | F43: 4500 | G43: =IF($F$70>0,F43/$F$70,F43/1) -> 0.0001108919 | I43: =SUM(B43+D43+F43) -> 13500 | K43: =+I43 -> 13500 | L43: =IF($I$70>0,I43/$I$70,I43/1) -> 0.00010088623 | M43: Reasonable for single phase
A44: Lender Legal | B44: 50000 | C44: =IF($B$70>0,B44/$B$70,B44/1) -> 0.0010844974 | D44: 50000 | E44: =IF($D$70>0,D44/$D$70,D44/1) -> 0.0010609013 | F44: 50000 | G44: =IF($F$70>0,F44/$F$70,F44/1) -> 0.0012321322 | I44: =SUM(B44+D44+F44) -> 150000 | K44: =SUM(R$5*N44) -> 18000 | L44: =IF($I$70>0,I44/$I$70,I44/1) -> 0.0011209581 | M44: Calculated on Per Unit Basis | N44: =SUM(I44/R$4) -> 250
A45: Other | B45: 0 | C45: =IF($B$70>0,B45/$B$70,B45/1) -> 0 | D45: 0 | E45: =IF($D$70>0,D45/$D$70,D45/1) -> 0 | F45: 0 | G45: =IF($F$70>0,F45/$F$70,F45/1) -> 0 | I45: =SUM(B45+D45+F45) -> 0 | L45: =IF($I$70>0,I45/$I$70,I45/1) -> 0
A46: PERMANENT FINANCE
A47: Perm. Loan Fees | B47: 75000 | C47: =IF($B$70>0,B47/$B$70,B47/1) -> 0.0016267462 | D47: 75000 | E47: =IF($D$70>0,D47/$D$70,D47/1) -> 0.0015913519 | F47: 75000 | G47: =IF($F$70>0,F47/$F$70,F47/1) -> 0.0018481983 | I47: =SUM(B47+D47+F47) -> 225000 | L47: =IF($I$70>0,I47/$I$70,I47/1) -> 0.0016814371 | M47: Calculated as 1% of Perm Loan
A48: Credit Enhancement | C48: =IF($B$70>0,B48/$B$70,B48/1) -> 0 | E48: =IF($D$70>0,D48/$D$70,D48/1) -> 0 | G48: =IF($F$70>0,F48/$F$70,F48/1) -> 0 | I48: =SUM(B48+D48+F48) -> 0 | L48: =IF($I$70>0,I48/$I$70,I48/1) -> 0
A49: Title and Recording | B49: 25000 | C49: =IF($B$70>0,B49/$B$70,B49/1) -> 0.00054224872 | D49: 25000 | E49: =IF($D$70>0,D49/$D$70,D49/1) -> 0.00053045064 | F49: 25000 | G49: =IF($F$70>0,F49/$F$70,F49/1) -> 0.00061606611 | I49: =SUM(B49+D49+F49) -> 75000 | K49: =SUM(R$5*N49) -> 9000 | L49: =IF($I$70>0,I49/$I$70,I49/1) -> 0.00056047904 | M49: Calculated on Per Unit Basis | N49: =SUM(I49/R$4) -> 125
A50: Lender Legal | B50: 50000 | C50: =IF($B$70>0,B50/$B$70,B50/1) -> 0.0010844974 | D50: 50000 | E50: =IF($D$70>0,D50/$D$70,D50/1) -> 0.0010609013 | F50: 50000 | G50: =IF($F$70>0,F50/$F$70,F50/1) -> 0.0012321322 | I50: =SUM(B50+D50+F50) -> 150000 | K50: =SUM(R$5*N50) -> 18000 | L50: =IF($I$70>0,I50/$I$70,I50/1) -> 0.0011209581 | M50: Calculated on Per Unit Basis | N50: =SUM(I50/R$4) -> 250
A51: Other | C51: =IF($B$70>0,B51/$B$70,B51/1) -> 0 | E51: =IF($D$70>0,D51/$D$70,D51/1) -> 0 | G51: =IF($F$70>0,F51/$F$70,F51/1) -> 0 | I51: =SUM(B51+D51+F51) -> 0 | L51: =IF($I$70>0,I51/$I$70,I51/1) -> 0
A52: SOFT COSTS
A53: Property Taxes | B53: 0 | C53: =IF($B$70>0,B53/$B$70,B53/1) -> 0 | D53: 0 | E53: =IF($D$70>0,D53/$D$70,D53/1) -> 0 | F53: 0 | G53: =IF($F$70>0,F53/$F$70,F53/1) -> 0 | I53: =SUM(B53+D53+F53) -> 0 | L53: =IF($I$70>0,I53/$I$70,I53/1) -> 0
A54: Constr. Insurance | B54: 777000 | C54: =IF($B$70>0,B54/$B$70,B54/1) -> 0.01685309 | D54: 777000 | E54: =IF($D$70>0,D54/$D$70,D54/1) -> 0.016486406 | F54: =777000*0.82 -> 637140 | G54: =IF($F$70>0,F54/$F$70,F54/1) -> 0.015700814 | I54: =SUM(B54+D54+F54) -> 2191140 | K54: =SUM(R$5*N54) -> 262936.8 | L54: =IF($I$70>0,I54/$I$70,I54/1) -> 0.016374507 | M54: Calculated on Per Unit Basis (1% on Comparable Cost Certfied Deal) Used in Model | N54: =SUM(I54/R$4) -> 3651.9
A55: Other Depreciable Soft | C55: =IF($B$70>0,B55/$B$70,B55/1) -> 0 | E55: =IF($D$70>0,D55/$D$70,D55/1) -> 0 | G55: =IF($F$70>0,F55/$F$70,F55/1) -> 0 | I55: =SUM(B55+D55+F55) -> 0 | L55: =IF($I$70>0,I55/$I$70,I55/1) -> 0
A56: Tax Credit Appl. Fee | B56: 15000 | C56: =IF($B$70>0,B56/$B$70,B56/1) -> 0.00032534923 | D56: 15000 | E56: =IF($D$70>0,D56/$D$70,D56/1) -> 0.00031827038 | F56: 15000 | G56: =IF($F$70>0,F56/$F$70,F56/1) -> 0.00036963966 | I56: =SUM(B56+D56+F56) -> 45000 | L56: =IF($I$70>0,I56/$I$70,I56/1) -> 0.00033628742 | M56: Calculated Per LHC Formula
A57: Tax Credit Mon. Fee | B57: 7029 | C57: =IF($B$70>0,B57/$B$70,B57/1) -> 0.00015245865 | D57: 7029 | E57: =IF($D$70>0,D57/$D$70,D57/1) -> 0.0001491415 | F57: =33*200 -> 6600 | G57: =IF($F$70>0,F57/$F$70,F57/1) -> 0.00016264145 | I57: =SUM(B57+D57+F57) -> 20658 | L57: =IF($I$70>0,I57/$I$70,I57/1) -> 0.00015437835 | M57: Calculated Per LHC Formula
A58: Marketing Expense | B58: 30000 | C58: =IF($B$70>0,B58/$B$70,B58/1) -> 0.00065069846 | D58: 30000 | E58: =IF($D$70>0,D58/$D$70,D58/1) -> 0.00063654077 | F58: 25000 | G58: =IF($F$70>0,F58/$F$70,F58/1) -> 0.00061606611 | I58: =SUM(B58+D58+F58) -> 85000 | K58: =+I58 -> 85000 | L58: =IF($I$70>0,I58/$I$70,I58/1) -> 0.00063520958
A59: Supervision | B59: 240000 | C59: =IF($B$70>0,B59/$B$70,B59/1) -> 0.0052055877 | D59: 252000 | E59: =IF($D$70>0,D59/$D$70,D59/1) -> 0.0053469425 | F59: =(240000*1.1)*0.82 -> 216480 | G59: =IF($F$70>0,F59/$F$70,F59/1) -> 0.0053346396 | I59: =SUM(B59+D59+F59) -> 708480 | K59: =SUM(R$5*N59) -> 85017.6 | L59: =IF($I$70>0,I59/$I$70,I59/1) -> 0.0052945092 | M59: Not Sure What This is - Calculated on Per Unit | N59: =SUM(I59/R$4) -> 1180.8
A60: Environmental Cont | B60: 160000 | C60: =IF($B$70>0,B60/$B$70,B60/1) -> 0.0034703918 | D60: 168000 | E60: =IF($D$70>0,D60/$D$70,D60/1) -> 0.0035646283 | F60: =(160000*1.1)*0.82 -> 144320 | G60: =IF($F$70>0,F60/$F$70,F60/1) -> 0.0035564264 | I60: =SUM(B60+D60+F60) -> 472320 | K60: =SUM(R$5*N60) -> 56678.4 | L60: =IF($I$70>0,I60/$I$70,I60/1) -> 0.0035296728 | N60: =SUM(I60/R$4) -> 787.2
A61: Syndication Expense | B61: 176045 | C61: =IF($B$70>0,B61/$B$70,B61/1) -> 0.003818407 | D61: 180919 | E61: =IF($D$70>0,D61/$D$70,D61/1) -> 0.003838744 | F61: =15651051*0.01 -> 156510.51 | G61: =IF($F$70>0,F61/$F$70,F61/1) -> 0.0038568328 | I61: =SUM(B61+D61+F61) -> 513474.51 | L61: =IF($I$70>0,I61/$I$70,I61/1) -> 0.0038372227 | M61: Appears very High; - Calculated per previous deals L& A has worked on
A62: Tax Opinion | B62: 9000 | C62: =IF($B$70>0,B62/$B$70,B62/1) -> 0.00019520954 | D62: 9000 | E62: =IF($D$70>0,D62/$D$70,D62/1) -> 0.00019096223 | F62: 9000 | G62: =IF($F$70>0,F62/$F$70,F62/1) -> 0.0002217838 | I62: =SUM(B62+D62+F62) -> 27000 | L62: =IF($I$70>0,I62/$I$70,I62/1) -> 0.00020177245 | M62: Included in syndication legal/other
A63: Rentup Expense | B63: 20000 | C63: =IF($B$70>0,B63/$B$70,B63/1) -> 0.00043379898 | D63: 20000 | E63: =IF($D$70>0,D63/$D$70,D63/1) -> 0.00042436051 | F63: 20000 | G63: =IF($F$70>0,F63/$F$70,F63/1) -> 0.00049285289 | I63: =SUM(B63+D63+F63) -> 60000 | K63: =+I63 -> 60000 | L63: =IF($I$70>0,I63/$I$70,I63/1) -> 0.00044838323 | M63: Appears Reasonable for Single Phase
A64: RESERVES
A65: Rentup Reserve | B65: 302758 | C65: =IF($B$70>0,B65/$B$70,B65/1) -> 0.0065668055 | D65: 314403 | E65: =IF($D$70>0,D65/$D$70,D65/1) -> 0.0066710109 | F65: 256631 | G65: =IF($F$70>0,F65/$F$70,F65/1) -> 0.0063240664 | I65: =SUM(B65+D65+F65) -> 873792 | L65: =IF($I$70>0,I65/$I$70,I65/1) -> 0.0065298947 | M65: Calculated 6 mo. Operating expenses + Debt Service
A66: Operating Reserve | C66: =IF($B$71>0,B66/$B$71,B66/1) -> 0 | E66: =IF($D$70>0,D66/$D$70,D66/1) -> 0 | G66: =IF($F$70>0,F66/$F$70,F66/1) -> 0 | I66: =SUM(B66+D66+F66) -> 0
A67: Bond D/S Reserve | C67: =IF($B$71>0,B67/$B$71,B67/1) -> 0 | E67: =IF($D$70>0,D67/$D$70,D67/1) -> 0 | G67: =IF($F$70>0,F67/$F$70,F67/1) -> 0 | I67: =SUM(B67+D67+F67) -> 0
A68: Working Capital | C68: =IF($B$71>0,B68/$B$71,B68/1) -> 0 | E68: =IF($D$70>0,D68/$D$70,D68/1) -> 0 | G68: =IF($F$70>0,F68/$F$70,F68/1) -> 0 | I68: =SUM(B68+D68+F68) -> 0
A69: Other | C69: =IF($B$71>0,B69/$B$71,B69/1) -> 0 | E69: =IF($D$70>0,D69/$D$70,D69/1) -> 0 | G69: =IF($F$70>0,F69/$F$70,F69/1) -> 0 | I69: =SUM(B69+D69+F69) -> 0
A70: DEVELOPMENT COST | B70: =SUM(B10:B69) -> 46104304 | C70: =IF($B$70>0,B70/$B$70,B70/1) -> 1 | D70: =SUM(D10:D69) -> 47129738 | E70: =IF($D$70>0,D70/$D$70,D70/1) -> 1 | F70: =SUM(F10:F69) -> 40580061 | G70: =IF($F$70>0,F70/$F$70,F70/1) -> 1 | I70: =SUM(I10:I69) -> 1.338141e+08
A71: Ck to Client Numbers: Sources | B71: =46104304-B70 -> -0.40000001 | D71: =+D70-47129738.5 -> 0 | F71: =+F70-40580061 -> -0.32976
A72: Ck to Client Numbers: Uses | B72: =46392336-B83 -> 0 | D72: =47129739-D83 -> 0 | F72: =40580061-F83 -> 0
A73: Sources of Funds
A75: Bank | B75: 14756563 | D75: 14980891 | F75: 12406291 | I75: =SUM(B75+D75+F75) -> 42143745
A76: Amortizing Loan | B76: 7831300 | D76: 7856930 | F76: 6651027 | I76: =SUM(B76+D76+F76) -> 22339257
A77: Deferred Loan | B77: 4000000 | D77: 4000000 | F77: 3750000 | I77: =SUM(B77+D77+F77) -> 11750000
A78: Grant (Soft Funds) | B78: 2200000 | D78: 2200000 | F78: 2200000 | I78: =SUM(B78+D78+F78) -> 6600000 | K78: =+'Sources & Uses'!V22 -> 1388100 | M78: Only eligible for 3.6 in cap funds, thus reduced by 1,500,000.
A79: Equity | B79: 17604473 | D79: 18091918 | F79: 15572743 | I79: =SUM(B79+D79+F79) -> 51269134 | M79: Assumed Capital Funds In deal | N79: =+'Sources & Uses'!V19 -> 1388100
A80: Deferred Fee | B80: 0 | D80: 0 | F80: 0
M81: NOTE: Increased PH Units to Max Cap Fund Eligilbity to 3,600000, which
M82: resulted in reduction of Perm Loan Proceeds as Follows:
A83: Total Sources | B83: =SUM(B75:B82) -> 46392336 | D83: =SUM(D75:D82) -> 47129739 | F83: =SUM(F75:F82) -> 40580061 | I83: =SUM(I75:I82) -> 134102136
M84: Perm Proceeds - Originally modeled with 14 PH units | N84: 31250000
M85: Perm Proceeds - Currently projected 23 PH Units | N85: =+#REF! -> #REF!
M86: Perm Loan Reduction | N86: =+N84-N85 -> #REF!

Sheet Construction Breakdown (PBC)
A2: Calliope Senior Village | F2: Per
A3: Original Assumptions | C3: 355 | D3: units | F3: Unit
A4: Original Assumptions | C4: 328000 | D4: SF | F4: Cost
A5: Updated on Per unit Basis - 2/5/19 | F5: 355 Units
A6: SITE IMPROVEMENTS
A7: Demolition
A8: On-Site Improvements | C8: 1566510 | F8: =SUM(C8/C$3) -> 4412.7042
A9: Off-Site Improvements
A11: CONSTRUCTION | E11: Fees to S/U
A12: Rehabilitation | C12: 2640000 | F12: 0
A13: New Construction | C13: 50361930 | F13: =SUM(C13/C$3) -> 141864.59
A14: Gen Requirements | C14: 3548750 | D14: =-C14+'Sources & Uses'!F26 -> -3259723.3 | E14: =SUM(C14:D14) -> 289026.68 | F14: =SUM(C14/C$3) -> 9996.4789
A15: Contractor Overhead | C15: 1073724 | E15: =+C15 -> 1073724 | F15: =SUM(C15/C$3) -> 3024.5746
A16: Contractor Profit | C16: 2135784 | D16: =-D14 -> 3259723.3 | E16: =SUM(C16:D16) -> 5395507.3 | F16: =SUM(C16/C$3) -> 6016.293
A17: P & P Bond | C17: 319152 | F17: =SUM(C17/C$3) -> 899.01972
A18: Contingency | C18: 4300000 | F18: =SUM(C18/C$3) -> 12112.676
A19: Permits & Impact Fees | C19: 321059 | F19: =SUM(C19/C$3) -> 904.39155
A20: Furnishings | C20: 223735 | F20: =SUM(C20/C$3) -> 630.23944
A22: TOTAL | C22: =SUM(C8:C20) -> 66490644
A23: Variance to S/U | C23: =+C22-'Sources & Uses'!E24 -> 52039310
C24: =C22/C3 -> 187297.59 | D24: cost/unit
C25: =C22/C4 -> 202.71538 | D25: cost/sf
A29: Total Hard Costs | C29: =SUM(C8:C13)+C20 -> 54792175 | D29: =+C29/C3 -> 154344.15
A30: Gen. Requirement | C30: =SUM(C14) -> 3548750 | D30: =+C30/C29 -> 0.06476746
A33: LHC Calculated Fee Limits:
A35: General Requirement | B35: 0.06 | C35: =SUM(C29*B35) -> 3287530.5 | D35: =+E14 -> 289026.68 | E35: =IF(D35+C35,"TEST MET","TEST NOT MET") -> TEST MET
A36: Overhead | B36: 0.02 | C36: =SUM(C29+C35)*B36 -> 1161594.1 | D36: =+E15 -> 1073724 | E36: =IF(D36+C36,"TEST MET","TEST NOT MET") -> TEST MET
A37: Builder Profit | B37: 0.06 | C37: =SUM(C29+C35)*B37 -> 3484782.3 | D37: =+E16 -> 5395507.3 | E37: =IF(D37+C37,"TEST MET","TEST NOT MET") -> TEST MET

Sheet Intermediary Cost
A1: =+'Sources & Uses'!A1 -> Lamar Building
A2: Intermediary Cost Worksheet
A5: Total Development Costs | F5: =+'Sources & Uses'!I75 -> 24500000
A8: Intermediary Costs:
A10: General Overhead | F10: =+'Sources & Uses'!F30 -> 722566.7
A11: Builder's Profit | F11: =+'Sources & Uses'!F31 -> 221105.41
A12: Developer Fee | F12: =+'Sources & Uses'!#REF! -> #REF!
A13: Syndication Costs | F13: =+'Sources & Uses'!F73 -> 0
A14: Architect's Fees | F14: =+'Sources & Uses'!F33+'Sources & Uses'!F34 -> 400000
A15: Legal Fees | F15: =+'Sources & Uses'!F48 -> 50000
A16: Organization Costs | F16: =+'Sources & Uses'!F50 -> 0
A17: Other Fees | F17: 0
A19: Total Intermediary Costs | F19: =SUM(F10:F18) -> #REF!
A22: Percentage of Total Development Costs | F22: =SUM(F19/F5) -> #REF!

Sheet TDC Per Unit
A1: =+'Sources & Uses'!A1 -> Lamar Building
A2: Calculation of TDC per Unit (Per QAP)
A6: Total Development Costs | H6: =+'Sources & Uses'!I75 -> 24500000
A8: Less Non-Basis Allowable Deletions:
B10: Permanent Financing Fee (2% of Loan Max.) | G10: 0
B11: Organization Costs ( 25,000 Max.) | G11: 0
B12: Non Eligible Legal | G12: =+'[2]Cost Allocation Basis'!I34 -> 0
B13: Community Facility | G13: 55000
B14: Reserves | G14: =+'Sources & Uses'!H65 -> 0
B15: Total Allowable Deletions | H15: =SUM(G10:G14) -> 55000
B17: Total Development Costs | H17: =SUM(H6-H15) -> 24445000
B19: Total Development Costs Per Unit | H19: =SUM(H17/'Sources & Uses'!B77) -> 339513.89
B21: Total Square Footage: | D21: Gross | H21: =+'Sq Footage'!L103 -> 155913
D22: Net | H22: =+H21 -> 155913
B23: TDC Per Square Footage - Gross | H23: =SUM(H17/H21) -> 156.78616 | I23: 105 | J23: =SUM(H23-I23) -> 51.786156 | K23: Variance Sq. Ftg.
J24: =SUM(H21*J23) -> 8074135 | K24: Cost Variance

Sheet Sources & Uses
A1: Lamar Building | E1: =+Rent!C44 -> 72 | F1: Acquisition/Rehabilitation
A2: Sources And Uses Statement | F2: Augusta GA | T2: Workspace and Notes
A4: Sources:
T5: Other Sources of Funds
A6: Construction Loan | F6: 18500000 | T6: =+'Interest Calculation'!G1 -> 0 | U6: Soft | V6: 0
T7: Other Sources of Funds | U7: Seller Note | V7: 0
A8: Equity | F8: 6000000 | V8: 0
A9: Total Sources From Debt and Equity | F9: =+F6+F7+F8 -> 24500000 | V9: =SUM(V6:V8) -> 0
A10: TOTAL SOURCES | I10: =+F9 -> 24500000
T11: Land Acquisition Price | U11: 127000 | V11: 0
T12: Buildng Acquisition | U12: 5000000 | V12: =+U12 -> 5000000
M13: =+I10 -> 24500000 | T13: Construction Breakdown:
A14: Uses: | T14: Total Land Improvements | V14: 201000
T15: Construction Hard Cost | V15: =+E1*190000 -> 13680000
A16: Land | B16: Acres/Price | D16: 0 | E16: =+V11 -> 0 | F16: 5000000 | G16: x | T16: Total Hard Cost | V16: =+V15+V14 -> 13881000
A17: Building Acquistion | G17: x | T17: Per Unit Hard Costs | V17: =+V16/E1 -> 192791.67
A18: Land Improvements
A19: Unusual Land Improvements | T19: Projected Hard Cost Contingency | V19: =+V16*0.1 -> 1388100
A20: Other Land Improvements | F20: 0 | T20: Excess OH; GR; BP | V20: 0
A21: Sub-Total Land Improvements | F21: =SUM(F19:F20) -> 0
T22: Total Contingency (Including Excess Bldr Fees. | V22: =SUM(V19:V21) -> 1388100
A23: Buildings
A24: Construction Hard Costs | C24: Ttl Constr Contract | E24: 14451334 | F24: 14451334 | G24: x
A25: (Contingency) Hard Costs | E25: 0.07 | F25: =+F24*E25 -> 1011593.4 | G25: x
A26: General Requirements | E26: 0.02 | F26: =SUM(F24*E26) -> 289026.68 | G26: x
A27: Sub-Total Buildings | F27: =SUM(F24:F26) -> 15751954
A29: Fees
A30: Builders Profit | E30: 0.05 | F30: =SUM(F24)*E30 -> 722566.7 | G30: x
A31: Builders O/H (2%) | E31: 0.015 | F31: =SUM(F24+F26)*E31 -> 221105.41 | G31: x
A32: Bond Premium/Impact Fees | F32: 0 | G32: x
A33: Architects Fee-Design | D33: =+U35 -> 0.8 | E33: =+U37 -> 0.027679106 | F33: =+V35 -> 400000 | G33: x
A34: Architects Fee-Supervision | D34: =+U36 -> 0.2 | F34: =+V36 -> 0 | G34: x | H34: =SUM(F33:F34) -> 400000 | T34: Architect Worksheet:
A35: Other- CM | F35: =+F24*0.05 -> 722566.7 | T35: Architect Contract: | U35: 0.8 | V35: 400000
A36: Sub-Total Fees | F36: =SUM(F30:F35) -> 2066238.8 | U36: 0.2 | V36: 0
U37: =+V37/E24 -> 0.027679106 | V37: =+V35+V36 -> 400000
A38: Charges and Financing | T38: Total Fees | U38: Fixed Fee | V38: =+V16*0.06 -> 832860
A39: Interest | F39: =+'Interest Calculation'!D50 -> 859375 | T39: Legal Fees Breakdown
A40: Financing Fee - Construction | F40: =17500000*0.003 -> 52500 | H40: 0.0125 | U40: Basis Elig.
A41: Bond Cost of Issuance | F41: 20000 | H41: Bond Structure Needed for Tax Abatement | T41: Lender Legal Const | U41: x | V41: 100000 | W41: =IF(U41="x",V41/V$45,0) -> 0.57142857 | AB41: CR | AH41: 55000
A42: Taxes | F42: 0 | T42: Lender Legal Perm | U42: x | V42: 75000 | W42: =IF(U42="x",V42/V$45,0) -> 0.42857143 | AB42: Perm | AH42: 21000
A43: Insurance | F43: 120000 | H43: Quoted Amount for Full Project | T43: Legal - Syndication | U43: 10K org syn. Rest in legal | V43: 0 | AB43: Total | AH43: =SUM(AH41:AH42) -> 76000
A44: Title/Recording | F44: 7000
F45: =SUM(F39:F44) -> 1058875 | T45: Total Legal | V45: =SUM(V41:V43) -> 175000 | W45: =SUM(W41:W43) -> 1 | AA45: Title Calc
W46: =1-W45 -> 0 | AA46: =SUM(F6/AC46*AB46) -> 41625 | AB46: 2.25 | AC46: 1000 | AD46: 1st
A47: Legal/Organizational | AA47: =SUM(F7/AC47*AB47) -> 0 | AB47: 2.75 | AC47: 1000 | AD47: 2nd
A48: Legal | F48: 50000 | G48: x | AA48: 1.5
A49: CPA Fees | F49: 25000 | G49: x | W49: =IF(U49="x",V49/V$52,0) -> 0
A50: Organizational | F50: 0
A51: Cost Certification | F51: 0 | G51: x
A52: Sub-Total Legal/Org. | F52: =SUM(F48:F51) -> 75000 | W52: =SUM(W48:W51) -> 0
W53: =1-W52 -> 1
A54: Other Fees and Cost
A55: Operational Fees | F55: 400000 | T55: Other Third Party Costs
A56: LIHTC Application Fee | F56: 0
A57: Tax Credit Commitment Fees | E57: 0.05 | F57: 0 | T57: Green Certification | V57: 5000 | W57: x
A58: =+T55 -> Other Third Party Costs | F58: 217742 | T58: Accessibility Review | V58: 2600 | W58: x
F59: =+V82 -> 0 | T59: Other - Constr. Materials Testing | V59: 5000 | W59: x
A60: Sub-Total Other | F60: =SUM(F55:F59) -> 617742 | T60: Building Permits | V60: 80000 | W60: x
T61: Appraisal | V61: 9000 | W61: x
T62: Market Study | V62: 6000 | W62: x
T63: Environmental | V63: 15000 | W63: x
T64: Alta Survey | V64: 6000 | W64: x
T65: Water Line Test | V65: 1000 | W65: x
T66: PCNA | V66: 6000 | W66: x
A67: Developer Fee Rehab.(Maximum 15%) | F67: 0 | H67: 0 | T67: Sponsor Costs | V67: 0
H68: 0 | V68: =SUM(V57:V67) -> 135600
A70: Syndication/ Other Expenses
A71: Syndication Legal | F71: 0
A72: Accountant Fees/Synd. Fee | F72: 0
A73: Sub-Total | F73: =SUM(F71:F72) -> 0
A75: TOTAL USES | F75: =+F27+F16+F36+F45+F52+F60 -> 24569810 | I75: =+I10 -> 24500000
A77: Total Units | B77: =+Rent!C44 -> 72
A78: Total Uses per Unit | I78: =I75/B77 -> 340277.78
A79: Total Development Cost Per Unit | I79: =SUM(I75/B77) -> 340277.78
A80: Profit Percentage (Rehab. Portion) | H80: 0.1
A81: Developer Fee Percentage | H81: =SUM(H67/F75) -> 0
A82: Hard Cost Per Unit | H82: =+(E24+V22)/E1 -> 219992.14
A83: Total Project Square Footage | H83: 78800
A84: Construction Cost per Square Foot | H84: =+F75/H83 -> 311.79962
A85: Builders Profit | B85: 0
A87: Total | B87: =SUM(B85:B86) -> 0
A88: less Deferred | B88: =-#REF!-#REF! -> #REF!
A89: Net Profits | B89: =SUM(B87:B88) -> #REF!
A90: Net/Unit | B90: =SUM(B89/B77) -> #REF!

Sheet Sheet3
B4: Amount | C4: Percentage
A5: Total Construction Cost | B5: =+'Sources & Uses'!F75 -> 24569810 | C5: N/A
A6: Loan from SRP | B6: =+'Sources & Uses'!F6 -> 18500000 | C6: =+B6/B5 -> 0.75295658
A7: Total Equity from HTC’s | B7: 6900000 | C7: =+B7/B5 -> 0.28083245
A8: Total Equity from Partners | B8: 3500000 | C8: =+B8/B5 -> 0.14245124
A9: Total Debt & Equity | B9: =+B8+B7+B6 -> 28900000 | C9: 1
A11: NOTE: | B11: Equity from HTC's enter the project as follows:
B13: =6900000*0.25 -> 1725000 | C13: At closing
B14: =+B13*2 -> 3450000 | C14: At construction completion
B15: =+B13 -> 1725000 | C15: At occupancy
A17: The balance of HTC funds from project projections held as contingency until loan paid in full

Sheet 3rd Mortgage
A1: =+'Sources & Uses'!A1 -> Lamar Building | E1: 3rd Mortgage Loan | G1: Grant Funds - Loaned In (CAP;CNO;LHC)
A4: PRINCIPLE: | D4: =+C4 -> 0
A5: YEARLY INT RATE: | C5: 0 | E5: PMT AMT: | G5: =-PMT(C5/C7,C6,C4)*0 -> 0
A6: TOTAL # PMTS: | C6: 40 | E6: Ann. Debt Serv. | G6: =G5*C7 -> 0
A7: # PMTS PER YEAR: | C7: 1 | E7: D.S.C. | G7: =+'Proforma (Application)'!D79 -> 9359 | I7: =+'Sources & Uses'!#REF! -> #REF!
G8: =SUM('Proforma (Application)'!D82:R82)/15 -> 0
B10: PMT # | C10: PMT AMT | D10: INTEREST | E10: PRINCIPAL | F10: REM BAL | G10: ACC INT
B11: 1 | C11: =$G$5 -> 0 | D11: =C4*$C$5/12 -> 0 | E11: =C11-D11 -> 0 | F11: =C4-E11 -> 0 | G11: =D11 -> 0
B12: 2 | C12: =$G$5 -> 0 | D12: =F11*$C$5/12 -> 0 | E12: =C12-D12 -> 0 | F12: =F11-E12 -> 0 | G12: =D12+G11 -> 0
B13: 3 | C13: =$G$5 -> 0 | D13: =F12*$C$5/12 -> 0 | E13: =C13-D13 -> 0 | F13: =F12-E13 -> 0 | G13: =D13+G12 -> 0
B14: 4 | C14: =+'Residual Calculation'!H55 -> #REF! | D14: =F13*$C$5/12 -> 0 | E14: =C14-D14 -> #REF! | F14: =F13-E14 -> #REF! | G14: =D14+G13 -> 0
B15: 5 | C15: =+'Residual Calculation'!I55 -> #REF! | D15: =F14*$C$5/12 -> #REF! | E15: =C15-D15 -> #REF! | F15: =F14-E15 -> #REF! | G15: =D15+G14 -> #REF!
B16: 6 | C16: =+'Residual Calculation'!J55 -> #REF! | D16: =F15*$C$5/12 -> #REF! | E16: =C16-D16 -> #REF! | F16: =F15-E16 -> #REF! | G16: =D16+G15 -> #REF!
B17: 7 | C17: =+'Residual Calculation'!K55 -> #REF! | D17: =F16*$C$5/12 -> #REF! | E17: =C17-D17 -> #REF! | F17: =F16-E17 -> #REF! | G17: =D17+G16 -> #REF!
B18: 8 | C18: =+'Residual Calculation'!L55 -> #REF! | D18: =F17*$C$5/12 -> #REF! | E18: =C18-D18 -> #REF! | F18: =F17-E18 -> #REF! | G18: =D18+G17 -> #REF!
B19: 9 | C19: =+'Residual Calculation'!M55 -> #REF! | D19: =F18*$C$5/12 -> #REF! | E19: =C19-D19 -> #REF! | F19: =F18-E19 -> #REF! | G19: =D19+G18 -> #REF!
B20: 10 | C20: =+'Residual Calculation'!N55 -> #REF! | D20: =F19*$C$5/12 -> #REF! | E20: =C20-D20 -> #REF! | F20: =F19-E20 -> #REF! | G20: =D20+G19 -> #REF!
B21: 11 | C21: =+'Residual Calculation'!O55 -> #REF! | D21: =F20*$C$5/12 -> #REF! | E21: =C21-D21 -> #REF! | F21: =F20-E21 -> #REF! | G21: =D21+G20 -> #REF!
B22: 12 | C22: =+'Residual Calculation'!P55 -> #REF! | D22: =F21*$C$5/12 -> #REF! | E22: =C22-D22 -> #REF! | F22: =F21-E22 -> #REF! | G22: =D22+G21 -> #REF!
B23: 13 | C23: =+'Residual Calculation'!Q55 -> #REF! | D23: =F22*$C$5/12 -> #REF! | E23: =C23-D23 -> #REF! | F23: =F22-E23 -> #REF! | G23: =D23+G22 -> #REF!
B24: 14 | C24: =+'Residual Calculation'!R55 -> #REF! | D24: =F23*$C$5/12 -> #REF! | E24: =C24-D24 -> #REF! | F24: =F23-E24 -> #REF! | G24: =D24+G23 -> #REF!
B25: 15 | C25: =+'Residual Calculation'!S55 -> #REF! | D25: =F24*$C$5/12 -> #REF! | E25: =C25-D25 -> #REF! | F25: =F24-E25 -> #REF! | G25: =D25+G24 -> #REF!
B26: 16 | C26: =+'Residual Calculation'!T55 -> #REF! | D26: =F25*$C$5/12 -> #REF! | E26: =C26-D26 -> #REF! | F26: =F25-E26 -> #REF! | G26: =D26+G25 -> #REF!
B27: 17 | C27: =+'Residual Calculation'!U55 -> #REF! | D27: =F26*$C$5/12 -> #REF! | E27: =C27-D27 -> #REF! | F27: =F26-E27 -> #REF! | G27: =D27+G26 -> #REF!
B28: 18 | C28: =+'Residual Calculation'!V55 -> #REF! | D28: =F27*$C$5/12 -> #REF! | E28: =C28-D28 -> #REF! | F28: =F27-E28 -> #REF! | G28: =D28+G27 -> #REF!
B29: 19 | C29: =+'Residual Calculation'!W55 -> #REF! | D29: =F28*$C$5/12 -> #REF! | E29: =C29-D29 -> #REF! | F29: =F28-E29 -> #REF! | G29: =D29+G28 -> #REF!
B30: 20 | C30: =+'Residual Calculation'!X55 -> #REF! | D30: =F29*$C$5/12 -> #REF! | E30: =C30-D30 -> #REF! | F30: =F29-E30 -> #REF! | G30: =D30+G29 -> #REF!
B31: 21 | C31: =$G$5 -> 0 | D31: =F30*$C$5/12 -> #REF! | E31: =C31-D31 -> #REF! | F31: =F30-E31 -> #REF! | G31: =D31+G30 -> #REF!
B32: 22 | C32: =$G$5 -> 0 | D32: =F31*$C$5/12 -> #REF! | E32: =C32-D32 -> #REF! | F32: =F31-E32 -> #REF! | G32: =D32+G31 -> #REF!
B33: 23 | C33: =$G$5 -> 0 | D33: =F32*$C$5/12 -> #REF! | E33: =C33-D33 -> #REF! | F33: =F32-E33 -> #REF! | G33: =D33+G32 -> #REF!
B34: 24 | C34: =$G$5 -> 0 | D34: =F33*$C$5/12 -> #REF! | E34: =C34-D34 -> #REF! | F34: =F33-E34 -> #REF! | G34: =D34+G33 -> #REF!
B35: 25 | C35: =$G$5 -> 0 | D35: =F34*$C$5/12 -> #REF! | E35: =C35-D35 -> #REF! | F35: =F34-E35 -> #REF! | G35: =D35+G34 -> #REF!
B36: 26 | C36: =$G$5 -> 0 | D36: =F35*$C$5/12 -> #REF! | E36: =C36-D36 -> #REF! | F36: =F35-E36 -> #REF! | G36: =D36+G35 -> #REF!
B37: 27 | C37: =$G$5 -> 0 | D37: =F36*$C$5/12 -> #REF! | E37: =C37-D37 -> #REF! | F37: =F36-E37 -> #REF! | G37: =D37+G36 -> #REF!
B38: 28 | C38: =$G$5 -> 0 | D38: =F37*$C$5/12 -> #REF! | E38: =C38-D38 -> #REF! | F38: =F37-E38 -> #REF! | G38: =D38+G37 -> #REF!
B39: 29 | C39: =$G$5 -> 0 | D39: =F38*$C$5/12 -> #REF! | E39: =C39-D39 -> #REF! | F39: =F38-E39 -> #REF! | G39: =D39+G38 -> #REF!
B40: 30 | C40: =$G$5 -> 0 | D40: =F39*$C$5/12 -> #REF! | E40: =C40-D40 -> #REF! | F40: =F39-E40 -> #REF! | G40: =D40+G39 -> #REF!
B41: 31 | C41: =$G$5 -> 0 | D41: =F40*$C$5/12 -> #REF! | E41: =C41-D41 -> #REF! | F41: =F40-E41 -> #REF! | G41: =D41+G40 -> #REF!
B42: 32 | C42: =$G$5 -> 0 | D42: =F41*$C$5/12 -> #REF! | E42: =C42-D42 -> #REF! | F42: =F41-E42 -> #REF! | G42: =D42+G41 -> #REF!
... B50: 40 | C50: =$G$5 -> 0 | D50: =F49*$C$5/12 -> #REF! | E50: =C50-D50 -> #REF! | F50: =F49-E50 -> #REF! | G50: =D50+G49 -> #REF!

Sheet Cost Allocation Basis
A1: =+'Sources & Uses'!A1 -> Lamar Building
A2: Cost Allocation
A4: Sources:
A6: First Mortgage - Conventional | F6: =+'Sources & Uses'!F6 -> 18500000
A7: Second Mortgage - Non - Profit | F7: =+'Sources & Uses'!F7 -> 0
A8: =+'Sources & Uses'!A8 -> Equity | F8: =+'Sources & Uses'!F8 -> 6000000
A9: Owner Contribution | F9: =+'Sources & Uses'!#REF! -> #REF!
A10: Tax Credit - Equity Contribution | F10: =+'Sources & Uses'!#REF! -> #REF!
A11: TOTAL SOURCES | F11: =SUM(F6:F10) -> #REF!
F13: Total | I13: Amortizable | K13: Non- Amortizable | M13: Eligible Basis | O13: Historic
A14: Uses: | F14: Development Cost | I14: Costs | K14: Non - Depreciable | M14: Costs | O14: Basis
A16: Land | F16: =+'Sources & Uses'!H16 -> 0 | I16: =SUM(H16*$F16) -> 0 | J16: 1 | K16: =SUM(J16*$F16) -> 0 | M16: =SUM(L16*$F16) -> 0 | O16: =SUM(N16*$F16) -> 0 | P16: =SUM(H16+J16+L16) -> 1 | Q16: 1000000
A17: Building Acquisition | F17: =+'Sources & Uses'!H17 -> 0 | L17: 1 | M17: =SUM(L17*$F17) -> 0 | P17: =SUM(H17+J17+L17) -> 1
A18: Unusual Land Improvements | F18: =+'Sources & Uses'!F19 -> 0 | I18: =SUM(H18*$F18) -> 0 | J18: 1 | K18: =SUM(J18*$F18) -> 0 | M18: =SUM(L18*$F18) -> 0 | O18: =SUM(N18*$F18) -> 0 | P18: =SUM(H18+J18+L18) -> 1
A19: Other Land Improvements | F19: =+'Sources & Uses'!F20 -> 0 | I19: =SUM(H19*$F19) -> 0 | J19: 0 | K19: =SUM(J19*$F19) -> 0 | L19: 1 | M19: =SUM(L19*$F19) -> 0 | O19: =SUM(N19*$F19) -> 0 | P19: =SUM(H19+J19+L19) -> 1
A20: Construction Hard Costs | F20: =+'Sources & Uses'!F24 -> 14451334 | I20: =SUM(H20*$F20) -> 0 | J20: 0 | K20: =SUM(J20*$F20) -> 0 | L20: 1 | M20: =SUM(L20*$F20) -> 14451334 | O20: =+F20 -> 14451334 | P20: =SUM(H20+J20+L20) -> 1 | Q20: 104296
A21: =+'Sources & Uses'!A25 -> (Contingency) Hard Costs | F21: =+'Sources & Uses'!F25 -> 1011593.4 | I21: =SUM(H21*$F21) -> 0 | K21: =SUM(J21*$F21) -> 0 | L21: 1 | M21: =SUM(L21*$F21) -> 1011593.4 | O21: =+F21 -> 1011593.4 | P21: =SUM(H21+J21+L21) -> 1
A22: General Requirements | F22: =+'Sources & Uses'!F26 -> 289026.68 | I22: =SUM(H22*$F22) -> 0 | K22: =SUM(J22*$F22) -> 0 | L22: 1 | M22: =SUM(L22*$F22) -> 289026.68 | O22: =+F22 -> 289026.68 | P22: =SUM(H22+J22+L22) -> 1
A23: Builders Profit | F23: =+'Sources & Uses'!F30 -> 722566.7 | I23: =SUM(H23*$F23) -> 0 | K23: =SUM(J23*$F23) -> 0 | L23: 1 | M23: =SUM(L23*$F23) -> 722566.7 | O23: =+F23 -> 722566.7 | P23: =SUM(H23+J23+L23) -> 1
A24: Builders O/H (2%) | F24: =+'Sources & Uses'!F31 -> 221105.41 | I24: =SUM(H24*$F24) -> 0 | K24: =SUM(J24*$F24) -> 0 | L24: 1 | M24: =SUM(L24*$F24) -> 221105.41 | O24: =+F24 -> 221105.41 | P24: =SUM(H24+J24+L24) -> 1
A25: Bond Premium | F25: =+'Sources & Uses'!F32 -> 0 | I25: =SUM(H25*$F25) -> 0 | K25: =SUM(J25*$F25) -> 0 | L25: 1 | M25: =SUM(L25*$F25) -> 0 | O25: =+F25 -> 0 | P25: =SUM(H25+J25+L25) -> 1
A26: Architects Fee-Design | F26: =+'Sources & Uses'!F33 -> 400000 | I26: =SUM(H26*$F26) -> 0 | K26: =SUM(J26*$F26) -> 0 | L26: 1 | M26: =SUM(L26*$F26) -> 400000 | O26: =+F26 -> 400000 | P26: =SUM(H26+J26+L26) -> 1 | Q26: 68000 | R26: x
A27: Architects Fee-Supervision | F27: =+'Sources & Uses'!F34 -> 0 | I27: =SUM(H27*$F27) -> 0 | K27: =SUM(J27*$F27) -> 0 | L27: 1 | M27: =SUM(L27*$F27) -> 0 | O27: =+F27 -> 0 | P27: =SUM(H27+J27+L27) -> 1
A28: =+'Sources & Uses'!A35 -> Other- CM | F28: =+'Sources & Uses'!F35 -> 722566.7 | I28: =SUM(H28*$F28) -> 0 | K28: =SUM(J28*$F28) -> 0 | L28: 1 | M28: =SUM(L28*$F28) -> 722566.7 | O28: =+F28 -> 722566.7 | P28: =SUM(H28+J28+L28) -> 1
A29: Interest | F29: =+'Sources & Uses'!F39 -> 859375 | I29: =SUM(H29*$F29) -> 0 | J29: =+L28-L29 -> 0 | K29: =+F29*J29 -> 0 | L29: 1 | M29: 0 | O29: =+F29 -> 859375 | P29: =SUM(H29+J29+L29) -> 1
A30: =+'Sources & Uses'!A40 -> Financing Fee - Construction | F30: =+'Sources & Uses'!F40 -> 52500 | H30: 1 | I30: =SUM(H30*$F30) -> 52500 | K30: =SUM(J30*$F30) -> 0 | M30: =SUM(L30*$F30) -> 0 | O30: 0 | P30: =SUM(H30+J30+L30) -> 1
A31: =+'Sources & Uses'!#REF! -> #REF! | F31: =+'Sources & Uses'!#REF! -> #REF! | I31: =SUM(H31*$F31) -> #REF! | J31: 0 | K31: =SUM(J31*$F31) -> #REF! | L31: 1 | M31: =SUM(L31*$F31) -> #REF! | O31: 0 | P31: =SUM(H31+J31+L31) -> 1
A32: =+'Sources & Uses'!A41 -> Bond Cost of Issuance | F32: =+'Sources & Uses'!F41 -> 20000 | J32: 1 | K32: =SUM(J32*$F32) -> 20000 | L32: 0 | M32: =SUM(L32*$F32) -> 0 | O32: 0 | P32: =SUM(H32+J32+L32) -> 1
A33: Taxes | F33: =+'Sources & Uses'!F42 -> 0 | I33: =SUM(H33*$F33) -> 0 | K33: =SUM(J33*$F33) -> 0 | L33: 1 | M33: =SUM(L33*$F33) -> 0 | O33: =+F33 -> 0 | P33: =SUM(H33+J33+L33) -> 1
A34: Insurance | F34: =+'Sources & Uses'!F43 -> 120000 | I34: =SUM(H34*$F34) -> 0 | K34: =SUM(J34*$F34) -> 0 | L34: 1 | M34: =SUM(L34*$F34) -> 120000 | O34: =+F34 -> 120000 | P34: =SUM(H34+J34+L34) -> 1
A35: Title/Recording | F35: =+'Sources & Uses'!F44 -> 7000 | I35: =SUM(H35*$F35) -> 0 | J35: 0 | K35: =SUM(J35*$F35) -> 0 | L35: 0 | M35: =SUM(L35*$F35) -> 0 | O35: 0 | P35: =SUM(H35+J35+L35) -> 0
A36: Legal | F36: =+'Sources & Uses'!F48 -> 50000 | I36: =SUM(H36*$F36) -> 0 | J36: =+'Sources & Uses'!W46 -> 0 | K36: =SUM(J36*$F36) -> 0 | L36: =+'Sources & Uses'!W45 -> 1 | M36: =SUM(L36*$F36) -> 50000 | O36: =+F36 -> 50000 | P36: =SUM(H36+J36+L36) -> 1
A37: CPA Fees | F37: =+'Sources & Uses'!F49 -> 25000 | I37: =SUM(H37*$F37) -> 0 | K37: =SUM(J37*$F37) -> 0 | L37: 1 | M37: =SUM(L37*$F37) -> 25000 | O37: 0 | P37: =SUM(H37+J37+L37) -> 1
A38: Organizational | F38: =+'Sources & Uses'!F50 -> 0 | H38: 1 | I38: =SUM(H38*$F38) -> 0 | K38: =SUM(J38*$F38) -> 0 | M38: =SUM(L38*$F38) -> 0 | O38: =+F38 -> 0 | P38: =SUM(H38+J38+L38) -> 1
A39: Cost Certification | F39: =+'Sources & Uses'!F51 -> 0 | I39: =SUM(H39*$F39) -> 0 | J39: 1 | K39: =SUM(J39*$F39) -> 0 | L39: 0 | M39: =SUM(L39*$F39) -> 0 | O39: 0 | P39: =SUM(H39+J39+L39) -> 1
A40: =+'Sources & Uses'!A55 -> Operational Fees | F40: =+'Sources & Uses'!F55 -> 400000 | I40: =SUM(H40*$F40) -> 0 | K40: =SUM(J40*$F40) -> 0 | L40: 1 | M40: =SUM(L40*$F40) -> 400000 | O40: =+F40 -> 400000 | P40: =SUM(H40+J40+L40) -> 1
A41: LIHTC Application Fee | F41: =+'Sources & Uses'!F56 -> 0 | I41: =SUM(H41*$F41) -> 0 | J41: 1 | K41: =SUM(J41*$F41) -> 0 | L41: 0 | M41: =SUM(L41*$F41) -> 0 | O41: =+K41 -> 0 | P41: =SUM(H41+J41+L41) -> 1
A42: Tax Credit Commitment Fees | F42: =+'Sources & Uses'!F57 -> 0 | I42: =SUM(H42*$F42) -> 0 | J42: 1 | K42: =SUM(J42*$F42) -> 0 | L42: 0 | O42: =+F42 -> 0 | P42: =SUM(H42+J42+L42) -> 1
A43: =+'Sources & Uses'!A58 -> Other Third Party Costs | F43: =+'Sources & Uses'!F58 -> 217742 | I43: =SUM(H43*$F43) -> 0 | J43: =+K43/F43 -> 0 | K43: =+'Sources & Uses'!Y68 -> 0 | L43: =+M43/F43 -> 0 | M43: =+'Sources & Uses'!X68 -> 0 | O43: =+F43 -> 217742 | P43: =SUM(H43+J43+L43) -> 0 | Q43: =1500+2140+6255+1965+3500 -> 15360
A44: =+'Sources & Uses'!A59 -> 0 | F44: =+'Sources & Uses'!F25 -> 1011593.4 | I44: =SUM(H44*$F44) -> 0 | J44: 0.15 | K44: =SUM(J44*$F44) -> 151739.01 | L44: 0.85 | M44: =SUM(L44*$F44) -> 859854.37 | O44: =+F44 -> 1011593.4 | P44: =SUM(H44+J44+L44) -> 1
A45: Operation Reserves | F45: =+'Sources & Uses'!H63 -> 0 | I45: =SUM(H45*$F45) -> 0 | J45: 1 | K45: =SUM(J45*$F45) -> 0 | M45: =SUM(L45*$F45) -> 0 | O45: =+F45 -> 0 | P45: =SUM(H45+J45+L45) -> 1
A46: Operating Deficit Reserves | F46: =+'Sources & Uses'!H64 -> 0 | I46: =SUM(H46*$F46) -> 0 | J46: 1 | K46: =SUM(J46*$F46) -> 0 | M46: =SUM(L46*$F46) -> 0 | O46: =+F46 -> 0 | P46: =SUM(H46+J46+L46) -> 1
A47: Developer Fee (Maximum 20%) | F47: =+'Sources & Uses'!H67 -> 0 | I47: =SUM(H47*$F47) -> 0 | K47: =SUM(J47*$F47) -> 0 | L47: 1 | M47: =+F47 -> 0 | O47: =+F47 -> 0 | P47: =SUM(H47+J47+L47) -> 1 | Q47: 390287
A48: Developer Fee (Maximum 5%) | F48: =+'Sources & Uses'!H68 -> 0 | I48: =SUM(H48*$F48) -> 0 | K48: =SUM(J48*$F48) -> 0 | L48: 1 | M48: =SUM(L48*$F48) -> 0 | O48: =+F48 -> 0 | P48: =SUM(H48+J48+L48) -> 1
A49: =+'Sources & Uses'!A71 -> Syndication Legal | F49: =+'Sources & Uses'!F71 -> 0 | I49: =SUM(H49*$F49) -> 0 | J49: 1 | K49: =SUM(J49*$F49) -> 0 | M49: =SUM(L49*$F49) -> 0 | O49: =+F49 -> 0 | P49: =SUM(H49+J49+L49) -> 1
A50: Accountant Fees/Synd. Fee | F50: =+'Sources & Uses'!F72 -> 0 | I50: =SUM(H50*$F50) -> 0 | J50: 1 | M50: =SUM(L50*$F50) -> 0 | O50: 0 | P50: =SUM(H50+J50+L50) -> 1
I51: =SUM(H51*$F51) -> 0 | K51: =SUM(J51*$F51) -> 0 | M51: =SUM(L51*$F51) -> 0 | O51: =SUM(N51*$F51) -> 0
A52: TOTAL USES | F52: =SUM(F16:F51) -> #REF! | I52: =SUM(I16:I50) -> #REF! | K52: =SUM(K16:K50) -> #REF! | M52: =SUM(M16:M50) -> #REF! | O52: =SUM(O16:O50) -> 20476903 | Q52: =SUM(Q16:Q51) -> 1577943
A55: REB Calculation:
A57: Add Land | M57: =+K16 -> 0
A59: REB | M59: =SUM(M52:M58) -> #REF!
A61: 10% Requirement | L61: 0.1 | M61: =SUM(M59*L61) -> #REF!
A63: Land | M63: =-M57 -> 0
A64: D.F Accrual | L64: 0.2 | M64: =SUM(M47*L64)*-1 -> 0
M68: =SUM(M61:M67) -> #REF!
A72: Engineering was added to Market Study Enviromental and appraisal
A73: Bond 50% Test Calculation
A75: Eligible Basis | M75: =+M52 -> #REF!
A76: Land | M76: =+K16 -> 0
A78: Total Agregate Basis | M78: =SUM(M75:M77) -> #REF!
A80: 50% Agregate Basis | K80: 0.5 | M80: =+M78*K80 -> #REF!
A83: Proposed Bonds Issue Amount | K83: =+M83/M78 -> #REF! | M83: =+#REF! -> #REF!

Sheet carryover calc
A1: St Landry Place
A2: Calculation of Reasonably Expected Basis
A3: FYE 2006 Carryover
A5: Total Eligible Basis per Allocation Schedule: | G5: =+'Cost Allocation Basis'!M52 -> #REF!
A7: Add Land | G7: =+'Cost Allocation Basis'!K16 -> 0
A9: Total Reasonably Expected Basis | G9: =SUM(G5:G8) -> #REF!
A11: 10% Requirement | F11: 0.1 | G11: =SUM(G9*F11) -> #REF!
A13: Costs incurred/ Accrued to meet test:
A15: Carryover Fees/Accounting Costs | G15: =9500+3500 -> 13000
A16: Developer Fee Accrual | E16: 0.2 | G16: =SUM(E16*'Cost Allocation Basis'!F47) -> 0
A17: Land Costs | G17: =+'Cost Allocation Basis'!F16 -> 0
A18: Market Study Costs | G18: 4800
A19: Neighborhood Review | G19: 750
A20: Phase I | G20: 0
A21: Architect Design Phase | G21: =+'Cost Allocation Basis'!F26 -> 400000
A22: Soils Report | G22: 1700
A23: Engineering | G23: 31500
A26: Total Costs | G26: =SUM(G15:G23) -> 451750
A28: Remaining Needed to meet 10% | G28: =SUM(G11-G26) -> #REF!
A31: Estimated Materials to Store: | G31: 100000
A34: Total Costs if Materials Used | G34: =SUM(G26+G31) -> 551750
A36: Percentage of REB | G36: =SUM(G34/G9) -> #REF!

Sheet Interest Calculation
A1: =+'Sources & Uses'!A1 -> Lamar Building | E1: Construction Loan
A4: PRINCIPAL: | C4: 18500000
A5: YEARLY INT RATE: | C5: 0.075
A6: TOTAL # PMTS: | C6: i.o
A7: # PMTS PER YEAR: | C7: 12
B10: PMT # | C10: Draw | D10: INTEREST | E10: Paydowns | F10: Balance
B11: 1 | C11: =$G$5 -> 0 | D11: =C$4*$C$5/1 -> 1387500 | E11: =C11-D11 -> -1387500 | F11: =C4-E11 -> 19887500 | G11: =D11 -> 1387500
B12: 2 | C12: =$G$5 -> 0 | D12: =C$4*$C$5/1 -> 1387500 | E12: =C12-D12 -> -1387500 | F12: =F11-E12 -> 21275000 | G12: =D12+G11 -> 2775000
B13: 3 | C13: =$G$5 -> 0 | D13: =C$4*$C$5/1 -> 1387500 | E13: =C13-D13 -> -1387500 | F13: =F12-E13 -> 22662500 | G13: =D13+G12 -> 4162500
B14: 4 | C14: =+'Residual Calculation'!H53 -> #REF! | D14: 0 | E14: =SUM(E13-D14) -> -1387500 | F14: =F13-E14 -> 24050000 | G14: =D14+G13 -> 4162500
B15: 5 | C15: =+'Residual Calculation'!I53 -> #REF! | D15: 0 | E15: =+C15+D15 -> #REF! | F15: =F14-E15 -> #REF! | G15: =D15+G14 -> 4162500
B16: 6 | C16: =+'Residual Calculation'!J53 -> #REF! | D16: 0 | E16: =+C16+D16 -> #REF! | F16: =F15-E16 -> #REF! | G16: =D16+G15 -> 4162500
B17: 7 | C17: =+'Residual Calculation'!K53 -> #REF! | D17: 0 | E17: =+C17+D17 -> #REF! | F17: =F16-E17 -> #REF! | G17: 0
B18: 8 | C18: =+'Residual Calculation'!L53 -> #REF! | D18: =C$4*$C$5/1*-1 -> -1387500 | E18: =+C18+D18 -> #REF! | F18: =F17-E18 -> #REF! | G18: 0
B19: 9 | C19: =+'Residual Calculation'!M53 -> #REF! | D19: =C$4*$C$5/1*-1 -> -1387500 | E19: =+C19+D19 -> #REF! | F19: =F18-E19 -> #REF! | G19: 0
B20: 10 | C20: =+'Residual Calculation'!N53 -> #REF! | D20: =C$4*$C$5/1*-1 -> -1387500 | E20: =+C20+D20 -> #REF! | F20: =F19-E20 -> #REF! | G20: 0
B21: 11 | C21: =+'Residual Calculation'!O53 -> #REF! | D21: =C$4*$C$5/1*-1 -> -1387500 | E21: =+C21+D21 -> #REF! | F21: =F20-E21 -> #REF! | G21: 0
B22: 12 | C22: =+'Residual Calculation'!P53 -> #REF! | D22: =C$4*$C$5/1*-1 -> -1387500 | E22: =+C22+D22 -> #REF! | F22: =F21-E22 -> #REF! | G22: 0
B23: 13 | C23: =+'Residual Calculation'!Q53 -> #REF! | D23: =C$4*$C$5/1*-1 -> -1387500 | E23: =+C23+D23 -> #REF! | F23: =F22-E23 -> #REF! | G23: 0
B24: 14 | C24: =+'Residual Calculation'!R53 -> #REF! | D24: =C$4*$C$5/1*-1 -> -1387500 | E24: =+C24+D24 -> #REF! | F24: =F23-E24 -> #REF! | G24: 0
B25: 15 | C25: =+'Residual Calculation'!S53 -> #REF! | D25: =C$4*$C$5/1*-1 -> -1387500 | E25: =+C25+D25 -> #REF! | F25: =F24-E25 -> #REF! | G25: 0
B26: 16 | C26: =+'Residual Calculation'!T53 -> #REF! | D26: =C$4*$C$5/1*-1 -> -1387500 | E26: =+C26+D26 -> #REF! | F26: =F25-E26 -> #REF! | G26: 0
B27: 17 | C27: =+'Residual Calculation'!U53 -> #REF! | D27: =C$4*$C$5/1*-1 -> -1387500 | E27: =+C27+D27 -> #REF! | F27: =F26-E27 -> #REF! | G27: 0
B28: 18 | C28: =+'Residual Calculation'!V53 -> #REF! | D28: =C$4*$C$5/1*-1 -> -1387500 | E28: =+C28+D28 -> #REF! | F28: =F27-E28 -> #REF! | G28: 0
B29: 19 | C29: =+'Residual Calculation'!W53 -> #REF! | D29: =C$4*$C$5/1*-1 -> -1387500 | E29: =+C29+D29 -> #REF! | F29: =F28-E29 -> #REF! | G29: 0
B30: 20 | C30: =+'Residual Calculation'!X53 -> #REF! | D30: =C$4*$C$5/1*-1 -> -1387500 | E30: =+C30+D30 -> #REF! | F30: =F29-E30 -> #REF! | G30: 0
C31: 1000000 | D31: 0 | F31: =+C31+D31-E31 -> 1000000
C32: 500000 | D32: =+(C32*$C$5/$C$7)+D31 -> 3125 | F32: =+C32+D32+F31 -> 1503125
C33: 1000000 | D33: =+(C33*$C$5/$C$7)+D32 -> 9375 | E33: 0 | F33: =+F32+C33+D33-E33 -> 2512500
C34: 1000000 | D34: =+(C34*$C$5/$C$7)+D33 -> 15625 | F34: =+C34+D34+F33 -> 3528125
C35: 1000000 | D35: =+(C35*$C$5/$C$7)+D34 -> 21875 | F35: =+C35+D35+F34 -> 4550000
C36: 1500000 | D36: =+(C36*$C$5/$C$7)+D35 -> 31250 | F36: =+C36+D36+F35 -> 6081250
C37: 1500000 | D37: =+(C37*$C$5/$C$7)+D36 -> 40625 | F37: =+C37+D37+F36 -> 7621875
C38: 1500000 | D38: =+(C38*$C$5/$C$7)+D37 -> 50000 | F38: =+C38+D38+F37 -> 9171875
C39: 1500000 | D39: =+(C39*$C$5/$C$7)+D38 -> 59375 | F39: =+C39+D39+F38 -> 10731250
C40: 1500000 | D40: =+(C40*$C$5/$C$7)+D39 -> 68750 | F40: =+C40+D40+F39 -> 12300000
C41: 1000000 | D41: =+(C41*$C$5/$C$7)+D40 -> 75000 | F41: =+C41+D41+F40 -> 13375000
C42: 1500000 | D42: =+(C42*$C$5/$C$7)+D41 -> 84375 | F42: =+C42+D42+F41 -> 14959375
C43: 1000000 | D43: =+(C43*$C$5/$C$7)+D42 -> 90625 | F43: =+C43+D43+F42 -> 16050000
C44: 1000000 | D44: =+(C44*$C$5/$C$7)+D43 -> 96875 | F44: =+C44+D44+F43 -> 17146875
C45: 1000000 | D45: =+(C45*$C$5/$C$7)+D44 -> 103125 | F45: =+C45+D45+F44 -> 18250000
C46: 1000000 | D46: =+(C46*$C$5/$C$7)+D45 -> 109375 | F46: =+C46+D46+F45-E46 -> 19359375
C50: =SUM(C31:C49) -> 18500000 | D50: =SUM(D31:D49) -> 859375 | E50: =SUM(E31:E49) -> 0 | G50: =+C50-E50 -> 18500000

Sheet CR Calculation
A1: =+'Sources & Uses'!A1 -> Lamar Building
A2: Credit Calculation Worksheet
A4: Total Eligible Basis | F4: =+'Sources & Uses'!F27+'Sources & Uses'!F30+'Sources & Uses'!F31+'Sources & Uses'!F33+'Sources & Uses'!F58+'Sources & Uses'!F67 -> 17313368 | H4: Tax Credit Basis only, based on Sources and Uses
A5: Less: Acquisition Costs
A6: Total Eligible Basis New Construciton /Rehab. | F6: =SUM(F4-F5) -> 17313368
A8: Calculation of Credits: | D8: % | H8: New Const./
F9: Total | H9: Rehabilition | I9: Acquisition
A10: Total Eligible Basis | F10: =SUM(H10:I10) -> 17313368 | H10: =+F6 -> 17313368 | I10: 0
I11: =-H11 -> 0
A12: Eligible Historic Credit | D12: 0
A14: Adjusted Eligible Basis | F14: =SUM(F10-F12) -> 17313368 | H14: =SUM(H10+H11) -> 17313368 | I14: =SUM(I10+I11) -> 0
K15: =+H20*0.15 -> 1688053.4
A16: Elibible Basis Adjusted for QCT/DDA | D16: 1.3 | F16: =SUM(H16:I16) -> 22507379 | H16: =SUM(H14*D16) -> 22507379 | I16: =SUM(I14) -> 0 | K16: =+I20*0.05 -> 0
A18: Low Income Percentage | D18: 0.5
A20: Total Qualified Basis | F20: =SUM(H20:I20) -> 11253689 | H20: =SUM(H16*D18) -> 11253689 | I20: =SUM(I16*D18) -> 0
A22: LIHTC Percentage | H22: 0.04 | I22: 0.04
A24: Total Annual Credits Calculated | F24: =SUM(H24:I24) -> 450147.57 | H24: =SUM(H20*H22) -> 450147.57 | I24: =SUM(I20*I22) -> 0
A26: Total Annual Credits Reserved | C26: (Lessor of Reserved/Calculated) | F26: =SUM(H26:I26) -> 450147.57 | H26: =+IF(H24>H38,H38,H24) -> 450147.57 | I26: =+I24 -> 0
A28: Equity Investment Percentage | H28: 0.9999 | I28: 0.9999
A30: Equity Raised | D30: 0.85 | F30: =SUM(F26*D33*D34)*D30/100 -> 3825871.7 | H30: =SUM(H26*H28*D30*10) -> 3825871.7 | I30: =SUM(I26*I28*D30*10) -> 0
A33: Total Tax Credit Period | D33: 10
A34: Investment Percentage | D34: 99.99
H35: =SUM(H26/H22) -> 11253689
H36: =+H20-H35 -> 0
C38: Maximum Credits Allowed | H38: =+F24 -> 450147.57
C39: Excess Basis Utilizing 9% | H39: =SUM(H24-H38)/H22 -> 0
C40: Excess Cash | E40: =+'Sources & Uses'!#REF!+'Sources & Uses'!#REF! -> #REF!
E43: 70
A44: Maximum Per Developer Credit | C44: 1500000
A45: Amt per Winnsboro | C45: 823000
C46: =+C44-C45 -> 677000
F48: 5062647
C51: Maximum Request | F51: 750000
A53: Historic Credit
A55: Eligible Historic Credit | F55: =+F6 -> 17313368
A57: Credits Calculated | E57: 0.2 | F57: =+F55*0.2 -> 3462673.6
A59: Equity Raised | D59: 0.8 | F59: =+F57*D59 -> 2770138.9
A62: State Credit
A64: Eligible Historic Credit | F64: =+F55 -> 17313368
A66: Credits Calculated | E66: 0.25 | F66: =+F64*0.25 -> 4328342
A68: Equity Raised | D68: 0.8 | F68: =+F66*D68 -> 3462673.6
A71: total credits | F71: =+F59+F68 -> 6232812.5
A73: Initial Draw | F73: 6616331
A75: Final Draw (at substantial occupancy) | F75: =+F71-F73 -> -383518.46

Sheet  Draw Schedule
B1: =+'Sources & Uses'!A1 -> Lamar Building
B2: CONSTRUCTION INTEREST CALCULATION:
B4: Total Construction Contract Amount | F4: =+'Sources & Uses'!E24 -> 14451334
G6: =+'Sources & Uses'!F34 -> 0 | H6: =+'Sources & Uses'!F59 -> 0 | I6: =SUM('Sources & Uses'!H67-'Sources & Uses'!#REF!-'Sources & Uses'!#REF!)*0 -> #REF!
E7: 0.05 | F7: Amount of | G7: Architect | H7: Payment of | I7: Developer fee | J7: Monthly | K7: Total
B8: Draw No: | D8: Draw Amt. | E8: Retainage | F8: Payment | G8: Inspection | H8: Contingency | I8: Pd. (Const. Term) | J8: Interest Pmt | K8: Payment Due
B9: Closing | K9: =+'Application of Funds'!G26 -> #REF!
A10: =+C10 -> 0.03 | B10: 1 | C10: 0.03 | D10: =SUM(C10*F$4) -> 433540.02 | E10: =SUM(D10*E$7)*-1 -> -21677.001 | F10: =SUM(D10:E10) -> 411863.02 | G10: =SUM(G$6/D$57) -> 0 | H10: =SUM(H$6/D$57) -> 0 | I10: =SUM(I$6/D$57) -> #REF! | J10: =+'Construction Loan'!E10 -> #REF! | K10: =SUM(F10:J10) -> #REF! | L10: =+'Application of Funds'!E30 -> 43770
A11: =+A10+C11 -> 0.06 | B11: =+B10+1 -> 2 | C11: 0.03 | D11: =SUM(C11*F$4) -> 433540.02 | E11: =SUM(D11*E$7)*-1 -> -21677.001 | F11: =SUM(D11:E11) -> 411863.02 | G11: =SUM(G$6/D$57) -> 0 | H11: =SUM(H$6/D$57) -> 0 | I11: =SUM(I$6/D$57) -> #REF! | J11: =+'Construction Loan'!E11 -> #REF! | K11: =SUM(F11:J11) -> #REF! | L11: =+'Application of Funds'!E31 -> 43800
A12: =+A11+C12 -> 0.09 | B12: =+B11+1 -> 3 | C12: 0.03 | D12: =SUM(C12*F$4) -> 433540.02 | E12: =SUM(D12*E$7)*-1 -> -21677.001 | F12: =SUM(D12:E12) -> 411863.02 | G12: =SUM(G$6/D$57) -> 0 | H12: =SUM(H$6/D$57) -> 0 | I12: =SUM(I$6/D$57) -> #REF! | J12: =+'Construction Loan'!E12 -> #REF! | K12: =SUM(F12:J12) -> #REF! | L12: =+'Application of Funds'!E32 -> 43831
A13: =+A12+C13 -> 0.12 | B13: =+B12+1 -> 4 | C13: 0.03 | D13: =SUM(C13*F$4) -> 433540.02 | E13: =SUM(D13*E$7)*-1 -> -21677.001 | F13: =SUM(D13:E13) -> 411863.02 | G13: =SUM(G$6/D$57) -> 0 | H13: =SUM(H$6/D$57) -> 0 | I13: =SUM(I$6/D$57) -> #REF! | J13: =+'Construction Loan'!E13 -> #REF! | K13: =SUM(F13:J13) -> #REF! | L13: =+'Application of Funds'!E34 -> 43862
A14: =+A13+C14 -> 0.17 | B14: =+B13+1 -> 5 | C14: 0.05 | D14: =SUM(C14*F$4) -> 722566.7 | E14: =SUM(D14*E$7)*-1 -> -36128.335 | F14: =SUM(D14:E14) -> 686438.37 | G14: =SUM(G$6/D$57) -> 0 | H14: =SUM(H$6/D$57) -> 0 | I14: =SUM(I$6/D$57) -> #REF! | J14: =+'Construction Loan'!E14 -> #REF! | K14: =SUM(F14:J14) -> #REF! | L14: =+'Application of Funds'!E35 -> 43892
A15: =+A14+C15 -> 0.24 | B15: =+B14+1 -> 6 | C15: 0.07 | D15: =SUM(C15*F$4) -> 1011593.4 | E15: =SUM(D15*E$7)*-1 -> -50579.669 | F15: =SUM(D15:E15) -> 961013.71 | G15: =SUM(G$6/D$57) -> 0 | H15: =SUM(H$6/D$57) -> 0 | I15: =SUM(I$6/D$57) -> #REF! | J15: =+'Construction Loan'!E15 -> #REF! | K15: =SUM(F15:J15) -> #REF! | L15: =+'Application of Funds'!E37 -> 43922
A16: =+A15+C16 -> 0.32 | B16: =+B15+1 -> 7 | C16: 0.08 | D16: =SUM(C16*F$4) -> 1156106.7 | E16: =SUM(D16*E$7)*-1 -> -57805.336 | F16: =SUM(D16:E16) -> 1098301.4 | G16: =SUM(G$6/D$57) -> 0 | H16: =SUM(H$6/D$57) -> 0 | I16: =SUM(I$6/D$57) -> #REF! | J16: =+'Construction Loan'!E16 -> #REF! | K16: =SUM(F16:J16) -> #REF! | L16: =+'Application of Funds'!E38 -> 43953
A17: =+A16+C17 -> 0.41 | B17: =+B16+1 -> 8 | C17: 0.09 | D17: =SUM(C17*F$4) -> 1300620.1 | E17: =SUM(D17*E$7)*-1 -> -65031.003 | F17: =SUM(D17:E17) -> 1235589.1 | G17: =SUM(G$6/D$57) -> 0 | H17: =SUM(H$6/D$57) -> 0 | I17: =SUM(I$6/D$57) -> #REF! | J17: =+'Construction Loan'!E17 -> #REF! | K17: =SUM(F17:J17) -> #REF! | L17: =+'Application of Funds'!E39 -> 43983
A18: =+A17+C18 -> 0.5 | B18: =+B17+1 -> 9 | C18: 0.09 | D18: =SUM(C18*F$4) -> 1300620.1 | E18: =SUM(D18*E$7)*-1 -> -65031.003 | F18: =SUM(D18:E18) -> 1235589.1 | G18: =SUM(G$6/D$57) -> 0 | H18: =SUM(H$6/D$57) -> 0 | I18: =SUM(I$6/D$57) -> #REF! | J18: =+'Construction Loan'!E18 -> #REF! | K18: =SUM(F18:J18) -> #REF! | L18: =+'Application of Funds'!E42 -> 44013
A19: =+A18+C19 -> 0.58 | B19: =+B18+1 -> 10 | C19: 0.08 | D19: =SUM(C19*F$4) -> 1156106.7 | E19: =SUM(D19*E$7)*-1 -> -57805.336 | F19: =SUM(D19:E19) -> 1098301.4 | G19: =SUM(G$6/D$57) -> 0 | H19: =SUM(H$6/D$57) -> 0 | I19: =SUM(I$6/D$57) -> #REF! | J19: =+'Construction Loan'!E19 -> #REF! | K19: =SUM(F19:J19) -> #REF! | L19: =+'Application of Funds'!E45 -> 44044
A20: =+A19+C20 -> 0.66 | B20: =+B19+1 -> 11 | C20: 0.08 | D20: =SUM(C20*F$4) -> 1156106.7 | E20: =SUM(D20*E$7)*-1 -> -57805.336 | F20: =SUM(D20:E20) -> 1098301.4 | G20: =SUM(G$6/D$57) -> 0 | H20: =SUM(H$6/D$57) -> 0 | I20: =SUM(I$6/D$57) -> #REF! | J20: =+'Construction Loan'!E20 -> #REF! | K20: =SUM(F20:J20) -> #REF! | L20: =+'Application of Funds'!E46 -> 44075
A21: =+A20+C21 -> 0.73 | B21: =+B20+1 -> 12 | C21: 0.07 | D21: =SUM(C21*F$4) -> 1011593.4 | E21: =SUM(D21*E$7)*-1 -> -50579.669 | F21: =SUM(D21:E21) -> 961013.71 | G21: =SUM(G$6/D$57) -> 0 | H21: =SUM(H$6/D$57) -> 0 | I21: =SUM(I$6/D$57) -> #REF! | J21: =+'Construction Loan'!E21 -> #REF! | K21: =SUM(F21:J21) -> #REF! | L21: =+'Application of Funds'!E47 -> 44106
A22: =+A21+C22 -> 0.8 | B22: =+B21+1 -> 13 | C22: 0.07 | D22: =SUM(C22*$F$4) -> 1011593.4 | E22: =SUM(D22*E$7)*-1 -> -50579.669 | F22: =SUM(D22:E22) -> 961013.71 | G22: =SUM(G$6/D$57) -> 0 | H22: =SUM(H$6/D$57) -> 0 | I22: =SUM(I$6/D$57) -> #REF! | J22: =+'Construction Loan'!E22 -> #REF! | K22: =SUM(F22:J22) -> #REF! | L22: =+'Application of Funds'!E48 -> 44136
A23: =+A22+C23 -> 0.86 | B23: =+B22+1 -> 14 | C23: 0.06 | D23: =SUM(C23*$F$4) -> 867080.04 | E23: =SUM(D23*E$7)*-1 -> -43354.002 | F23: =SUM(D23:E23) -> 823726.04 | G23: =SUM(G$6/D$57) -> 0 | H23: =SUM(H$6/D$57) -> 0 | I23: =SUM(I$6/D$57) -> #REF! | J23: =+'Construction Loan'!E23 -> #REF! | K23: =SUM(F23:J23) -> #REF! | L23: =+'Application of Funds'!E49 -> 44166
A24: =+A23+C24 -> 0.93 | B24: 15 | C24: 0.07 | D24: =SUM(C24*$F$4) -> 1011593.4 | E24: =SUM(D24*E$7)*-1 -> -50579.669 | F24: =SUM(D24:E24) -> 961013.71 | G24: =SUM(G$6/D$57) -> 0 | H24: =SUM(H$6/D$57) -> 0 | J24: =+'Construction Loan'!E24 -> #REF! | K24: =SUM(F24:J24) -> #REF! | L24: =+'Application of Funds'!E51 -> 44197
A25: =+A24+C25 -> 0.96 | B25: 16 | C25: 0.03 | D25: =SUM(C25*$F$4) -> 433540.02 | E25: =SUM(D25*E$7)*-1 -> -21677.001 | F25: =SUM(D25:E25) -> 411863.02 | G25: =SUM(G$6/D$57) -> 0 | H25: =SUM(H$6/D$57) -> 0 | J25: =+'Construction Loan'!E25 -> #REF! | K25: =SUM(F25:J25) -> #REF! | L25: =+'Application of Funds'!E53 -> 44228
A26: =+A25+C26 -> 0.98 | B26: 17 | C26: 0.02 | D26: =SUM(C26*$F$4) -> 289026.68 | E26: =SUM(D26*E$7)*-1 -> -14451.334 | F26: =SUM(D26:E26) -> 274575.35 | G26: =SUM(G$6/D$57) -> 0 | H26: =SUM(H$6/D$57) -> 0 | J26: =+'Construction Loan'!E26 -> #REF! | K26: =SUM(F26:J26) -> #REF! | L26: =+'Application of Funds'!E55 -> 44258
A27: =+A26+C27 -> 1 | B27: 18 | C27: 0.02 | D27: =SUM(C27*$F$4) -> 289026.68 | E27: =SUM(D27*E$7)*-1 -> -14451.334 | F27: =SUM(D27:E27) -> 274575.35 | G27: =SUM(G$6/D$57) -> 0 | H27: =SUM(H$6/D$57) -> 0 | J27: =+'Construction Loan'!E27 -> #REF! | K27: =SUM(F27:J27) -> #REF! | L27: =+'Application of Funds'!E57 -> 44288
B28: 19 | D28: =SUM(C28*$F$4) -> 0 | E28: =SUM(D28*E$7)*-1 -> 0 | F28: =SUM(D28:E28) -> 0 | J28: =+'Construction Loan'!E28 -> #REF! | K28: =SUM(F28:J28) -> #REF! | L28: =+L27+31 -> 44319
B29: 20 | D29: =SUM(C29*$F$4) -> 0 | E29: =SUM(D29*E$7)*-1 -> 0 | F29: =SUM(D29:E29) -> 0 | J29: =+'Construction Loan'!E29 -> #REF! | K29: =SUM(F29:J29) -> #REF! | L29: =+L28+30 -> 44349
B30: 21 | J30: =+'Construction Loan'!E30 -> #REF! | K30: =SUM(F30:J30) -> #REF! | L30: =+L29+30 -> 44379
B31: 22 | J31: =+'Construction Loan'!E31 -> #REF! | K31: =SUM(F31:J31) -> #REF! | L31: =+'Application of Funds'!E67 -> 44409
B32: 23 | J32: =+'Construction Loan'!E32 -> #REF! | K32: =SUM(F32:J32) -> #REF! | L32: =+'Application of Funds'!E73 -> 44440
B33: 24
C36: =SUM(C10:C27) -> 1 | D36: =SUM(D10:D33) -> 14451334 | E36: =SUM(E10:E33) -> -722566.7 | F36: =SUM(F10:F33) -> 13728767 | G36: =SUM(G10:G33) -> 0 | H36: =SUM(H10:H33) -> 0 | I36: =SUM(I10:I33) -> #REF! | J36: =SUM(J10:J33) -> #REF! | K36: =SUM(K10:K23) -> #REF!
D38: Capitalizable Construction Interest
D39: Interest to Operating Deficit
B41: Days in Year | D41: 360
B42: Days In Month | D42: 30
B46: Construction Loan Calculation:
B48: Total Development Costs
B50: Less 1st Equity Installment
B51: Less Unpaid Developer Fee
B52: Less Construction Contingency
B53: Construction Loan Amount Calculated
B57: Total Draws | D57: =+B27 -> 18

Sheet Application of Funds
H1: Tax Credit Equity | J1: Construction/Bridge Loan | L1: Interim Bonds | N1: LHC CDBG | P1: Cash Collateral Fund | R1: Permanent Loan
A2: =+'Sources & Uses'!A1 -> Lamar Building | D2: Percentage | E2: Projected | G2: Total | I2: Remaining | K2: Const/Bridge | M2: Available | O2: Available | Q2: Available | S2: Available | W2: Pari-Passu Calculation | AB2: CDBG | AC2: CDBG | AD2: Const/Bridge
A3: Schedule of Draws and Application of Funds | D3: Paid | E3: Date Paid | G3: Costs Incurred | H3: Draws | I3: Balance | J3: Draws | K3: Loan Balance | L3: Draws | M3: Funds | O3: Funds | Q3: Funds | R3: Draws | S3: Funds | T3: Def. Dev. Fee | W3: 50% Draw | X3: Equity | Y3: Cont/Br. | Z3: BONDS | AA3: CDBG | AB3: Balance | AC3: CK | AD3: Collateral Daw
I4: 0 | M4: 0 | O4: =+'Sources & Uses'!V7 -> 0 | S4: =+#REF! -> #REF! | T4: =+'Sources & Uses'!#REF!+'Sources & Uses'!#REF!+'Sources & Uses'!V8 -> #REF!
I5: =+I4+H5 -> 0 | K5: 0 | M5: =+M4+L5 -> 0 | O5: =+O4+N5 -> 0 | Q5: 0 | S5: =+S4-R5 -> #REF! | U5: =SUM(+G5+H5+J5+L5+P5+T5+N5+R5) -> 0
A6: Equtiy Paid At Closing | D6: 0.1 | E6: 43739 | H6: =SUM('CR Calculation'!F30*'Application of Funds'!D6) -> 382587.17 | I6: =+I5+H6 -> 382587.17 | K6: =+K5+J6 -> 0 | M6: =+M5+L6 -> 0 | O6: =+O5+N6 -> 0 | Q6: =+Q5+P6 -> 0 | S6: =+S5+R6 -> #REF! | U6: =SUM(+G6+H6+J6+L6+P6+T6+N6+R6) -> 382587.17
I7: =+I6+H7 -> 382587.17 | K7: =+K6+J7 -> 0 | M7: =+M6+L7 -> 0 | O7: =+O6+N7 -> 0 | Q7: =+Q6+P7 -> 0 | S7: =+S6+R7 -> #REF! | U7: =SUM(+G7+H7+J7+L7+P7+T7+N7+R7) -> 0
A8: Items to Be paid/Reimbursed at Closing: | I8: =+I7+H8 -> 382587.17 | K8: =+K7+J8 -> 0 | M8: =+M7+L8 -> 0 | O8: =+O7+N8 -> 0 | Q8: =+Q7+P8 -> 0 | S8: =+S7+R8 -> #REF! | U8: =SUM(+G8+H8+J8+L8+P8+T8+N8+R8) -> 0
I9: =+I8+H9 -> 382587.17 | K9: =+K8+J9 -> 0 | M9: =+M8+L9 -> 0 | O9: =+O8+N9 -> 0 | Q9: =+Q8+P9 -> 0 | S9: =+S8+R9 -> #REF! | U9: =SUM(+G9+H9+J9+L9+P9+T9+N9+R9) -> 0
A10: Cls. Draw | B10: Land & Building Acquistion | E10: =+E6 -> 43739 | F10: =+'Sources & Uses'!H16+'Sources & Uses'!H17 -> 0 | I10: =+I9+H10 -> 382587.17 | K10: =+K9+J10 -> 0 | M10: =+M9+L10 -> 0 | O10: =+O9+N10 -> 0 | Q10: =+Q9+P10 -> 0 | S10: =+S9+R10 -> #REF! | U10: =SUM(+G10+H10+J10+L10+P10+T10+N10+R10) -> 0
B11: =+'Sources & Uses'!A33 -> Architects Fee-Design | E11: =+E10 -> 43739 | F11: =+'Sources & Uses'!F33 -> 400000 | I11: =+I10+H11 -> 382587.17 | K11: =+K10+J11 -> 0 | M11: =+M10+L11 -> 0 | O11: =+O10+N11 -> 0 | Q11: =+Q10+P11 -> 0 | S11: =+S10+R11 -> #REF! | U11: =SUM(+G11+H11+J11+L11+P11+T11+N11+R11) -> 0
B12: =+'Sources & Uses'!A35 -> Other- CM | E12: =+E11 -> 43739 | F12: =+'Sources & Uses'!F35 -> 722566.7 | I12: =+I11+H12 -> 382587.17 | K12: =+K11+J12 -> 0 | M12: =+M11+L12 -> 0 | O12: =+O11+N12 -> 0 | Q12: =+Q11+P12 -> 0 | S12: =+S11+R12 -> #REF! | U12: =SUM(+G12+H12+J12+L12+P12+T12+N12+R12) -> 0
B13: =+'Sources & Uses'!#REF! -> #REF! | E13: =+E12 -> 43739 | F13: =+'Sources & Uses'!#REF! -> #REF! | I13: =+I12+H13 -> 382587.17 | K13: =+K12+J13 -> 0 | M13: =+M12+L13 -> 0 | O13: =+O12+N13 -> 0 | Q13: =+Q12+P13 -> 0 | S13: =+S12+R13 -> #REF! | U13: =SUM(+G13+H13+J13+L13+P13+T13+N13+R13) -> 0
B14: =+'Sources & Uses'!A41 -> Bond Cost of Issuance | E14: =+E13 -> 43739 | F14: =+'Sources & Uses'!F41 -> 20000 | I14: =+I13+H14 -> 382587.17 | K14: =+K13+J14 -> 0 | M14: =+M13+L14 -> 0 | O14: =+O13+N14 -> 0 | Q14: =+Q13+P14 -> 0 | S14: =+S13+R14 -> #REF! | U14: =SUM(+G14+H14+J14+L14+P14+T14+N14+R14) -> 0
B15: =+'Sources & Uses'!A42 -> Taxes | E15: =+E13 -> 43739 | F15: =+'Sources & Uses'!F42 -> 0 | I15: =+I14+H15 -> 382587.17 | K15: =+K14+J15 -> 0 | M15: =+M14+L15 -> 0 | O15: =+O14+N15 -> 0 | Q15: =+Q14+P15 -> 0 | S15: =+S14+R15 -> #REF! | U15: =SUM(+G15+H15+J15+L15+P15+T15+N15+R15) -> 0
B16: =+'Sources & Uses'!A43 -> Insurance | E16: =+E15 -> 43739 | F16: =+'Sources & Uses'!F43 -> 120000 | I16: =+I15+H16 -> 382587.17 | K16: =+K15+J16 -> 0 | M16: =+M15+L16 -> 0 | O16: =+O15+N16 -> 0 | Q16: =+Q15+P16 -> 0 | S16: =+S15+R16 -> #REF! | U16: =SUM(+G16+H16+J16+L16+P16+T16+N16+R16) -> 0
B17: =+'Sources & Uses'!A44 -> Title/Recording | E17: =+E16 -> 43739 | F17: =+'Sources & Uses'!F44 -> 7000 | I17: =+I16+H17 -> 382587.17 | K17: =+K16+J17 -> 0 | M17: =+M16+L17 -> 0 | O17: =+O16+N17 -> 0 | Q17: =+Q16+P17 -> 0 | S17: =+S16+R17 -> #REF! | U17: =SUM(+G17+H17+J17+L17+P17+T17+N17+R17) -> 0
B18: =+'Sources & Uses'!A48 -> Legal | E18: =+E17 -> 43739 | F18: =+'Sources & Uses'!F48 -> 50000 | I18: =+I17+H18 -> 382587.17 | K18: =+K17+J18 -> 0 | M18: =+M17+L18 -> 0 | O18: =+O17+N18 -> 0 | Q18: =+Q17+P18 -> 0 | S18: =+S17+R18 -> #REF! | U18: =SUM(+G18+H18+J18+L18+P18+T18+N18+R18) -> 0
B19: =+'Sources & Uses'!A49 -> CPA Fees | E19: =+E18 -> 43739 | F19: =+'Sources & Uses'!F49 -> 25000 | I19: =+I18+H19 -> 382587.17 | K19: =+K18+J19 -> 0 | M19: =+M18+L19 -> 0 | O19: =+O18+N19 -> 0 | Q19: =+Q18+P19 -> 0 | S19: =+S18+R19 -> #REF! | U19: =SUM(+G19+H19+J19+L19+P19+T19+N19+R19) -> 0
B20: =+'Sources & Uses'!A56 -> LIHTC Application Fee | E20: =+E19 -> 43739 | F20: =+'Sources & Uses'!F56 -> 0 | I20: =+I19+H20 -> 382587.17 | K20: =+K19+J20 -> 0 | M20: =+M19+L20 -> 0 | O20: =+O19+N20 -> 0 | Q20: =+Q19+P20 -> 0 | S20: =+S19+R20 -> #REF! | U20: =SUM(+G20+H20+J20+L20+P20+T20+N20+R20) -> 0
B21: =+'Sources & Uses'!A57 -> Tax Credit Commitment Fees | E21: =+E20 -> 43739 | F21: =+'Sources & Uses'!F57 -> 0 | I21: =+I20+H21 -> 382587.17 | K21: =+K20+J21 -> 0 | M21: =+M20+L21 -> 0 | O21: =+O20+N21 -> 0 | Q21: =+Q20+P21 -> 0 | S21: =+S20+R21 -> #REF! | U21: =SUM(+G21+H21+J21+L21+P21+T21+N21+R21) -> 0
B22: =+'Sources & Uses'!A58 -> Other Third Party Costs | E22: =+E21 -> 43739 | F22: =+'Sources & Uses'!F58 -> 217742 | I22: =+I21+H22 -> 382587.17 | K22: =+K21+J22 -> 0 | M22: =+M21+L22 -> 0 | O22: =+O21+N22 -> 0 | Q22: =+Q21+P22 -> 0 | S22: =+S21+R22 -> #REF! | U22: =SUM(+G22+H22+J22+L22+P22+T22+N22+R22) -> 0
B23: Initial Deposit to Replacement Reserve | E23: =+E22 -> 43739 | F23: =+'Sources & Uses'!H64 -> 0 | I23: =+I22+H23 -> 382587.17 | K23: =+K22+J23 -> 0 | M23: =+M22+L23 -> 0 | O23: =+O22+N23 -> 0 | Q23: =+Q22+P23 -> 0 | S23: =+S22+R23 -> #REF! | U23: =SUM(+G23+H23+J23+L23+P23+T23+N23+R23) -> 0
B24: =+'Sources & Uses'!A70 -> Syndication/ Other Expenses | E24: =+E22 -> 43739 | F24: =+'Sources & Uses'!F73 -> 0 | I24: =+I23+H24 -> 382587.17 | K24: =+K23+J24 -> 0 | M24: =+M23+L24 -> 0 | O24: =+O23+N24 -> 0 | Q24: =+Q23+P24 -> 0 | S24: =+S23+R24 -> #REF! | U24: =SUM(+G24+H24+J24+L24+P24+T24+N24+R24) -> 0
B25: Payment of Developer Fees | C25: (See Draw Schedule) | D25: 0 | E25: =+E22 -> 43739 | F25: =+D25*'Sources & Uses'!H67 -> 0 | I25: =+I24+H25 -> 382587.17 | K25: =+K24+J25 -> 0 | M25: =+M24+L25 -> 0 | O25: =+O24+N25 -> 0 | Q25: =+Q24+P25 -> 0 | S25: =+S24+R25 -> #REF! | U25: =SUM(+G25+H25+J25+L25+P25+T25+N25+R25) -> 0
A26: Total Soft Costs Paid/Reimbursed at Closing | E26: =+E25 -> 43739 | G26: =SUM(F10:F25) -> #REF! | H26: =-I25 -> -382587.17 | I26: =+I25+H26 -> 0 | J26: =-Y26 -> #REF! | K26: =+K25+J26 -> #REF! | L26: =-Z26 -> #REF! | M26: =+M25+L26 -> #REF! | N26: =+L26 -> #REF! | O26: =+O25+N26 -> #REF! | P26: =-N26 -> #REF! | Q26: =+Q25+P26 -> #REF! | S26: =+S25+R26 -> #REF! | U26: =SUM(+G26+H26+J26+L26+P26+T26+N26+R26) -> #REF! | W26: =G26*0.5 -> #REF! | X26: =-H26 -> 382587.17 | Y26: =+W26-X26 -> #REF! | Z26: =+G26-X26-Y26+AD26 -> #REF! | AA26: =-N26 -> #REF! | AB26: =+AA26 -> #REF! | AC26: =IF(AB26<=D$97,"OK","ERROR") -> #REF!
A27: Total paid from HOME and Construction Loan Funds | G27: =SUM(H7:H25)+SUM(J5:J25)+SUM(N5:N25)+SUM(L5:L25)-P10 -> 0 | I27: =+I26+H27 -> 0 | K27: =+K26+J27 -> #REF! | M27: =+M26+L27 -> #REF! | N27: =+L27 -> 0 | O27: =+O26+N27 -> #REF! | P27: =-N27 -> 0 | Q27: =+Q26+P27 -> #REF! | S27: =+S26+R27 -> #REF! | U27: =SUM(+G27+H27+J27+L27+P27+T27+N27+R27) -> 0 | Z27: =+G27-X27-Y27+AD27 -> 0 | AA27: =-N27 -> 0 | AB27: =+AB26+AA27 -> #REF! | AC27: =IF(AB27<=D$97,"OK","ERROR") -> #REF!
A28: Variance | G28: =+G26+G27 -> #REF! | I28: =+I27+H28 -> 0 | K28: =+K27+J28 -> #REF! | M28: =+M27+L28 -> #REF! | N28: =+L28 -> 0 | O28: =+O27+N28 -> #REF! | P28: =-N28+AD28 -> 0 | Q28: =+Q27+P28 -> #REF! | S28: =+S27+R28 -> #REF! | U28: =SUM(+G28+H28+J28+L28+P28+T28+N28+R28) -> #REF! | Z28: =+G28-X28-Y28+AD28 -> #REF! | AA28: =-N28 -> 0 | AB28: =+AB27+AA28 -> #REF! | AC28: =IF(AB28<=D$97,"OK","ERROR") -> #REF!
A29: Draw # | B29: All Draws Pari-Passu; Equity/Const.Bridge and Bond-Interim | I29: =+I28+H29 -> 0 | K29: =+K27+J29 -> #REF! | M29: =+M28+L29 -> #REF! | N29: =+L29 -> 0 | O29: =+O28+N29 -> #REF! | P29: =-N29+AD29 -> 0 | Q29: =+Q28+P29 -> #REF! | S29: =+S28+R29 -> #REF! | U29: =SUM(+G29+H29+J29+L29+P29+T29+N29+R29) -> 0 | Z29: =+G29-X29-Y29+AD29 -> 0 | AA29: =-N29 -> 0 | AB29: =+AB28+AA29 -> #REF! | AC29: =IF(AB29<=D$97,"OK","ERROR") -> #REF!
A30: 1 | B30: Total Draw | C30: Const./Inspection/Interest Payment | E30: =+E26+31 -> 43770 | G30: =+' Draw Schedule'!K10 -> #REF! | H30: =-I29 -> 0 | I30: =+I29+H30 -> 0 | J30: =-Y30 -> #REF! | K30: =+K29+J30 -> #REF! | L30: =-Z30 -> #REF! | M30: =+M29+L30 -> #REF! | N30: =+L30+AD30 -> #REF! | O30: =+O29+N30 -> #REF! | P30: =-N30+AD30 -> #REF! | Q30: =+Q29+P30 -> #REF! | S30: =+S29+R30 -> #REF! | U30: =SUM(+G30+H30+J30+L30+P30+T30+N30+R30) -> #REF! | W30: =G30*0.5 -> #REF! | X30: =-H30 -> 0 | Y30: =+W30-X30 -> #REF! | Z30: =+G30-X30-Y30+AD30 -> #REF! | AA30: =-N30 -> #REF! | AB30: =+AB29+AA30 -> #REF! | AC30: =IF(AB30<=D$97,"OK","ERROR") -> #REF!
A31: 2 | B31: Total Draw | C31: Const./Inspection/Interest Payment | E31: =+E30+30 -> 43800 | G31: =+' Draw Schedule'!K11 -> #REF! | I31: =+I30+H31 -> 0 | J31: =-Y31 -> #REF! | K31: =+K30+J31 -> #REF! | L31: =-Z31 -> #REF! | M31: =+M30+L31 -> #REF! | N31: =+L31+AD31 -> #REF! | O31: =+O30+N31 -> #REF! | P31: =-N31+AD31 -> #REF! | Q31: =+Q30+P31 -> #REF! | S31: =+S30+R31 -> #REF! | U31: =SUM(+G31+H31+J31+L31+P31+T31+N31+R31) -> #REF! | W31: =G31*0.5 -> #REF! | X31: =-H31 -> 0 | Y31: =+W31-X31 -> #REF! | Z31: =+G31-X31-Y31+AD31 -> #REF! | AA31: =-N31 -> #REF! | AB31: =+AB30+AA31 -> #REF! | AC31: =IF(AB31<=D$97,"OK","ERROR") -> #REF!
A32: 3 | B32: Total Draw | C32: Const./Inspection/Interest Payment | E32: =+E31+31 -> 43831 | G32: =+' Draw Schedule'!K12 -> #REF! | I32: =+I31+H32 -> 0 | J32: =-Y32 -> #REF! | K32: =+K31+J32 -> #REF! | L32: =-Z32 -> #REF! | M32: =+M31+L32 -> #REF! | N32: =+L32+AD32 -> #REF! | O32: =+O31+N32 -> #REF! | P32: =-N32+AD32 -> #REF! | Q32: =+Q31+P32 -> #REF! | S32: =+S31+R32 -> #REF! | U32: =SUM(+G32+H32+J32+L32+P32+T32+N32+R32) -> #REF! | W32: =G32*0.5 -> #REF! | X32: =-H32 -> 0 | Y32: =+W32-X32 -> #REF! | Z32: =+G32-X32-Y32+AD32 -> #REF! | AA32: =-N32 -> #REF! | AB32: =+AB31+AA32 -> #REF! | AC32: =IF(AB32<=D$97,"OK","ERROR") -> #REF!
C33: Const./Inspection/Interest Payment | E33: =+E32 -> 43831 | I33: =+I32+H33 -> 0 | J33: =-Y33 -> 0 | K33: =+K32+J33 -> #REF! | L33: =-Z33 -> 0 | M33: =+M32+L33 -> #REF! | N33: =+L33+AD33 -> 0 | O33: =+O32+N33 -> #REF! | P33: =-N33+AD33 -> 0 | Q33: =+Q32+P33 -> #REF! | S33: =+S32+R33 -> #REF! | U33: =SUM(+G33+H33+J33+L33+P33+T33+N33+R33) -> 0 | Z33: =+G33-X33-Y33+AD33 -> 0 | AA33: =-N33 -> 0 | AB33: =+AB32+AA33 -> #REF! | AC33: =IF(AB33<=D$97,"OK","ERROR") -> #REF!
A34: 4 | B34: Total Draw | C34: Const./Inspection/Interest Payment | E34: =+E32+31 -> 43862 | G34: =+' Draw Schedule'!K13 -> #REF! | I34: =+I33+H34 -> 0 | J34: =-Y34 -> #REF! | K34: =+K33+J34 -> #REF! | L34: =-Z34 -> #REF! | M34: =+M33+L34 -> #REF! | N34: =+L34+AD34 -> #REF! | O34: =+O33+N34 -> #REF! | P34: =-N34+AD34 -> #REF! | Q34: =+Q33+P34 -> #REF! | S34: =+S33+R34 -> #REF! | U34: =SUM(+G34+H34+J34+L34+P34+T34+N34+R34) -> #REF! | W34: =G34*0.5 -> #REF! | X34: =-H34 -> 0 | Y34: =+W34-X34 -> #REF! | Z34: =+G34-X34-Y34+AD34 -> #REF! | AA34: =-N34 -> #REF! | AB34: =+AB33+AA34 -> #REF! | AC34: =IF(AB34<=D$97,"OK","ERROR") -> #REF!
A35: 5 | B35: Total Draw | C35: Const./Inspection/Interest Payment | E35: =+E34+30 -> 43892 | G35: =+' Draw Schedule'!K14 -> #REF! | I35: =+I34+H35 -> 0 | J35: =-Y35 -> #REF! | K35: =+K34+J35 -> #REF! | L35: =-Z35 -> #REF! | M35: =+M34+L35 -> #REF! | N35: =+L35+AD35 -> #REF! | O35: =+O34+N35 -> #REF! | P35: =-N35+AD35 -> #REF! | Q35: =+Q34+P35 -> #REF! | S35: =+S34+R35 -> #REF! | U35: =SUM(+G35+H35+J35+L35+P35+T35+N35+R35) -> #REF! | W35: =G35*0.5 -> #REF! | X35: =-H35 -> 0 | Y35: =+W35-X35 -> #REF! | Z35: =+G35-X35-Y35+AD35 -> #REF! | AA35: =-N35 -> #REF! | AB35: =+AB34+AA35 -> #REF! | AC35: =IF(AB35<=D$97,"OK","ERROR") -> #REF!
C36: Const./Inspection/Interest Payment | D36: 0 | E36: =+E35 -> 43892 | I36: =+I35+H36 -> 0 | J36: =-Y36 -> 0 | K36: =+K35+J36 -> #REF! | L36: =-Z36 -> 0 | M36: =+M35+L36 -> #REF! | N36: =+L36+AD36 -> 0 | O36: =+O35+N36 -> #REF! | P36: =-N36+AD36 -> 0 | Q36: =+Q35+P36 -> #REF! | S36: =+S35+R36 -> #REF! | U36: =SUM(+G36+H36+J36+L36+P36+T36+N36+R36) -> 0 | Z36: =+G36-X36-Y36+AD36 -> 0 | AA36: =-N36 -> 0 | AB36: =+AB35+AA36 -> #REF! | AC36: =IF(AB36<=D$97,"OK","ERROR") -> #REF!
A37: 6 | B37: Total Draw | C37: Const./Inspection/Interest Payment | E37: =+E36+30 -> 43922 | G37: =+' Draw Schedule'!K15 -> #REF! | I37: =+I36+H37 -> 0 | J37: =-Y37 -> #REF! | K37: =+K35+J37 -> #REF! | L37: =-Z37 -> #REF! | M37: =+M36+L37 -> #REF! | N37: =+L37+AD37 -> #REF! | O37: =+O36+N37 -> #REF! | P37: =-N37+AD37 -> #REF! | Q37: =+Q36+P37 -> #REF! | S37: =+S36+R37 -> #REF! | U37: =SUM(+G37+H37+J37+L37+P37+T37+N37+R37) -> #REF! | W37: =G37*0.5 -> #REF! | X37: =-H37 -> 0 | Y37: =+W37-X37 -> #REF! | Z37: =+G37-X37-Y37+AD37 -> #REF! | AA37: =-N37 -> #REF! | AB37: =+AB36+AA37 -> #REF! | AC37: =IF(AB37<=D$97,"OK","ERROR") -> #REF!
A38: 7 | B38: Total Draw | C38: Const./Inspection/Interest Payment | E38: =+E37+31 -> 43953 | G38: =+' Draw Schedule'!K16 -> #REF! | I38: =+I37+H38 -> 0 | J38: =-Y38 -> #REF! | K38: =+K37+J38 -> #REF! | L38: =-Z38 -> #REF! | M38: =+M37+L38 -> #REF! | N38: =+L38+AD38 -> #REF! | O38: =+O37+N38 -> #REF! | P38: =-N38+AD38 -> #REF! | Q38: =+Q37+P38 -> #REF! | S38: =+S37+R38 -> #REF! | U38: =SUM(+G38+H38+J38+L38+P38+T38+N38+R38) -> #REF! | W38: =G38*0.5 -> #REF! | X38: =-H38 -> 0 | Y38: =+W38-X38 -> #REF! | Z38: =+G38-X38-Y38+AD38 -> #REF! | AA38: =-N38 -> #REF! | AB38: =+AB37+AA38 -> #REF! | AC38: =IF(AB38<=D$97,"OK","ERROR") -> #REF!
A39: 8 | B39: Total Draw | C39: Const./Inspection/Interest Payment | E39: =+E38+30 -> 43983 | G39: =+' Draw Schedule'!K17 -> #REF! | I39: =+I38+H39 -> 0 | J39: =-Y39 -> #REF! | K39: =+K38+J39 -> #REF! | L39: =-Z39 -> #REF! | M39: =+M38+L39 -> #REF! | N39: =+L39+AD39 -> #REF! | O39: =+O38+N39 -> #REF! | P39: =-N39+AD39 -> #REF! | Q39: =+Q38+P39 -> #REF! | S39: =+S38+R39 -> #REF! | U39: =SUM(+G39+H39+J39+L39+P39+T39+N39+R39) -> #REF! | W39: =G39*0.5 -> #REF! | X39: =-H39 -> 0 | Y39: =+W39-X39 -> #REF! | Z39: =+G39-X39-Y39+AD39 -> #REF! | AA39: =-N39 -> #REF! | AB39: =+AB38+AA39 -> #REF! | AC39: =IF(AB39<=D$97,"OK","ERROR") -> #REF!
D40: 0 | E40: =+E39 -> 43983 | I40: =+I39+H40 -> 0 | J40: =-Y40 -> 0 | K40: =+K39+J40 -> #REF! | L40: =-Z40 -> 0 | M40: =+M39+L40 -> #REF! | N40: =+L40+AD40 -> 0 | O40: =+O39+N40 -> #REF! | P40: =-N40+AD40 -> 0 | Q40: =+Q39+P40 -> #REF! | S40: =+S39+R40 -> #REF! | U40: =SUM(+G40+H40+J40+L40+P40+T40+N40+R40) -> 0 | Z40: =+G40-X40-Y40+AD40 -> 0 | AA40: =-N40 -> 0 | AB40: =+AB39+AA40 -> #REF! | AC40: =IF(AB40<=D$97,"OK","ERROR") -> #REF!
E41: =+E40 -> 43983 | I41: =+I40+H41 -> 0 | J41: =-Y41 -> 0 | K41: =+K40+J41 -> #REF! | L41: =-Z41 -> 0 | M41: =+M40+L41 -> #REF! | N41: =+L41+AD41 -> 0 | O41: =+O40+N41 -> #REF! | P41: =-N41+AD41 -> 0 | Q41: =+Q40+P41 -> #REF! | S41: =+S40+R41 -> #REF! | U41: =SUM(+G41+H41+J41+L41+P41+T41+N41+R41) -> 0 | Z41: =+G41-X41-Y41+AD41 -> 0 | AA41: =-N41 -> 0 | AB41: =+AB40+AA41 -> #REF! | AC41: =IF(AB41<=D$97,"OK","ERROR") -> #REF!
A42: 9 | B42: Total Draw | C42: Const./Inspection/Interest Payment | E42: =+E41+30 -> 44013 | G42: =+' Draw Schedule'!K18 -> #REF! | I42: =+I41+H42 -> 0 | J42: =-Y42 -> #REF! | K42: =+K41+J42 -> #REF! | L42: =-Z42 -> #REF! | M42: =+M41+L42 -> #REF! | N42: =+L42+AD42 -> #REF! | O42: =+O41+N42 -> #REF! | P42: =-N42+AD42 -> #REF! | Q42: =+Q41+P42 -> #REF! | S42: =+S41+R42 -> #REF! | U42: =SUM(+G42+H42+J42+L42+P42+T42+N42+R42) -> #REF! | W42: =G42*0.5 -> #REF! | X42: =-H42 -> 0 | Y42: =+W42-X42 -> #REF! | Z42: =+G42-X42-Y42+AD42 -> #REF! | AA42: =-N42 -> #REF! | AB42: =+AB41+AA42 -> #REF! | AC42: =IF(AB42<=D$97,"OK","ERROR") -> #REF!
E43: =+E42 -> 44013 | I43: =+I42+H43 -> 0 | J43: =-Y43 -> 0 | K43: =+K42+J43 -> #REF! | L43: =-Z43 -> 0 | M43: =+M42+L43 -> #REF! | N43: =+L43+AD43 -> 0 | O43: =+O42+N43 -> #REF! | P43: =-N43+AD43 -> 0 | Q43: =+Q42+P43 -> #REF! | S43: =+S42+R43 -> #REF! | U43: =SUM(+G43+H43+J43+L43+P43+T43+N43+R43) -> 0 | Z43: =+G43-X43-Y43+AD43 -> 0 | AA43: =-N43 -> 0 | AB43: =+AB42+AA43 -> #REF! | AC43: =IF(AB43<=D$97,"OK","ERROR") -> #REF!
E44: =+E43 -> 44013 | I44: =+I43+H44 -> 0 | J44: =-Y44 -> 0 | K44: =+K43+J44 -> #REF! | L44: =-Z44 -> 0 | M44: =+M43+L44 -> #REF! | N44: =+L44+AD44 -> 0 | O44: =+O43+N44 -> #REF! | P44: =-N44+AD44 -> 0 | Q44: =+Q43+P44 -> #REF! | S44: =+S43+R44 -> #REF! | U44: =SUM(+G44+H44+J44+L44+P44+T44+N44+R44) -> 0 | Z44: =+G44-X44-Y44+AD44 -> 0 | AA44: =-N44 -> 0 | AB44: =+AB43+AA44 -> #REF! | AC44: =IF(AB44<=D$97,"OK","ERROR") -> #REF!
A45: 10 | B45: Total Draw | C45: Const./Inspection/Interest Payment | E45: =+E42+31 -> 44044 | G45: =+' Draw Schedule'!K19 -> #REF! | I45: =+I44+H45 -> 0 | J45: =-Y45 -> #REF! | K45: =+K44+J45 -> #REF! | L45: =-Z45 -> #REF! | M45: =+M44+L45 -> #REF! | N45: =+L45+AD45 -> #REF! | O45: =+O44+N45 -> #REF! | P45: =-N45+AD45 -> #REF! | Q45: =+Q44+P45 -> #REF! | S45: =+S44+R45 -> #REF! | U45: =SUM(+G45+H45+J45+L45+P45+T45+N45+R45) -> #REF! | W45: =G45*0.5 -> #REF! | X45: =-H45 -> 0 | Y45: =+W45-X45 -> #REF! | Z45: =+G45-X45-Y45+AD45 -> #REF! | AA45: =-N45 -> #REF! | AB45: =+AB44+AA45 -> #REF! | AC45: =IF(AB45<=D$97,"OK","ERROR") -> #REF!
A46: 11 | B46: Total Draw | C46: Const./Inspection/Interest Payment | E46: =+E45+31 -> 44075 | G46: =+' Draw Schedule'!K20 -> #REF! | I46: =+I45+H46 -> 0 | J46: =-Y46 -> #REF! | K46: =+K45+J46 -> #REF! | L46: =-Z46 -> #REF! | M46: =+M45+L46 -> #REF! | N46: =+L46+AD46 -> #REF! | O46: =+O45+N46 -> #REF! | P46: =-N46+AD46 -> #REF! | Q46: =+Q45+P46 -> #REF! | S46: =+S45+R46 -> #REF! | U46: =SUM(+G46+H46+J46+L46+P46+T46+N46+R46) -> #REF! | W46: =G46*0.5 -> #REF! | X46: =-H46 -> 0 | Y46: =+W46-X46 -> #REF! | Z46: =+G46-X46-Y46+AD46 -> #REF! | AA46: =-N46 -> #REF! | AB46: =+AB45+AA46 -> #REF! | AC46: =IF(AB46<=D$97,"OK","ERROR") -> #REF!
A47: 12 | B47: Total Draw | C47: Const./Inspection/Interest Payment | E47: =+E46+31 -> 44106 | G47: =+' Draw Schedule'!K21 -> #REF! | I47: =+I46+H47 -> 0 | J47: =-Y47 -> #REF! | K47: =+K46+J47 -> #REF! | L47: =-Z47 -> #REF! | M47: =+M46+L47 -> #REF! | N47: =+L47+AD47 -> #REF! | O47: =+O46+N47 -> #REF! | P47: =-N47+AD47 -> #REF! | Q47: =+Q46+P47 -> #REF! | S47: =+S46+R47 -> #REF! | U47: =SUM(+G47+H47+J47+L47+P47+T47+N47+R47) -> #REF! | W47: =G47*0.5 -> #REF! | X47: =-H47 -> 0 | Y47: =+W47-X47 -> #REF! | Z47: =+G47-X47-Y47+AD47 -> #REF! | AA47: =-N47 -> #REF! | AB47: =+AB46+AA47 -> #REF! | AC47: =IF(AB47<=D$97,"OK","ERROR") -> #REF!
A48: 13 | B48: Total Draw | C48: Const./Inspection/Interest Payment | E48: =+E47+30 -> 44136 | G48: =+' Draw Schedule'!K22 -> #REF! | I48: =+I47+H48 -> 0 | J48: =-Y48 -> #REF! | K48: =+K47+J48 -> #REF! | L48: =-Z48 -> #REF! | M48: =+M47+L48 -> #REF! | N48: =+L48+AD48 -> #REF! | O48: =+O47+N48 -> #REF! | P48: =-N48+AD48 -> #REF! | Q48: =+Q47+P48 -> #REF! | S48: =+S47+R48 -> #REF! | U48: =SUM(+G48+H48+J48+L48+P48+T48+N48+R48) -> #REF! | W48: =G48*0.5 -> #REF! | X48: =-H48 -> 0 | Y48: =+W48-X48 -> #REF! | Z48: =+G48-X48-Y48+AD48 -> #REF! | AA48: =-N48 -> #REF! | AB48: =+AB47+AA48 -> #REF! | AC48: =IF(AB48<=D$97,"OK","ERROR") -> #REF!
A49: 14 | B49: Total Draw | C49: Const./Inspection/Interest Payment | E49: =+E48+30 -> 44166 | G49: =+' Draw Schedule'!K23 -> #REF! | I49: =+I48+H49 -> 0 | J49: =-Y49 -> #REF! | K49: =+K48+J49 -> #REF! | L49: =-Z49 -> #REF! | M49: =+M48+L49 -> #REF! | N49: =+L49+AD49 -> #REF! | O49: =+O48+N49 -> #REF! | P49: =-N49+AD49 -> #REF! | Q49: =+Q48+P49 -> #REF! | S49: =+S48+R49 -> #REF! | U49: =SUM(+G49+H49+J49+L49+P49+T49+N49+R49) -> #REF! | W49: =G49*0.5 -> #REF! | X49: =-H49 -> 0 | Y49: =+W49-X49 -> #REF! | Z49: =+G49-X49-Y49+AD49 -> #REF! | AA49: =-N49 -> #REF! | AB49: =+AB48+AA49 -> #REF! | AC49: =IF(AB49<=D$97,"OK","ERROR") -> #REF!
E50: =+E49 -> 44166 | I50: =+I49+H50 -> 0 | J50: =-Y50 -> 0 | K50: =+K49+J50 -> #REF! | L50: =-Z50 -> 0 | M50: =+M49+L50 -> #REF! | N50: =+L50+AD50 -> 0 | O50: =+O49+N50 -> #REF! | P50: =-N50+AD50 -> 0 | Q50: =+Q49+P50 -> #REF! | S50: =+S49+R50 -> #REF! | U50: =SUM(+G50+H50+J50+L50+P50+T50+N50+R50) -> 0 | W50: =G50*0.5 -> 0 | X50: =-H50 -> 0 | Y50: =+W50-X50 -> 0 | Z50: =+G50-X50-Y50+AD50 -> 0 | AA50: =-N50 -> 0 | AB50: =+AB49+AA50 -> #REF! | AC50: =IF(AB50<=D$97,"OK","ERROR") -> #REF!
A51: 15 | B51: Total Draw | C51: Const./Inspection/Interest Payment | E51: =+E50+31 -> 44197 | G51: =+' Draw Schedule'!K24 -> #REF! | I51: =+I50+H51 -> 0 | J51: =-Y51 -> #REF! | K51: =+K50+J51 -> #REF! | L51: =-Z51 -> #REF! | M51: =+M50+L51 -> #REF! | N51: =+L51+AD51 -> #REF! | O51: =+O50+N51 -> #REF! | P51: =-N51+AD51 -> #REF! | Q51: =+Q50+P51 -> #REF! | S51: =+S50+R51 -> #REF! | U51: =SUM(+G51+H51+J51+L51+P51+T51+N51+R51) -> #REF! | W51: =G51*0.5 -> #REF! | X51: =-H51 -> 0 | Y51: =+W51-X51 -> #REF! | Z51: =+G51-X51-Y51+AD51 -> #REF! | AA51: =-N51 -> #REF! | AB51: =+AB50+AA51 -> #REF! | AC51: =IF(AB51<=D$97,"OK","ERROR") -> #REF! | AD51: =+Y51 -> #REF!
E52: =+E51 -> 44197 | I52: =+I51+H52 -> 0 | J52: =-Y52 -> 0 | K52: =+K51+J52 -> #REF! | L52: =-Z52 -> 0 | M52: =+M51+L52 -> #REF! | N52: =+L52+AD52 -> 0 | O52: =+O51+N52 -> #REF! | P52: =-N52+AD52 -> 0 | Q52: =+Q51+P52 -> #REF! | S52: =+S51+R52 -> #REF! | U52: =SUM(+G52+H52+J52+L52+P52+T52+N52+R52) -> 0 | W52: =G52*0.5 -> 0 | X52: =-H52 -> 0 | Y52: =+W52-X52 -> 0 | Z52: =+G52-X52-Y52+AD52 -> 0 | AA52: =-N52 -> 0 | AB52: =+AB51+AA52 -> #REF! | AC52: =IF(AB52<=D$97,"OK","ERROR") -> #REF!
A53: 16 | B53: Total Draw | C53: Const./Inspection/Interest Payment | E53: =+E52+31 -> 44228 | G53: =+' Draw Schedule'!K25 -> #REF! | I53: =+I52+H53 -> 0 | J53: =-Y53 -> #REF! | K53: =+K52+J53 -> #REF! | L53: =-Z53 -> #REF! | M53: =+M52+L53 -> #REF! | N53: =+L53+AD53 -> #REF! | O53: =+O52+N53 -> #REF! | P53: =-N53+AD53 -> #REF! | Q53: =+Q52+P53 -> #REF! | S53: =+S52+R53 -> #REF! | U53: =SUM(+G53+H53+J53+L53+P53+T53+N53+R53) -> #REF! | W53: =G53*0.5 -> #REF! | X53: =-H53 -> 0 | Y53: =+W53-X53 -> #REF! | Z53: =+G53-X53-Y53+AD53 -> #REF! | AA53: =-N53 -> #REF! | AB53: =+AB52+AA53 -> #REF! | AC53: =IF(AB53<=D$97,"OK","ERROR") -> #REF! | AD53: =+Y53 -> #REF!
E54: =+E53 -> 44228 | I54: =+I53+H54 -> 0 | J54: =-Y54 -> 0 | K54: =+K53+J54 -> #REF! | L54: =-Z54 -> 0 | M54: =+M53+L54 -> #REF! | N54: =+L54+AD54 -> 0 | O54: =+O53+N54 -> #REF! | P54: =-N54+AD54 -> 0 | Q54: =+Q53+P54 -> #REF! | S54: =+S53+R54 -> #REF! | U54: =SUM(+G54+H54+J54+L54+P54+T54+N54+R54) -> 0 | W54: =G54*0.5 -> 0 | X54: =-H54 -> 0 | Y54: =+W54-X54 -> 0 | Z54: =+G54-X54-Y54+AD54 -> 0 | AA54: =-N54 -> 0 | AB54: =+AB53+AA54 -> #REF! | AC54: =IF(AB54<=D$97,"OK","ERROR") -> #REF! | AD54: =+Y54 -> 0
A55: 17 | B55: Total Draw | C55: Const./Inspection/Interest Payment | E55: =+E54+30 -> 44258 | G55: =+' Draw Schedule'!K26 -> #REF! | I55: =+I54+H55 -> 0 | J55: =-Y55 -> #REF! | K55: =+K54+J55 -> #REF! | L55: =-Z55 -> #REF! | M55: =+M54+L55 -> #REF! | N55: =+L55+AD55 -> #REF! | O55: =+O54+N55 -> #REF! | P55: =-N55+AD55 -> #REF! | Q55: =+Q54+P55 -> #REF! | S55: =+S54+R55 -> #REF! | U55: =SUM(+G55+H55+J55+L55+P55+T55+N55+R55) -> #REF! | W55: =G55*0.5 -> #REF! | X55: =-H55 -> 0 | Y55: =+W55-X55 -> #REF! | Z55: =+G55-X55-Y55+AD55 -> #REF! | AA55: =-N55 -> #REF! | AB55: =+AB54+AA55 -> #REF! | AC55: =IF(AB55<=D$97,"OK","ERROR") -> #REF! | AD55: =+Y55 -> #REF!
E56: =+E55 -> 44258 | I56: =+I55+H56 -> 0 | J56: =-Y56 -> 0 | K56: =+K55+J56 -> #REF! | L56: =-Z56 -> 0 | M56: =+M55+L56 -> #REF! | N56: =+L56+AD56 -> 0 | O56: =+O55+N56 -> #REF! | P56: =-N56+AD56 -> 0 | Q56: =+Q55+P56 -> #REF! | S56: =+S55+R56 -> #REF! | U56: =SUM(+G56+H56+J56+L56+P56+T56+N56+R56) -> 0 | W56: =G56*0.5 -> 0 | X56: =-H56 -> 0 | Y56: =+W56-X56 -> 0 | Z56: =+G56-X56-Y56+AD56 -> 0 | AA56: =-N56 -> 0 | AB56: =+AB55+AA56 -> #REF! | AC56: =IF(AB56<=D$97,"OK","ERROR") -> #REF! | AD56: =+Y56 -> 0
A57: 18 | B57: Total Draw | C57: Const./Inspection/Interest Payment | E57: =+E56+30 -> 44288 | G57: =+' Draw Schedule'!K27 -> #REF! | I57: =+I56+H57 -> 0 | J57: =-Y57 -> #REF! | K57: =+K56+J57 -> #REF! | L57: =-Z57 -> #REF! | M57: =+M56+L57 -> #REF! | N57: =+L57+AD57 -> #REF! | O57: =+O56+N57 -> #REF! | P57: =-N57+AD57 -> #REF! | Q57: =+Q56+P57 -> #REF! | S57: =+S56+R57 -> #REF! | U57: =SUM(+G57+H57+J57+L57+P57+T57+N57+R57) -> #REF! | W57: =G57*0.5 -> #REF! | X57: =-H57 -> 0 | Y57: =+W57-X57 -> #REF! | Z57: =+G57-X57-Y57+AD57 -> #REF! | AA57: =-N57 -> #REF! | AB57: =+AB56+AA57 -> #REF! | AC57: =IF(AB57<=D$97,"OK","ERROR") -> #REF! | AD57: =+Y57 -> #REF!
C58: PIS DATE | E58: =+E57 -> 44288 | I58: =+I57+H58 -> 0 | J58: =-Y58 -> 0 | K58: =+K57+J58 -> #REF! | L58: =-Z58 -> 0 | M58: =+M57+L58 -> #REF! | N58: =+L58+AD58 -> 0 | O58: =+O57+N58 -> #REF! | P58: =-N58+AD58 -> 0 | Q58: =+Q57+P58 -> #REF! | S58: =+S57+R58 -> #REF! | U58: =SUM(+G58+H58+J58+L58+P58+T58+N58+R58) -> 0 | W58: =G58*0.5 -> 0 | X58: =-H58 -> 0 | Y58: =+W58-X58 -> 0 | Z58: =+G58-X58-Y58+AD58 -> 0 | AA58: =-N58 -> 0 | AB58: =+AB57+AA58 -> #REF! | AC58: =IF(AB58<=D$97,"OK","ERROR") -> #REF! | AD58: =+Y58 -> 0
B59: Interest Payment | E59: =+E58+31 -> 44319 | G59: =+' Draw Schedule'!K28 -> #REF! | I59: =+I58+H59 -> 0 | J59: =-Y59 -> #REF! | K59: =+K58+J59 -> #REF! | L59: =-Z59 -> #REF! | M59: =+M58+L59 -> #REF! | N59: =+L59+AD59 -> #REF! | O59: =+O58+N59 -> #REF! | P59: =-N59+AD59 -> #REF! | Q59: =+Q58+P59 -> #REF! | S59: =+S58+R59 -> #REF! | U59: =SUM(+G59+H59+J59+L59+P59+T59+N59+R59) -> #REF! | W59: =G59*0.5 -> #REF! | X59: =-H59 -> 0 | Y59: =+W59-X59 -> #REF! | Z59: =+G59-X59-Y59+AD59 -> #REF! | AA59: =-N59 -> #REF! | AB59: =+AB58+AA59 -> #REF! | AC59: =IF(AB59<=D$97,"OK","ERROR") -> #REF!
E60: =+E59 -> 44319 | I60: =+I59+H60 -> 0 | J60: =-Y60 -> 0 | K60: =+K59+J60 -> #REF! | L60: =-Z60 -> 0 | M60: =+M59+L60 -> #REF! | N60: =+L60+AD60 -> 0 | O60: =+O59+N60 -> #REF! | P60: =-N60+AD60 -> 0 | Q60: =+Q59+P60 -> #REF! | S60: =+S59+R60 -> #REF! | U60: =SUM(+G60+H60+J60+L60+P60+T60+N60+R60) -> 0 | W60: =G60*0.5 -> 0 | X60: =-H60 -> 0 | Y60: =+W60-X60 -> 0 | Z60: =+G60-X60-Y60+AD60 -> 0 | AA60: =-N60 -> 0 | AB60: =+AB59+AA60 -> #REF! | AC60: =IF(AB60<=D$97,"OK","ERROR") -> #REF!
B61: Estimated 3rd Equity Pmt | D61: 0.6 | E61: =+E60+30 -> 44349 | H61: =SUM('CR Calculation'!F30*'Application of Funds'!D61) -> 2295523 | I61: =+I60+H61 -> 2295523 | J61: =-Y61 -> 0 | K61: =+K60+J61 -> #REF! | L61: =-Z61 -> 0 | M61: =+M60+L61 -> #REF! | N61: =-AA61 -> 0 | O61: =+O60+N61 -> #REF! | P61: =-N61+AD61 -> 0 | Q61: =+Q60+P61 -> #REF! | S61: =+S60+R61 -> #REF! | U61: =SUM(+G61+H61+J61+L61+P61+T61+N61+R61) -> 2295523 | Z61: =+G61-X61-Y61+AD61 -> 0 | AB61: =+AB60+AA61 -> #REF! | AC61: =IF(AB61<=D$97,"OK","ERROR") -> #REF!
B62: Payment on Contruction Loan | E62: =+E61 -> 44349 | H62: -1300000 | I62: =+I61+H62 -> 995523.04 | J62: =-Y62 -> 1300000 | K62: =+K61+J62 -> #REF! | L62: =-Z62 -> 0 | M62: =+M61+L62 -> #REF! | N62: =-AA62 -> 0 | O62: =+O61+N62 -> -13755013 | P62: =-N62+AD62 -> 0 | Q62: =+Q61+P62 -> 14323093 | S62: =+S61+R62 -> #REF! | U62: =SUM(+G62+H62+J62+L62+P62+T62+N62+R62) -> 0 | W62: =G62*0.5 -> 0 | X62: =-H62 -> 1300000 | Y62: =+W62-X62 -> -1300000 | Z62: =+G62-X62-Y62+AD62 -> 0 | AA62: =-N62 -> 0 | AB62: =+AB61+AA62 -> 13755013 | AC62: =IF(AB62<=D$97,"OK","ERROR") -> ERROR
B63: Interest Payment | E63: =+E61 -> 44349 | G63: =+' Draw Schedule'!K29 -> #REF! | H63: =-G63 -> #REF! | I63: =+I62+H63 -> #REF! | J63: =-Y63 -> 0 | K63: =+K62+J63 -> #REF! | L63: =-Z63 -> #REF! | M63: =+M62+L63 -> #REF! | N63: =-AA63 -> 0 | O63: =+O61+N63 -> -13755013 | P63: =-N63+AD63 -> 0 | Q63: =+Q61+P63 -> 14323093 | S63: =+S61+R63 -> #REF! | U63: =SUM(+G63+H63+J63+L63+P63+T63+N63+R63) -> 0 | W63: =G63*0.5 -> #REF! | X63: =-H63 -> #REF! | Y63: 0 | Z63: =+G63-X63-Y63+AD63 -> #REF! | AA63: =-N63 -> 0 | AB63: =+AB62+AA63 -> 13755013 | AC63: =IF(AB63<=D$97,"OK","ERROR") -> ERROR
B64: Interest Payment | E64: =+E63+30 -> 44379 | G64: =+' Draw Schedule'!K30 -> #REF! | H64: =-G64 -> #REF! | I64: =+I63+H64 -> #REF! | J64: =-Y64 -> 0 | K64: =+K63+J64 -> #REF! | L64: =-Z64 -> #REF! | M64: =+M63+L64 -> #REF! | N64: =-AA64 -> 0 | O64: =+O63+N64 -> -13755013 | P64: =-N64+AD64 -> 0 | Q64: =+Q63+P64 -> 14323093 | S64: =+S63+R64 -> #REF! | U64: =SUM(+G64+H64+J64+L64+P64+T64+N64+R64) -> 0 | W64: =G64*0.5 -> #REF! | X64: =-H64 -> #REF! | Y64: 0 | Z64: =+G64-X64-Y64+AD64 -> #REF! | AA64: =-N64 -> 0 | AB64: =+AB63+AA64 -> 13755013 | AC64: =IF(AB64<=D$97,"OK","ERROR") -> ERROR
B65: Payment of Cost Certfication | C65: 90 Days Post PIS Date | E65: =+E64 -> 44379 | G65: =+'Sources & Uses'!F51 -> 0 | H65: =-G65 -> 0 | I65: =+I64+H65 -> #REF! | J65: =-Y65 -> 0 | K65: =+K64+J65 -> #REF! | L65: =-Z65 -> 0 | M65: =+M61+L65 -> #REF! | N65: =-AA65 -> 0 | O65: =+O61+N65 -> -13755013 | P65: =-N65+AD65 -> 0 | Q65: =+Q61+P65 -> 14323093 | S65: =+S61+R65 -> #REF! | U65: =SUM(+G65+H65+J65+L65+P65+T65+N65+R65) -> 0 | W65: =G65*0.5 -> 0 | X65: =-H65 -> 0 | Y65: 0 | Z65: =+G65-X65-Y65+AD65 -> 0 | AA65: =-N65 -> 0 | AB65: =+AB64+AA65 -> 13755013 | AC65: =IF(AB65<=D$97,"OK","ERROR") -> ERROR
B66: Payment of Construction Retainage | C66: =+C65 -> 90 Days Post PIS Date | E66: =+E65 -> 44379 | G66: =-' Draw Schedule'!E36 -> 722566.7 | H66: 0 | I66: =+I65+H66 -> #REF! | J66: =-Y66 -> -722566.7 | K66: =+K65+J66 -> #REF! | L66: =-Z66 -> -229821.9 | M66: =+M65+L66 -> #REF! | N66: =-AA66 -> 0 | O66: =+O65+N66 -> -13755013 | P66: =-N66+AD66 -> 229821.9 | Q66: =+Q65+P66 -> 14552914 | S66: =+S65+R66 -> #REF! | U66: =SUM(+G66+H66+J66+L66+P66+T66+N66+R66) -> 0 | W66: =G66*0.5 -> 361283.35 | X66: =-H66 -> 0 | Y66: =+W66*2 -> 722566.7 | Z66: =+G66-X66-Y66+AD66 -> 229821.9 | AA66: =-N66 -> 0 | AB66: =+AB65+AA66 -> 13755013 | AC66: =IF(AB66<=D$97,"OK","ERROR") -> ERROR | AD66: 229821.9
B67: Interest Payment | E67: =+E65+30 -> 44409 | G67: =+' Draw Schedule'!K31 -> #REF! | H67: =-G67 -> #REF! | I67: =+I66+H67 -> #REF! | J67: =-Y67 -> 0 | K67: =+K66+J67 -> #REF! | L67: =-Z67 -> #REF! | M67: =+M66+L67 -> #REF! | N67: =-AA67 -> 0 | O67: =+O66+N67 -> -13755013 | P67: =-N67+AD67 -> 0 | Q67: =+Q66+P67 -> 14552914 | S67: =+S66+R67 -> #REF! | U67: =SUM(+G67+H67+J67+L67+P67+T67+N67+R67) -> 0 | W67: =G67*0.5 -> #REF! | X67: =-H67 -> #REF! | Y67: 0 | Z67: =+G67-X67-Y67+AD67 -> #REF! | AA67: =-N67 -> 0 | AB67: =+AB66+AA67 -> 13755013 | AC67: =IF(AB67<=D$97,"OK","ERROR") -> ERROR
B68: Pay Down on Construction/Interim | E68: =+E67 -> 44409 | I68: =+I67+H68 -> #REF! | K68: =+K67+J68 -> #REF! | L68: =-Z68 -> 0 | M68: =+M67+L68 -> #REF! | N68: =-AA68 -> 0 | O68: =+O67+N68 -> -13755013 | P68: =-N68+AD68 -> 0 | Q68: =+Q67+P68 -> 14552914 | S68: =+S67+R68 -> #REF! | U68: =SUM(+G68+H68+J68+L68+P68+T68+N68+R68) -> 0 | W68: =G68*0.5 -> 0 | X68: =-H68 -> 0 | Y68: =+W68-X68 -> 0 | Z68: =+G68-X68-Y68+AD68 -> 0 | AA68: =-N68 -> 0 | AB68: =+AB67+AA68 -> 13755013 | AC68: =IF(AB68<=D$97,"OK","ERROR") -> ERROR
E69: =+E67 -> 44409 | I69: =+I68+H69 -> #REF! | J69: =-Y69 -> 0 | K69: =+K68+J69 -> #REF! | L69: =-Z69 -> 0 | M69: =+M68+L69 -> #REF! | N69: =-AA69 -> 0 | O69: =+O68+N69 -> -13755013 | P69: =-N69+AD69 -> 0 | Q69: =+Q68+P69 -> 14552914 | S69: =+S68+R69 -> #REF! | U69: =SUM(+G69+H69+J69+L69+P69+T69+N69+R69) -> 0 | W69: =G69*0.5 -> 0 | X69: =-H69 -> 0 | Y69: =+W69-X69 -> 0 | Z69: =+G69-X69-Y69+AD69 -> 0 | AA69: =-N69 -> 0 | AB69: =+AB68+AA69 -> 13755013 | AC69: =IF(AB69<=D$97,"OK","ERROR") -> ERROR
E70: =+E69 -> 44409 | I70: =+I69+H70 -> #REF! | J70: =-Y70 -> 0 | K70: =+K69+J70 -> #REF! | L70: =-Z70 -> 0 | M70: =+M69+L70 -> #REF! | N70: =-AA70 -> 0 | O70: =+O69+N70 -> -13755013 | P70: =-N70+AD70 -> 0 | Q70: =+Q69+P70 -> 14552914 | S70: =+S69+R70 -> #REF! | U70: =SUM(+G70+H70+J70+L70+P70+T70+N70+R70) -> 0 | W70: =G70*0.5 -> 0 | X70: =-H70 -> 0 | Y70: =+W70-X70 -> 0 | Z70: =+G70-X70-Y70+AD70 -> 0 | AA70: =-N70 -> 0 | AB70: =+AB69+AA70 -> 13755013 | AC70: =IF(AB70<=D$97,"OK","ERROR") -> ERROR
E71: =+E70 -> 44409 | I71: =+I70+H71 -> #REF! | J71: =-Y71 -> 0 | K71: =+K70+J71 -> #REF! | L71: =-Z71 -> 0 | M71: =+M70+L71 -> #REF! | N71: =-AA71 -> 0 | O71: =+O70+N71 -> -13755013 | P71: =-N71+AD71 -> 0 | Q71: =+Q70+P71 -> 14552914 | S71: =+S70+R71 -> #REF! | U71: =SUM(+G71+H71+J71+L71+P71+T71+N71+R71) -> 0 | W71: =G71*0.5 -> 0 | X71: =-H71 -> 0 | Y71: =+W71-X71 -> 0 | Z71: =+G71-X71-Y71+AD71 -> 0 | AA71: =-N71 -> 0 | AB71: =+AB70+AA71 -> 13755013 | AC71: =IF(AB71<=D$97,"OK","ERROR") -> ERROR
E72: =+E70 -> 44409 | I72: =+I71+H72 -> #REF! | J72: =-Y72 -> 0 | K72: =+K71+J72 -> #REF! | L72: =-Z72 -> 0 | M72: =+M71+L72 -> #REF! | N72: =-AA72 -> 0 | O72: =+O71+N72 -> -13755013 | P72: =-N72+AD72 -> 0 | Q72: =+Q71+P72 -> 14552914 | S72: =+S71+R72 -> #REF! | U72: =SUM(+G72+H72+J72+L72+P72+T72+N72+R72) -> 0 | W72: =G72*0.5 -> 0 | X72: =-H72 -> 0 | Y72: =+W72-X72 -> 0 | Z72: =+G72-X72-Y72+AD72 -> 0 | AA72: =-N72 -> 0 | AB72: =+AB71+AA72 -> 13755013 | AC72: =IF(AB72<=D$97,"OK","ERROR") -> ERROR
B73: Interest Payment | E73: =+E72+31 -> 44440 | G73: =+' Draw Schedule'!K32 -> #REF! | H73: =-G73 -> #REF! | I73: =+I72+H73 -> #REF! | J73: =-Y73 -> 0 | K73: =+K72+J73 -> #REF! | L73: =-Z73 -> #REF! | M73: =+M72+L73 -> #REF! | N73: =-AA73 -> 0 | O73: =+O72+N73 -> -13755013 | P73: =-N73+AD73 -> 0 | Q73: =+Q72+P73 -> 14552914 | S73: =+S72+R73 -> #REF! | U73: =SUM(+G73+H73+J73+L73+P73+T73+N73+R73) -> 0 | W73: =G73*0.5 -> #REF! | X73: =-H73 -> #REF! | Y73: 0 | Z73: =+G73-X73-Y73+AD73 -> #REF! | AA73: =-N73 -> 0 | AB73: =+AB72+AA73 -> 13755013 | AC73: =IF(AB73<=D$97,"OK","ERROR") -> ERROR
B74: Permanent Loan Closing | C74: 120 Days Post PIS Date | E74: =+E73+30 -> 44470 | I74: =+I73+H74 -> #REF! | J74: =-Y74 -> 0 | K74: =+K73+J74 -> #REF! | L74: =-Z74 -> 0 | M74: =+M73+L74 -> #REF! | N74: =-AA74 -> 0 | O74: =+O73+N74 -> -13755013 | P74: =-N74+AD74 -> 0 | Q74: =+Q73+P74 -> 14552914 | S74: =+S73+R74 -> #REF! | U74: =SUM(+G74+H74+J74+L74+P74+T74+N74+R74) -> 0
B75: Permanent Loan Closing Fees | E75: =+E73 -> 44440 | G75: =+'Sources & Uses'!F40 -> 52500 | H75: =-G75 -> -52500 | I75: =+I74+H75 -> #REF! | J75: =-Y75 -> 0 | K75: =+K74+J75 -> #REF! | L75: =-Z75 -> 0 | M75: =+M74+L75 -> #REF! | N75: =-AA75 -> 0 | O75: =+O74+N75 -> -13755013 | P75: =-N75+AD75 -> 0 | Q75: =+Q74+P75 -> 14552914 | S75: =+S74+R75 -> #REF! | U75: =SUM(+G75+H75+J75+L75+P75+T75+N75+R75) -> 0
E76: =+E75 -> 44440 | H76: =-G76 -> 0 | I76: =+I75+H76 -> #REF! | J76: =-Y76 -> 0 | K76: =+K75+J76 -> #REF! | L76: =-Z76 -> 0 | M76: =+M75+L76 -> #REF! | N76: =-AA76 -> 0 | O76: =+O75+N76 -> -13755013 | P76: =-N76+AD76 -> 0 | Q76: =+Q75+P76 -> 14552914 | S76: =+S75+R76 -> #REF! | U76: =SUM(+G76+H76+J76+L76+P76+T76+N76+R76) -> 0
B77: Paydown - Construction Loan | E77: =+E75 -> 44440 | I77: =+I76+H77 -> #REF! | J77: =-Y77 -> 0 | K77: =+K76+J77 -> #REF! | L77: =-Z77 -> 0 | M77: =+M75+L77 -> #REF! | N77: =-AA77 -> 0 | O77: =+O75+N77 -> -13755013 | P77: =-N77+AD77 -> 0 | Q77: =+Q75+P77 -> 14552914 | S77: =+S75+R77 -> #REF! | U77: =SUM(+G77+H77+J77+L77+P77+T77+N77+R77) -> 0
E78: =+E77 -> 44440 | G78: =SUM('Sources & Uses'!H67-'Application of Funds'!G25-' Draw Schedule'!I36)*0 -> #REF! | I78: =+I77+H78 -> #REF! | J78: =-Y78 -> 0 | K78: =+K77+J78 -> #REF! | L78: =-Z78 -> 0 | M78: =+M73+L78 -> #REF! | N78: =-AA78 -> 0 | O78: =+O73+N78 -> -13755013 | P78: =-N78+AD78 -> 0 | Q78: =+Q76+P78 -> 14552914 | S78: =+S76+R78 -> #REF! | U78: =SUM(+G78+H78+J78+L78+P78+T78+N78+R78) -> #REF!
E79: =+E77 -> 44440 | I79: =+I78+H79 -> #REF! | J79: =-Y79 -> 0 | K79: =+K78+J79 -> #REF! | L79: =-Z79 -> 0 | M79: =+M78+L79 -> #REF! | N79: =-AA79 -> 0 | O79: =+O78+N79 -> -13755013 | P79: =-N79+AD79 -> 0 | Q79: =+Q77+P79 -> 14552914 | S79: =+S77+R79 -> #REF! | U79: =SUM(+G79+H79+J79+L79+P79+T79+N79+R79) -> 0
B80: Reciept of Permanent Loan/Final Equity | D80: 0.3 | E80: =+E79 -> 44440 | H80: =SUM('CR Calculation'!F30*'Application of Funds'!D80) -> 1147761.5 | I80: =+I79+H80 -> #REF! | J80: =-Y80 -> 0 | K80: =+K79+J80 -> #REF! | L80: =-Z80 -> 0 | M80: =+M79+L80 -> #REF! | N80: =-AA80 -> 0 | O80: =+O79+N80 -> -13755013 | P80: =-N80+AD80 -> 0 | Q80: =+Q78+P80 -> 14552914 | S80: =+S78+R80 -> #REF! | U80: =SUM(+G80+H80+J80+L80+P80+T80+N80+R80) -> 1147761.5
B81: Funding of Reserves | E81: =+E80 -> 44440 | G81: =+'Sources & Uses'!H63 -> 0 | H81: =-G81+G79 -> 0 | I81: =+I80+H81 -> #REF! | J81: =-Y81 -> 0 | K81: =+K80+J81 -> #REF! | L81: =-Z81 -> 0 | M81: =+M80+L81 -> #REF! | N81: =-AA81 -> 0 | O81: =+O80+N81 -> -13755013 | P81: =-N81+AD81 -> 0 | Q81: =+Q79+P81 -> 14552914 | S81: =+S79+R81 -> #REF! | U81: =SUM(+G81+H81+J81+L81+P81+T81+N81+R81) -> 0
B82: Pay Off Construction Loan; Redeem Bonds | E82: =+E81 -> 44440 | H82: =-I81 -> #REF! | I82: =+I81+H82 -> #REF! | J82: =-K81 -> #REF! | K82: =+K81+J82 -> #REF! | L82: =-M81 -> #REF! | M82: =+M81+L82 -> #REF! | N82: =-D95-O81 -> 13755013 | O82: =+O81+N82 -> 0 | P82: =-Q81 -> -14552914 | Q82: =+Q80+P82 -> 0 | R82: -1036344.6 | S82: =+S80+R82 -> #REF! | U82: =SUM(+G82+H82+J82+L82+P82+T82+N82+R82) -> 19575131
B83: Payment of Development Fee | E83: =+E82 -> 44440 | G83: =SUM('Sources & Uses'!H67+'Sources & Uses'!H68-' Draw Schedule'!I36-'Application of Funds'!F25) -> #REF! | I83: =+I82+H83 -> #REF! | J83: =-K82 -> #REF! | K83: =+K82+J83 -> #REF! | L83: =-Z83 -> 0 | M83: =+M82+L83 -> #REF! | N83: =-AA83 -> 0 | O83: =+O82+N83 -> 0 | Q83: =+Q82+P83 -> 0 | R83: =-S82 -> #REF! | S83: =+S82+R83 -> #REF! | T83: =-T4 -> #REF! | U83: =SUM(+G83+H83+J83+L83+P83+T83+N83+R83) -> #REF!
D84: =SUM(D6:D83)-D25 -> 1 | G84: =SUM(G26:G83)-G28 -> #REF! | H84: =SUM(H4:H83) -> #REF! | J84: =SUM(J5:J83) -> #REF! | L84: =SUM(L5:L83) -> #REF! | P84: =SUM(P34:P83) -> #REF! | R84: =SUM(R34:R83) -> #REF! | T84: =SUM(T4:T83) -> #REF!
U86: =SUM(U4:U85) -> #REF!
U87: =-U74 -> 0
B88: Variance from Source & Use Worksheet | G88: =SUM('Sources & Uses'!I75-'Application of Funds'!G84) -> #REF!
D89: Total Permanent Sources | G89: =SUM(H6+H61+H80+P80) -> 3825871.7
G90: =SUM(H26+H30+H31+H32+H34+H65+H66+H67+H70+H81+H83+J34+J35+J37+J38+J39+J42+J45+J46+J47) -> #REF!
U91: =SUM(U86:U87) -> #REF!
B92: Total LHC HOME funds holdback | E92: 0 | G92: =SUM(M4*E92) -> 0 | U92: =SUM(U91-'CR Calculation'!F30) -> #REF!
B93: Total PHA Holdback | E93: 0 | G93: =SUM(E93*O4) -> 0
B95: Total CDBG Award | D95: =+'Interest Calculation'!C4 -> 18500000
B96: Percentage to be drawn during construction | D96: 0.95
B97: Total CDBG avaialbe for Collateral Draws - PIS | D97: =+D95*D96 -> 17575000

Sheet Construction Loan
A1: =+'Sources & Uses'!A1 -> Lamar Building
A2: CONSTRUCTION INTEREST CALCULATION:
I3: Bridge Loan over bond amount
A4: CONSTRUCTION LOAN AMOUNT | E4: 4000000 | I4: Up to Amount (See Actual on Application of Funds) | J4: 0.0025 | K4: =SUM(E4*J4) -> 10000
A5: INTEREST RATE | E5: =+O5/100 -> 0.0498 | I5: Libor + 275bps | M5: 2.23 | N5: 2.75 | O5: =+M5+N5 -> 4.98
A6: Days In Month for Int. Calculation | E6: 30
A7: Days In Year For Int. Calculation | E7: 360
C8: Cumulative | D8: Total | E8: Monthly | I8: Accrual
A9: Draw No: | B9: Draw Amt. | C9: Balance | D9: Days Outs. | E9: Interest | F9: Interest | G9: Mo.s | H9: Weighted Average | I9: Date
A10: 1 | B10: =-'Application of Funds'!J26 -> #REF! | C10: =+B10 -> #REF! | E10: =SUM(C10*E$6/E$7*E$5) -> #REF! | I10: =+'Application of Funds'!E26 -> 43739
A11: =+A10+1 -> 2 | B11: =-'Application of Funds'!J30 -> #REF! | C11: =+C10+B11 -> #REF! | D11: 330 | E11: =SUM(C11*E$6/E$7*E$5) -> #REF! | F11: =SUM(D11/360*B11*E5) -> #REF! | G11: =SUM(D11/B$40) -> 11 | H11: 100000 | I11: =+'Application of Funds'!E30 -> 43770
A12: =+A11+1 -> 3 | B12: =-'Application of Funds'!J31 -> #REF! | C12: =+C11+B12 -> #REF! | D12: =+D11-B$40 -> 300 | E12: =SUM(C12*E$6/E$7*E$5) -> #REF! | F12: =SUM(D12/360*B12*E5) -> #REF! | G12: =SUM(D12/B$40) -> 10 | H12: 112500 | I12: =+'Application of Funds'!E31 -> 43800
A13: =+A12+1 -> 4 | B13: =-'Application of Funds'!J32 -> #REF! | C13: =+C12+B13 -> #REF! | D13: =+D12-B$40 -> 270 | E13: =SUM(C13*E$6/E$7*E$5) -> #REF! | F13: =SUM(D13/360*B13*E5) -> #REF! | G13: =SUM(D13/B$40) -> 9 | H13: 93750 | I13: =+'Application of Funds'!E32 -> 43831
A14: =+A13+1 -> 5 | B14: =-'Application of Funds'!J34 -> #REF! | C14: =+C13+B14 -> #REF! | D14: =+D13-B$40 -> 240 | E14: =SUM(C14*E$6/E$7*E$5) -> #REF! | F14: =SUM(D14/360*B14*E5) -> #REF! | G14: =SUM(D14/B$40) -> 8 | H14: 125000 | I14: =+'Application of Funds'!E34 -> 43862
A15: =+A14+1 -> 6 | B15: =-'Application of Funds'!J35 -> #REF! | C15: =+C14+B15 -> #REF! | D15: =+D14-B$40 -> 210 | E15: =SUM(C15*E$6/E$7*E$5) -> #REF! | F15: =SUM(D15/360*B15*E5) -> #REF! | G15: =SUM(D15/B$40) -> 7 | H15: 56250 | I15: =+'Application of Funds'!E35 -> 43892
A16: =+A15+1 -> 7 | B16: =-'Application of Funds'!J37 -> #REF! | C16: =+C15+B16 -> #REF! | D16: =+D15-B$40 -> 180 | E16: =SUM(C16*E$6/E$7*E$5) -> #REF! | F16: =SUM(D16/360*B16*E$5) -> #REF! | G16: =SUM(D16/B$40) -> 6 | H16: 50000 | I16: =+'Application of Funds'!E37 -> 43922
A17: =+A16+1 -> 8 | B17: =-'Application of Funds'!J38 -> #REF! | C17: =+C16+B17 -> #REF! | D17: =+D16-B$40 -> 150 | E17: =SUM(C17*E$6/E$7*E$5) -> #REF! | F17: =SUM(D17/360*B17*E$5) -> #REF! | G17: =SUM(D17/B$40) -> 5 | I17: =+'Application of Funds'!E38 -> 43953
A18: =+A17+1 -> 9 | B18: =-'Application of Funds'!J39 -> #REF! | C18: =+C17+B18 -> #REF! | D18: =+D17-B$40 -> 120 | E18: =SUM(C18*E$6/E$7*E$5) -> #REF! | F18: =SUM(D18/360*B18*E$5) -> #REF! | G18: =SUM(D18/B$40) -> 4 | I18: =+'Application of Funds'!E39 -> 43983
A19: =+A18+1 -> 10 | B19: =SUM('Application of Funds'!J42:J44)*-1 -> #REF! | C19: =+C18+B19 -> #REF! | D19: =+D18-B$40 -> 90 | E19: =SUM(C19*E$6/E$7*E$5) -> #REF! | G19: =SUM(D19/B$40) -> 3 | I19: =+'Application of Funds'!E42 -> 44013
A20: =+A19+1 -> 11 | B20: =SUM('Application of Funds'!J45)*-1 -> #REF! | C20: =SUM(C19+B20) -> #REF! | D20: =+D19-B$40 -> 60 | E20: =SUM(C20*E$6/E$7*E$5) -> #REF! | G20: =SUM(D20/B$40) -> 2 | I20: =+'Application of Funds'!E45 -> 44044
A21: =+A20+1 -> 12 | B21: =-'Application of Funds'!J46 -> #REF! | C21: =+C20+B21 -> #REF! | D21: =+D20-B$40 -> 30 | E21: =SUM(C21*E$6/E$7*E$5) -> #REF! | G21: =SUM(D21/B$40) -> 1 | I21: =+'Application of Funds'!E46 -> 44075
A22: =+A21+1 -> 13 | B22: =-'Application of Funds'!J47 -> #REF! | C22: =+C21+B22 -> #REF! | D22: =+D21-B$40 -> 0 | E22: =SUM(C22*E$6/E$7*E$5) -> #REF! | G22: =SUM(D22/B$40) -> 0 | I22: =+'Application of Funds'!E47 -> 44106
A23: =+A22+1 -> 14 | B23: =-'Application of Funds'!J48 -> #REF! | C23: =+C22+B23 -> #REF! | E23: =SUM(C23*E$6/E$7*E$5) -> #REF! | G23: =SUM(D23/B$40) -> 0 | I23: =+'Application of Funds'!E48 -> 44136
A24: =+A23+1 -> 15 | B24: =-'Application of Funds'!J49 -> #REF! | C24: =+C23+B24 -> #REF! | E24: =SUM(C24*E$6/E$7*E$5) -> #REF! | G24: =SUM(D24/B$40) -> 0 | I24: =+'Application of Funds'!E49 -> 44166
A25: 16 | B25: =-'Application of Funds'!J51 -> #REF! | C25: =+C24+B25 -> #REF! | E25: =SUM(C25*E$6/E$7*E$5) -> #REF! | I25: =+'Application of Funds'!E51 -> 44197
A26: 17 | B26: =-'Application of Funds'!J53 -> #REF! | C26: =+C25+B26 -> #REF! | E26: =SUM(C26*E$6/E$7*E$5) -> #REF! | I26: =+'Application of Funds'!E53 -> 44228
A27: 18 | B27: =-'Application of Funds'!J55 -> #REF! | C27: =+C26+B27 -> #REF! | E27: =SUM(C27*E$6/E$7*E$5) -> #REF! | I27: =+'Application of Funds'!E55 -> 44258
A28: 19 | B28: =-'Application of Funds'!J57 -> #REF! | C28: =+C27+B28 -> #REF! | E28: =SUM(C28*E$6/E$7*E$5) -> #REF! | I28: =+'Application of Funds'!E57 -> 44288
A29: 20 | B29: =-'Application of Funds'!J59 -> #REF! | C29: =+C28+B29 -> #REF! | E29: =SUM(C29*E$6/E$7*E$5) -> #REF! | I29: =+'Application of Funds'!E59 -> 44319
A30: 21 | B30: =-'Application of Funds'!J62 -> -1300000 | C30: =+C29+B30 -> #REF! | E30: =SUM(C30*E$6/E$7*E$5) -> #REF! | I30: =+'Application of Funds'!E62 -> 44349
A31: 22 | B31: =-'Application of Funds'!J66 -> 722566.7 | C31: =+C30+B31 -> #REF! | E31: =SUM(C31*E$6/E$7*E$5) -> #REF! | I31: =+'Application of Funds'!E66 -> 44379
A32: 23 | C32: =+C31+B32 -> #REF! | E32: =SUM(C32*E$6/E$7*E$5) -> #REF! | I32: =+'Application of Funds'!E67 -> 44409
A33: 24 | B33: =-'Application of Funds'!J82 -> #REF! | C33: =+C32+B33 -> #REF! | E33: =SUM(C33*E$6/E$7*E$5) -> #REF! | I33: =+'Application of Funds'!E83 -> 44440
B34: =SUM(B10:B33) -> #REF! | E34: =SUM(E10:E33) -> #REF! | F34: =SUM(F11:F24) -> #REF! | H34: =SUM(H11:H24) -> 537500
B36: Capitalizable Construction Interest | H36: =F34 -> #REF!
B37: Interest to Operating Deficit | H37: 0
A39: Days in Year | B39: 360
A40: Days In Month | B40: 30
A44: Construction Loan Calculation:
A46: Total Development Costs | H46: =+'Sources & Uses'!I75 -> 24500000
A48: Less 1st Equity Installment | H48: =704940+704940 -> 1409880
A49: Less Unpaid Developer Fee | H49: =SUM('Sources & Uses'!#REF!-'Sources & Uses'!#REF!)*'Construction Loan'!I49 -> #REF! | I49: 0.75
A50: Less Construction Contingency | H50: =SUM('Sources & Uses'!E24*'Construction Loan'!I50) -> 1445133.4 | I50: 0.1
A51: Construction Loan Amount Calculated | H51: =SUM(H46-H48-H49-H50) -> #REF!
E54: 131978 | I54: 0.085
E55: 135943
J56: =SUM(E54-E55) -> -3965

Sheet Proforma (Reality) 
A1: Fifteen Year | G1: Percent Annual Adjustment: | J1: 0.02 | K1: Income
A2: Operating Proforma | D2: =+'Sources & Uses'!A1 -> Lamar Building | J2: 0.03 | K2: Expense
J3: 0.07 | K3: Vacancy Rate
J4: 0.02 | K4: Other Income
D7: Year | E7: Year | F7: Year | G7: Year | H7: Year | I7: Year | J7: Year | K7: Year | L7: Year | M7: Year | N7: Year | O7: Year | P7: Year | Q7: Year | R7: Year
D8: One | E8: Two | F8: Three | G8: Four | H8: Five | I8: Six | J8: Seven | K8: Eight | L8: Nine | M8: Ten | N8: Eleven | O8: Twelve | P8: Thirteen | Q8: Fourteen | R8: Fifteen | S8: Total
A9: Income
A10: Gross Rental Income | D10: =+Rent!I44 -> 1833000 | E10: =D10*(1+($J1)) -> 1869660 | F10: =E10*(1+($J1)) -> 1907053.2 | G10: =F10*(1+($J1)) -> 1945194.3 | H10: =G10*(1+($J1)) -> 1984098.1 | I10: =H10*(1+($J1)) -> 2023780.1 | J10: =I10*(1+($J1)) -> 2064255.7 | K10: =J10*(1+($J1)) -> 2105540.8 | L10: =K10*(1+($J1)) -> 2147651.6 | ... R10: =Q10*(1+($J1)) -> 2418604.6 | S10: =SUM(D10:R10) -> 31698833
A11: TIF Income | C11: 0 | D11: =SUM($C11*D23) -> 0 | E11: =SUM($C11*E23) -> 0 | F11: =SUM($C11*F23) -> 0 | G11: =SUM($C11*G23) -> 0 | H11: =SUM($C11*H23) -> 0 | I11: =SUM($C11*I23) -> 0 | J11: =SUM($C11*J23) -> 0 | K11: =SUM($C11*K23) -> 0 | ... R11: =SUM($C11*R23) -> 0
A12: Other Income | D12: =SUM(D10*$J$4) -> 36660 | E12: =SUM(E10*$J$4) -> 37393.2 | F12: =SUM(F10*$J$4) -> 38141.064 | G12: =SUM(G10*$J$4) -> 38903.885 | H12: =SUM(H10*$J$4) -> 39681.963 | I12: =SUM(I10*$J$4) -> 40475.602 | J12: =SUM(J10*$J$4) -> 41285.114 | K12: =SUM(K10*$J$4) -> 42110.817 | ... R12: =SUM(R10*$J$4) -> 48372.091 | S12: =SUM(D12:R12) -> 633976.66
A13: Sutotal Income | D13: =SUM(D10:D12) -> 1869660 | E13: =SUM(E10:E12) -> 1907053.2 | F13: =SUM(F10:F12) -> 1945194.3 | G13: =SUM(G10:G12) -> 1984098.1 | H13: =SUM(H10:H12) -> 2023780.1 | I13: =SUM(I10:I12) -> 2064255.7 | J13: =SUM(J10:J12) -> 2105540.8 | K13: =SUM(K10:K12) -> 2147651.6 | ... S13: =SUM(S10:S12) -> 32332810
A14: Less Vacancy | D14: =SUM(D13*$J$3)*-1 -> -130876.2 | E14: =SUM(E13*$J$3)*-1 -> -133493.72 | F14: =SUM(F13*$J$3)*-1 -> -136163.6 | G14: =SUM(G13*$J$3)*-1 -> -138886.87 | H14: =SUM(H13*$J$3)*-1 -> -141664.61 | I14: =SUM(I13*$J$3)*-1 -> -144497.9 | J14: =SUM(J13*$J$3)*-1 -> -147387.86 | K14: =SUM(K13*$J$3)*-1 -> -150335.62 | ... R14: =SUM(R13*$J$3)*-1 -> -172688.37 | S14: =SUM(D14:R14) -> -2263296.7
A16: Total Income | D16: =SUM(D13:D15) -> 1738783.8 | E16: =SUM(E13:E15) -> 1773559.5 | F16: =SUM(F13:F15) -> 1809030.7 | G16: =SUM(G13:G15) -> 1845211.3 | H16: =SUM(H13:H15) -> 1882115.5 | I16: =SUM(I13:I15) -> 1919757.8 | J16: =SUM(J13:J15) -> 1958153 | K16: =SUM(K13:K15) -> 1997316 | ... R16: =SUM(R13:R15) -> 2294288.3 | S16: =SUM(S10:S14) -> 62402323
A19: Expenses
A20: Administrative | D20: =SUM(H47*$D$53) -> 70848 | E20: =D20*(1+($J2)) -> 72973.44 | F20: =E20*(1+($J2)) -> 75162.643 | G20: =F20*(1+($J2)) -> 77417.522 | H20: =G20*(1+($J2)) -> 79740.048 | I20: =H20*(1+($J2)) -> 82132.25 | J20: =I20*(1+($J2)) -> 84596.217 | K20: =J20*(1+($J2)) -> 87134.104 | L20: =K20*(1+($J2)) -> 89748.127 | ... R20: =Q20*(1+($J2)) -> 107163.96 | S20: =SUM(D20:R20) -> 1317695.9
A21: Operating | D21: =SUM(H48*$D$53) -> 82656 | E21: =D21*(1+($J2)) -> 85135.68 | F21: =E21*(1+($J2)) -> 87689.75 | G21: =F21*(1+($J2)) -> 90320.443 | H21: =G21*(1+($J2)) -> 93030.056 | I21: =H21*(1+($J2)) -> 95820.958 | J21: =I21*(1+($J2)) -> 98695.587 | K21: =J21*(1+($J2)) -> 101656.45 | L21: =K21*(1+($J2)) -> 104706.15 | ... R21: =Q21*(1+($J2)) -> 125024.62 | S21: =SUM(D21:R21) -> 1537311.8
A22: Maintenance | D22: =SUM(H49*$D$53) -> 41328 | E22: =D22*(1+($J2)) -> 42567.84 | F22: =E22*(1+($J2)) -> 43844.875 | G22: =F22*(1+($J2)) -> 45160.221 | H22: =G22*(1+($J2)) -> 46515.028 | I22: =H22*(1+($J2)) -> 47910.479 | J22: =I22*(1+($J2)) -> 49347.793 | K22: =J22*(1+($J2)) -> 50828.227 | L22: =K22*(1+($J2)) -> 52353.074 | ... R22: =Q22*(1+($J2)) -> 62512.308 | S22: =SUM(D22:R22) -> 768655.91
A23: Property Tax | D23: =SUM(H50*$D$53) -> 35424 | E23: =D23*(1+($J2)) -> 36486.72 | F23: =E23*(1+($J2)) -> 37581.322 | G23: =F23*(1+($J2)) -> 38708.761 | H23: =G23*(1+($J2)) -> 39870.024 | I23: =H23*(1+($J2)) -> 41066.125 | J23: =I23*(1+($J2)) -> 42298.109 | K23: =J23*(1+($J2)) -> 43567.052 | L23: =K23*(1+($J2)) -> 44874.063 | ... R23: =Q23*(1+($J2)) -> 53581.978 | S23: =SUM(D23:R23) -> 658847.93
A24: Insurance | D24: =SUM(H51*$D$53) -> 59040 | E24: =D24*(1+($J2)) -> 60811.2 | F24: =E24*(1+($J2)) -> 62635.536 | G24: =F24*(1+($J2)) -> 64514.602 | H24: =G24*(1+($J2)) -> 66450.04 | I24: =H24*(1+($J2)) -> 68443.541 | J24: =I24*(1+($J2)) -> 70496.848 | K24: =J24*(1+($J2)) -> 72611.753 | L24: =K24*(1+($J2)) -> 74790.106 | ... R24: =Q24*(1+($J2)) -> 89303.297 | S24: =SUM(D24:R24) -> 1098079.9
A25: Replacements | D25: =SUM(D51*Rent!C44) -> 21600 | E25: =D25*(1+($J2)) -> 22248 | F25: =E25*(1+($J2)) -> 22915.44 | G25: =F25*(1+($J2)) -> 23602.903 | H25: =G25*(1+($J2)) -> 24310.99 | I25: =H25*(1+($J2)) -> 25040.32 | J25: =I25*(1+($J2)) -> 25791.53 | K25: =J25*(1+($J2)) -> 26565.275 | L25: =K25*(1+($J2)) -> 27362.234 | ... R25: =Q25*(1+($J2)) -> 32671.938 | S25: =SUM(D25:R25) -> 401736.54
A26: Miscellaneous (Supportive Services) | D26: =SUM(H53*$D$53) -> 5904 | E26: =D26*(1+($J2)) -> 6081.12 | F26: =E26*(1+($J2)) -> 6263.5536 | G26: =F26*(1+($J2)) -> 6451.4602 | H26: =G26*(1+($J2)) -> 6645.004 | I26: =H26*(1+($J2)) -> 6844.3541 | J26: =I26*(1+($J2)) -> 7049.6848 | K26: =J26*(1+($J2)) -> 7261.1753 | L26: =K26*(1+($J2)) -> 7479.0106 | ... R26: =Q26*(1+($J2)) -> 8930.3297 | S26: =SUM(D26:R26) -> 109807.99
A28: TOTAL EXPENSES | D28: =SUM(D20:D26) -> 316800 | E28: =SUM(E20:E26) -> 326304 | F28: =SUM(F20:F26) -> 336093.12 | G28: =SUM(G20:G26) -> 346175.91 | H28: =SUM(H20:H26) -> 356561.19 | I28: =SUM(I20:I26) -> 367258.03 | J28: =SUM(J20:J26) -> 378275.77 | K28: =SUM(K20:K26) -> 389624.04 | ... R28: =SUM(R20:R26) -> 479188.42 | S28: =SUM(D28:R28) -> 5892135.9
A30: NET OPERATING INCOME | D30: =D16-D28 -> 1421983.8 | E30: =E16-E28 -> 1447255.5 | F30: =F16-F28 -> 1472937.5 | G30: =G16-G28 -> 1499035.4 | H30: =H16-H28 -> 1525554.3 | I30: =I16-I28 -> 1552499.8 | J30: =J16-J28 -> 1579877.2 | K30: =K16-K28 -> 1607692 | ... R30: =R16-R28 -> 1815099.9 | S30: =SUM(D30:R30) -> 24177377
A31: Less Debt Service - 1st Mort. | D31: =+#REF! -> #REF! | E31: =+D31 -> #REF! | F31: =+E31 -> #REF! | G31: =+F31 -> #REF! | H31: =+G31 -> #REF! | I31: =+H31 -> #REF! | J31: =+I31 -> #REF! | K31: =+J31 -> #REF! | L31: =+K31 -> #REF! | ... R31: =+Q31 -> #REF! | S31: =SUM(D31:R31) -> #REF!
A32: Less Debt Service - H.O.M.E. | D32: =+'Interest Calculation'!G6 -> 0 | E32: =+D32 -> 0 | F32: =+E32 -> 0 | G32: =+F32 -> 0 | H32: =+G32 -> 0 | I32: =+H32 -> 0 | J32: =+I32 -> 0 | K32: =+J32 -> 0 | L32: =+K32 -> 0 | ... R32: =+Q32 -> 0 | S32: =SUM(D32:R32) -> 0
A34: NET CASH FLOW AFTER DT. SERV. | D34: =D30-D31 -> #REF! | E34: =E30-E31 -> #REF! | F34: =F30-F31 -> #REF! | G34: =G30-G31 -> #REF! | H34: =H30-H31 -> #REF! | I34: =I30-I31 -> #REF! | J34: =J30-J31 -> #REF! | K34: =K30-K31 -> #REF! | ... S34: =S30-S31 -> #REF!
A36: Debt Service Cov. Ratio - 1st | D36: =SUM(D30/D31) -> #REF! | E36: =SUM(E30/E31) -> #REF! | F36: =SUM(F30/F31) -> #REF! | G36: =SUM(G30/G31) -> #REF! | H36: =SUM(H30/H31) -> #REF! | I36: =SUM(I30/I31) -> #REF! | J36: =SUM(J30/J31) -> #REF! | K36: =SUM(K30/K31) -> #REF! | ... R36: =SUM(R30/R31) -> #REF!
A37: Debt Service Cov. Ratio - Combined | D37: =SUM(D30/(D31+D32)) -> #REF! | E37: =SUM(E30/(E31+E32)) -> #REF! | F37: =SUM(F30/(F31+F32)) -> #REF! | G37: =SUM(G30/(G31+G32)) -> #REF! | H37: =SUM(H30/(H31+H32)) -> #REF! | I37: =SUM(I30/(I31+I32)) -> #REF! | J37: =SUM(J30/(J31+J32)) -> #REF! | K37: =SUM(K30/(K31+K32)) -> #REF! | ... R37: =SUM(R30/(R31+R32)) -> #REF!
A39: Cash Flow over 10 Years | D39: =SUM(D34:M34) -> #REF!
A40: Cash Flow Over 15 years | D40: =SUM(D34:R34) -> #REF!
L41: =+L31*1.15 -> #REF! | M41: =+M31*1.15 -> #REF! | N41: =+N31*1.15 -> #REF! | O41: =+O31*1.15 -> #REF! | P41: =+P31*1.15 -> #REF! | Q41: =+Q31*1.15 -> #REF! | R41: =+R31*1.15 -> #REF!
M42: =+M30-M41 -> #REF! | N42: =+N30-N41 -> #REF! | O42: =+O30-O41 -> #REF! | P42: =+P30-P41 -> #REF! | Q42: =+Q30-Q41 -> #REF! | R42: =+R30-R41 -> #REF!
A44: General Information regarding Proforma:
D47: 531000 | F47: Administrative | H47: 0.24
A48: Debt Service 1st Mortgage: | D48: =D31 -> #REF! | F48: Operating | H48: 0.28
A49: Debt Service 2nd Mortgage: | D49: =D32 -> 0 | F49: Maintenance | H49: 0.14
A50: Per Unit Operating Expense Ratio | D50: 4400 | F50: Property Tax | H50: 0.12 | I50: =SUM(D23/Rent!C44) -> 492 | J50: per unit
A51: Replacement Per Unit | D51: 300 | F51: Insurance | H51: 0.2 | I51: =SUM(D24/Rent!C44) -> 820 | J51: per unti
A52: Per Unit Operating Expense Net of Reserve | D52: =SUM(D50-D51) -> 4100 | F52: Replacements
A53: Total Net Operating Expenses | D53: =SUM(D52*Rent!C44) -> 295200 | F53: Miscellaneous | H53: 0.02
H54: =SUM(H47:H53) -> 1
B56: Additional Annual Asset management fee | E56: 5000
B57: Per unit AMF | E57: =+E56/'Sources & Uses'!B77 -> 69.444444

Sheet Utility Allowance
A2: Utility Allowance Worksheet
A7: Utility | E7: Unit Bedroom Size | I7: Utility | J7: Paid
B8: Efficiency | C8: 1BR | D8: 2BR | E8: 3BR | F8: 4BR | G8: 5BR | H8: Other | I8: Type | J8: By:
A10: Heating | B10: 0 | C10: 13 | D10: 15 | E10: 0 | F10: 0 | G10: 0 | I10: e
A11: A/C | B11: 0 | C11: 21 | D11: 27 | E11: 0 | F11: 0 | G11: 0 | I11: e
A12: Cooking | B12: 0 | C12: 7 | D12: 9 | E12: 0 | F12: 0 | G12: 0 | I12: e
A13: Lighting | B13: 0 | C13: 32 | D13: 38 | E13: 0 | F13: 0 | G13: 0 | I13: e
A14: Hot Water | B14: 0 | C14: 16 | D14: 21 | E14: 0 | F14: 0 | G14: 0 | I14: e
A15: Water | C15: 11 | D15: 15 | J15: c
A16: Sewer | C16: 23 | D16: 35 | J16: c
A17: Trash | C17: 20 | D17: 20 | J17: c
A18: Other | J18: c
A19: Total | B19: =SUM(B10:B18) -> 0 | C19: =SUM(C10:C18) -> 143 | D19: =SUM(D10:D18) -> 180 | E19: =SUM(E10:E18) -> 0 | F19: =SUM(F10:F18) -> 0 | G19: =SUM(G10:G18) -> 0 | H19: =SUM(H10:H18) -> 0
A22: Source: | B22: PHA Utility Chart
A23: Date: | B23: 3.17.19 Updated Appl.

Sheet Rent
A1: Rent Calculation
A2: Project Name: | C2: =+'Sources & Uses'!A1 -> Lamar Building
A3: County/Parish | C3: Augusta GA
A4: Is project Rural? | C4: No | D4: **
A6: Income Limits | C6: 2019
A7: H.U.D. Median Income | C7: 73500 | E7: 1 Person | F7: 2 Person | G7: 3 Person | H7: 4 Person | I7: 5 Person | J7: 6 Person
A9: National Poverty Income Guiedlines | E9: 11770 | F9: 15930 | G9: 20090 | H9: 24250 | I9: 28410 | J9: 31800
A11: PSH Unit Rents | D11: (30% M.I.) | E11: =+E15*0.5 -> 15450 | F11: =+F15*0.5 -> 17640 | G11: =+G15*0.5 -> 19860 | H11: =+H15*0.5 -> 20250 | I11: =+I15*0.5 -> 23820 | J11: =+J15*0.5 -> 25590
A13: Very Low Income Per Bedroom Size | D13: (50% M.I.) | E13: 25750 | F13: 29400 | G13: 33100 | H13: 33750 | I13: 39700 | J13: 42650
A15: Low Income Per Bedroom Size | D15: (60% M.I.) | E15: =SUM(E13*1.2) -> 30900 | F15: =SUM(F13*1.2) -> 35280 | G15: =SUM(G13*1.2) -> 39720 | H15: =SUM(H13*1.2) -> 40500 | I15: =SUM(I13*1.2) -> 47640 | J15: =SUM(J13*1.2) -> 51180
E17: 1 Bdrm. | F17: 2 Bdrm. | G17: 3 Bdrm. | H17: 4 Bdrm.
A18: Unity Allowance by Bdrm. Size | E18: =+'Utility Allowance'!C19 -> 143 | F18: =+'Utility Allowance'!D19 -> 180 | G18: =+'Utility Allowance'!E19 -> 0 | H18: =+'Utility Allowance'!F19 -> 0
I19: FM Less
A20: Maximum Allowable L.I.H.C. Rent | D20: (20%) Rent | E20: (30%) Rent | F20: (50%) Rent | G20: (60%) Rent | H20: F.M. Rent | I20: Utility All | J20: 30% Rent
A22: 1 Bedroom Apartment | E22: =SUM((($E$9+F9)/2*0.3)/12)-$E$18 -> 203.25 | F22: =SUM((($E$13+F13)/2*0.3)/12)-$E$18 -> 546.375 | G22: =SUM((($E$15+F15)/2*0.3)/12)-$E$18 -> 684.25 | H22: 827 | I22: =+H22-E18 -> 684 | J22: =SUM(((E9+F9)/2)*0.3)/12-E18 -> 203.25
A24: 2 Bedroom Apartment | E24: =SUM(($G$9*0.3)/12)-$F$18 -> 322.25 | F24: =SUM(($G$13*0.3)/12)-$F$18 -> 647.5 | G24: =SUM(($G$15*0.3)/12)-$F$18 -> 813 | H24: 996 | I24: =+H24-F18 -> 816 | J24: =SUM(G11*0.3)/12-F18 -> 316.5
A26: 3 Bedroom Apartment | E26: =SUM((($H$9+$I9)/2*0.3)/12)-$G$18 -> 658.25 | F26: =SUM((($H$13+$I13)/2*0.3)/12)-$G$18 -> 918.125 | G26: =SUM((($H$15+$I15)/2*0.3)/12)-$G$18 -> 1101.75 | H26: 1277 | I26: =+H26-G18 -> 1277 | J26: =SUM(((H11+I11)/2)*0.3)/12-G18 -> 550.875
A28: 4 Bedroom Apartment | E28: =SUM(($J$9*0.3)/12)-$H$18 -> 795 | F28: =SUM(($J$13*0.3)/12)-$H$18 -> 1066.25 | G28: =SUM(($J$15*0.3)/12)-$H$18 -> 1279.5 | H28: 1477 | I28: =+H28-H18 -> 1477 | J28: =SUM(J11*0.3)/12-H18 -> 639.75
A30: Rent Calculation | S30: (as per Appraisal)
C31: # of Units | F31: Actual Rents | G31: Mo Rent | I31: Ann. Rents | K31: DSC | S31: Less Actual | W31: Sq Foot
A32: 1 Bedroom (50%) | C32: 0 | F32: 0 | G32: =SUM(C32*F32) -> 0 | I32: =G32*12 -> 0 | K32: ='Proforma (Application)'!D79 -> 9359 | Q32: 12
A33: 1 Bedroom (HHM FMR) | C33: 0 | F33: 0 | G33: =SUM(C33*F33) -> 0 | I33: =G33*12 -> 0
C34: 0 | F34: 0 | G34: =SUM(C34*F34) -> 0 | I34: =G34*12 -> 0 | P34: Unit Type | Q34: 12 | R34: Current Rent | S34: Vacancy | T34: X12 Mo | V34: Sq Footage | W34: Per Mo.
C35: 0 | D35: 0 | E35: 0 | G35: =SUM(C35*F35) -> 0 | I35: =G35*12 -> 0 | Q35: 12
A36: 1 Bedroom Market (Lower) | C36: 23 | F36: 1900 | G36: =SUM(C36*F36) -> 43700 | I36: =G36*12 -> 524400
A37: 1 Bedroom Market (Upper) | C37: 21 | E37: 0 | F37: 2100 | G37: =SUM(C37*F37) -> 44100 | I37: =G37*12 -> 529200 | J37: 8th Floor | K37: 1050 | M37: =+K37*C37 -> 22050 | P37: 1BR | Q37: 12 | R37: =((373-153)*12)+(6*526)+(24*626)+(18*652)+(2*652)+(10*652) -> 40380 | S37: =+R37*0.95 -> 38361 | T37: =+S37*12 -> 460332 | V37: =7584+28880+6170 -> 42634 | W37: =+V37/S37 -> 1.1113892
A38: 2 Bedroom Market (Lower) | C38: 15 | E38: 0 | F38: 2250 | G38: =SUM(C38*F38) -> 33750 | I38: =G38*12 -> 405000 | P38: 2BR | Q38: 12 | R38: =((478-174)*42)+(28*(708-174))+(2*882) -> 29484 | S38: =+R38*0.95 -> 28009.8 | T38: =+S38*12 -> 336117.6 | V38: =34440+22176+1584 -> 58200 | W38: =+V38/S38 -> 2.0778442
A39: 2 Bedroom Market (Upper) | C39: 13 | F39: 2400 | G39: =SUM(C39*F39) -> 31200 | I39: =G39*12 -> 374400 | J39: 8th Floor | S39: =+R39*0.95 -> 0 | T39: =+S39*12 -> 0
C40: 0 | G40: =SUM(C40*F40) -> 0 | I40: =G40*12 -> 0 | K40: 1250 | M40: =+K40*C40 -> 0 | P40: 3BR | Q40: 12 | R40: =((888-210)*36)+(4*(888-210)) -> 27120 | S40: =+R40*0.95 -> 25764 | T40: =+S40*12 -> 309168 | V40: =37584+3808 -> 41392 | W40: =+V40/S40 -> 1.6065828
C41: 0 | G41: =SUM(C41*F41) -> 0 | I41: =G41*12 -> 0 | P41: 4BR | Q41: 12 | R41: =((958-221)*9) -> 6633 | S41: =+R41*0.95 -> 6301.35 | T41: =+S41*12 -> 75616.2 | V41: =12490 -> 12490 | W41: =+V41/S41 -> 1.9821149
C42: 0 | G42: =SUM(C42*F42) -> 0 | I42: =G42*12 -> 0
C43: 0 | G43: =SUM(C43*F43) -> 0 | I43: =G43*12 -> 0 | K43: 1350 | M43: =+K43*C43 -> 0 | Q43: 12 | R43: =SUM(R37:R41) -> 103617 | S43: =SUM(S37:S41) -> 98436.15 | T43: =SUM(T37:T41) -> 1181233.8 | V43: =SUM(V37:V41) -> 154716 | W43: =SUM(W37:W41) -> 6.7779311
A44: Totals | C44: =SUM(C32:C43) -> 72 | F44: =SUM(F32:F43) -> 8650 | G44: =SUM(G32:G43) -> 152750 | I44: =SUM(I32:I43) -> 1833000
M45: =SUM(M37:M43) -> 22050
A46: DSC RATIO | C46: =+'Proforma (Application)'!D79 -> 9359 | M46: 85
A47: Total 50% Units | C47: =SUM(C32+C35+C38+C41) -> 15 | E47: Total HHMFMR Units | H47: =+G69 -> 14 | I47: Total 4 Bedroom Units | M47: =+M45*M46 -> 1874250 | N47: =SUM(C41:C43) -> 0
A48: Required Very Low Units | C48: =+E58 -> 2.8 | E48: RequiredHHM FMR Units | H48: =SUM(E57-C47) -> -1 | I48: 4 Bedroom Unit Required | N48: 0
A49: Set Aside Result | C49: =IF(C47>=C48,"TEST MET","SET ASIDE ERROR") -> TEST MET | E49: Set Aside Result | H49: =IF(H47>=H48,"TEST MET","TEST NOT MET") -> TEST MET | N49: =IF(N47>=N48,"TEST MET","TEST NOT MET") -> TEST MET
E50: 0.2 | G50: Required Set Aside | I50: 0.2
A52: HOME Assisted Units:
B54: Total Home Funds | E54: ='Sources & Uses'!V6 -> 0
B55: TDC | E55: =+'Sources & Uses'!I75 -> 24500000
B56: HOME % | E56: =SUM(E54/E55) -> 0
B57: Total HOME Assisted Units | E57: =IF(E56*C44<=H69,H69,E56*C44) -> 14 | F57: 0.2
B58: Total 50% Units | E58: =SUM(F57*E57) -> 2.8
B59: Total Maxed at FMR | E59: =+E57-E58 -> 11.2
A61: Maximum Subsidy Per Unit Test: | E61: =IF('Interest Calculation'!C4<=Rent!J69,"HOME SUBSIDY PER UNIT TEST MET","HOME SUBSIDY PER UNIT TEST NOT MET") -> HOME SUBSIDY PER UNIT TEST NOT MET
D62: Required | E62: Adjusted | F62: Required | G62: Adjusted | H62: Total HOME | I62: 221(D)(3)(ii) | J62: Maximum
C63: TTL Units | D63: LHM Units | E63: LHM Units | F63: HHMFMR Units | G63: HHMFMR Units | H63: Assisted Units | I63: Limits | J63: HOME Funds
A64: 1 | B64: Bedroom | C64: =SUM(C32:C34) -> 0 | D64: =SUM($C64/$C$69)*$E$58 -> 0 | E64: 0 | F64: =SUM($C64/$C$69)*$E$59 -> 0 | G64: 5 | H64: =SUM(E64+G64) -> 5 | I64: 60597 | J64: =SUM(H64*I64) -> 302985
A65: 2 | B65: Bedroom | C65: =SUM(C35:C37) -> 44 | D65: =SUM($C65/$C$69)*$E$58 -> 1.7111111 | E65: 0 | F65: =SUM($C65/$C$69)*$E$59 -> 6.8444444 | G65: 5 | H65: =SUM(E65+G65) -> 5 | I65: 125000 | J65: =SUM(H65*I65) -> 625000
A66: 3 | B66: Bedroom | C66: =SUM(C38:C40) -> 28 | D66: =SUM($C66/$C$69)*$E$58 -> 1.0888889 | E66: 0 | F66: =SUM($C66/$C$69)*$E$59 -> 4.3555556 | G66: 3 | H66: =SUM(E66+G66) -> 3 | I66: 95325 | J66: =SUM(H66*I66) -> 285975
A67: 4 | B67: Bedroom | C67: =SUM(C41:C43) -> 0 | D67: =SUM($C67/$C$69)*$E$58 -> 0 | E67: 0 | F67: =SUM($C67/$C$69)*$E$59 -> 0 | G67: 1 | H67: =SUM(E67+G67) -> 1 | I67: 104638 | J67: =SUM(H67*I67) -> 104638
C69: =SUM(C64:C67) -> 72 | D69: =SUM(D64:D67) -> 2.8 | E69: =SUM(E64:E67) -> 0 | F69: =SUM(F64:F67) -> 11.2 | G69: =SUM(G64:G67) -> 14 | H69: =SUM(H64:H67) -> 14 | J69: =SUM(J64:J67) -> 1318598
C74: =+C35/C44 -> 0
A77: Max 2 Bedrooms | C77: 24
A79: Public Housing Units | C79: =SUM('Modeling Assp Wkst'!N79/'Sources & Uses'!I11)*'Sources & Uses'!E1 -> #DIV/0! | E79: Based on proportion of Cap Funds to TDC
A80: Capital Funds Subsidy per Unit Test
A81: Max Cap Funds Per PH Unit | D81: 158990
A82: Total PH Units | D82: =+C34 -> 0
A83: Max Subsidy - Eligilbe | D83: =+D81*D82 -> 0
A84: Cap Funds (Rounded - Nearest 100k) | D84: =+'Sources & Uses'!V19 -> 1388100
A85: Subsidy Test Result | D85: =IF(D84<=D83,"OK","ERROR") -> ERROR

Sheet Repl.-Reserve
A1: =+'Sources & Uses'!A1 -> Lamar Building
A3: Replacement Reserve Calculation
A5: This number must be the greater of 300/unit or 1% of Replacement costs.
A7: Amount Per Unit | C7: 200 | E7: =SUM(C7*Rent!C44) -> 14400
A9: % of Replacement | C9: 0.01 | E9: =SUM(C9*('Sources & Uses'!F24+'Sources & Uses'!F20+'Sources & Uses'!F25)) -> 154629.27
A12: Total Replacement Reserves | E12: =+E9 -> 154629.27
A14: Total Replacement Reserves/unit | E14: =SUM(E12/Rent!C44) -> 2147.6288

Sheet Cost Estimate
A1: =+'Sources & Uses'!A1 -> Lamar Building
D2: Input | F2: Calculated
C3: Total Costs | D3: Value | F3: Value
A4: Concrete | C4: =SUM(D4*$F$41) -> 1558462.1 | D4: 0.100787 | F4: =+C4/C$41 -> 0.100787
A5: Masonry | C5: =SUM(D5*$F$41) -> 157690.93 | D5: 0.010198
A6: Metals | C6: =SUM(D6*$F$41) -> 145320.59 | D6: 0.009398
A7: Rough Carpentry | C7: =SUM(D7*$F$41) -> 2966949.2 | D7: 0.191875
A8: Finish Carpentry | C8: =SUM(D8*$F$41) -> 1818208.3 | D8: 0.117585
A9: Waterproofing | C9: =SUM(D9*$F$41) -> 0 | D9: 0
A10: Insulation | C10: =SUM(D10*$F$41) -> 310758.45 | D10: 0.020097
A11: Roofing | C11: =SUM(D11*$F$41) -> 338591.72 | D11: 0.021897
A12: Sheet Metal | C12: =SUM(D12*$F$41) -> 123687.96 | D12: 0.007999
A13: Doors | C13: =SUM(D13*$F$41) -> 231943.91 | D13: 0.015
A14: Windows | C14: =SUM(D14*$F$41) -> 299934.4 | D14: 0.019397
A15: Glass | C15: =SUM(D15*$F$41) -> 0 | D15: 0
A16: Drywall | C16: =SUM(D16*$F$41) -> 927775.64 | D16: 0.06
... A36: On-Site Improvements - Fences | C36: =SUM(D36*$F$41) -> 0 | D36: 0
A37: Lawns and Planting | C37: =SUM(D37*$F$41) -> 368558.87 | D37: 0.023835 | E37: Calculated
A38: Unusual On-Site Conditions
A39: Off-Site Development
A40: Miscellaneous (Labor and Materials) | C40: 0
A41: Total Hard Costs | C41: =ROUND(SUM(C4:C40),2) -> 15462927 | D41: =SUM(D4:D39) -> 1 | F41: =+'Sources & Uses'!F24+'Sources & Uses'!F25 -> 15462927
A42: General Requirements | C42: =+'Sources & Uses'!F26 -> 289026.68 | D42: =+C42/C41 -> 0.018691589
A43: General Overhead | C43: =+'Sources & Uses'!F31 -> 221105.41 | D43: =+C43/C41 -> 0.014299065
A44: Contingency
A46: Total Costs | C46: =SUM(C41:C45) -> 15973059
A47: Builders Profit | C47: =+'Sources & Uses'!F30 -> 722566.7 | D47: =+C47/C41 -> 0.046728972
A48: Subtotal | C48: =SUM(C46:C47) -> 16695626
A49: Contingency | C49: 0
A50: Total Contract | C50: =+C48+C49 -> 16695626
A52: Breakdown of General Requirment:
A53: Supervision | C53: =SUM($F$63*D53) -> 179899.59 | D53: =SUM(65000/104429) -> 0.62243247
A54: Field Engineering | C54: =SUM($F$63*D54) -> 17989.959 | D54: =SUM(6500/104429) -> 0.062243247
A55: Field Office | C55: =SUM($F$63*D55) -> 20757.645 | D55: =SUM(7500/104429) -> 0.071819131
A56: Temporary Facilities | C56: =SUM($F$63*D56) -> 12454.587 | D56: =SUM(4500/104429) -> 0.043091478
A57: Temporary Utilities | C57: =SUM($F$63*D57) -> 17989.959 | D57: =SUM(6500/104429) -> 0.062243247
A58: Cleaning Rubbish | C58: =SUM($F$63*D58) -> 13423.277 | D58: =SUM(4850/104429) -> 0.046443038
A59: Builders Risk Ins. | C59: =SUM($F$63*D59) -> 17989.959 | D59: =SUM(6500/104429) -> 0.062243247
A60: Watchmans Wages | C60: =SUM($F$63*D60) -> 5754.0192 | D60: =SUM(2079/104429) -> 0.019908263
A61: Project Signs | C61: =SUM($F$63*D61) -> 2767.686 | D61: =SUM(1000/104429) -> 0.0095758841
A63: Total | C63: =SUM(C53:C61) -> 289026.68 | D63: =SUM(D53:D61) -> 1 | F63: =SUM(+C42) -> 289026.68
E65: Adjusted | F65: Draw # | G65: Draw # | H65: Draw # | I65: Draw # | J65: Draw # | K65: Draw # | L65: Draw # | M65: Draw # | N65: Draw # | O65: Draw # | P65: Draw # | Q65: Draw # | R65: Draw # | S65: Draw # | T65: Draw # | U65: Draw # | V65: Balance to
A66: Cosntruction Schedule of Values - PBC | C66: Total | D66: Adjustments | E66: Total | F66: 1 | G66: 2 | H66: 3 | I66: 4 | J66: 5 | K66: 6 | L66: 7 | M66: 8 | N66: 9 | O66: 10 | P66: 11 | Q66: 12 | R66: 13 | V66: Finish
A69: =+A4 -> Concrete | B69: xx | C69: =+C4 -> 1558462.1 | E69: =SUM(C69:D69) -> 1558462.1 | H69: 180880 | I69: 320400 | J69: 120460 | K69: 67111 | V69: =SUM(E69-F69-G69-I69-J69-H69-K69-L69-M69-N69-R69-O69-P69-Q69) -> 869611.06
A70: =+A5 -> Masonry | B70: x | C70: =+C5 -> 157690.93 | E70: =SUM(C70:D70) -> 157690.93 | M70: 127500 | N70: 119085 | V70: =SUM(E70-F70-G70-I70-J70-H70-K70-L70-M70-N70-R70-O70-P70-Q70) -> -88894.067
A71: =+A6 -> Metals | B71: x | C71: =+C6 -> 145320.59 | E71: =SUM(C71:D71) -> 145320.59 | V71: =SUM(E71-F71-G71-I71-J71-H71-K71-L71-M71-N71-R71-O71-P71-Q71) -> 145320.59
A72: =+A7 -> Rough Carpentry | C72: =+C7 -> 2966949.2 | E72: =SUM(C72:D72) -> 2966949.2 | I72: 191757 | J72: 345600 | L72: 117076 | V72: =SUM(E72-F72-G72-I72-J72-H72-K72-L72-M72-N72-R72-O72-P72-Q72) -> 2312516.2
A73: =+A8 -> Finish Carpentry | B73: xx | C73: =+C8 -> 1818208.3 | E73: =SUM(C73:D73) -> 1818208.3 | M73: 85460 | N73: 20460 | O73: 21460 | P73: 8576 | V73: =SUM(E73-F73-G73-I73-J73-H73-K73-L73-M73-N73-R73-O73-P73-Q73) -> 1682252.3
A74: =+A9 -> Waterproofing | B74: x | C74: =+C9 -> 0 | E74: =SUM(C74:D74) -> 0 | V74: =SUM(E74-F74-G74-I74-J74-H74-K74-L74-M74-N74-R74-O74-P74-Q74) -> 0
A75: =+A10 -> Insulation | B75: x | C75: =+C10 -> 310758.45 | E75: =SUM(C75:D75) -> 310758.45 | L75: 13457 | M75: 34843 | V75: =SUM(E75-F75-G75-I75-J75-H75-K75-L75-M75-N75-R75-O75-P75-Q75) -> 262458.45
A76: =+A11 -> Roofing | B76: xx | C76: =+C11 -> 338591.72 | E76: =SUM(C76:D76) -> 338591.72 | J76: 80400 | K76: 120460 | L76: 62132 | V76: =SUM(E76-F76-G76-I76-J76-H76-K76-L76-M76-N76-R76-O76-P76-Q76) -> 75599.721
A77: =+A12 -> Sheet Metal | C77: =+C12 -> 123687.96 | E77: =SUM(C77:D77) -> 123687.96 | V77: =SUM(E77-F77-G77-I77-J77-H77-K77-L77-M77-N77-R77-O77-P77-Q77) -> 123687.96
A78: =+A13 -> Doors | C78: =+C13 -> 231943.91 | E78: =SUM(C78:D78) -> 231943.91 | V78: =SUM(E78-F78-G78-I78-J78-H78-K78-L78-M78-N78-R78-O78-P78-Q78) -> 231943.91
A79: =+A14 -> Windows | C79: =+C14 -> 299934.4 | E79: =SUM(C79:D79) -> 299934.4 | J79: 59810 | K79: 115152 | V79: =SUM(E79-F79-G79-I79-J79-H79-K79-L79-M79-N79-R79-O79-P79-Q79) -> 124972.4
A80: =+A15 -> Glass | C80: =+C15 -> 0 | E80: =SUM(C80:D80) -> 0 | P80: 12900 | V80: =SUM(E80-F80-G80-I80-J80-H80-K80-L80-M80-N80-R80-O80-P80-Q80) -> -12900
A81: =+A16 -> Drywall | C81: =+C16 -> 927775.64 | E81: =SUM(C81:D81) -> 927775.64 | K81: 140713 | L81: 187500 | V81: =SUM(E81-F81-G81-I81-J81-H81-K81-L81-M81-N81-R81-O81-P81-Q81) -> 599562.64
A82: =+A17 -> Tile Work | C82: =+C17 -> 0 | E82: =SUM(C82:D82) -> 0 | V82: =SUM(E82-F82-G82-I82-J82-H82-K82-L82-M82-N82-R82-O82-P82-Q82) -> 0
A83: =+A18 -> Acoustical | C83: =+C18 -> 0 | E83: =SUM(C83:D83) -> 0 | V83: =SUM(E83-F83-G83-I83-J83-H83-K83-L83-M83-N83-R83-O83-P83-Q83) -> 0
A84: =+A19 -> Resilient Flooring | C84: =+C19 -> 0 | E84: =SUM(C84:D84) -> 0 | N84: 19545 | O84: 114398 | V84: =SUM(E84-F84-G84-I84-J84-H84-K84-L84-M84-N84-R84-O84-P84-Q84) -> -133943
A85: =+A20 -> Painting and Decorating | C85: =+C20 -> 669451.98 | E85: =SUM(C85:D85) -> 669451.98 | N85: 109103 | O85: 152376 | V85: =SUM(E85-F85-G85-I85-J85-H85-K85-L85-M85-N85-R85-O85-P85-Q85) -> 407972.98
A86: =+A21 -> Specialties - Siding | C86: =+C21 -> 0 | E86: =SUM(C86:D86) -> 0 | M86: 98056 | N86: 64742 | V86: =SUM(E86-F86-G86-I86-J86-H86-K86-L86-M86-N86-R86-O86-P86-Q86) -> -162798
A87: =+A22 -> Special Equipment | C87: =+C22 -> 0 | E87: =SUM(C87:D87) -> 0 | V87: =SUM(E87-F87-G87-I87-J87-H87-K87-L87-M87-N87-R87-O87-P87-Q87) -> 0
A88: =+A23 -> Cabinets | C88: =+C23 -> 355600.94 | E88: =SUM(C88:D88) -> 355600.94 | O88: 10395 | P88: 115896 | V88: =SUM(E88-F88-G88-I88-J88-H88-K88-L88-M88-N88-R88-O88-P88-Q88) -> 229309.94
A89: =+A24 -> Appliances | C89: =+C24 -> 315397.33 | E89: =SUM(C89:D89) -> 315397.33 | P89: 37876 | Q89: 54389 | V89: =SUM(E89-F89-G89-I89-J89-H89-K89-L89-M89-N89-R89-O89-P89-Q89) -> 223132.33
A90: =+A25 -> Blinds, Shades, and Artwork | C90: =+C25 -> 92777.564 | E90: =SUM(C90:D90) -> 92777.564 | V90: =SUM(E90-F90-G90-I90-J90-H90-K90-L90-M90-N90-R90-O90-P90-Q90) -> 92777.564
A91: =+A26 -> Carpets | C91: =+C26 -> 432900.11 | E91: =SUM(C91:D91) -> 432900.11 | V91: =SUM(E91-F91-G91-I91-J91-H91-K91-L91-M91-N91-R91-O91-P91-Q91) -> 432900.11
A92: =+A27 -> Special Construction | C92: =+C27 -> 0 | E92: =SUM(C92:D92) -> 0 | V92: =SUM(E92-F92-G92-I92-J92-H92-K92-L92-M92-N92-R92-O92-P92-Q92) -> 0
A93: =+A28 -> Elevators | B93: x | C93: =+C28 -> 0 | E93: =SUM(C93:D93) -> 0 | V93: =SUM(E93-F93-G93-I93-J93-H93-K93-L93-M93-N93-R93-O93-P93-Q93) -> 0
A94: =+A29 -> Plumbing and Hot Water | C94: =+C29 -> 907550.13 | E94: =SUM(C94:D94) -> 907550.13 | H94: 62500 | I94: 62500 | J94: 62500 | K94: 69833 | L94: 32500 | M94: 21250 | N94: 31250 | V94: =SUM(E94-F94-G94-I94-J94-H94-K94-L94-M94-N94-R94-O94-P94-Q94) -> 565217.13
A95: =+A30 -> Heat and Ventilation | C95: =+C30 -> 298388.11 | E95: =SUM(C95:D95) -> 298388.11 | V95: =SUM(E95-F95-G95-I95-J95-H95-K95-L95-M95-N95-R95-O95-P95-Q95) -> 298388.11
A96: =+A31 -> Air Conditioning | C96: =+C31 -> 298388.11 | E96: =SUM(C96:D96) -> 298388.11 | K96: 85460 | L96: 85640 | M96: 57660 | V96: =SUM(E96-F96-G96-I96-J96-H96-K96-L96-M96-N96-R96-O96-P96-Q96) -> 69628.11
A97: =+A32 -> Electrical | C97: =+C32 -> 697285.25 | E97: =SUM(C97:D97) -> 697285.25 | K97: 70041 | L97: 170465 | M97: 120620 | N97: 57824 | V97: =SUM(E97-F97-G97-I97-J97-H97-K97-L97-M97-N97-R97-O97-P97-Q97) -> 278335.25
A98: =+A33 -> Earth Work | C98: 240000 | E98: =SUM(C98:D98) -> 240000 | F98: 120000 | G98: 120000 | V98: =SUM(E98-F98-G98-I98-J98-H98-K98-L98-M98-N98-R98-O98-P98-Q98) -> 0
A99: =+A34 -> On-Site Utilities | C99: =+C34 -> 332452.94 | E99: =SUM(C99:D99) -> 332452.94 | V99: =SUM(E99-F99-G99-I99-J99-H99-K99-L99-M99-N99-R99-O99-P99-Q99) -> 332452.94
A100: =+A35 -> Roads and Walks | B100: x | C100: 630000 | E100: =SUM(C100:D100) -> 630000 | F100: 178629 | G100: 178629 | H100: 178629 | I100: 94113 | V100: =SUM(E100-F100-G100-I100-J100-H100-K100-L100-M100-N100-R100-O100-P100-Q100) -> 0
A101: =+A36 -> On-Site Improvements - Fences | B101: x | C101: =+C36 -> 0 | E101: =SUM(C101:D101) -> 0 | Q101: 56357 | V101: =SUM(E101-F101-G101-I101-J101-H101-K101-L101-M101-N101-R101-O101-P101-Q101) -> -56357
A102: =+A37 -> Lawns and Planting | B102: xx | C102: =+C37 -> 368558.87 | E102: =SUM(C102:D102) -> 368558.87 | Q102: 64500 | V102: =SUM(E102-F102-G102-I102-J102-H102-K102-L102-M102-N102-R102-O102-P102-Q102) -> 304058.87
A103: =+A38 -> Unusual On-Site Conditions | B103: x | C103: =+C38 -> 0 | E103: =SUM(C103:D103) -> 0 | V103: =SUM(E103-F103-G103-I103-J103-H103-K103-L103-M103-N103-R103-O103-P103-Q103) -> 0
A104: =+A39 -> Off-Site Development | C104: =+C39 | E104: =SUM(C104:D104) -> 0 | V104: =SUM(E104-F104-G104-I104-J104-H104-K104-L104-M104-N104-R104-O104-P104-Q104) -> 0
A105: =+A40 -> Miscellaneous (Labor and Materials) | C105: =+C40 -> 0 | E105: =SUM(C105:D105) -> 0 | V105: =SUM(E105-F105-G105-I105-J105-H105-K105-L105-M105-N105-R105-O105-P105-Q105) -> 0
E106: =SUM(C106:D106) -> 0 | V106: =SUM(E106-F106-G106-I106-J106-H106-K106-L106-M106-N106-R106-O106-P106-Q106) -> 0
A107: General Requirement | C107: =+C42 -> 289026.68 | E107: =SUM(C107:D107) -> 289026.68 | F107: =+$E$107/12 -> 24085.557 | G107: =+$E$107/12 -> 24085.557 | H107: =+$E$107/12 -> 24085.557 | I107: =+$E$107/12 -> 24085.557 | J107: =+$E$107/12 -> 24085.557 | K107: =+$E$107/12 -> 24085.557 | L107: =+$E$107/12 -> 24085.557 | M107: =+$E$107/12 -> 24085.557 | ... Q107: =+$E$107/12 -> 24085.557 | V107: =SUM(E107-F107-G107-I107-J107-H107-K107-L107-M107-N107-R107-O107-P107-Q107) -> -2.1827873e-11
A108: Profit | C108: =+C47 -> 722566.7 | E108: =SUM(C108:D108) -> 722566.7 | F108: =+$E108/12 -> 60213.892 | G108: =+$E108/12 -> 60213.892 | H108: =+$E108/12 -> 60213.892 | I108: =+$E108/12 -> 60213.892 | J108: =+$E108/12 -> 60213.892 | K108: =+$E108/12 -> 60213.892 | L108: =+$E108/12 -> 60213.892 | M108: =+$E108/12 -> 60213.892 | ... Q108: =+$E108/12 -> 60213.892 | V108: =SUM(E108-F108-G108-I108-J108-H108-K108-L108-M108-N108-R108-O108-P108-Q108) -> -7.2759576e-11
A109: Overhead | C109: =+C43 -> 221105.41 | E109: =SUM(C109:D109) -> 221105.41 | F109: =+$E$109/12 -> 18425.451 | G109: =+$E$109/12 -> 18425.451 | H109: =+$E$109/12 -> 18425.451 | I109: =+$E$109/12 -> 18425.451 | J109: =+$E$109/12 -> 18425.451 | K109: =+$E$109/12 -> 18425.451 | L109: =+$E$109/12 -> 18425.451 | M109: =+$E$109/12 -> 18425.451 | ... Q109: =+$E$109/12 -> 18425.451 | V109: =SUM(E109-F109-G109-I109-J109-H109-K109-L109-M109-N109-R109-O109-P109-Q109) -> 5.0931703e-11
A110: Contingency | C110: =+C49 -> 0 | E110: =SUM(C110:D110) -> 0 | F110: =+$E110/12 -> 0 | G110: =+$E110/12 -> 0 | H110: =+$E110/12 -> 0 | I110: =+$E110/12 -> 0 | J110: =+$E110/12 -> 0 | K110: =+$E110/12 -> 0 | L110: =+$E110/12 -> 0 | M110: =+$E110/12 -> 0 | ... Q110: =+$E110/12 -> 0 | V110: =SUM(E110-F110-G110-I110-J110-H110-K110-L110-M110-N110-R110-O110-P110-Q110) -> 0
E111: =SUM(C111:D111) -> 0 | V111: =SUM(E111-F111-G111-I111-J111-H111-K111-L111-M111-N111-R111-O111-P111-Q111) -> 0
A112: Total | C112: =SUM(C68:C111) -> 15750773 | D112: =SUM(D69:D111) -> 0 | E112: =SUM(E69:E111) -> 15750773 | F112: =SUM(F69:F111) -> 401353.9 | G112: =SUM(G69:G111) -> 401353.9 | H112: =SUM(H69:H111) -> 524733.9 | I112: =SUM(I69:I111) -> 771494.9 | J112: =SUM(J69:J111) -> 771494.9 | K112: =SUM(K69:K111) -> 771494.9 | ... R112: =SUM(R69:R111) -> 0 | V112: =SUM(V69:V111) -> 9207206.5
A113: Amount per Amec Total
A114: Variance | C114: =+C112-C113 -> 15750773
C116: Construction Draw Total - Draw Schedule | F116: =+' Draw Schedule'!D10+' Draw Schedule'!D11 -> 867080.04 | G116: =+' Draw Schedule'!D12+' Draw Schedule'!D13 -> 867080.04 | H116: =+' Draw Schedule'!D14 -> 722566.7 | I116: =+' Draw Schedule'!D15 -> 1011593.4 | J116: =+' Draw Schedule'!D16 -> 1156106.7 | K116: =+' Draw Schedule'!D17 -> 1300620.1 | L116: =+' Draw Schedule'!D18 -> 1300620.1 | M116: =+' Draw Schedule'!D19 -> 1156106.7 | N116: =+' Draw Schedule'!D20 -> 1156106.7 | O116: =+' Draw Schedule'!D21 -> 1011593.4 | P116: =+' Draw Schedule'!D22 -> 1011593.4 | Q116: =+' Draw Schedule'!D23 -> 867080.04
C117: Variance to Draw | F117: =SUM(F116-F112) -> 465726.14 | G117: =SUM(G116-G112) -> 465726.14 | H117: =SUM(H116-H112) -> 197832.8 | I117: =SUM(I116-I112) -> 240098.48 | J117: =SUM(J116-J112) -> 384611.82 | K117: =SUM(K116-K112) -> 529125.16 | L117: =SUM(L116-L112) -> 529125.16 | M117: =SUM(M116-M112) -> 507992.82 | ... Q117: =SUM(Q116-Q112) -> 589109.14 | R117: =SUM(F116:R116)-E112 -> -3322626.1
C118: Amount - AMEC | F118: 370141 | G118: 370141 | H118: 493521 | I118: 740282 | J118: 740282 | K118: 740282 | L118: 740282 | M118: 616901 | N118: 493521
A119: Category Grouping Schedule: | F119: =+F112-F118 -> 31212.899 | G119: =+G112-G118 -> 31212.899 | H119: =+H112-H118 -> 31212.899 | I119: =+I112-I118 -> 31212.899 | J119: =+J112-J118 -> 31212.899 | K119: =+K112-K118 -> 31212.899 | L119: =+L112-L118 -> 31212.899 | M119: =+M112-M118 -> 31212.899 | ... R119: =+R112-R118 -> 0
A121: Woods & Plastics | B121: xx | C121: 762424
A123: Rough Carpentry | B123: x | C123: -562424 | G123: =+G73 -> 0 | I123: =+I73 -> 0 | J123: 2067
A124: Roofing | B124: x | C124: -200000 | J124: 200000
C125: =SUM(C121:C124) -> 0
A127: Finishes | B127: xx | C127: =+C76 -> 338591.72
A128: Risilient Flooring | B128: x | C128: -73400 | N128: 73400
A129: Finish Carpentry | B129: x | C129: -216224 | L129: =+L76 -> 62132 | M129: 101333
...

Sheet Cost by Building
A1: =+'Sources & Uses'!A1 -> Lamar Building
A2: Schedule of Rehab Costs by Building
A6: =+A1 -> Lamar Building
V7: ***
H8: Bedroom | J8: Square | L8: Approximate | N8: Allocated | P8: Allocated Bldg | R8: Allocated Rehab | T8: Allocated | V8: Allocated
B9: Site | D9: Address | F9: Census Tract | H9: Size | J9: Footage | L9: Lot Size | N9: Land Cost | P9: Acquisition Cost | R9: Costs | T9: Hard Costs | V9: Eligible Basis
B10: =+'Sq Footage'!B9 -> Westside | D10: 159 & 161 & 163 Maurice Drive, Leesville, LA | F10: 9504 | H10: =+'Sq Footage'!C9 -> 3-1BR | J10: =+'Sq Footage'!L9 -> 1896 | L10: 115*65 | N10: =SUM($J10/$J$100)*N$100 -> 0 | P10: =SUM($J10/$J$100)*P$100 -> 0 | R10: =SUM($J10/$J$100)*R$100 -> 300240.44 | T10: =SUM($J10/$J$100)*T$100 -> 177096.93 | V10: =SUM($J10/$J$100)*V$100 -> 275821.44
B11: =+'Sq Footage'!B10 -> Westside | D11: 133 & 135 & 137 George Avenue, Leesville, LA | F11: 9504 | H11: =+'Sq Footage'!C10 -> 3-1BR | J11: =+'Sq Footage'!L10 -> 1896 | L11: 115*65 | N11: =SUM($J11/$J$100)*N$100 -> 0 | P11: =SUM($J11/$J$100)*P$100 -> 0 | R11: =SUM($J11/$J$100)*R$100 -> 300240.44 | T11: =SUM(J11/J$100)*T$100 -> 177096.93 | V11: =SUM($J11/$J$100)*V$100 -> 275821.44
B12: =+'Sq Footage'!B11 -> Westside | D12: 130 & 132 & 134 George Avenue, Leesville, LA | F12: 9504 | H12: =+'Sq Footage'!C11 -> 3-1BR | J12: =+'Sq Footage'!L11 -> 1896 | L12: 115*65 | N12: =SUM($J12/$J$100)*N$100 -> 0 | P12: =SUM($J12/$J$100)*P$100 -> 0 | R12: =SUM($J12/$J$100)*R$100 -> 300240.44 | T12: =SUM(J12/J$100)*T$100 -> 177096.93 | V12: =SUM($J12/$J$100)*V$100 -> 275821.44
B13: =+'Sq Footage'!B12 -> Westside | D13: 120 & 122 & 124 Maurice Drive, Leesville, LA | F13: 9504 | H13: =+'Sq Footage'!C12 -> 3-1BR | J13: =+'Sq Footage'!L12 -> 1896 | L13: 115*65 | N13: =SUM($J13/$J$100)*N$100 -> 0 | P13: =SUM($J13/$J$100)*P$100 -> 0 | R13: =SUM($J13/$J$100)*R$100 -> 300240.44 | T13: =SUM(J13/J$100)*T$100 -> 177096.93 | V13: =SUM($J13/$J$100)*V$100 -> 275821.44
B14: =+'Sq Footage'!B13 -> Westside | D14: 209 Pollard & 211 Blackburn, Leesville, LA | F14: 9504 | H14: =+'Sq Footage'!C13 -> 2-2BR | J14: =+'Sq Footage'!L13 -> 1640 | L14: 115*65 | N14: =SUM($J14/$J$100)*N$100 -> 0 | P14: =SUM($J14/$J$100)*P$100 -> 0 | R14: =SUM($J14/$J$100)*R$100 -> 259701.65 | T14: =SUM(J14/J$100)*T$100 -> 153185.11 | V14: =SUM($J14/$J$100)*V$100 -> 238579.73
B15: =+'Sq Footage'!B14 -> Westside | D15: 180 Pollard & 182 Blackburn, Leesville, LA | F15: 9504 | H15: =+'Sq Footage'!C14 -> 2-2BR | J15: =+'Sq Footage'!L14 -> 1640 | L15: 115*65 | N15: =SUM($J15/$J$100)*N$100 -> 0 | P15: =SUM($J15/$J$100)*P$100 -> 0 | R15: =SUM($J15/$J$100)*R$100 -> 259701.65 | T15: =SUM(J15/J$100)*T$100 -> 153185.11 | V15: =SUM($J15/$J$100)*V$100 -> 238579.73
B16: =+'Sq Footage'!B15 -> Westside | D16: 176 & 178 Pollard Avenue, Leesville, LA | F16: 9504 | H16: =+'Sq Footage'!C15 -> 2-2BR | J16: =+'Sq Footage'!L15 -> 1640 | L16: 115*65 | N16: =SUM($J16/$J$100)*N$100 -> 0 | P16: =SUM($J16/$J$100)*P$100 -> 0 | R16: =SUM($J16/$J$100)*R$100 -> 259701.65 | T16: =SUM(J16/J$100)*T$100 -> 153185.11 | V16: =SUM($J16/$J$100)*V$100 -> 238579.73
B17: =+'Sq Footage'!B16 -> Westside | D17: 203 & 205 Pollard Avenue, Leesville, LA | F17: 9504 | H17: =+'Sq Footage'!C16 -> 2-2BR | J17: =+'Sq Footage'!L16 -> 1640 | L17: 115*65 | N17: =SUM($J17/$J$100)*N$100 -> 0 | P17: =SUM($J17/$J$100)*P$100 -> 0 | R17: =SUM($J17/$J$100)*R$100 -> 259701.65 | T17: =SUM(J17/J$100)*T$100 -> 153185.11 | V17: =SUM($J17/$J$100)*V$100 -> 238579.73
B18: =+'Sq Footage'!B17 -> Westside | D18: 197 George & 197 Pollard, Leesville, LA | F18: 9504 | H18: =+'Sq Footage'!C17 -> 2-2BR | J18: =+'Sq Footage'!L17 -> 1640 | L18: 115*65 | N18: =SUM($J18/$J$100)*N$100 -> 0 | P18: =SUM($J18/$J$100)*P$100 -> 0 | R18: =SUM($J18/$J$100)*R$100 -> 259701.65 | T18: =SUM(J18/J$100)*T$100 -> 153185.11 | V18: =SUM($J18/$J$100)*V$100 -> 238579.73
B19: =+'Sq Footage'!B18 -> Westside | D19: 170 George & 172 Pollard, Leesville, LA | F19: 9504 | H19: =+'Sq Footage'!C18 -> 2-2BR | J19: =+'Sq Footage'!L18 -> 1640 | L19: 115*65 | N19: =SUM($J19/$J$100)*N$100 -> 0 | P19: =SUM($J19/$J$100)*P$100 -> 0 | R19: =SUM($J19/$J$100)*R$100 -> 259701.65 | T19: =SUM(J19/J$100)*T$100 -> 153185.11 | V19: =SUM($J19/$J$100)*V$100 -> 238579.73
B20: =+'Sq Footage'!B19 -> Westside | D20: 191 & 193 Pollard Avenue, Leesville, LA | F20: 9504 | H20: =+'Sq Footage'!C19 -> 2-2BR | J20: =+'Sq Footage'!L19 -> 1640 | L20: 115*65 | N20: =SUM($J20/$J$100)*N$100 -> 0 | P20: =SUM($J20/$J$100)*P$100 -> 0 | R20: =SUM($J20/$J$100)*R$100 -> 259701.65 | T20: =SUM(J20/J$100)*T$100 -> 153185.11 | V20: =SUM($J20/$J$100)*V$100 -> 238579.73
B21: =+'Sq Footage'!B20 -> Westside | D21: 185 & 187 Pollard Avenue, Leesville, LA | F21: 9504 | H21: =+'Sq Footage'!C20 -> 2-2BR | J21: =+'Sq Footage'!L20 -> 1640 | L21: 115*65 | N21: =SUM($J21/$J$100)*N$100 -> 0 | P21: =SUM($J21/$J$100)*P$100 -> 0 | R21: =SUM($J21/$J$100)*R$100 -> 259701.65 | T21: =SUM(J21/J$100)*T$100 -> 153185.11 | V21: =SUM($J21/$J$100)*V$100 -> 238579.73
B22: =+'Sq Footage'!B21 -> Westside | D22: 173 & 175 George Avenue, Leesville, LA | F22: 9504 | H22: =+'Sq Footage'!C21 -> 2-2BR | J22: =+'Sq Footage'!L21 -> 1640 | L22: 115*65 | N22: =SUM($J22/$J$100)*N$100 -> 0 | P22: =SUM($J22/$J$100)*P$100 -> 0 | R22: =SUM($J22/$J$100)*R$100 -> 259701.65 | T22: =SUM(J22/J$100)*T$100 -> 153185.11 | V22: =SUM($J22/$J$100)*V$100 -> 238579.73
... B98: =+'Sq Footage'!B97 -> Wesley | D98: 714 & 715 Wesley Lane, Leesville, LA | F98: 9504 | H98: =+'Sq Footage'!C97 -> 2-2BR | J98: =+'Sq Footage'!L97 -> 1584 | L98: 115*65 | N98: =SUM($J98/$J$100)*N$100 -> 0 | P98: =SUM($J98/$J$100)*P$100 -> 0 | R98: =SUM($J98/$J$100)*R$100 -> 250833.79 | T98: =SUM(J98/J$100)*T$100 -> 147954.4 | V98: =SUM($J98/$J$100)*V$100 -> 230433.1
J100: =SUM(J10:J99) -> 154716 | N100: =+'Sources & Uses'!H16 -> 0 | P100: =+'Sources & Uses'!H17 -> 0 | R100: =+'Sources & Uses'!I75-'Sources & Uses'!E16 -> 24500000 | T100: =+'Sources & Uses'!E24 -> 14451334 | V100: =+'CR Calculation'!H16 -> 22507379
N104: =SUM(N10:N99) -> 0 | P104: =SUM(P10:P99) -> 0 | R104: =SUM(R10:R99) -> 24500000 | T104: =SUM(T10:T99) -> 14451334 | V104: =SUM(V10:V99) -> 22507379

Sheet Sq Footage
A1: =+'Sources & Uses'!A1 -> Lamar Building
A2: Schedule of Unit Mix by Building and Building Area
D5: One Bedroom | F5: Two Bedroom | H5: Three Bedroom | J5: Four bedroom | N5: Rounded | O5: Construction | P5: Construction
A6: Bldg. | B6: Bldg | C6: Building | D6: No. of | E6: Per Unit | F6: No. of | G6: Per Unit | H6: No. of | I6: Per Unit | J6: No. of | K6: Per Unit | L6: Total | M6: Allocation | N6: Total for | O6: Contract | P6: Contract
A7: Number | B7: Site | C7: Description | D7: Units | E7: Square Ft. | F7: Units | G7: Square Ft. | H7: Units | I7: Square Ft. | J7: Units | K7: Square Ft. | L7: Square Ft. | M7: to Res Bldg | N7: Appl. | O7: Per Unit | P7: Per Sq. Ft.
A9: 1 | B9: Westside | C9: 3-1BR | D9: 3 | E9: 632 | G9: 820 | I9: 1044 | K9: 1249 | L9: =SUM(G9*F9)+(I9*H9)+(K9*J9)+D9*E9 -> 1896 | M9: =+L9/$L$100*0 -> 0 | N9: =+L9+M9 -> 1896 | O9: =SUM(N9/N$100*'Sources & Uses'!E$24) -> 177096.93 | P9: =SUM(O9/N9) -> 93.405556
A10: =+A9+1 -> 2 | B10: Westside | C10: 3-1BR | D10: 3 | E10: =+E9 -> 632 | G10: =+G9 -> 820 | I10: =+I9 -> 1044 | K10: =+K9 -> 1249 | L10: =SUM(G10*F10)+(I10*H10)+(K10*J10)+D10*E10 -> 1896 | M10: =+L10/$L$100*0 -> 0 | N10: =+L10+M10 -> 1896 | O10: =SUM(N10/N$100*'Sources & Uses'!E$24) -> 177096.93 | P10: =SUM(O10/N10) -> 93.405556
A11: =+A10+1 -> 3 | B11: Westside | C11: 3-1BR | D11: 3 | E11: =+E10 -> 632 | G11: =+G10 -> 820 | I11: =+I10 -> 1044 | K11: =+K10 -> 1249 | L11: =SUM(G11*F11)+(I11*H11)+(K11*J11)+D11*E11 -> 1896 | M11: =+L11/$L$100*0 -> 0 | N11: =+L11+M11 -> 1896 | O11: =SUM(N11/N$100*'Sources & Uses'!E$24) -> 177096.93 | P11: =SUM(O11/N11) -> 93.405556
A12: =+A11+1 -> 4 | B12: Westside | C12: 3-1BR | D12: 3 | E12: =+E11 -> 632 | G12: =+G11 -> 820 | I12: =+I11 -> 1044 | K12: =+K11 -> 1249 | L12: =SUM(G12*F12)+(I12*H12)+(K12*J12)+D12*E12 -> 1896 | M12: =+L12/$L$100*0 -> 0 | N12: =+L12+M12 -> 1896 | O12: =SUM(N12/N$100*'Sources & Uses'!E$24) -> 177096.93 | P12: =SUM(O12/N12) -> 93.405556
A13: =+A12+1 -> 5 | B13: Westside | C13: 2-2BR | E13: =+E12 -> 632 | F13: 2 | G13: 820 | I13: =+I12 -> 1044 | K13: =+K12 -> 1249 | L13: =SUM(G13*F13)+(I13*H13)+(K13*J13)+D13*E13 -> 1640 | M13: =+L13/$L$100*0 -> 0 | N13: =+L13+M13 -> 1640 | O13: =SUM(N13/N$100*'Sources & Uses'!E$24) -> 153185.11 | P13: =SUM(O13/N13) -> 93.405556
A14: =+A13+1 -> 6 | B14: Westside | C14: 2-2BR | E14: =+E13 -> 632 | F14: 2 | G14: =+G13 -> 820 | I14: =+I13 -> 1044 | K14: =+K13 -> 1249 | L14: =SUM(G14*F14)+(I14*H14)+(K14*J14)+D14*E14 -> 1640 | M14: =+L14/$L$100*0 -> 0 | N14: =+L14+M14 -> 1640 | O14: =SUM(N14/N$100*'Sources & Uses'!E$24) -> 153185.11 | P14: =SUM(O14/N14) -> 93.405556
A15: =+A14+1 -> 7 | B15: Westside | C15: 2-2BR | E15: =+E14 -> 632 | F15: 2 | G15: =+G14 -> 820 | I15: =+I14 -> 1044 | K15: =+K14 -> 1249 | L15: =SUM(G15*F15)+(I15*H15)+(K15*J15)+D15*E15 -> 1640 | M15: =+L15/$L$100*0 -> 0 | N15: =+L15+M15 -> 1640 | O15: =SUM(N15/N$100*'Sources & Uses'!E$24) -> 153185.11 | P15: =SUM(O15/N15) -> 93.405556
A16: =+A15+1 -> 8 | B16: Westside | C16: 2-2BR | E16: =+E15 -> 632 | F16: 2 | G16: =+G15 -> 820 | I16: =+I15 -> 1044 | K16: =+K15 -> 1249 | L16: =SUM(G16*F16)+(I16*H16)+(K16*J16)+D16*E16 -> 1640 | M16: =+L16/$L$100*0 -> 0 | N16: =+L16+M16 -> 1640 | O16: =SUM(N16/N$100*'Sources & Uses'!E$24) -> 153185.11 | P16: =SUM(O16/N16) -> 93.405556
A17: =+A16+1 -> 9 | B17: Westside | C17: 2-2BR | E17: =+E16 -> 632 | F17: 2 | G17: =+G16 -> 820 | I17: =+I16 -> 1044 | K17: =+K16 -> 1249 | L17: =SUM(G17*F17)+(I17*H17)+(K17*J17)+D17*E17 -> 1640 | M17: =+L17/$L$100*0 -> 0 | N17: =+L17+M17 -> 1640 | O17: =SUM(N17/N$100*'Sources & Uses'!E$24) -> 153185.11 | P17: =SUM(O17/N17) -> 93.405556
A18: =+A17+1 -> 10 | B18: Westside | C18: 2-2BR | E18: =+E17 -> 632 | F18: 2 | G18: =+G17 -> 820 | I18: =+I17 -> 1044 | K18: =+K17 -> 1249 | L18: =SUM(G18*F18)+(I18*H18)+(K18*J18)+D18*E18 -> 1640 | M18: =+L18/$L$100*0 -> 0 | N18: =+L18+M18 -> 1640 | O18: =SUM(N18/N$100*'Sources & Uses'!E$24) -> 153185.11 | P18: =SUM(O18/N18) -> 93.405556
A19: =+A18+1 -> 11 | B19: Westside | C19: 2-2BR | E19: =+E18 -> 632 | F19: 2 | G19: =+G18 -> 820 | I19: =+I18 -> 1044 | K19: =+K18 -> 1249 | L19: =SUM(G19*F19)+(I19*H19)+(K19*J19)+D19*E19 -> 1640 | M19: =+L19/$L$100*0 -> 0 | N19: =+L19+M19 -> 1640 | O19: =SUM(N19/N$100*'Sources & Uses'!E$24) -> 153185.11 | P19: =SUM(O19/N19) -> 93.405556
A20: =+A19+1 -> 12 | B20: Westside | C20: 2-2BR | E20: =+E19 -> 632 | F20: 2 | G20: =+G19 -> 820 | I20: =+I19 -> 1044 | K20: =+K19 -> 1249 | L20: =SUM(G20*F20)+(I20*H20)+(K20*J20)+D20*E20 -> 1640 | M20: =+L20/$L$100*0 -> 0 | N20: =+L20+M20 -> 1640 | O20: =SUM(N20/N$100*'Sources & Uses'!E$24) -> 153185.11 | P20: =SUM(O20/N20) -> 93.405556
A21: =+A20+1 -> 13 | B21: Westside | C21: 2-2BR | E21: =+E20 -> 632 | F21: 2 | G21: =+G20 -> 820 | I21: =+I20 -> 1044 | K21: =+K20 -> 1249 | L21: =SUM(G21*F21)+(I21*H21)+(K21*J21)+D21*E21 -> 1640 | M21: =+L21/$L$100*0 -> 0 | N21: =+L21+M21 -> 1640 | O21: =SUM(N21/N$100*'Sources & Uses'!E$24) -> 153185.11 | P21: =SUM(O21/N21) -> 93.405556
A22: =+A21+1 -> 14 | B22: Westside | C22: 2-2BR | E22: =+E21 -> 632 | F22: 2 | G22: =+G21 -> 820 | I22: =+I21 -> 1044 | K22: =+K21 -> 1249 | L22: =SUM(G22*F22)+(I22*H22)+(K22*J22)+D22*E22 -> 1640 | M22: =+L22/$L$100*0 -> 0 | N22: =+L22+M22 -> 1640 | O22: =SUM(N22/N$100*'Sources & Uses'!E$24) -> 153185.11 | P22: =SUM(O22/N22) -> 93.405556
A23: =+A22+1 -> 15 | B23: Westside | C23: 2-2BR | E23: =+E22 -> 632 | F23: 2 | G23: =+G22 -> 820 | I23: =+I22 -> 1044 | K23: =+K22 -> 1249 | L23: =SUM(G23*F23)+(I23*H23)+(K23*J23)+D23*E23 -> 1640 | M23: =+L23/$L$100*0 -> 0 | N23: =+L23+M23 -> 1640 | O23: =SUM(N23/N$100*'Sources & Uses'!E$24) -> 153185.11 | P23: =SUM(O23/N23) -> 93.405556
A24: =+A23+1 -> 16 | B24: Westside | C24: 2-2BR | E24: =+E23 -> 632 | F24: 2 | G24: =+G23 -> 820 | I24: =+I23 -> 1044 | K24: =+K23 -> 1249 | L24: =SUM(G24*F24)+(I24*H24)+(K24*J24)+D24*E24 -> 1640 | M24: =+L24/$L$100*0 -> 0 | N24: =+L24+M24 -> 1640 | O24: =SUM(N24/N$100*'Sources & Uses'!E$24) -> 153185.11 | P24: =SUM(O24/N24) -> 93.405556
A25: =+A24+1 -> 17 | B25: Westside | C25: 2-2BR | E25: =+E24 -> 632 | F25: 2 | G25: =+G24 -> 820 | I25: =+I24 -> 1044 | K25: =+K24 -> 1249 | L25: =SUM(G25*F25)+(I25*H25)+(K25*J25)+D25*E25 -> 1640 | M25: =+L25/$L$100*0 -> 0 | N25: =+L25+M25 -> 1640 | O25: =SUM(N25/N$100*'Sources & Uses'!E$24) -> 153185.11 | P25: =SUM(O25/N25) -> 93.405556
... A33: =+A32+1 -> 25 | B33: Westside | C33: 2-2BR | E33: =+E32 -> 632 | F33: 2 | G33: =+G32 -> 820 | I33: =+I32 -> 1044 | K33: =+K32 -> 1249 | L33: =SUM(G33*F33)+(I33*H33)+(K33*J33)+D33*E33 -> 1640 | M33: =+L33/$L$100*0 -> 0 | N33: =+L33+M33 -> 1640 | O33: =SUM(N33/N$100*'Sources & Uses'!E$24) -> 153185.11 | P33: =SUM(O33/N33) -> 93.405556
A34: =+A33+1 -> 26 | B34: Westside | C34: 2-3BR | E34: =+E33 -> 632 | G34: =+G33 -> 820 | H34: 2 | I34: 1044 | K34: =+K33 -> 1249 | L34: =SUM(G34*F34)+(I34*H34)+(K34*J34)+D34*E34 -> 2088 | M34: =+L34/$L$100*0 -> 0 | N34: =+L34+M34 -> 2088 | O34: =SUM(N34/N$100*'Sources & Uses'!E$24) -> 195030.8 | P34: =SUM(O34/N34) -> 93.405556
A35: =+A34+1 -> 27 | B35: Westside | C35: 2-3BR | E35: =+E34 -> 632 | G35: =+G34 -> 820 | H35: 2 | I35: =+I34 -> 1044 | K35: =+K34 -> 1249 | L35: =SUM(G35*F35)+(I35*H35)+(K35*J35)+D35*E35 -> 2088 | M35: =+L35/$L$100*0 -> 0 | N35: =+L35+M35 -> 2088 | O35: =SUM(N35/N$100*'Sources & Uses'!E$24) -> 195030.8 | P35: =SUM(O35/N35) -> 93.405556
A36: =+A35+1 -> 28 | B36: Westside | C36: 2-3BR | E36: =+E35 -> 632 | G36: =+G35 -> 820 | H36: 2 | I36: =+I35 -> 1044 | K36: =+K35 -> 1249 | L36: =SUM(G36*F36)+(I36*H36)+(K36*J36)+D36*E36 -> 2088 | M36: =+L36/$L$100*0 -> 0 | N36: =+L36+M36 -> 2088 | O36: =SUM(N36/N$100*'Sources & Uses'!E$24) -> 195030.8 | P36: =SUM(O36/N36) -> 93.405556
A37: =+A36+1 -> 29 | B37: Westside | C37: 2-3BR | E37: =+E36 -> 632 | G37: =+G36 -> 820 | H37: 2 | I37: =+I36 -> 1044 | K37: =+K36 -> 1249 | L37: =SUM(G37*F37)+(I37*H37)+(K37*J37)+D37*E37 -> 2088 | M37: =+L37/$L$100*0 -> 0 | N37: =+L37+M37 -> 2088 | O37: =SUM(N37/N$100*'Sources & Uses'!E$24) -> 195030.8 | P37: =SUM(O37/N37) -> 93.405556
A38: =+A37+1 -> 30 | B38: Westside | C38: 2-3BR | E38: =+E37 -> 632 | G38: =+G37 -> 820 | H38: 2 | I38: =+I37 -> 1044 | K38: =+K37 -> 1249 | L38: =SUM(G38*F38)+(I38*H38)+(K38*J38)+D38*E38 -> 2088 | M38: =+L38/$L$100*0 -> 0 | N38: =+L38+M38 -> 2088 | O38: =SUM(N38/N$100*'Sources & Uses'!E$24) -> 195030.8 | P38: =SUM(O38/N38) -> 93.405556
A39: =+A38+1 -> 31 | B39: Westside | C39: 2-3BR | E39: =+E38 -> 632 | G39: =+G38 -> 820 | H39: 2 | I39: =+I38 -> 1044 | K39: =+K38 -> 1249 | L39: =SUM(G39*F39)+(I39*H39)+(K39*J39)+D39*E39 -> 2088 | M39: =+L39/$L$100*0 -> 0 | N39: =+L39+M39 -> 2088 | O39: =SUM(N39/N$100*'Sources & Uses'!E$24) -> 195030.8 | P39: =SUM(O39/N39) -> 93.405556
A40: =+A39+1 -> 32 | B40: Westside | C40: 2-3BR | E40: =+E39 -> 632 | G40: =+G39 -> 820 | H40: 2 | I40: =+I39 -> 1044 | K40: =+K39 -> 1249 | L40: =SUM(G40*F40)+(I40*H40)+(K40*J40)+D40*E40 -> 2088 | M40: =+L40/$L$100*0 -> 0 | N40: =+L40+M40 -> 2088 | O40: =SUM(N40/N$100*'Sources & Uses'!E$24) -> 195030.8 | P40: =SUM(O40/N40) -> 93.405556
A41: =+A40+1 -> 33 | B41: Westside | C41: 2-3BR | E41: =+E40 -> 632 | G41: =+G40 -> 820 | H41: 2 | I41: =+I40 -> 1044 | K41: =+K40 -> 1249 | L41: =SUM(G41*F41)+(I41*H41)+(K41*J41)+D41*E41 -> 2088 | M41: =+L41/$L$100*0 -> 0 | N41: =+L41+M41 -> 2088 | O41: =SUM(N41/N$100*'Sources & Uses'!E$24) -> 195030.8 | P41: =SUM(O41/N41) -> 93.405556
A42: =+A41+1 -> 34 | B42: Westside | C42: 2-3BR | E42: =+E41 -> 632 | G42: =+G41 -> 820 | H42: 2 | I42: =+I41 -> 1044 | K42: =+K41 -> 1249 | L42: =SUM(G42*F42)+(I42*H42)+(K42*J42)+D42*E42 -> 2088 | M42: =+L42/$L$100*0 -> 0 | N42: =+L42+M42 -> 2088 | O42: =SUM(N42/N$100*'Sources & Uses'!E$24) -> 195030.8 | P42: =SUM(O42/N42) -> 93.405556
A43: =+A42+1 -> 35 | B43: Westside | C43: 2-3BR | E43: =+E42 -> 632 | G43: =+G42 -> 820 | H43: 2 | I43: =+I42 -> 1044 | K43: =+K42 -> 1249 | L43: =SUM(G43*F43)+(I43*H43)+(K43*J43)+D43*E43 -> 2088 | M43: =+L43/$L$100*0 -> 0 | N43: =+L43+M43 -> 2088 | O43: =SUM(N43/N$100*'Sources & Uses'!E$24) -> 195030.8 | P43: =SUM(O43/N43) -> 93.405556
A44: =+A43+1 -> 36 | B44: Westside | C44: 2-3BR | E44: =+E43 -> 632 | G44: =+G43 -> 820 | H44: 2 | I44: =+I43 -> 1044 | K44: =+K43 -> 1249 | L44: =SUM(G44*F44)+(I44*H44)+(K44*J44)+D44*E44 -> 2088 | M44: =+L44/$L$100*0 -> 0 | N44: =+L44+M44 -> 2088 | O44: =SUM(N44/N$100*'Sources & Uses'!E$24) -> 195030.8 | P44: =SUM(O44/N44) -> 93.405556
A45: =+A44+1 -> 37 | B45: Westside | C45: 2-3BR | E45: =+E44 -> 632 | G45: =+G44 -> 820 | H45: 2 | I45: =+I44 -> 1044 | K45: =+K44 -> 1249 | L45: =SUM(G45*F45)+(I45*H45)+(K45*J45)+D45*E45 -> 2088 | M45: =+L45/$L$100*0 -> 0 | N45: =+L45+M45 -> 2088 | O45: =SUM(N45/N$100*'Sources & Uses'!E$24) -> 195030.8 | P45: =SUM(O45/N45) -> 93.405556
A46: =+A45+1 -> 38 | B46: Westside | C46: 2-3BR | E46: =+E45 -> 632 | G46: =+G45 -> 820 | H46: 2 | I46: =+I45 -> 1044 | K46: =+K45 -> 1249 | L46: =SUM(G46*F46)+(I46*H46)+(K46*J46)+D46*E46 -> 2088 | M46: =+L46/$L$100*0 -> 0 | N46: =+L46+M46 -> 2088 | O46: =SUM(N46/N$100*'Sources & Uses'!E$24) -> 195030.8 | P46: =SUM(O46/N46) -> 93.405556
... A51: =+A50+1 -> 43 | B51: Westside | C51: 2-3BR | E51: =+E50 -> 632 | G51: =+G50 -> 820 | H51: 2 | I51: =+I50 -> 1044 | K51: =+K50 -> 1249 | L51: =SUM(G51*F51)+(I51*H51)+(K51*J51)+D51*E51 -> 2088 | M51: =+L51/$L$100*0 -> 0 | N51: =+L51+M51 -> 2088 | O51: =SUM(N51/N$100*'Sources & Uses'!E$24) -> 195030.8 | P51: =SUM(O51/N51) -> 93.405556
A52: =+A51+1 -> 44 | B52: Westside | C52: 1-4BR | E52: =+E51 -> 632 | G52: =+G51 -> 820 | I52: =+I51 -> 1044 | J52: 1 | K52: =+K51 -> 1249 | L52: =SUM(G52*F52)+(I52*H52)+(K52*J52)+D52*E52 -> 1249 | M52: =+L52/$L$100*0 -> 0 | N52: =+L52+M52 -> 1249 | O52: =SUM(N52/N$100*'Sources & Uses'!E$24) -> 116663.54 | P52: =SUM(O52/N52) -> 93.405556
A53: =+A52+1 -> 45 | B53: Westside | C53: 1-4BR | E53: =+E52 -> 632 | G53: =+G52 -> 820 | I53: =+I52 -> 1044 | J53: 1 | K53: =+K52 -> 1249 | L53: =SUM(G53*F53)+(I53*H53)+(K53*J53)+D53*E53 -> 1249 | M53: =+L53/$L$100*0 -> 0 | N53: =+L53+M53 -> 1249 | O53: =SUM(N53/N$100*'Sources & Uses'!E$24) -> 116663.54 | P53: =SUM(O53/N53) -> 93.405556
A54: =+A53+1 -> 46 | B54: Westside | C54: 1-4BR | E54: =+E53 -> 632 | G54: =+G53 -> 820 | I54: =+I53 -> 1044 | J54: 1 | K54: =+K53 -> 1249 | L54: =SUM(G54*F54)+(I54*H54)+(K54*J54)+D54*E54 -> 1249 | M54: =+L54/$L$100*0 -> 0 | N54: =+L54+M54 -> 1249 | O54: =SUM(N54/N$100*'Sources & Uses'!E$24) -> 116663.54 | P54: =SUM(O54/N54) -> 93.405556
A55: =+A54+1 -> 47 | B55: Westside | C55: 1-4BR | E55: =+E54 -> 632 | G55: =+G54 -> 820 | I55: =+I54 -> 1044 | J55: 1 | K55: =+K54 -> 1249 | L55: =SUM(G55*F55)+(I55*H55)+(K55*J55)+D55*E55 -> 1249 | M55: =+L55/$L$100*0 -> 0 | N55: =+L55+M55 -> 1249 | O55: =SUM(N55/N$100*'Sources & Uses'!E$24) -> 116663.54 | P55: =SUM(O55/N55) -> 93.405556
A56: =+A55+1 -> 48 | B56: Westside | C56: 1-4BR | E56: =+E55 -> 632 | G56: =+G55 -> 820 | I56: =+I55 -> 1044 | J56: 1 | K56: =+K55 -> 1249 | L56: =SUM(G56*F56)+(I56*H56)+(K56*J56)+D56*E56 -> 1249 | M56: =+L56/$L$100*0 -> 0 | N56: =+L56+M56 -> 1249 | O56: =SUM(N56/N$100*'Sources & Uses'!E$24) -> 116663.54 | P56: =SUM(O56/N56) -> 93.405556
A57: =+A56+1 -> 49 | B57: Westside | C57: 1-4BR | E57: =+E56 -> 632 | G57: =+G56 -> 820 | I57: =+I56 -> 1044 | J57: 1 | K57: =+K56 -> 1249 | L57: =SUM(G57*F57)+(I57*H57)+(K57*J57)+D57*E57 -> 1249 | M57: =+L57/$L$100*0 -> 0 | N57: =+L57+M57 -> 1249 | O57: =SUM(N57/N$100*'Sources & Uses'!E$24) -> 116663.54 | P57: =SUM(O57/N57) -> 93.405556
A58: =+A57+1 -> 50 | B58: Westside | C58: 1-4BR | E58: =+E57 -> 632 | G58: =+G57 -> 820 | I58: =+I57 -> 1044 | J58: 1 | K58: =+K57 -> 1249 | L58: =SUM(G58*F58)+(I58*H58)+(K58*J58)+D58*E58 -> 1249 | M58: =+L58/$L$100*0 -> 0 | N58: =+L58+M58 -> 1249 | O58: =SUM(N58/N$100*'Sources & Uses'!E$24) -> 116663.54 | P58: =SUM(O58/N58) -> 93.405556
A59: =+A58+1 -> 51 | B59: Westside | C59: 1-4BR | E59: =+E58 -> 632 | G59: =+G58 -> 820 | I59: =+I58 -> 1044 | J59: 1 | K59: =+K58 -> 1249 | L59: =SUM(G59*F59)+(I59*H59)+(K59*J59)+D59*E59 -> 1249 | M59: =+L59/$L$100*0 -> 0 | N59: =+L59+M59 -> 1249 | O59: =SUM(N59/N$100*'Sources & Uses'!E$24) -> 116663.54 | P59: =SUM(O59/N59) -> 93.405556
A60: =+A59+1 -> 52 | B60: Westside | C60: 1-4BR | E60: =+E59 -> 632 | G60: =+G59 -> 820 | I60: =+I59 -> 1044 | J60: 1 | K60: =+K59 -> 1249 | L60: =SUM(G60*F60)+(I60*H60)+(K60*J60)+D60*E60 -> 1249 | M60: =+L60/$L$100*0 -> 0 | N60: =+L60+M60 -> 1249 | O60: =SUM(N60/N$100*'Sources & Uses'!E$24) -> 116663.54 | P60: =SUM(O60/N60) -> 93.405556
A61: =+A60+1 -> 53 | B61: Westside | C61: 1-4BR | E61: =+E60 -> 632 | G61: =+G60 -> 820 | I61: =+I60 -> 1044 | J61: 1 | K61: =+K60 -> 1249 | L61: =SUM(G61*F61)+(I61*H61)+(K61*J61)+D61*E61 -> 1249 | M61: =+L61/$L$100*0 -> 0 | N61: =+L61+M61 -> 1249 | O61: =SUM(N61/N$100*'Sources & Uses'!E$24) -> 116663.54 | P61: =SUM(O61/N61) -> 93.405556
A62: =+A61+1 -> 54 | B62: Logan | C62: 2-1BR | D62: 2 | E62: 631 | G62: =+G61 -> 820 | I62: =+I61 -> 1044 | K62: =+K61 -> 1249 | L62: =SUM(G62*F62)+(I62*H62)+(K62*J62)+D62*E62 -> 1262 | M62: =+L62/$L$100*0 -> 0 | N62: =+L62+M62 -> 1262 | O62: =SUM(N62/N$100*'Sources & Uses'!E$24) -> 117877.81 | P62: =SUM(O62/N62) -> 93.405556
A63: =+A62+1 -> 55 | B63: Logan | C63: 3-1BR | D63: 3 | E63: =+E62 -> 631 | G63: =+G62 -> 820 | I63: =+I62 -> 1044 | K63: =+K62 -> 1249 | L63: =SUM(G63*F63)+(I63*H63)+(K63*J63)+D63*E63 -> 1893 | M63: =+L63/$L$100*0 -> 0 | N63: =+L63+M63 -> 1893 | O63: =SUM(N63/N$100*'Sources & Uses'!E$24) -> 176816.72 | P63: =SUM(O63/N63) -> 93.405556
A64: =+A63+1 -> 56 | B64: Logan | C64: 3-1BR | D64: 3 | E64: =+E63 -> 631 | G64: =+G63 -> 820 | I64: =+I63 -> 1044 | K64: =+K63 -> 1249 | L64: =SUM(G64*F64)+(I64*H64)+(K64*J64)+D64*E64 -> 1893 | M64: =+L64/$L$100*0 -> 0 | N64: =+L64+M64 -> 1893 | O64: =SUM(N64/N$100*'Sources & Uses'!E$24) -> 176816.72 | P64: =SUM(O64/N64) -> 93.405556
A65: =+A64+1 -> 57 | B65: Logan | C65: 3-1BR | D65: 3 | E65: =+E64 -> 631 | G65: =+G64 -> 820 | I65: =+I64 -> 1044 | K65: =+K64 -> 1249 | L65: =SUM(G65*F65)+(I65*H65)+(K65*J65)+D65*E65 -> 1893 | M65: =+L65/$L$100*0 -> 0 | N65: =+L65+M65 -> 1893 | O65: =SUM(N65/N$100*'Sources & Uses'!E$24) -> 176816.72 | P65: =SUM(O65/N65) -> 93.405556
A66: =+A65+1 -> 58 | B66: Logan | C66: 3-1BR | D66: 3 | E66: =+E65 -> 631 | G66: =+G65 -> 820 | I66: =+I65 -> 1044 | K66: =+K65 -> 1249 | L66: =SUM(G66*F66)+(I66*H66)+(K66*J66)+D66*E66 -> 1893 | M66: =+L66/$L$100*0 -> 0 | N66: =+L66+M66 -> 1893 | O66: =SUM(N66/N$100*'Sources & Uses'!E$24) -> 176816.72 | P66: =SUM(O66/N66) -> 93.405556
A67: =+A66+1 -> 59 | B67: Logan | C67: 3-1BR | D67: 3 | E67: =+E66 -> 631 | G67: =+G66 -> 820 | I67: =+I66 -> 1044 | K67: =+K66 -> 1249 | L67: =SUM(G67*F67)+(I67*H67)+(K67*J67)+D67*E67 -> 1893 | M67: =+L67/$L$100*0 -> 0 | N67: =+L67+M67 -> 1893 | O67: =SUM(N67/N$100*'Sources & Uses'!E$24) -> 176816.72 | P67: =SUM(O67/N67) -> 93.405556
A68: =+A67+1 -> 60 | B68: Logan | C68: 3-1BR | D68: 3 | E68: =+E67 -> 631 | G68: =+G67 -> 820 | I68: =+I67 -> 1044 | K68: =+K67 -> 1249 | L68: =SUM(G68*F68)+(I68*H68)+(K68*J68)+D68*E68 -> 1893 | M68: =+L68/$L$100*0 -> 0 | N68: =+L68+M68 -> 1893 | O68: =SUM(N68/N$100*'Sources & Uses'!E$24) -> 176816.72 | P68: =SUM(O68/N68) -> 93.405556
A69: =+A68+1 -> 61 | B69: Logan | C69: 4-1BR | D69: 4 | E69: 542 | G69: =+G68 -> 820 | I69: =+I68 -> 1044 | K69: =+K68 -> 1249 | L69: =SUM(G69*F69)+(I69*H69)+(K69*J69)+D69*E69 -> 2168 | M69: =+L69/$L$100*0 -> 0 | N69: =+L69+M69 -> 2168 | O69: =SUM(N69/N$100*'Sources & Uses'!E$24) -> 202503.25 | P69: =SUM(O69/N69) -> 93.405556
A70: =+A69+1 -> 62 | B70: Logan | C70: 4-1BR | D70: 4 | E70: =+E69 -> 542 | G70: =+G69 -> 820 | I70: =+I69 -> 1044 | K70: =+K69 -> 1249 | L70: =SUM(G70*F70)+(I70*H70)+(K70*J70)+D70*E70 -> 2168 | M70: =+L70/$L$100*0 -> 0 | N70: =+L70+M70 -> 2168 | O70: =SUM(N70/N$100*'Sources & Uses'!E$24) -> 202503.25 | P70: =SUM(O70/N70) -> 93.405556
A71: =+A70+1 -> 63 | B71: Logan | C71: 4-1BR | D71: 4 | E71: =+E70 -> 542 | G71: =+G70 -> 820 | I71: =+I70 -> 1044 | K71: =+K70 -> 1249 | L71: =SUM(G71*F71)+(I71*H71)+(K71*J71)+D71*E71 -> 2168 | M71: =+L71/$L$100*0 -> 0 | N71: =+L71+M71 -> 2168 | O71: =SUM(N71/N$100*'Sources & Uses'!E$24) -> 202503.25 | P71: =SUM(O71/N71) -> 93.405556
A72: =+A71+1 -> 64 | B72: Logan | C72: 4-1BR | D72: 4 | E72: =+E71 -> 542 | G72: =+G71 -> 820 | I72: =+I71 -> 1044 | K72: =+K71 -> 1249 | L72: =SUM(G72*F72)+(I72*H72)+(K72*J72)+D72*E72 -> 2168 | M72: =+L72/$L$100*0 -> 0 | N72: =+L72+M72 -> 2168 | O72: =SUM(N72/N$100*'Sources & Uses'!E$24) -> 202503.25 | P72: =SUM(O72/N72) -> 93.405556
A73: =+A72+1 -> 65 | B73: Logan | C73: 4-1BR | D73: 4 | E73: =+E72 -> 542 | G73: =+G72 -> 820 | I73: =+I72 -> 1044 | K73: =+K72 -> 1249 | L73: =SUM(G73*F73)+(I73*H73)+(K73*J73)+D73*E73 -> 2168 | M73: =+L73/$L$100*0 -> 0 | N73: =+L73+M73 -> 2168 | O73: =SUM(N73/N$100*'Sources & Uses'!E$24) -> 202503.25 | P73: =SUM(O73/N73) -> 93.405556
A74: =+A73+1 -> 66 | B74: Logan | C74: 4-1BR | D74: 4 | E74: =+E73 -> 542 | G74: =+G73 -> 820 | I74: =+I73 -> 1044 | K74: =+K73 -> 1249 | L74: =SUM(G74*F74)+(I74*H74)+(K74*J74)+D74*E74 -> 2168 | M74: =+L74/$L$100*0 -> 0 | N74: =+L74+M74 -> 2168 | O74: =SUM(N74/N$100*'Sources & Uses'!E$24) -> 202503.25 | P74: =SUM(O74/N74) -> 93.405556
A75: =+A74+1 -> 67 | B75: Logan | C75: 6-1BR | D75: 6 | E75: =+E74 -> 542 | G75: =+G74 -> 820 | I75: =+I74 -> 1044 | K75: =+K74 -> 1249 | L75: =SUM(G75*F75)+(I75*H75)+(K75*J75)+D75*E75 -> 3252 | M75: =+L75/$L$100*0 -> 0 | N75: =+L75+M75 -> 3252 | O75: =SUM(N75/N$100*'Sources & Uses'!E$24) -> 303754.87 | P75: =SUM(O75/N75) -> 93.405556
A76: =+A75+1 -> 68 | B76: Campbell | C76: 2-2BR | E76: =+E75 -> 542 | F76: 2 | G76: 792 | I76: =+I75 -> 1044 | K76: =+K75 -> 1249 | L76: =SUM(G76*F76)+(I76*H76)+(K76*J76)+D76*E76 -> 1584 | M76: =+L76/$L$100*0 -> 0 | N76: =+L76+M76 -> 1584 | O76: =SUM(N76/N$100*'Sources & Uses'!E$24) -> 147954.4 | P76: =SUM(O76/N76) -> 93.405556
A77: =+A76+1 -> 69 | B77: Campbell | C77: 2-2BR | E77: =+E76 -> 542 | F77: 2 | G77: =+G76 -> 792 | I77: =+I76 -> 1044 | K77: =+K76 -> 1249 | L77: =SUM(G77*F77)+(I77*H77)+(K77*J77)+D77*E77 -> 1584 | M77: =+L77/$L$100*0 -> 0 | N77: =+L77+M77 -> 1584 | O77: =SUM(N77/N$100*'Sources & Uses'!E$24) -> 147954.4 | P77: =SUM(O77/N77) -> 93.405556
A78: =+A77+1 -> 70 | B78: Campbell | C78: 2-2BR | E78: =+E77 -> 542 | F78: 2 | G78: =+G77 -> 792 | I78: =+I77 -> 1044 | K78: =+K77 -> 1249 | L78: =SUM(G78*F78)+(I78*H78)+(K78*J78)+D78*E78 -> 1584 | M78: =+L78/$L$100*0 -> 0 | N78: =+L78+M78 -> 1584 | O78: =SUM(N78/N$100*'Sources & Uses'!E$24) -> 147954.4 | P78: =SUM(O78/N78) -> 93.405556
A79: =+A78+1 -> 71 | B79: Campbell | C79: 2-2BR | E79: =+E78 -> 542 | F79: 2 | G79: =+G78 -> 792 | I79: =+I78 -> 1044 | K79: =+K78 -> 1249 | L79: =SUM(G79*F79)+(I79*H79)+(K79*J79)+D79*E79 -> 1584 | M79: =+L79/$L$100*0 -> 0 | N79: =+L79+M79 -> 1584 | O79: =SUM(N79/N$100*'Sources & Uses'!E$24) -> 147954.4 | P79: =SUM(O79/N79) -> 93.405556
A80: =+A79+1 -> 72 | B80: Campbell | C80: 2-2BR | E80: =+E79 -> 542 | F80: 2 | G80: =+G79 -> 792 | I80: =+I79 -> 1044 | K80: =+K79 -> 1249 | L80: =SUM(G80*F80)+(I80*H80)+(K80*J80)+D80*E80 -> 1584 | M80: =+L80/$L$100*0 -> 0 | N80: =+L80+M80 -> 1584 | O80: =SUM(N80/N$100*'Sources & Uses'!E$24) -> 147954.4 | P80: =SUM(O80/N80) -> 93.405556
A81: =+A80+1 -> 73 | B81: Campbell | C81: 2-2BR | E81: =+E80 -> 542 | F81: 2 | G81: =+G80 -> 792 | I81: =+I80 -> 1044 | K81: =+K80 -> 1249 | L81: =SUM(G81*F81)+(I81*H81)+(K81*J81)+D81*E81 -> 1584 | M81: =+L81/$L$100*0 -> 0 | N81: =+L81+M81 -> 1584 | O81: =SUM(N81/N$100*'Sources & Uses'!E$24) -> 147954.4 | P81: =SUM(O81/N81) -> 93.405556
A82: =+A81+1 -> 74 | B82: Campbell | C82: 2-2BR | E82: =+E81 -> 542 | F82: 2 | G82: =+G81 -> 792 | I82: =+I81 -> 1044 | K82: =+K81 -> 1249 | L82: =SUM(G82*F82)+(I82*H82)+(K82*J82)+D82*E82 -> 1584 | M82: =+L82/$L$100*0 -> 0 | N82: =+L82+M82 -> 1584 | O82: =SUM(N82/N$100*'Sources & Uses'!E$24) -> 147954.4 | P82: =SUM(O82/N82) -> 93.405556
A83: =+A82+1 -> 75 | B83: Campbell | C83: 2-2BR | E83: =+E82 -> 542 | F83: 2 | G83: =+G82 -> 792 | I83: =+I82 -> 1044 | K83: =+K82 -> 1249 | L83: =SUM(G83*F83)+(I83*H83)+(K83*J83)+D83*E83 -> 1584 | M83: =+L83/$L$100*0 -> 0 | N83: =+L83+M83 -> 1584 | O83: =SUM(N83/N$100*'Sources & Uses'!E$24) -> 147954.4 | P83: =SUM(O83/N83) -> 93.405556
A84: =+A83+1 -> 76 | B84: Campbell | C84: 2-2BR | E84: =+E83 -> 542 | F84: 2 | G84: =+G83 -> 792 | I84: =+I83 -> 1044 | K84: =+K83 -> 1249 | L84: =SUM(G84*F84)+(I84*H84)+(K84*J84)+D84*E84 -> 1584 | M84: =+L84/$L$100*0 -> 0 | N84: =+L84+M84 -> 1584 | O84: =SUM(N84/N$100*'Sources & Uses'!E$24) -> 147954.4 | P84: =SUM(O84/N84) -> 93.405556
A85: =+A84+1 -> 77 | B85: Campbell | C85: 2-2BR | E85: =+E84 -> 542 | F85: 2 | G85: =+G84 -> 792 | I85: =+I84 -> 1044 | K85: =+K84 -> 1249 | L85: =SUM(G85*F85)+(I85*H85)+(K85*J85)+D85*E85 -> 1584 | M85: =+L85/$L$100*0 -> 0 | N85: =+L85+M85 -> 1584 | O85: =SUM(N85/N$100*'Sources & Uses'!E$24) -> 147954.4 | P85: =SUM(O85/N85) -> 93.405556
A86: =+A85+1 -> 78 | B86: Campbell | C86: 2-2BR | E86: =+E85 -> 542 | F86: 2 | G86: =+G85 -> 792 | I86: =+I85 -> 1044 | K86: =+K85 -> 1249 | L86: =SUM(G86*F86)+(I86*H86)+(K86*J86)+D86*E86 -> 1584 | M86: =+L86/$L$100*0 -> 0 | N86: =+L86+M86 -> 1584 | O86: =SUM(N86/N$100*'Sources & Uses'!E$24) -> 147954.4 | P86: =SUM(O86/N86) -> 93.405556
A87: =+A86+1 -> 79 | B87: Campbell | C87: 2-2BR | E87: =+E86 -> 542 | F87: 2 | G87: =+G86 -> 792 | I87: =+I86 -> 1044 | K87: =+K86 -> 1249 | L87: =SUM(G87*F87)+(I87*H87)+(K87*J87)+D87*E87 -> 1584 | M87: =+L87/$L$100*0 -> 0 | N87: =+L87+M87 -> 1584 | O87: =SUM(N87/N$100*'Sources & Uses'!E$24) -> 147954.4 | P87: =SUM(O87/N87) -> 93.405556
A88: =+A87+1 -> 80 | B88: Campbell | C88: 2-2BR | E88: =+E87 -> 542 | F88: 2 | G88: =+G87 -> 792 | I88: =+I87 -> 1044 | K88: =+K87 -> 1249 | L88: =SUM(G88*F88)+(I88*H88)+(K88*J88)+D88*E88 -> 1584 | M88: =+L88/$L$100*0 -> 0 | N88: =+L88+M88 -> 1584 | O88: =SUM(N88/N$100*'Sources & Uses'!E$24) -> 147954.4 | P88: =SUM(O88/N88) -> 93.405556
A89: =+A88+1 -> 81 | B89: Campbell | C89: 2-2BR | E89: =+E88 -> 542 | F89: 2 | G89: =+G88 -> 792 | I89: =+I88 -> 1044 | K89: =+K88 -> 1249 | L89: =SUM(G89*F89)+(I89*H89)+(K89*J89)+D89*E89 -> 1584 | M89: =+L89/$L$100*0 -> 0 | N89: =+L89+M89 -> 1584 | O89: =SUM(N89/N$100*'Sources & Uses'!E$24) -> 147954.4 | P89: =SUM(O89/N89) -> 93.405556
A90: =+A89+1 -> 82 | B90: Campbell | C90: 2-3BR | E90: =+E89 -> 542 | G90: =+G89 -> 792 | H90: 2 | I90: 952 | K90: =+K89 -> 1249 | L90: =SUM(G90*F90)+(I90*H90)+(K90*J90)+D90*E90 -> 1904 | M90: =+L90/$L$100*0 -> 0 | N90: =+L90+M90 -> 1904 | O90: =SUM(N90/N$100*'Sources & Uses'!E$24) -> 177844.18 | P90: =SUM(O90/N90) -> 93.405556
A91: =+A90+1 -> 83 | B91: Campbell | C91: 2-3BR | E91: =+E90 -> 542 | G91: =+G90 -> 792 | H91: 2 | I91: =+I90 -> 952 | K91: =+K90 -> 1249 | L91: =SUM(G91*F91)+(I91*H91)+(K91*J91)+D91*E91 -> 1904 | M91: =+L91/$L$100*0 -> 0 | N91: =+L91+M91 -> 1904 | O91: =SUM(N91/N$100*'Sources & Uses'!E$24) -> 177844.18 | P91: =SUM(O91/N91) -> 93.405556
A92: =+A91+1 -> 84 | B92: Wesley | C92: 2-1BR | D92: 2 | E92: 617 | G92: =+G91 -> 792 | I92: =+I91 -> 952 | K92: =+K91 -> 1249 | L92: =SUM(G92*F92)+(I92*H92)+(K92*J92)+D92*E92 -> 1234 | M92: =+L92/$L$100*0 -> 0 | N92: =+L92+M92 -> 1234 | O92: =SUM(N92/N$100*'Sources & Uses'!E$24) -> 115262.46 | P92: =SUM(O92/N92) -> 93.405556
A93: =+A92+1 -> 85 | B93: Wesley | C93: 2-1BR | D93: 2 | E93: =+E92 -> 617 | G93: =+G92 -> 792 | I93: =+I92 -> 952 | K93: =+K92 -> 1249 | L93: =SUM(G93*F93)+(I93*H93)+(K93*J93)+D93*E93 -> 1234 | M93: =+L93/$L$100*0 -> 0 | N93: =+L93+M93 -> 1234 | O93: =SUM(N93/N$100*'Sources & Uses'!E$24) -> 115262.46 | P93: =SUM(O93/N93) -> 93.405556
A94: =+A93+1 -> 86 | B94: Wesley | C94: 2-1BR | D94: 2 | E94: =+E93 -> 617 | G94: =+G93 -> 792 | I94: =+I93 -> 952 | K94: =+K93 -> 1249 | L94: =SUM(G94*F94)+(I94*H94)+(K94*J94)+D94*E94 -> 1234 | M94: =+L94/$L$100*0 -> 0 | N94: =+L94+M94 -> 1234 | O94: =SUM(N94/N$100*'Sources & Uses'!E$24) -> 115262.46 | P94: =SUM(O94/N94) -> 93.405556
A95: =+A94+1 -> 87 | B95: Wesley | C95: 2-1BR | D95: 2 | E95: =+E94 -> 617 | G95: =+G94 -> 792 | I95: =+I94 -> 952 | K95: =+K94 -> 1249 | L95: =SUM(G95*F95)+(I95*H95)+(K95*J95)+D95*E95 -> 1234 | M95: =+L95/$L$100*0 -> 0 | N95: =+L95+M95 -> 1234 | O95: =SUM(N95/N$100*'Sources & Uses'!E$24) -> 115262.46 | P95: =SUM(O95/N95) -> 93.405556
A96: =+A95+1 -> 88 | B96: Wesley | C96: 2-1BR | D96: 2 | E96: =+E95 -> 617 | G96: =+G95 -> 792 | I96: =+I95 -> 952 | K96: =+K95 -> 1249 | L96: =SUM(G96*F96)+(I96*H96)+(K96*J96)+D96*E96 -> 1234 | M96: =+L96/$L$100*0 -> 0 | N96: =+L96+M96 -> 1234 | O96: =SUM(N96/N$100*'Sources & Uses'!E$24) -> 115262.46 | P96: =SUM(O96/N96) -> 93.405556
A97: =+A96+1 -> 89 | B97: Wesley | C97: 2-2BR | E97: =+E96 -> 617 | F97: 2 | G97: =+G96 -> 792 | I97: =+I96 -> 952 | K97: =+K96 -> 1249 | L97: =SUM(G97*F97)+(I97*H97)+(K97*J97)+D97*E97 -> 1584 | M97: =+L97/$L$100*0 -> 0 | N97: =+L97+M97 -> 1584 | O97: =SUM(N97/N$100*'Sources & Uses'!E$24) -> 147954.4 | P97: =SUM(O97/N97) -> 93.405556
D100: =SUM(D9:D99) -> 72 | E100: =SUM(E9:E99) -> 54081 | F100: =SUM(F9:F99) -> 72 | G100: =SUM(G9:G99) -> 72364 | H100: =SUM(H9:H99) -> 40 | I100: =SUM(I9:I99) -> 92180 | J100: =SUM(J9:J99) -> 10 | K100: =SUM(K9:K99) -> 111161 | ... O100: =SUM(O9:O99) -> 14451334 | P100: =AVERAGE(P9:P18) -> 93.405556
C102: Total Units | D102: =SUM(D100+F100+H100+J100) -> 194 | L102: 1197 | M102: Community Room | O102: =SUM(L102*P100) -> 111806.45 | Q102: Estimated Cost of Community Facility
L103: =SUM(L100:L102) -> 155913 | O103: =SUM(O100:O102) -> 14563140 | Q103: Total Estimated Contract

Sheet QOC
A1: =+'Sources & Uses'!A1 -> Lamar Building
A2: Qualified Occupancy Summary
A3: Year: | B3: 2007
C4: Completion
C5: Mo.Per Asmp. | D5: Total Units | E5: JAN | F5: FEB | G5: MAR | H5: APR | I5: MAY | J5: JUN | K5: JUL | L5: AUG | M5: SEPT | N5: OCT | O5: NOV | P5: DEC | Q5: TOTAL
A6: =+'1st Year Cr'!A7 -> LA-08-00 | B6: =+'1st Year Cr'!B7 -> 234 | C6: 2 | D6: 1 | E6: 0 | F6: 0 | G6: 1 | H6: 1 | I6: 1 | J6: 1 | K6: 1 | L6: 1 | M6: 1 | N6: 1 | O6: 1 | P6: 1
E7: =SUM(E6/$D6) -> 0 | F7: =SUM(F6/$D6) -> 0 | G7: =SUM(G6/$D6) -> 1 | H7: =SUM(H6/$D6) -> 1 | I7: =SUM(I6/$D6) -> 1 | J7: =SUM(J6/$D6) -> 1 | K7: =SUM(K6/$D6) -> 1 | L7: =SUM(L6/$D6) -> 1 | ... P7: =SUM(P6/$D6) -> 1 | Q7: =SUM(E7:P7)/12 -> 0.83333333
A8: =+'1st Year Cr'!A9 -> LA-08-00 | B8: =+'1st Year Cr'!B9 -> 235 | C8: 2 | D8: 1 | E8: 0 | F8: 0 | G8: 1 | H8: 1 | I8: 0 | J8: 1 | K8: 1 | L8: 1 | M8: 1 | N8: 1 | O8: 1 | P8: 1
E9: =SUM(E8/$D8) -> 0 | F9: =SUM(F8/$D8) -> 0 | G9: =SUM(G8/$D8) -> 1 | H9: =SUM(H8/$D8) -> 1 | I9: =SUM(I8/$D8) -> 0 | J9: =SUM(J8/$D8) -> 1 | K9: =SUM(K8/$D8) -> 1 | L9: =SUM(L8/$D8) -> 1 | ... P9: =SUM(P8/$D8) -> 1 | Q9: =SUM(E9:P9)/12 -> 0.75
A10: =+'1st Year Cr'!A11 -> LA-08-00 | B10: =+'1st Year Cr'!B11 -> 236 | C10: 2 | D10: 1 | E10: 0 | F10: 0 | G10: 1 | H10: 1 | I10: 1 | J10: 1 | K10: 1 | L10: 1 | M10: 1 | N10: 1 | O10: 1 | P10: 1
E11: =SUM(E10/$D10) -> 0 | F11: =SUM(F10/$D10) -> 0 | G11: =SUM(G10/$D10) -> 1 | H11: =SUM(H10/$D10) -> 1 | I11: =SUM(I10/$D10) -> 1 | J11: =SUM(J10/$D10) -> 1 | K11: =SUM(K10/$D10) -> 1 | L11: =SUM(L10/$D10) -> 1 | ... P11: =SUM(P10/$D10) -> 1 | Q11: =SUM(E11:P11)/12 -> 0.83333333
A12: =+'1st Year Cr'!A13 -> LA-08-00 | B12: =+'1st Year Cr'!B13 -> 237 | C12: 2 | D12: 1 | E12: 0 | F12: 0 | G12: 1 | H12: 1 | I12: 1 | J12: 1 | K12: 1 | L12: 1 | M12: 1 | N12: 1 | O12: 1 | P12: 1
E13: =SUM(E12/$D12) -> 0 | F13: =SUM(F12/$D12) -> 0 | G13: =SUM(G12/$D12) -> 1 | H13: =SUM(H12/$D12) -> 1 | I13: =SUM(I12/$D12) -> 1 | J13: =SUM(J12/$D12) -> 1 | K13: =SUM(K12/$D12) -> 1 | L13: =SUM(L12/$D12) -> 1 | ... P13: =SUM(P12/$D12) -> 1 | Q13: =SUM(E13:P13)/12 -> 0.83333333
A14: =+'1st Year Cr'!A15 -> LA-08-00 | B14: =+'1st Year Cr'!B15 -> 238 | C14: 2 | D14: 1 | E14: 0 | F14: 0 | G14: 1 | H14: 1 | I14: 1 | J14: 1 | K14: 1 | L14: 1 | M14: 1 | N14: 1 | O14: 1 | P14: 1
E15: =SUM(E14/$D14) -> 0 | F15: =SUM(F14/$D14) -> 0 | G15: =SUM(G14/$D14) -> 1 | H15: =SUM(H14/$D14) -> 1 | I15: =SUM(I14/$D14) -> 1 | J15: =SUM(J14/$D14) -> 1 | K15: =SUM(K14/$D14) -> 1 | L15: =SUM(L14/$D14) -> 1 | ... P15: =SUM(P14/$D14) -> 1 | Q15: =SUM(E15:P15)/12 -> 0.83333333
A16: =+'1st Year Cr'!A17 -> LA-08-00 | B16: =+'1st Year Cr'!B17 -> 239 | C16: 2 | D16: 1 | E16: 0 | F16: 0 | G16: 1 | H16: 1 | I16: 1 | J16: 1 | K16: 1 | L16: 1 | M16: 1 | N16: 1 | O16: 1 | P16: 1
E17: =SUM(E16/$D16) -> 0 | F17: =SUM(F16/$D16) -> 0 | G17: =SUM(G16/$D16) -> 1 | H17: =SUM(H16/$D16) -> 1 | I17: =SUM(I16/$D16) -> 1 | J17: =SUM(J16/$D16) -> 1 | K17: =SUM(K16/$D16) -> 1 | L17: =SUM(L16/$D16) -> 1 | ... P17: =SUM(P16/$D16) -> 1 | Q17: =SUM(E17:P17)/12 -> 0.83333333
A18: =+'1st Year Cr'!A19 -> LA-08-00 | B18: =+'1st Year Cr'!B19 -> 240 | C18: 2 | D18: 1 | E18: 0 | F18: 0 | G18: 0 | H18: 1 | I18: 1 | J18: 1 | K18: 1 | L18: 1 | M18: 1 | N18: 1 | O18: 1 | P18: 1
E19: =SUM(E18/$D18) -> 0 | F19: =SUM(F18/$D18) -> 0 | G19: =SUM(G18/$D18) -> 0 | H19: =SUM(H18/$D18) -> 1 | I19: =SUM(I18/$D18) -> 1 | J19: =SUM(J18/$D18) -> 1 | K19: =SUM(K18/$D18) -> 1 | L19: =SUM(L18/$D18) -> 1 | ... P19: =SUM(P18/$D18) -> 1 | Q19: =SUM(E19:P19)/12 -> 0.75
A20: =+'1st Year Cr'!A21 -> LA-08-00 | B20: =+'1st Year Cr'!B21 -> 241 | C20: 3 | D20: 1 | E20: 0 | F20: 0 | G20: 0 | H20: 1 | I20: 1 | J20: 1 | K20: 1 | L20: 1 | M20: 1 | N20: 1 | O20: 1 | P20: 1
E21: =SUM(E20/$D20) -> 0 | F21: =SUM(F20/$D20) -> 0 | G21: =SUM(G20/$D20) -> 0 | H21: =SUM(H20/$D20) -> 1 | I21: =SUM(I20/$D20) -> 1 | J21: =SUM(J20/$D20) -> 1 | K21: =SUM(K20/$D20) -> 1 | L21: =SUM(L20/$D20) -> 1 | ... P21: =SUM(P20/$D20) -> 1 | Q21: =SUM(E21:P21)/12 -> 0.75
A22: =+'1st Year Cr'!A23 -> LA-08-00 | B22: =+'1st Year Cr'!B23 -> 242 | C22: 3 | D22: 1 | E22: 0 | F22: 0 | G22: 0 | H22: 1 | I22: 1 | J22: 1 | K22: 1 | L22: 1 | M22: 1 | N22: 1 | O22: 1 | P22: 1
E23: =SUM(E22/$D22) -> 0 | F23: =SUM(F22/$D22) -> 0 | G23: =SUM(G22/$D22) -> 0 | H23: =SUM(H22/$D22) -> 1 | I23: =SUM(I22/$D22) -> 1 | J23: =SUM(J22/$D22) -> 1 | K23: =SUM(K22/$D22) -> 1 | L23: =SUM(L22/$D22) -> 1 | ... P23: =SUM(P22/$D22) -> 1 | Q23: =SUM(E23:P23)/12 -> 0.75
A24: =+'1st Year Cr'!A25 -> LA-08-00 | B24: =+'1st Year Cr'!B25 -> 243 | C24: 3 | D24: 1 | E24: 0 | F24: 0 | G24: 0 | H24: 1 | I24: 1 | J24: 1 | K24: 1 | L24: 1 | M24: 1 | N24: 1 | O24: 1 | P24: 1
E25: =SUM(E24/$D24) -> 0 | F25: =SUM(F24/$D24) -> 0 | G25: =SUM(G24/$D24) -> 0 | H25: =SUM(H24/$D24) -> 1 | I25: =SUM(I24/$D24) -> 1 | J25: =SUM(J24/$D24) -> 1 | K25: =SUM(K24/$D24) -> 1 | L25: =SUM(L24/$D24) -> 1 | ... P25: =SUM(P24/$D24) -> 1 | Q25: =SUM(E25:P25)/12 -> 0.75
A26: =+'1st Year Cr'!A27 -> LA-08-00 | B26: =+'1st Year Cr'!B27 -> 244 | C26: 4 | D26: 1 | E26: 0 | F26: 0 | G26: 0 | H26: 1 | I26: 1 | J26: 1 | K26: 1 | L26: 1 | M26: 1 | N26: 1 | O26: 1 | P26: 1
E27: =SUM(E26/$D26) -> 0 | F27: =SUM(F26/$D26) -> 0 | G27: =SUM(G26/$D26) -> 0 | H27: =SUM(H26/$D26) -> 1 | I27: =SUM(I26/$D26) -> 1 | J27: =SUM(J26/$D26) -> 1 | K27: =SUM(K26/$D26) -> 1 | L27: =SUM(L26/$D26) -> 1 | ... P27: =SUM(P26/$D26) -> 1 | Q27: =SUM(E27:P27)/12 -> 0.75
A28: =+'1st Year Cr'!A29 -> LA-08-00 | B28: =+'1st Year Cr'!B29 -> 245 | C28: 4 | D28: 1 | E28: 0 | F28: 0 | G28: 0 | H28: 1 | I28: 1 | J28: 1 | K28: 1 | L28: 1 | M28: 1 | N28: 1 | O28: 1 | P28: 1
E29: =SUM(E28/$D28) -> 0 | F29: =SUM(F28/$D28) -> 0 | G29: =SUM(G28/$D28) -> 0 | H29: =SUM(H28/$D28) -> 1 | I29: =SUM(I28/$D28) -> 1 | J29: =SUM(J28/$D28) -> 1 | K29: =SUM(K28/$D28) -> 1 | L29: =SUM(L28/$D28) -> 1 | ... P29: =SUM(P28/$D28) -> 1 | Q29: =SUM(E29:P29)/12 -> 0.75
A30: =+'1st Year Cr'!A31 -> LA-08-00 | B30: =+'1st Year Cr'!B31 -> 246 | C30: 4 | D30: 1 | E30: 0 | F30: 0 | G30: 0 | H30: 0 | I30: 1 | J30: 1 | K30: 1 | L30: 1 | M30: 1 | N30: 1 | O30: 1 | P30: 1
E31: =SUM(E30/$D30) -> 0 | F31: =SUM(F30/$D30) -> 0 | G31: =SUM(G30/$D30) -> 0 | H31: =SUM(H30/$D30) -> 0 | I31: =SUM(I30/$D30) -> 1 | J31: =SUM(J30/$D30) -> 1 | K31: =SUM(K30/$D30) -> 1 | L31: =SUM(L30/$D30) -> 1 | ... P31: =SUM(P30/$D30) -> 1 | Q31: =SUM(E31:P31)/12 -> 0.66666667
A32: =+'1st Year Cr'!A33 -> LA-08-00 | B32: =+'1st Year Cr'!B33 -> 247 | C32: 4 | D32: 1 | E32: 0 | F32: 0 | G32: 0 | H32: 0 | I32: 1 | J32: 1 | K32: 1 | L32: 1 | M32: 1 | N32: 1 | O32: 1 | P32: 1
E33: =SUM(E32/$D32) -> 0 | F33: =SUM(F32/$D32) -> 0 | G33: =SUM(G32/$D32) -> 0 | H33: =SUM(H32/$D32) -> 0 | I33: =SUM(I32/$D32) -> 1 | J33: =SUM(J32/$D32) -> 1 | K33: =SUM(K32/$D32) -> 1 | L33: =SUM(L32/$D32) -> 1 | ... P33: =SUM(P32/$D32) -> 1 | Q33: =SUM(E33:P33)/12 -> 0.66666667
A34: =+'1st Year Cr'!A35 -> LA-08-00 | B34: =+'1st Year Cr'!B35 -> 248 | C34: 4 | D34: 1 | E34: 0 | F34: 0 | G34: 0 | H34: 0 | I34: 1 | J34: 1 | K34: 1 | L34: 1 | M34: 1 | N34: 1 | O34: 1 | P34: 1
E35: =SUM(E34/$D34) -> 0 | F35: =SUM(F34/$D34) -> 0 | G35: =SUM(G34/$D34) -> 0 | H35: =SUM(H34/$D34) -> 0 | I35: =SUM(I34/$D34) -> 1 | J35: =SUM(J34/$D34) -> 1 | K35: =SUM(K34/$D34) -> 1 | L35: =SUM(L34/$D34) -> 1 | ... P35: =SUM(P34/$D34) -> 1 | Q35: =SUM(E35:P35)/12 -> 0.66666667
A36: =+'1st Year Cr'!A37 -> LA-08-00 | B36: =+'1st Year Cr'!B37 -> 249 | C36: 5 | D36: 1 | E36: 0 | F36: 0 | G36: 0 | H36: 0 | I36: 1 | J36: 1 | K36: 1 | L36: 1 | M36: 1 | N36: 1 | O36: 1 | P36: 1
E37: =SUM(E36/$D36) -> 0 | F37: =SUM(F36/$D36) -> 0 | G37: =SUM(G36/$D36) -> 0 | H37: =SUM(H36/$D36) -> 0 | I37: =SUM(I36/$D36) -> 1 | J37: =SUM(J36/$D36) -> 1 | K37: =SUM(K36/$D36) -> 1 | L37: =SUM(L36/$D36) -> 1 | ... P37: =SUM(P36/$D36) -> 1 | Q37: =SUM(E37:P37)/12 -> 0.66666667
A38: =+'1st Year Cr'!A39 -> LA-08-00 | B38: =+'1st Year Cr'!B39 -> 250 | C38: 5 | D38: 1 | E38: 0 | F38: 0 | G38: 0 | H38: 0 | I38: 1 | J38: 1 | K38: 1 | L38: 1 | M38: 1 | N38: 1 | O38: 1 | P38: 1
E39: =SUM(E38/$D38) -> 0 | F39: =SUM(F38/$D38) -> 0 | G39: =SUM(G38/$D38) -> 0 | H39: =SUM(H38/$D38) -> 0 | I39: =SUM(I38/$D38) -> 1 | J39: =SUM(J38/$D38) -> 1 | K39: =SUM(K38/$D38) -> 1 | L39: =SUM(L38/$D38) -> 1 | ... P39: =SUM(P38/$D38) -> 1 | Q39: =SUM(E39:P39)/12 -> 0.66666667
A40: =+'1st Year Cr'!A41 -> LA-08-00 | B40: =+'1st Year Cr'!B41 -> 251 | C40: 5 | D40: 1 | E40: 0 | F40: 0 | G40: 0 | H40: 0 | I40: 0 | J40: 1 | K40: 1 | L40: 1 | M40: 1 | N40: 1 | O40: 1 | P40: 1
E41: =SUM(E40/$D40) -> 0 | F41: =SUM(F40/$D40) -> 0 | G41: =SUM(G40/$D40) -> 0 | H41: =SUM(H40/$D40) -> 0 | I41: =SUM(I40/$D40) -> 0 | J41: =SUM(J40/$D40) -> 1 | K41: =SUM(K40/$D40) -> 1 | L41: =SUM(L40/$D40) -> 1 | ... P41: =SUM(P40/$D40) -> 1 | Q41: =SUM(E41:P41)/12 -> 0.58333333
A42: =+'1st Year Cr'!A43 -> LA-08-00 | B42: =+'1st Year Cr'!B43 -> 252 | C42: 5 | D42: 1 | E42: 0 | F42: 0 | G42: 0 | H42: 0 | I42: 0 | J42: 1 | K42: 1 | L42: 1 | M42: 1 | N42: 1 | O42: 1 | P42: 1
E43: =SUM(E42/$D42) -> 0 | F43: =SUM(F42/$D42) -> 0 | G43: =SUM(G42/$D42) -> 0 | H43: =SUM(H42/$D42) -> 0 | I43: =SUM(I42/$D42) -> 0 | J43: =SUM(J42/$D42) -> 1 | K43: =SUM(K42/$D42) -> 1 | L43: =SUM(L42/$D42) -> 1 | ... P43: =SUM(P42/$D42) -> 1 | Q43: =SUM(E43:P43)/12 -> 0.58333333
A44: =+'1st Year Cr'!A45 -> LA-08-00 | B44: =+'1st Year Cr'!B45 -> 253 | C44: 5 | D44: 1 | E44: 0 | F44: 0 | G44: 0 | H44: 0 | I44: 0 | J44: 1 | K44: 1 | L44: 1 | M44: 1 | N44: 1 | O44: 1 | P44: 1
E45: =SUM(E44/$D44) -> 0 | F45: =SUM(F44/$D44) -> 0 | G45: =SUM(G44/$D44) -> 0 | H45: =SUM(H44/$D44) -> 0 | I45: =SUM(I44/$D44) -> 0 | J45: =SUM(J44/$D44) -> 1 | K45: =SUM(K44/$D44) -> 1 | L45: =SUM(L44/$D44) -> 1 | ... P45: =SUM(P44/$D44) -> 1 | Q45: =SUM(E45:P45)/12 -> 0.58333333
A46: =+'1st Year Cr'!A47 -> LA-08-00 | B46: =+'1st Year Cr'!B47 -> 254 | C46: 6 | D46: 1 | E46: 0 | F46: 0 | G46: 0 | H46: 0 | I46: 1 | J46: 1 | K46: 1 | L46: 1 | M46: 1 | N46: 1 | O46: 1 | P46: 1
E47: =SUM(E46/$D46) -> 0 | F47: =SUM(F46/$D46) -> 0 | G47: =SUM(G46/$D46) -> 0 | H47: =SUM(H46/$D46) -> 0 | I47: =SUM(I46/$D46) -> 1 | J47: =SUM(J46/$D46) -> 1 | K47: =SUM(K46/$D46) -> 1 | L47: =SUM(L46/$D46) -> 1 | ... P47: =SUM(P46/$D46) -> 1 | Q47: =SUM(E47:P47)/12 -> 0.66666667
A48: =+'1st Year Cr'!A49 -> LA-08-00 | B48: =+'1st Year Cr'!B49 -> 255 | C48: 6 | D48: 1 | E48: 0 | F48: 0 | G48: 0 | H48: 0 | I48: 0 | J48: 1 | K48: 1 | L48: 1 | M48: 1 | N48: 1 | O48: 1 | P48: 1
E49: =SUM(E48/$D48) -> 0 | F49: =SUM(F48/$D48) -> 0 | G49: =SUM(G48/$D48) -> 0 | H49: =SUM(H48/$D48) -> 0 | I49: =SUM(I48/$D48) -> 0 | J49: =SUM(J48/$D48) -> 1 | K49: =SUM(K48/$D48) -> 1 | L49: =SUM(L48/$D48) -> 1 | ... P49: =SUM(P48/$D48) -> 1 | Q49: =SUM(E49:P49)/12 -> 0.58333333
A50: =+'1st Year Cr'!A51 -> LA-08-00 | B50: =+'1st Year Cr'!B51 -> 256 | C50: 6 | D50: 1 | E50: 0 | F50: 0 | G50: 0 | H50: 0 | I50: 0 | J50: 0 | K50: 1 | L50: 1 | M50: 1 | N50: 1 | O50: 1 | P50: 1
E51: =SUM(E50/$D50) -> 0 | F51: =SUM(F50/$D50) -> 0 | G51: =SUM(G50/$D50) -> 0 | H51: =SUM(H50/$D50) -> 0 | I51: =SUM(I50/$D50) -> 0 | J51: =SUM(J50/$D50) -> 0 | K51: =SUM(K50/$D50) -> 1 | L51: =SUM(L50/$D50) -> 1 | ... P51: =SUM(P50/$D50) -> 1 | Q51: =SUM(E51:P51)/12 -> 0.5
A52: =+'1st Year Cr'!A53 -> LA-08-00 | B52: =+'1st Year Cr'!B53 -> 257 | C52: 6 | D52: 1 | E52: 0 | F52: 0 | G52: 0 | H52: 0 | I52: 0 | J52: 0 | K52: 1 | L52: 1 | M52: 1 | N52: 1 | O52: 1 | P52: 1
E53: =SUM(E52/$D52) -> 0 | F53: =SUM(F52/$D52) -> 0 | G53: =SUM(G52/$D52) -> 0 | H53: =SUM(H52/$D52) -> 0 | I53: =SUM(I52/$D52) -> 0 | J53: =SUM(J52/$D52) -> 0 | K53: =SUM(K52/$D52) -> 1 | L53: =SUM(L52/$D52) -> 1 | ... P53: =SUM(P52/$D52) -> 1 | Q53: =SUM(E53:P53)/12 -> 0.5
A54: =+'1st Year Cr'!A55 -> LA-08-00 | B54: =+'1st Year Cr'!B55 -> 258 | C54: 6 | D54: 1 | E54: 0 | F54: 0 | G54: 0 | H54: 0 | I54: 0 | J54: 0 | K54: 1 | L54: 1 | M54: 1 | N54: 1 | O54: 1 | P54: 1
E55: =SUM(E54/$D54) -> 0 | F55: =SUM(F54/$D54) -> 0 | G55: =SUM(G54/$D54) -> 0 | H55: =SUM(H54/$D54) -> 0 | I55: =SUM(I54/$D54) -> 0 | J55: =SUM(J54/$D54) -> 0 | K55: =SUM(K54/$D54) -> 1 | L55: =SUM(L54/$D54) -> 1 | ... P55: =SUM(P54/$D54) -> 1 | Q55: =SUM(E55:P55)/12 -> 0.5
A56: =+'1st Year Cr'!A57 -> LA-08-00 | B56: =+'1st Year Cr'!B57 -> 259 | C56: 6 | D56: 1 | E56: 0 | F56: 0 | G56: 0 | H56: 0 | I56: 0 | J56: 0 | K56: 1 | L56: 1 | M56: 1 | N56: 1 | O56: 1 | P56: 1
E57: =SUM(E56/$D56) -> 0 | F57: =SUM(F56/$D56) -> 0 | G57: =SUM(G56/$D56) -> 0 | H57: =SUM(H56/$D56) -> 0 | I57: =SUM(I56/$D56) -> 0 | J57: =SUM(J56/$D56) -> 0 | K57: =SUM(K56/$D56) -> 1 | L57: =SUM(L56/$D56) -> 1 | ... P57: =SUM(P56/$D56) -> 1 | Q57: =SUM(E57:P57)/12 -> 0.5
A58: =+'1st Year Cr'!A59 -> LA-08-00 | B58: =+'1st Year Cr'!B59 -> 260 | C58: 6 | D58: 1 | E58: 0 | F58: 0 | G58: 0 | H58: 0 | I58: 0 | J58: 0 | K58: 1 | L58: 1 | M58: 1 | N58: 1 | O58: 1 | P58: 1
E59: =SUM(E58/$D58) -> 0 | F59: =SUM(F58/$D58) -> 0 | G59: =SUM(G58/$D58) -> 0 | H59: =SUM(H58/$D58) -> 0 | I59: =SUM(I58/$D58) -> 0 | J59: =SUM(J58/$D58) -> 0 | K59: =SUM(K58/$D58) -> 1 | L59: =SUM(L58/$D58) -> 1 | ... P59: =SUM(P58/$D58) -> 1 | Q59: =SUM(E59:P59)/12 -> 0.5
A60: =+'1st Year Cr'!A61 -> LA-08-00 | B60: =+'1st Year Cr'!B61 -> 261 | C60: 6 | D60: 1 | E60: 0 | F60: 0 | G60: 0 | H60: 0 | I60: 0 | J60: 0 | K60: 0 | L60: 1 | M60: 1 | N60: 1 | O60: 1 | P60: 1
E61: =SUM(E60/$D60) -> 0 | F61: =SUM(F60/$D60) -> 0 | G61: =SUM(G60/$D60) -> 0 | H61: =SUM(H60/$D60) -> 0 | I61: =SUM(I60/$D60) -> 0 | J61: =SUM(J60/$D60) -> 0 | K61: =SUM(K60/$D60) -> 0 | L61: =SUM(L60/$D60) -> 1 | ... P61: =SUM(P60/$D60) -> 1 | Q61: =SUM(E61:P61)/12 -> 0.41666667
A62: =+'1st Year Cr'!A63 -> LA-08-00 | B62: =+'1st Year Cr'!B63 -> 262 | C62: 6 | D62: 1 | E62: 0 | F62: 0 | G62: 0 | H62: 0 | I62: 0 | J62: 0 | K62: 0 | L62: 1 | M62: 1 | N62: 1 | O62: 1 | P62: 1
E63: =SUM(E62/$D62) -> 0 | F63: =SUM(F62/$D62) -> 0 | G63: =SUM(G62/$D62) -> 0 | H63: =SUM(H62/$D62) -> 0 | I63: =SUM(I62/$D62) -> 0 | J63: =SUM(J62/$D62) -> 0 | K63: =SUM(K62/$D62) -> 0 | L63: =SUM(L62/$D62) -> 1 | ... P63: =SUM(P62/$D62) -> 1 | Q63: =SUM(E63:P63)/12 -> 0.41666667
A64: =+'1st Year Cr'!A65 -> LA-08-00 | B64: =+'1st Year Cr'!B65 -> 263 | C64: 6 | D64: 1 | E64: 0 | F64: 0 | G64: 0 | H64: 0 | I64: 0 | J64: 0 | K64: 0 | L64: 1 | M64: 1 | N64: 1 | O64: 1 | P64: 1
E65: =SUM(E64/$D64) -> 0 | F65: =SUM(F64/$D64) -> 0 | G65: =SUM(G64/$D64) -> 0 | H65: =SUM(H64/$D64) -> 0 | I65: =SUM(I64/$D64) -> 0 | J65: =SUM(J64/$D64) -> 0 | K65: =SUM(K64/$D64) -> 0 | L65: =SUM(L64/$D64) -> 1 | ... P65: =SUM(P64/$D64) -> 1 | Q65: =SUM(E65:P65)/12 -> 0.41666667
A66: =+'1st Year Cr'!A67 -> LA-08-00 | B66: =+'1st Year Cr'!B67 -> 264 | C66: 6 | D66: 1 | E66: 0 | F66: 0 | G66: 0 | H66: 0 | I66: 0 | J66: 0 | K66: 0 | L66: 1 | M66: 1 | N66: 1 | O66: 1 | P66: 1
