Workbook

Sheet Inputs
A1: Inputs — Pricing Tiers & Cost Assumptions
A3: Global Inputs
A4: Billing Period | B4: Monthly | D4: Choose whether prices entered below are Monthly or Annual subscription prices.
A5: CAC per Customer (optional) | D5: If provided, CAC Payback will be calculated using gross profit per month.
A6: Default Variable Cost per Usage Unit | B6: 0.002 | D6: Used when a tier doesn't specify a variable cost per usage unit.
A7: Gross Margin Target (reference) | B7: 0.75 | D7: Reference only (helps judge how close tiers are to target).
A8: Scenario (selected in Scenario Explorer) | B8: ='Scenario Explorer'!$B$4 -> Cheap / Volume | D8: Scenario drives multipliers and adjusts price/customers/usage/costs.
A10: Pricing Tiers (editable inputs in blue)
A11: Tier Name | B11: Base Price (per billing period) | C11: # Customers | D11: Usage / Customer (per month) | E11: Fixed Cost / Customer (per month) | F11: Var Cost / Usage Unit | G11: Usage Price / Unit (optional) | H11: Cost to Serve / Customer (per month) | I11: Notes
A12: Starter | B12: 29 | C12: 800 | D12: 200 | E12: 3.5 | G12: 0 | H12: =IF($A12="","", $E12 + $D12*IF($F12="", $B$6, $F12)) -> 3.9 | I12: Low-touch self-serve
A13: Pro | B13: 99 | C13: 250 | D13: 800 | E13: 6 | F13: 0.0015 | G13: 0.0008 | H13: =IF($A13="","", $E13 + $D13*IF($F13="", $B$6, $F13)) -> 7.2 | I13: Team plans, moderate usage
A14: Business | B14: 249 | C14: 90 | D14: 2000 | E14: 12 | F14: 0.0012 | G14: 0.0007 | H14: =IF($A14="","", $E14 + $D14*IF($F14="", $B$6, $F14)) -> 14.4 | I14: Higher usage + support
A15: Enterprise | B15: 999 | C15: 20 | D15: 8000 | E15: 50 | F15: 0.001 | G15: 0.0005 | H15: =IF($A15="","", $E15 + $D15*IF($F15="", $B$6, $F15)) -> 58 | I15: High support, negotiated
H16: =IF($A16="","", $E16 + $D16*IF($F16="", $B$6, $F16))
H17: =IF($A17="","", $E17 + $D17*IF($F17="", $B$6, $F17))
H18: =IF($A18="","", $E18 + $D18*IF($F18="", $B$6, $F18))
H19: =IF($A19="","", $E19 + $D19*IF($F19="", $B$6, $F19))
H20: =IF($A20="","", $E20 + $D20*IF($F20="", $B$6, $F20))
H21: =IF($A21="","", $E21 + $D21*IF($F21="", $B$6, $F21))
H22: =IF($A22="","", $E22 + $D22*IF($F22="", $B$6, $F22))
H23: =IF($A23="","", $E23 + $D23*IF($F23="", $B$6, $F23))
A25: Tip: Add more tiers by filling in the next blank row within this table (rows 12–23). Cost-to-serve (col H) auto-fills; copy it down if needed.

Sheet Unit Economics
A1: Output — Revenue & Unit Economics by Tier (auto-calculated)
A3: Billing Period: | B3: =Inputs!$B$4 -> Monthly | D3: CAC: | E3: =Inputs!$B$5 -> 0 | G3: Gross Margin Target: | H3: =Inputs!$B$7 -> 0.75 | J3: Period Months | K3: =IF(Inputs!$B$4="Annual",12,1) -> 1
A4: Scenario: | B4: ='Scenario Explorer'!$B$4 -> Cheap / Volume
A6: Tier | B6: Adj Base Price | C6: Adj Customers | D6: Total Revenue | E6: Total Cost | F6: Gross Profit | G6: Gross Margin % | H6: ARPU | I6: Gross Profit / Cust / Month | J6: CAC Payback (months) | K6: Flag
A7: =Inputs!$A12 -> Starter | B7: =IF($A7="","", Inputs!$B12*'Scenario Explorer'!$A$16) -> 20.3 | C7: =IF($A7="","", Inputs!$C12*'Scenario Explorer'!$B$16) -> 1440 | D7: =IF($A7="","", $C7 * ( $B7 + ((Inputs!$D12*'Scenario Explorer'!$C$16)*(Inputs!$G12*'Scenario Explorer'!$F$16)*$K$3) ) ) -> 29232 | E7: =IF($A7="","", $C7 * ( ((Inputs!$E12*'Scenario Explorer'!$D$16) + (Inputs!$D12*'Scenario Explorer'!$C$16)*(IF(Inputs!$F12="", Inputs!$B$6, Inputs!$F12)*'Scenario Explorer'!$E$16)) * $K$3 ) ) -> 6304.32 | F7: =IF($A7="","", $D7 - $E7) -> 22927.68 | G7: =IF($A7="","", IF($D7=0,"", $F7/$D7)) -> 0.78433498 | H7: =IF($A7="","", IF($C7=0,"", $D7/$C7)) -> 20.3 | I7: =IF($A7="","", IF($K$3=0,"", ($H7*$G7)/$K$3)) -> 15.922 | J7: =IF($A7="","", IF(Inputs!$B$5="","", IF($I7=0,"", Inputs!$B$5/$I7))) | K7: =IF($A7="","", IF(AND($G7>=MAX($G$7:$G$18), OR(Inputs!$B$5="", $J7<=MIN($J$7:$J$18))), "BEST", ""))
A8: =Inputs!$A13 -> Pro | B8: =IF($A8="","", Inputs!$B13*'Scenario Explorer'!$A$16) -> 69.3 | C8: =IF($A8="","", Inputs!$C13*'Scenario Explorer'!$B$16) -> 450 | D8: =IF($A8="","", $C8 * ( $B8 + ((Inputs!$D13*'Scenario Explorer'!$C$16)*(Inputs!$G13*'Scenario Explorer'!$F$16)*$K$3) ) ) -> 31496.04 | E8: =IF($A8="","", $C8 * ( ((Inputs!$E13*'Scenario Explorer'!$D$16) + (Inputs!$D13*'Scenario Explorer'!$C$16)*(IF(Inputs!$F13="", Inputs!$B$6, Inputs!$F13)*'Scenario Explorer'!$E$16)) * $K$3 ) ) -> 3682.8 | F8: =IF($A8="","", $D8 - $E8) -> 27813.24 | G8: =IF($A8="","", IF($D8=0,"", $F8/$D8)) -> 0.88307101 | H8: =IF($A8="","", IF($C8=0,"", $D8/$C8)) -> 69.9912 | I8: =IF($A8="","", IF($K$3=0,"", ($H8*$G8)/$K$3)) -> 61.8072 | J8: =IF($A8="","", IF(Inputs!$B$5="","", IF($I8=0,"", Inputs!$B$5/$I8))) | K8: =IF($A8="","", IF(AND($G8>=MAX($G$7:$G$18), OR(Inputs!$B$5="", $J8<=MIN($J$7:$J$18))), "BEST", ""))
A9: =Inputs!$A14 -> Business | B9: =IF($A9="","", Inputs!$B14*'Scenario Explorer'!$A$16) -> 174.3 | C9: =IF($A9="","", Inputs!$C14*'Scenario Explorer'!$B$16) -> 162 | D9: =IF($A9="","", $C9 * ( $B9 + ((Inputs!$D14*'Scenario Explorer'!$C$16)*(Inputs!$G14*'Scenario Explorer'!$F$16)*$K$3) ) ) -> 28481.544 | E9: =IF($A9="","", $C9 * ( ((Inputs!$E14*'Scenario Explorer'!$D$16) + (Inputs!$D14*'Scenario Explorer'!$C$16)*(IF(Inputs!$F14="", Inputs!$B$6, Inputs!$F14)*'Scenario Explorer'!$E$16)) * $K$3 ) ) -> 2651.616 | F9: =IF($A9="","", $D9 - $E9) -> 25829.928 | G9: =IF($A9="","", IF($D9=0,"", $F9/$D9)) -> 0.90690055 | H9: =IF($A9="","", IF($C9=0,"", $D9/$C9)) -> 175.812 | I9: =IF($A9="","", IF($K$3=0,"", ($H9*$G9)/$K$3)) -> 159.444 | J9: =IF($A9="","", IF(Inputs!$B$5="","", IF($I9=0,"", Inputs!$B$5/$I9))) | K9: =IF($A9="","", IF(AND($G9>=MAX($G$7:$G$18), OR(Inputs!$B$5="", $J9<=MIN($J$7:$J$18))), "BEST", "")) -> BEST
A10: =Inputs!$A15 -> Enterprise | B10: =IF($A10="","", Inputs!$B15*'Scenario Explorer'!$A$16) -> 699.3 | C10: =IF($A10="","", Inputs!$C15*'Scenario Explorer'!$B$16) -> 36 | D10: =IF($A10="","", $C10 * ( $B10 + ((Inputs!$D15*'Scenario Explorer'!$C$16)*(Inputs!$G15*'Scenario Explorer'!$F$16)*$K$3) ) ) -> 25330.32 | E10: =IF($A10="","", $C10 * ( ((Inputs!$E15*'Scenario Explorer'!$D$16) + (Inputs!$D15*'Scenario Explorer'!$C$16)*(IF(Inputs!$F15="", Inputs!$B$6, Inputs!$F15)*'Scenario Explorer'!$E$16)) * $K$3 ) ) -> 2360.16 | F10: =IF($A10="","", $D10 - $E10) -> 22970.16 | G10: =IF($A10="","", IF($D10=0,"", $F10/$D10)) -> 0.90682471 | H10: =IF($A10="","", IF($C10=0,"", $D10/$C10)) -> 703.62 | I10: =IF($A10="","", IF($K$3=0,"", ($H10*$G10)/$K$3)) -> 638.06 | J10: =IF($A10="","", IF(Inputs!$B$5="","", IF($I10=0,"", Inputs!$B$5/$I10))) | K10: =IF($A10="","", IF(AND($G10>=MAX($G$7:$G$18), OR(Inputs!$B$5="", $J10<=MIN($J$7:$J$18))), "BEST", ""))
A11: =Inputs!$A16 -> 0 | B11: =IF($A11="","", Inputs!$B16*'Scenario Explorer'!$A$16) -> 0 | C11: =IF($A11="","", Inputs!$C16*'Scenario Explorer'!$B$16) -> 0 | D11: =IF($A11="","", $C11 * ( $B11 + ((Inputs!$D16*'Scenario Explorer'!$C$16)*(Inputs!$G16*'Scenario Explorer'!$F$16)*$K$3) ) ) -> 0 | E11: =IF($A11="","", $C11 * ( ((Inputs!$E16*'Scenario Explorer'!$D$16) + (Inputs!$D16*'Scenario Explorer'!$C$16)*(IF(Inputs!$F16="", Inputs!$B$6, Inputs!$F16)*'Scenario Explorer'!$E$16)) * $K$3 ) ) -> 0 | F11: =IF($A11="","", $D11 - $E11) -> 0 | G11: =IF($A11="","", IF($D11=0,"", $F11/$D11)) | H11: =IF($A11="","", IF($C11=0,"", $D11/$C11)) | I11: =IF($A11="","", IF($K$3=0,"", ($H11*$G11)/$K$3)) -> #VALUE! | J11: =IF($A11="","", IF(Inputs!$B$5="","", IF($I11=0,"", Inputs!$B$5/$I11))) | K11: =IF($A11="","", IF(AND($G11>=MAX($G$7:$G$18), OR(Inputs!$B$5="", $J11<=MIN($J$7:$J$18))), "BEST", "")) -> BEST
A12: =Inputs!$A17 -> 0 | B12: =IF($A12="","", Inputs!$B17*'Scenario Explorer'!$A$16) -> 0 | C12: =IF($A12="","", Inputs!$C17*'Scenario Explorer'!$B$16) -> 0 | D12: =IF($A12="","", $C12 * ( $B12 + ((Inputs!$D17*'Scenario Explorer'!$C$16)*(Inputs!$G17*'Scenario Explorer'!$F$16)*$K$3) ) ) -> 0 | E12: =IF($A12="","", $C12 * ( ((Inputs!$E17*'Scenario Explorer'!$D$16) + (Inputs!$D17*'Scenario Explorer'!$C$16)*(IF(Inputs!$F17="", Inputs!$B$6, Inputs!$F17)*'Scenario Explorer'!$E$16)) * $K$3 ) ) -> 0 | F12: =IF($A12="","", $D12 - $E12) -> 0 | G12: =IF($A12="","", IF($D12=0,"", $F12/$D12)) | H12: =IF($A12="","", IF($C12=0,"", $D12/$C12)) | I12: =IF($A12="","", IF($K$3=0,"", ($H12*$G12)/$K$3)) -> #VALUE! | J12: =IF($A12="","", IF(Inputs!$B$5="","", IF($I12=0,"", Inputs!$B$5/$I12))) | K12: =IF($A12="","", IF(AND($G12>=MAX($G$7:$G$18), OR(Inputs!$B$5="", $J12<=MIN($J$7:$J$18))), "BEST", "")) -> BEST
A13: =Inputs!$A18 -> 0 | B13: =IF($A13="","", Inputs!$B18*'Scenario Explorer'!$A$16) -> 0 | C13: =IF($A13="","", Inputs!$C18*'Scenario Explorer'!$B$16) -> 0 | D13: =IF($A13="","", $C13 * ( $B13 + ((Inputs!$D18*'Scenario Explorer'!$C$16)*(Inputs!$G18*'Scenario Explorer'!$F$16)*$K$3) ) ) -> 0 | E13: =IF($A13="","", $C13 * ( ((Inputs!$E18*'Scenario Explorer'!$D$16) + (Inputs!$D18*'Scenario Explorer'!$C$16)*(IF(Inputs!$F18="", Inputs!$B$6, Inputs!$F18)*'Scenario Explorer'!$E$16)) * $K$3 ) ) -> 0 | F13: =IF($A13="","", $D13 - $E13) -> 0 | G13: =IF($A13="","", IF($D13=0,"", $F13/$D13)) | H13: =IF($A13="","", IF($C13=0,"", $D13/$C13)) | I13: =IF($A13="","", IF($K$3=0,"", ($H13*$G13)/$K$3)) -> #VALUE! | J13: =IF($A13="","", IF(Inputs!$B$5="","", IF($I13=0,"", Inputs!$B$5/$I13))) | K13: =IF($A13="","", IF(AND($G13>=MAX($G$7:$G$18), OR(Inputs!$B$5="", $J13<=MIN($J$7:$J$18))), "BEST", "")) -> BEST
A14: =Inputs!$A19 -> 0 | B14: =IF($A14="","", Inputs!$B19*'Scenario Explorer'!$A$16) -> 0 | C14: =IF($A14="","", Inputs!$C19*'Scenario Explorer'!$B$16) -> 0 | D14: =IF($A14="","", $C14 * ( $B14 + ((Inputs!$D19*'Scenario Explorer'!$C$16)*(Inputs!$G19*'Scenario Explorer'!$F$16)*$K$3) ) ) -> 0 | E14: =IF($A14="","", $C14 * ( ((Inputs!$E19*'Scenario Explorer'!$D$16) + (Inputs!$D19*'Scenario Explorer'!$C$16)*(IF(Inputs!$F19="", Inputs!$B$6, Inputs!$F19)*'Scenario Explorer'!$E$16)) * $K$3 ) ) -> 0 | F14: =IF($A14="","", $D14 - $E14) -> 0 | G14: =IF($A14="","", IF($D14=0,"", $F14/$D14)) | H14: =IF($A14="","", IF($C14=0,"", $D14/$C14)) | I14: =IF($A14="","", IF($K$3=0,"", ($H14*$G14)/$K$3)) -> #VALUE! | J14: =IF($A14="","", IF(Inputs!$B$5="","", IF($I14=0,"", Inputs!$B$5/$I14))) | K14: =IF($A14="","", IF(AND($G14>=MAX($G$7:$G$18), OR(Inputs!$B$5="", $J14<=MIN($J$7:$J$18))), "BEST", "")) -> BEST
A15: =Inputs!$A20 -> 0 | B15: =IF($A15="","", Inputs!$B20*'Scenario Explorer'!$A$16) -> 0 | C15: =IF($A15="","", Inputs!$C20*'Scenario Explorer'!$B$16) -> 0 | D15: =IF($A15="","", $C15 * ( $B15 + ((Inputs!$D20*'Scenario Explorer'!$C$16)*(Inputs!$G20*'Scenario Explorer'!$F$16)*$K$3) ) ) -> 0 | E15: =IF($A15="","", $C15 * ( ((Inputs!$E20*'Scenario Explorer'!$D$16) + (Inputs!$D20*'Scenario Explorer'!$C$16)*(IF(Inputs!$F20="", Inputs!$B$6, Inputs!$F20)*'Scenario Explorer'!$E$16)) * $K$3 ) ) -> 0 | F15: =IF($A15="","", $D15 - $E15) -> 0 | G15: =IF($A15="","", IF($D15=0,"", $F15/$D15)) | H15: =IF($A15="","", IF($C15=0,"", $D15/$C15)) | I15: =IF($A15="","", IF($K$3=0,"", ($H15*$G15)/$K$3)) -> #VALUE! | J15: =IF($A15="","", IF(Inputs!$B$5="","", IF($I15=0,"", Inputs!$B$5/$I15))) | K15: =IF($A15="","", IF(AND($G15>=MAX($G$7:$G$18), OR(Inputs!$B$5="", $J15<=MIN($J$7:$J$18))), "BEST", "")) -> BEST
A16: =Inputs!$A21 -> 0 | B16: =IF($A16="","", Inputs!$B21*'Scenario Explorer'!$A$16) -> 0 | C16: =IF($A16="","", Inputs!$C21*'Scenario Explorer'!$B$16) -> 0 | D16: =IF($A16="","", $C16 * ( $B16 + ((Inputs!$D21*'Scenario Explorer'!$C$16)*(Inputs!$G21*'Scenario Explorer'!$F$16)*$K$3) ) ) -> 0 | E16: =IF($A16="","", $C16 * ( ((Inputs!$E21*'Scenario Explorer'!$D$16) + (Inputs!$D21*'Scenario Explorer'!$C$16)*(IF(Inputs!$F21="", Inputs!$B$6, Inputs!$F21)*'Scenario Explorer'!$E$16)) * $K$3 ) ) -> 0 | F16: =IF($A16="","", $D16 - $E16) -> 0 | G16: =IF($A16="","", IF($D16=0,"", $F16/$D16)) | H16: =IF($A16="","", IF($C16=0,"", $D16/$C16)) | I16: =IF($A16="","", IF($K$3=0,"", ($H16*$G16)/$K$3)) -> #VALUE! | J16: =IF($A16="","", IF(Inputs!$B$5="","", IF($I16=0,"", Inputs!$B$5/$I16))) | K16: =IF($A16="","", IF(AND($G16>=MAX($G$7:$G$18), OR(Inputs!$B$5="", $J16<=MIN($J$7:$J$18))), "BEST", "")) -> BEST
A17: =Inputs!$A22 -> 0 | B17: =IF($A17="","", Inputs!$B22*'Scenario Explorer'!$A$16) -> 0 | C17: =IF($A17="","", Inputs!$C22*'Scenario Explorer'!$B$16) -> 0 | D17: =IF($A17="","", $C17 * ( $B17 + ((Inputs!$D22*'Scenario Explorer'!$C$16)*(Inputs!$G22*'Scenario Explorer'!$F$16)*$K$3) ) ) -> 0 | E17: =IF($A17="","", $C17 * ( ((Inputs!$E22*'Scenario Explorer'!$D$16) + (Inputs!$D22*'Scenario Explorer'!$C$16)*(IF(Inputs!$F22="", Inputs!$B$6, Inputs!$F22)*'Scenario Explorer'!$E$16)) * $K$3 ) ) -> 0 | F17: =IF($A17="","", $D17 - $E17) -> 0 | G17: =IF($A17="","", IF($D17=0,"", $F17/$D17)) | H17: =IF($A17="","", IF($C17=0,"", $D17/$C17)) | I17: =IF($A17="","", IF($K$3=0,"", ($H17*$G17)/$K$3)) -> #VALUE! | J17: =IF($A17="","", IF(Inputs!$B$5="","", IF($I17=0,"", Inputs!$B$5/$I17))) | K17: =IF($A17="","", IF(AND($G17>=MAX($G$7:$G$18), OR(Inputs!$B$5="", $J17<=MIN($J$7:$J$18))), "BEST", "")) -> BEST
A18: =Inputs!$A23 -> 0 | B18: =IF($A18="","", Inputs!$B23*'Scenario Explorer'!$A$16) -> 0 | C18: =IF($A18="","", Inputs!$C23*'Scenario Explorer'!$B$16) -> 0 | D18: =IF($A18="","", $C18 * ( $B18 + ((Inputs!$D23*'Scenario Explorer'!$C$16)*(Inputs!$G23*'Scenario Explorer'!$F$16)*$K$3) ) ) -> 0 | E18: =IF($A18="","", $C18 * ( ((Inputs!$E23*'Scenario Explorer'!$D$16) + (Inputs!$D23*'Scenario Explorer'!$C$16)*(IF(Inputs!$F23="", Inputs!$B$6, Inputs!$F23)*'Scenario Explorer'!$E$16)) * $K$3 ) ) -> 0 | F18: =IF($A18="","", $D18 - $E18) -> 0 | G18: =IF($A18="","", IF($D18=0,"", $F18/$D18)) | H18: =IF($A18="","", IF($C18=0,"", $D18/$C18)) | I18: =IF($A18="","", IF($K$3=0,"", ($H18*$G18)/$K$3)) -> #VALUE! | J18: =IF($A18="","", IF(Inputs!$B$5="","", IF($I18=0,"", Inputs!$B$5/$I18))) | K18: =IF($A18="","", IF(AND($G18>=MAX($G$7:$G$18), OR(Inputs!$B$5="", $J18<=MIN($J$7:$J$18))), "BEST", "")) -> BEST
A19: TOTAL | D19: =SUM($D$7:$D$18) -> 114539.9 | E19: =SUM($E$7:$E$18) -> 14998.896 | F19: =SUM($F$7:$F$18) -> 99541.008 | G19: =IF($D19=0,"", $F19/$D19) -> 0.86905091 | H19: =IF(SUM($C$7:$C$18)=0,"", $D19/SUM($C$7:$C$18)) -> 54.856276 | J19: =IF(Inputs!$B$5="","", AVERAGEIF($J$7:$J$18,">0"))

Sheet Scenario Explorer
A1: Scenario Explorer — Compare Pricing Strategies
A3: Scenario Controls
A4: Scenario | B4: Cheap / Volume | D4: Pick a strategy preset, or switch Mode to Custom to edit multipliers.
A5: Mode | B5: Preset
A7: Preset Multipliers
A8: Scenario | B8: Price Mult | C8: Customer Mult | D8: Usage Mult | E8: Fixed Cost Mult | F8: Var Cost Mult | G8: Usage Price Mult | H8: Notes
A9: Base | B9: 1 | C9: 1 | D9: 1 | E9: 1 | F9: 1 | G9: 1 | H9: No adjustments
A10: Cheap / Volume | B10: 0.7 | C10: 1.8 | D10: 1.2 | E10: 1.1 | F10: 1.1 | G10: 0.9 | H10: Lower price, more customers
A11: Premium / Fewer Customers | B11: 1.4 | C11: 0.6 | D11: 1.5 | E11: 1.3 | F11: 1.2 | G11: 1.1 | H11: Higher price, fewer customers
A12: Usage-Based Hybrid | B12: 1 | C12: 1 | D12: 2.5 | E12: 1.4 | F12: 1.4 | G12: 1.2 | H12: Usage-driven growth
A14: Active Multipliers (used by Unit Economics + Dashboard)
A15: Price Mult | B15: Customer Mult | C15: Usage Mult | D15: Fixed Cost Mult | E15: Var Cost Mult | F15: Usage Price Mult
A16: {=IF($B$5="Preset", INDEX($B$9:$B$12, MATCH($B$4, $A$9:$A$12, 0)), $A$18)} -> 0.7 | B16: {=IF($B$5="Preset", INDEX($C$9:$C$12, MATCH($B$4, $A$9:$A$12, 0)), $B$18)} -> 1.8 | C16: {=IF($B$5="Preset", INDEX($D$9:$D$12, MATCH($B$4, $A$9:$A$12, 0)), $C$18)} -> 1.2 | D16: {=IF($B$5="Preset", INDEX($E$9:$E$12, MATCH($B$4, $A$9:$A$12, 0)), $D$18)} -> 1.1 | E16: {=IF($B$5="Preset", INDEX($F$9:$F$12, MATCH($B$4, $A$9:$A$12, 0)), $E$18)} -> 1.1 | F16: {=IF($B$5="Preset", INDEX($G$9:$G$12, MATCH($B$4, $A$9:$A$12, 0)), $F$18)} -> 0.9
A17: Manual (Custom Mode)
A18: 1 | B18: 1 | C18: 1 | D18: 1 | E18: 1 | F18: 1 | G18: (Edit row 18 multipliers in Custom Mode)
A20: Scenario Summary (active)
A21: Total Revenue (per billing period) | B21: ='Unit Economics'!$D$19 -> 114539.9
A22: Overall Gross Margin | B22: ='Unit Economics'!$G$19 -> 0.86905091
A23: Avg CAC Payback (months) | B23: ='Unit Economics'!$J$19
A24: Top Performing Tier | B24: {=IFERROR(INDEX('Unit Economics'!$A$7:$A$18, MATCH("BEST",'Unit Economics'!$K$7:$K$18,0)),"")} -> Business

Sheet Dashboard
A1: Dashboard — Pricing Strategy Snapshot
A3: Total Revenue | C3: Overall Gross Margin | E3: Avg CAC Payback (months) | G3: Top Tier (current scenario)
A4: ='Unit Economics'!$D$19 -> 114539.9 | C4: ='Unit Economics'!$G$19 -> 0.86905091 | E4: ='Unit Economics'!$J$19 | G4: ='Scenario Explorer'!$B$24 -> Business
A6: Charts update automatically from Inputs + Scenario Explorer.
