Workbook

Sheet Cover
B2: Venture Capital Method Model
B4: A clean, scenario-aware VC Method template (Google Sheets / Excel compatible).
B6: Quick Start
B7: 1) Go to Inputs & Assumptions → fill the yellow cells.
B8: 2) Pick a Scenario (Base / Upside / Downside).
B9: 3) Review Valuation for terminal value and required ownership.
B10: 4) Review Returns for IRR / MOIC and cash flow timeline.
B11: 5) Use Dashboard for the investor-ready summary.
B13: Legend
B14: Yellow cells | C14: Inputs you can change
B15: Blue text | C15: User inputs
B16: Black text | C16: Formulas / outputs
B17: Green shading | C17: Meets / exceeds target
B18: Red shading | C18: Below target / watch item

Sheet Inputs & Assumptions
A1: Inputs & Assumptions
A3: Fill yellow cells only. Everything else is calculated.
A5: Scenario | B5: Base | D5: Tip: scenarios scale base assumptions (see Scenario Factors).
A7: Valuation Assumptions
A8: General
A9: Currency | B9: USD
A10: Valuation Date | B10: 45657
A11: Exit Year (years from now) | B11: 10 | C11: years
A12: Target Investor IRR / Discount Rate | B12: 0.25
A13: Exit Metric | B13: Revenue
A14: Base EV / Revenue Multiple | B14: 10 | C14: x
A15: Base EV / EBITDA Multiple | B15: 20 | C15: x
A17: Exit-Year Operating Assumptions (Base)
A18: Revenue in Exit Year | B18: 50000000
A19: EBITDA in Exit Year | B19: 10000000
A20: Financial Debt in Exit Year | B20: 0
A21: Cash in Exit Year | B21: 0
A22: Net Debt (Debt - Cash) | B22: =B20-B21 -> 0
A24: Scenario Factors (applied to base assumptions) - Scenario factors scale revenue, EBITDA, and exit multiples.
A25: Operating factors scale Revenue/EBITDA; Multiple factors scale the selected exit multiple.
A26: Upside Operating Factor | B26: 1.25
A27: Downside Operating Factor | B27: 0.75
A28: Upside Multiple Factor | B28: 1.15
A29: Downside Multiple Factor | B29: 0.85
A31: Selected Operating Factor | B31: =IF($B$5="Upside",$B$26,IF($B$5="Downside",$B$27,1)) -> 1
A32: Selected Multiple Factor | B32: =IF($B$5="Upside",$B$28,IF($B$5="Downside",$B$29,1)) -> 1
A34: Investment Terms
A35: Entry, dilution, and preferred terms
A36: Investment Amount | B36: 5000000 | D36: Check: ownership & dilution drive returns more than the headline valuation.
A37: Investor Ownership at Entry | B37: 0.15 | D37: Assumes a single investor class for simplicity.
A38: Expected Cumulative Dilution by Exit | B38: 0.4
A39: Investor Ownership at Exit | B39: =B37*(1-B38) -> 0.09
A41: Preferred Terms (optional)
A42: Liquidation Preference Multiple | B42: 1 | D42: Preference modeled as non-participating; payout is capped at total equity value.
A43: Dividends Paid? | B43: No
A44: Dividend % on Invested Capital (annual) | B44: 0.08
A45: Dividend Payment Starts in Year | B45: 3

Sheet Valuation
A1: Valuation (VC Method + Deal Economics)
A3: All values are scenario-adjusted based on Inputs → Scenario & Factors.
A5: Scenario-adjusted Exit Inputs
A6: Exit Revenue (scenario) | B6: ='Inputs & Assumptions'!B18*'Inputs & Assumptions'!B31 -> 50000000
A7: Exit EBITDA (scenario) | B7: ='Inputs & Assumptions'!B19*'Inputs & Assumptions'!B31 -> 10000000
A8: EV / Revenue Multiple (scenario) | B8: ='Inputs & Assumptions'!B14*'Inputs & Assumptions'!B32 -> 10
A9: EV / EBITDA Multiple (scenario) | B9: ='Inputs & Assumptions'!B15*'Inputs & Assumptions'!B32 -> 20
A10: Exit Debt | B10: ='Inputs & Assumptions'!B20 -> 0
A11: Exit Cash | B11: ='Inputs & Assumptions'!B21 -> 0
A13: Terminal Value (Exit)
A14: Exit Enterprise Value | B14: =IF('Inputs & Assumptions'!B13="Revenue",B6*B8,B7*B9) -> 500000000
A15: Exit Equity Value | B15: =B14-B10+B11 -> 500000000
A16: PV of Equity Value (today) | B16: =B15/(1+'Inputs & Assumptions'!B12)^'Inputs & Assumptions'!B11 -> 53687091
A18: VC Method Ownership Requirements
A19: FV Required on Investment | B19: ='Inputs & Assumptions'!B36*(1+'Inputs & Assumptions'!B12)^'Inputs & Assumptions'!B11 -> 46566129 | D19: Required ownership is what a VC needs (after dilution) to hit the target IRR.
A20: Required Ownership at Exit | B20: =IF(B15=0,0,B19/B15) -> 0.093132257
A21: Required Ownership at Entry (gross of dilution) | B21: =IF(1-'Inputs & Assumptions'!B38=0,0,B20/(1-'Inputs & Assumptions'!B38)) -> 0.15522043
A22: Implied Post-money Valuation Today (VC Method) | B22: =IF(B21=0,0,'Inputs & Assumptions'!B36/B21) -> 32212255
A23: Implied Pre-money Valuation Today | B23: =B22-'Inputs & Assumptions'!B36 -> 27212255
A25: Deal Economics (based on your proposed ownership)
A26: Proposed Ownership at Entry | B26: ='Inputs & Assumptions'!B37 -> 0.15
A27: Proposed Ownership at Exit | B27: ='Inputs & Assumptions'!B39 -> 0.09
A28: As-Converted Proceeds at Exit | B28: =B15*B27 -> 45000000
A29: Liquidation Preference (return of capital) | B29: ='Inputs & Assumptions'!B36*'Inputs & Assumptions'!B42 -> 5000000
A30: Exit Proceeds to Investor (max of pref vs as-converted, capped) | B30: =MIN(B15,MAX(B28,B29)) -> 45000000

Sheet Returns
A1: Investor Returns (Cash Flows, IRR, MOIC)
A3: Cash flows use proposed ownership, dilution, and preferred terms from Inputs.
A5: Summary
D6: Helper calcs | E6: Value | F6: Format
D7: Model IRR | E7: =IF('Inputs & Assumptions'!B11=1,IRR(B14:B15),IF('Inputs & Assumptions'!B11=2,IRR(B14:B16),IF('Inputs & Assumptions'!B11=3,IRR(B14:B17),IF('Inputs & Assumptions'!B11=4,IRR(B14:B18),IF('Inputs & Assumptions'!B11=5,IRR(B14:B19),IF('Inputs & Assumptions'!B11=6,IRR(B14:B20),IF('Inputs & Assumptions'!B11=7,IRR(B14:B21),IF('Inputs & Assumptions'!B11=8,IRR(B14:B22),IF('Inputs & Assumptions'!B11=9,IRR(B14:B23),IF('Inputs & Assumptions'!B11=10,IRR(B14:B24),IF('Inputs & Assumptions'!B11=11,IRR(B14:B25),IF('Inputs & Assumptions'!B11=12,IRR(B14:B26),IF('Inputs & Assumptions'!B11=13,IRR(B14:B27),IF('Inputs & Assumptions'!B11=14,IRR(B14:B28),IF('Inputs & Assumptions'!B11=15,IRR(B14:B29),NA()))))))))))))))) -> 0.24573094 | F7: 0.0%
D8: Total Distributions | E8: =Valuation!B30 + IF('Inputs & Assumptions'!B43="Yes", MAX(0,'Inputs & Assumptions'!B11-'Inputs & Assumptions'!B45)*'Inputs & Assumptions'!B36*'Inputs & Assumptions'!B44, 0) -> 45000000 | F8: $
D9: MOIC | E9: =IF('Inputs & Assumptions'!B36=0,0,E8/'Inputs & Assumptions'!B36) -> 9 | F9: x
A12: Cash Flow Timeline
A13: Year | B13: Cash Flow | C13: Notes
A14: 0 | B14: =IF(A14=0, -'Inputs & Assumptions'!B36,IF(A14='Inputs & Assumptions'!B11, Valuation!B30,IF(AND('Inputs & Assumptions'!B43="Yes",A14>='Inputs & Assumptions'!B45,A14<'Inputs & Assumptions'!B11),'Inputs & Assumptions'!B36*'Inputs & Assumptions'!B44,0))) -> -5000000 | C14: =IF(A14=0,"Investment outflow",IF(A14='Inputs & Assumptions'!B11,"Exit proceeds",IF(AND('Inputs & Assumptions'!B43="Yes",A14>='Inputs & Assumptions'!B45,A14<'Inputs & Assumptions'!B11),"Dividend", ""))) -> Investment outflow
A15: 1 | B15: =IF(A15=0, -'Inputs & Assumptions'!B36,IF(A15='Inputs & Assumptions'!B11, Valuation!B30,IF(AND('Inputs & Assumptions'!B43="Yes",A15>='Inputs & Assumptions'!B45,A15<'Inputs & Assumptions'!B11),'Inputs & Assumptions'!B36*'Inputs & Assumptions'!B44,0))) -> 0 | C15: =IF(A15=0,"Investment outflow",IF(A15='Inputs & Assumptions'!B11,"Exit proceeds",IF(AND('Inputs & Assumptions'!B43="Yes",A15>='Inputs & Assumptions'!B45,A15<'Inputs & Assumptions'!B11),"Dividend", "")))
A16: 2 | B16: =IF(A16=0, -'Inputs & Assumptions'!B36,IF(A16='Inputs & Assumptions'!B11, Valuation!B30,IF(AND('Inputs & Assumptions'!B43="Yes",A16>='Inputs & Assumptions'!B45,A16<'Inputs & Assumptions'!B11),'Inputs & Assumptions'!B36*'Inputs & Assumptions'!B44,0))) -> 0 | C16: =IF(A16=0,"Investment outflow",IF(A16='Inputs & Assumptions'!B11,"Exit proceeds",IF(AND('Inputs & Assumptions'!B43="Yes",A16>='Inputs & Assumptions'!B45,A16<'Inputs & Assumptions'!B11),"Dividend", "")))
A17: 3 | B17: =IF(A17=0, -'Inputs & Assumptions'!B36,IF(A17='Inputs & Assumptions'!B11, Valuation!B30,IF(AND('Inputs & Assumptions'!B43="Yes",A17>='Inputs & Assumptions'!B45,A17<'Inputs & Assumptions'!B11),'Inputs & Assumptions'!B36*'Inputs & Assumptions'!B44,0))) -> 0 | C17: =IF(A17=0,"Investment outflow",IF(A17='Inputs & Assumptions'!B11,"Exit proceeds",IF(AND('Inputs & Assumptions'!B43="Yes",A17>='Inputs & Assumptions'!B45,A17<'Inputs & Assumptions'!B11),"Dividend", "")))
A18: 4 | B18: =IF(A18=0, -'Inputs & Assumptions'!B36,IF(A18='Inputs & Assumptions'!B11, Valuation!B30,IF(AND('Inputs & Assumptions'!B43="Yes",A18>='Inputs & Assumptions'!B45,A18<'Inputs & Assumptions'!B11),'Inputs & Assumptions'!B36*'Inputs & Assumptions'!B44,0))) -> 0 | C18: =IF(A18=0,"Investment outflow",IF(A18='Inputs & Assumptions'!B11,"Exit proceeds",IF(AND('Inputs & Assumptions'!B43="Yes",A18>='Inputs & Assumptions'!B45,A18<'Inputs & Assumptions'!B11),"Dividend", "")))
A19: 5 | B19: =IF(A19=0, -'Inputs & Assumptions'!B36,IF(A19='Inputs & Assumptions'!B11, Valuation!B30,IF(AND('Inputs & Assumptions'!B43="Yes",A19>='Inputs & Assumptions'!B45,A19<'Inputs & Assumptions'!B11),'Inputs & Assumptions'!B36*'Inputs & Assumptions'!B44,0))) -> 0 | C19: =IF(A19=0,"Investment outflow",IF(A19='Inputs & Assumptions'!B11,"Exit proceeds",IF(AND('Inputs & Assumptions'!B43="Yes",A19>='Inputs & Assumptions'!B45,A19<'Inputs & Assumptions'!B11),"Dividend", "")))
A20: 6 | B20: =IF(A20=0, -'Inputs & Assumptions'!B36,IF(A20='Inputs & Assumptions'!B11, Valuation!B30,IF(AND('Inputs & Assumptions'!B43="Yes",A20>='Inputs & Assumptions'!B45,A20<'Inputs & Assumptions'!B11),'Inputs & Assumptions'!B36*'Inputs & Assumptions'!B44,0))) -> 0 | C20: =IF(A20=0,"Investment outflow",IF(A20='Inputs & Assumptions'!B11,"Exit proceeds",IF(AND('Inputs & Assumptions'!B43="Yes",A20>='Inputs & Assumptions'!B45,A20<'Inputs & Assumptions'!B11),"Dividend", "")))
A21: 7 | B21: =IF(A21=0, -'Inputs & Assumptions'!B36,IF(A21='Inputs & Assumptions'!B11, Valuation!B30,IF(AND('Inputs & Assumptions'!B43="Yes",A21>='Inputs & Assumptions'!B45,A21<'Inputs & Assumptions'!B11),'Inputs & Assumptions'!B36*'Inputs & Assumptions'!B44,0))) -> 0 | C21: =IF(A21=0,"Investment outflow",IF(A21='Inputs & Assumptions'!B11,"Exit proceeds",IF(AND('Inputs & Assumptions'!B43="Yes",A21>='Inputs & Assumptions'!B45,A21<'Inputs & Assumptions'!B11),"Dividend", "")))
A22: 8 | B22: =IF(A22=0, -'Inputs & Assumptions'!B36,IF(A22='Inputs & Assumptions'!B11, Valuation!B30,IF(AND('Inputs & Assumptions'!B43="Yes",A22>='Inputs & Assumptions'!B45,A22<'Inputs & Assumptions'!B11),'Inputs & Assumptions'!B36*'Inputs & Assumptions'!B44,0))) -> 0 | C22: =IF(A22=0,"Investment outflow",IF(A22='Inputs & Assumptions'!B11,"Exit proceeds",IF(AND('Inputs & Assumptions'!B43="Yes",A22>='Inputs & Assumptions'!B45,A22<'Inputs & Assumptions'!B11),"Dividend", "")))
A23: 9 | B23: =IF(A23=0, -'Inputs & Assumptions'!B36,IF(A23='Inputs & Assumptions'!B11, Valuation!B30,IF(AND('Inputs & Assumptions'!B43="Yes",A23>='Inputs & Assumptions'!B45,A23<'Inputs & Assumptions'!B11),'Inputs & Assumptions'!B36*'Inputs & Assumptions'!B44,0))) -> 0 | C23: =IF(A23=0,"Investment outflow",IF(A23='Inputs & Assumptions'!B11,"Exit proceeds",IF(AND('Inputs & Assumptions'!B43="Yes",A23>='Inputs & Assumptions'!B45,A23<'Inputs & Assumptions'!B11),"Dividend", "")))
A24: 10 | B24: =IF(A24=0, -'Inputs & Assumptions'!B36,IF(A24='Inputs & Assumptions'!B11, Valuation!B30,IF(AND('Inputs & Assumptions'!B43="Yes",A24>='Inputs & Assumptions'!B45,A24<'Inputs & Assumptions'!B11),'Inputs & Assumptions'!B36*'Inputs & Assumptions'!B44,0))) -> 45000000 | C24: =IF(A24=0,"Investment outflow",IF(A24='Inputs & Assumptions'!B11,"Exit proceeds",IF(AND('Inputs & Assumptions'!B43="Yes",A24>='Inputs & Assumptions'!B45,A24<'Inputs & Assumptions'!B11),"Dividend", ""))) -> Exit proceeds
A25: 11 | B25: =IF(A25=0, -'Inputs & Assumptions'!B36,IF(A25='Inputs & Assumptions'!B11, Valuation!B30,IF(AND('Inputs & Assumptions'!B43="Yes",A25>='Inputs & Assumptions'!B45,A25<'Inputs & Assumptions'!B11),'Inputs & Assumptions'!B36*'Inputs & Assumptions'!B44,0))) -> 0 | C25: =IF(A25=0,"Investment outflow",IF(A25='Inputs & Assumptions'!B11,"Exit proceeds",IF(AND('Inputs & Assumptions'!B43="Yes",A25>='Inputs & Assumptions'!B45,A25<'Inputs & Assumptions'!B11),"Dividend", "")))
A26: 12 | B26: =IF(A26=0, -'Inputs & Assumptions'!B36,IF(A26='Inputs & Assumptions'!B11, Valuation!B30,IF(AND('Inputs & Assumptions'!B43="Yes",A26>='Inputs & Assumptions'!B45,A26<'Inputs & Assumptions'!B11),'Inputs & Assumptions'!B36*'Inputs & Assumptions'!B44,0))) -> 0 | C26: =IF(A26=0,"Investment outflow",IF(A26='Inputs & Assumptions'!B11,"Exit proceeds",IF(AND('Inputs & Assumptions'!B43="Yes",A26>='Inputs & Assumptions'!B45,A26<'Inputs & Assumptions'!B11),"Dividend", "")))
A27: 13 | B27: =IF(A27=0, -'Inputs & Assumptions'!B36,IF(A27='Inputs & Assumptions'!B11, Valuation!B30,IF(AND('Inputs & Assumptions'!B43="Yes",A27>='Inputs & Assumptions'!B45,A27<'Inputs & Assumptions'!B11),'Inputs & Assumptions'!B36*'Inputs & Assumptions'!B44,0))) -> 0 | C27: =IF(A27=0,"Investment outflow",IF(A27='Inputs & Assumptions'!B11,"Exit proceeds",IF(AND('Inputs & Assumptions'!B43="Yes",A27>='Inputs & Assumptions'!B45,A27<'Inputs & Assumptions'!B11),"Dividend", "")))
A28: 14 | B28: =IF(A28=0, -'Inputs & Assumptions'!B36,IF(A28='Inputs & Assumptions'!B11, Valuation!B30,IF(AND('Inputs & Assumptions'!B43="Yes",A28>='Inputs & Assumptions'!B45,A28<'Inputs & Assumptions'!B11),'Inputs & Assumptions'!B36*'Inputs & Assumptions'!B44,0))) -> 0 | C28: =IF(A28=0,"Investment outflow",IF(A28='Inputs & Assumptions'!B11,"Exit proceeds",IF(AND('Inputs & Assumptions'!B43="Yes",A28>='Inputs & Assumptions'!B45,A28<'Inputs & Assumptions'!B11),"Dividend", "")))
A29: 15 | B29: =IF(A29=0, -'Inputs & Assumptions'!B36,IF(A29='Inputs & Assumptions'!B11, Valuation!B30,IF(AND('Inputs & Assumptions'!B43="Yes",A29>='Inputs & Assumptions'!B45,A29<'Inputs & Assumptions'!B11),'Inputs & Assumptions'!B36*'Inputs & Assumptions'!B44,0))) -> 0 | C29: =IF(A29=0,"Investment outflow",IF(A29='Inputs & Assumptions'!B11,"Exit proceeds",IF(AND('Inputs & Assumptions'!B43="Yes",A29>='Inputs & Assumptions'!B45,A29<'Inputs & Assumptions'!B11),"Dividend", "")))

Sheet Dashboard
A1: Summary Dashboard
A3: Investor-ready metrics (scenario-aware).
A5: Key Metrics
A6: Metric | B6: Value | C6: Unit | D6: Notes
A7: Scenario | B7: ='Inputs & Assumptions'!B5 -> Base | D7: Base/Upside/Downside selection
A8: Target Investor IRR | B8: ='Inputs & Assumptions'!B12 -> 0.25 | C8: % | D8: Common early-stage VC hurdle rates vary by fund/round
A9: Model IRR | B9: =Returns!E7 -> 0.24573094 | C9: % | D9: IRR from modeled annual cash flows
A10: MOIC (Multiple on Invested Capital) | B10: =Returns!E9 -> 9 | C10: x | D10: Total distributions / investment
A11: Absolute Gain | B11: =Returns!E8-'Inputs & Assumptions'!B36 -> 40000000 | C11: $ | D11: Total distributions minus invested amount
A12: Holding Period | B12: ='Inputs & Assumptions'!B11 -> 10 | C12: years | D12: Years from today to exit
A13: Exit Enterprise Value | B13: =Valuation!B14 -> 500000000 | C13: $ | D13: Terminal enterprise value at exit
A14: Exit Equity Value | B14: =Valuation!B15 -> 500000000 | C14: $ | D14: EV minus net debt
A15: Exit Proceeds to Investor | B15: =Valuation!B30 -> 45000000 | C15: $ | D15: Max(pref, as-converted), capped at equity value
A16: Ownership at Entry (proposed) | B16: ='Inputs & Assumptions'!B37 -> 0.15 | C16: % | D16: Stake at investment
A17: Ownership at Exit (after dilution) | B17: ='Inputs & Assumptions'!B39 -> 0.09 | C17: % | D17: Stake remaining at exit
A18: Required Ownership at Entry (VC Method) | B18: =Valuation!B21 -> 0.15522043 | C18: % | D18: Stake needed to hit target IRR given dilution
A19: Implied Post-money Today (VC Method) | B19: =Valuation!B22 -> 32212255 | C19: $ | D19: Investment / required ownership at entry
A22: Exit Snapshot
A23: Exit Metric Used | B23: ='Inputs & Assumptions'!B13 -> Revenue | D23: Revenue or EBITDA multiple
A24: Scenario Exit Revenue | B24: =Valuation!B6 -> 50000000 | C24: $
A25: Scenario Exit EBITDA | B25: =Valuation!B7 -> 10000000 | C25: $
A26: Selected Multiple | B26: =IF('Inputs & Assumptions'!B13="Revenue",Valuation!B8,Valuation!B9) -> 10 | C26: x
